Workbook

Sheet Assumptions
A1: Boston Beer Margin Comparison — Read Me, Controls & Assumptions
A2: Built from Boston_Pricing_Analysis.xlsx (all pricing per keg) + InvoiceTransReport_GSHARKEY_20260903 (Kohler actuals 7/1/2026–8/31/2026).
A4: CONTROLS — change these and every margin in the workbook recalculates
A6: Apply DA to FRONTLINE margin? | B6: N | C6: Default N. In the source file the DA is annotated only on best-price cells, so it is treated as funding the discounted price, not everyday frontline business. Set to Y if the allowance is earned on every case/keg regardless of the price sold at.
A7: Apply DA to BEST-PRICE margin? | B7: Y | C7: Default Y. Effective cost on best-price business = laid-in cost − DA. This is the assumption that makes Truly 15.5 at $115 profitable (see note below).
A9: COLOR LEGEND
A10: Blue text on pale blue fill | C10: EDITABLE INPUT — type over these (laid-in cost, DA, frontline price, best price)
A11: Black text | C11: CALCULATED — formula driven, do not type over
A12: Green text | C12: LINK to another tab in this workbook
A13: Yellow fill | C13: Key assumption / control cell
A15: HOW MARGIN IS CALCULATED
A16: Frontline margin $ | C16: Frontline price − frontline cost basis
A17: Frontline margin % | C17: Frontline margin $ ÷ frontline price (gross margin on selling price, not markup on cost)
A18: Best-price margin $ | C18: Best price − best-price cost basis
A19: Best-price margin % | C19: Best-price margin $ ÷ best price
A20: Frontline cost basis | C20: Laid-in cost — or laid-in − DA, if the FRONTLINE control above is set to Y
A21: Best-price cost basis | C21: Laid-in − DA when the BEST-PRICE control is Y (default), otherwise plain laid-in cost
A23: ASSUMPTIONS & JUDGEMENT CALLS (read before using the numbers)
A24: DA is a cost reducer, not a price reducer | C24: The source file records DA as free text inside the price cell — Twisted Tea 5.2 best price "58 ($9 DA)" and Truly 15.5 "$115 ($35.40 DA)". Those are read as: the number shown IS the selling price, and the DA lowers our cost. Truly 15.5 proves it — $115 against a $114.11 laid-in is $0.89 of margin (0.8%), which is not a real price. Net of the $35.40 DA the cost is $78.71 and the margin is $36.29 / 31.6%, right in line with the rest of the book. The DA has been split into its own editable column so it is no longer buried in text.
A25: DA applies only where the source annotated it | C25: Current book: Twisted Tea 5.2 ($9) and Truly 15.5 ($35.40), on Kohler and on the Boston Beer suggested price. New book: the same two SKUs carry the same allowances. Peerless and Shore Point DA is UNKNOWN — entered as 0, so their best-price margins are shown before any allowance they may receive and are therefore conservative (understated). Enter their DA if you learn it.
A26: One laid-in cost per product, applied to every distributor | C26: The source file carries a single "Laid In" column, not one per wholesaler. Competitor margins are therefore modelled on KOHLER'S laid-in cost. Freight, fuel and any supplier-specific terms will move a competitor's real cost, so treat Peerless / Shore Point margin figures as directional, not as their books. The cost cell is editable per row if you want to model a different competitor cost.
A27: "Suggested" is a benchmark, not a competitor | C27: The Suggested columns are Boston Beer's suggested pricing. It is carried as a fourth row per product so you can see how far each wholesaler sits off the supplier's intent, but it is not a distributor in the market.
A28: Pack size = keg size | C28: 15.5 = half barrel, 5.2 = sixtel. Every price and cost in the source is per keg, so no case-pack conversion is applied anywhere. $/gallon columns are added so a 15.5 and a 5.2 can be compared on the same basis (price ÷ gallons).
A29: Truly 15.5 — Peerless does not carry it | C29: The source shows "NA". Those cells are left blank and no margin is computed, rather than being scored as a zero.
A30: New-scenario prices are SEEDED, not sourced | C30: The source file supplies new laid-in cost and new SUGGESTED prices only — the Kohler and competitor new-price cells were blank question marks. On the New Pricing tab, Kohler / Peerless / Shore Point frontline and best prices are seeded with their CURRENT prices, i.e. "hold price and eat the cost increase". They are blue editable cells — overwrite them with what you actually intend to charge and every margin follows.
A31: Twisted Tea 15.5 new suggested best price | C31: The source shows a new suggested best of $184 against a new suggested frontline of $189 — only $5 of promotional room, versus $16 in the current book. Carried through as written; worth confirming with the supplier.
A32: Kohler Actuals tab | C32: Weighted-average realized price = Σ(units × unit price) ÷ units, from the invoice transaction report for 7/1/2026–8/31/2026. Zero-price lines (18 lines / 21 kegs of samples and comps) and backorder-only lines are excluded. The realized prices confirm the Kohler columns in the pricing file: every frontline and best price in the analysis appears in the invoice data as an actual charged price.
A34: TABS
A35: Current Pricing | C35: Today's laid-in cost and today's prices — every product × every distributor.
A36: New Pricing | C36: New laid-in cost, new suggested pricing, and your editable new prices. Shows the margin change vs today.
A37: Summary | C37: Kohler vs Peerless vs Shore Point vs Suggested, by product, on one screen.
A38: Kohler Actuals | C38: What Kohler actually charged and shipped, 7/1–8/31/2026, per product.
A39: Source Data | C39: The original Boston_Pricing_Analysis.xlsx sheet, untouched.

Sheet Current Pricing
A1: Current Pricing & Margin — by Product and Distributor
A2: Laid-in cost and prices per keg. Blue cells are editable; everything else recalculates. Competitor margins use Kohler's laid-in cost (see Assumptions).
A4: Product | B4: Keg Size (Gal) | C4: Distributor | D4: Old Laid-In Cost ($/keg) | E4: DA ($/keg) | F4: Frontline Price ($/keg) | G4: Best Price ($/keg) | H4: Frontline Cost Basis ($) | I4: Frontline Margin $ | J4: Frontline Margin % | K4: Best-Price Cost Basis ($) | L4: Best-Price Margin $ | M4: Best-Price Margin % | N4: Best vs Frontline ($) | O4: Frontline $/Gal | P4: Best $/Gal | Q4: Notes
A5: Sam Adams 15.5 | B5: 15.5 | C5: Kohler | D5: 114.61 | E5: 0 | F5: 185 | G5: 175 | H5: =IF($D5="","",IF(UPPER(Assumptions!$B$6)="Y",$D5-$E5,$D5)) -> 114.61 | I5: =IF(OR($F5="",$H5=""),"",$F5-$H5) -> 70.39 | J5: =IF(OR($I5="",$F5=""),"",IFERROR($I5/$F5,"")) -> 0.38048649 | K5: =IF($D5="","",IF(UPPER(Assumptions!$B$7)="Y",$D5-$E5,$D5)) -> 114.61 | L5: =IF(OR($G5="",$K5=""),"",$G5-$K5) -> 60.39 | M5: =IF(OR($L5="",$G5=""),"",IFERROR($L5/$G5,"")) -> 0.34508571 | N5: =IF(OR($F5="",$G5=""),"",$G5-$F5) -> -10 | O5: =IF($F5="","",IFERROR($F5/$B5,"")) -> 11.935484 | P5: =IF($G5="","",IFERROR($G5/$B5,"")) -> 11.290323
A6: Sam Adams 15.5 | B6: 15.5 | C6: Peerless | D6: 114.61 | E6: 0 | F6: 209 | G6: 188 | H6: =IF($D6="","",IF(UPPER(Assumptions!$B$6)="Y",$D6-$E6,$D6)) -> 114.61 | I6: =IF(OR($F6="",$H6=""),"",$F6-$H6) -> 94.39 | J6: =IF(OR($I6="",$F6=""),"",IFERROR($I6/$F6,"")) -> 0.45162679 | K6: =IF($D6="","",IF(UPPER(Assumptions!$B$7)="Y",$D6-$E6,$D6)) -> 114.61 | L6: =IF(OR($G6="",$K6=""),"",$G6-$K6) -> 73.39 | M6: =IF(OR($L6="",$G6=""),"",IFERROR($L6/$G6,"")) -> 0.39037234 | N6: =IF(OR($F6="",$G6=""),"",$G6-$F6) -> -21 | O6: =IF($F6="","",IFERROR($F6/$B6,"")) -> 13.483871 | P6: =IF($G6="","",IFERROR($G6/$B6,"")) -> 12.129032
A7: Sam Adams 15.5 | B7: 15.5 | C7: Shore Point | D7: 114.61 | E7: 0 | F7: 207 | G7: 188 | H7: =IF($D7="","",IF(UPPER(Assumptions!$B$6)="Y",$D7-$E7,$D7)) -> 114.61 | I7: =IF(OR($F7="",$H7=""),"",$F7-$H7) -> 92.39 | J7: =IF(OR($I7="",$F7=""),"",IFERROR($I7/$F7,"")) -> 0.4463285 | K7: =IF($D7="","",IF(UPPER(Assumptions!$B$7)="Y",$D7-$E7,$D7)) -> 114.61 | L7: =IF(OR($G7="",$K7=""),"",$G7-$K7) -> 73.39 | M7: =IF(OR($L7="",$G7=""),"",IFERROR($L7/$G7,"")) -> 0.39037234 | N7: =IF(OR($F7="",$G7=""),"",$G7-$F7) -> -19 | O7: =IF($F7="","",IFERROR($F7/$B7,"")) -> 13.354839 | P7: =IF($G7="","",IFERROR($G7/$B7,"")) -> 12.129032
A8: Sam Adams 15.5 | B8: 15.5 | C8: Suggested (Boston Beer) | D8: 114.61 | E8: 0 | F8: 185 | G8: 169 | H8: =IF($D8="","",IF(UPPER(Assumptions!$B$6)="Y",$D8-$E8,$D8)) -> 114.61 | I8: =IF(OR($F8="",$H8=""),"",$F8-$H8) -> 70.39 | J8: =IF(OR($I8="",$F8=""),"",IFERROR($I8/$F8,"")) -> 0.38048649 | K8: =IF($D8="","",IF(UPPER(Assumptions!$B$7)="Y",$D8-$E8,$D8)) -> 114.61 | L8: =IF(OR($G8="",$K8=""),"",$G8-$K8) -> 54.39 | M8: =IF(OR($L8="",$G8=""),"",IFERROR($L8/$G8,"")) -> 0.32183432 | N8: =IF(OR($F8="",$G8=""),"",$G8-$F8) -> -16 | O8: =IF($F8="","",IFERROR($F8/$B8,"")) -> 11.935484 | P8: =IF($G8="","",IFERROR($G8/$B8,"")) -> 10.903226 | Q8: Boston Beer suggested price — benchmark, not a distributor.
A9: Sam Adams 5.2 | B9: 5.2 | C9: Kohler | D9: 48.12 | E9: 0 | F9: 80 | G9: 78 | H9: =IF($D9="","",IF(UPPER(Assumptions!$B$6)="Y",$D9-$E9,$D9)) -> 48.12 | I9: =IF(OR($F9="",$H9=""),"",$F9-$H9) -> 31.88 | J9: =IF(OR($I9="",$F9=""),"",IFERROR($I9/$F9,"")) -> 0.3985 | K9: =IF($D9="","",IF(UPPER(Assumptions!$B$7)="Y",$D9-$E9,$D9)) -> 48.12 | L9: =IF(OR($G9="",$K9=""),"",$G9-$K9) -> 29.88 | M9: =IF(OR($L9="",$G9=""),"",IFERROR($L9/$G9,"")) -> 0.38307692 | N9: =IF(OR($F9="",$G9=""),"",$G9-$F9) -> -2 | O9: =IF($F9="","",IFERROR($F9/$B9,"")) -> 15.384615 | P9: =IF($G9="","",IFERROR($G9/$B9,"")) -> 15
A10: Sam Adams 5.2 | B10: 5.2 | C10: Peerless | D10: 48.12 | E10: 0 | F10: 97.5 | G10: 88.5 | H10: =IF($D10="","",IF(UPPER(Assumptions!$B$6)="Y",$D10-$E10,$D10)) -> 48.12 | I10: =IF(OR($F10="",$H10=""),"",$F10-$H10) -> 49.38 | J10: =IF(OR($I10="",$F10=""),"",IFERROR($I10/$F10,"")) -> 0.50646154 | K10: =IF($D10="","",IF(UPPER(Assumptions!$B$7)="Y",$D10-$E10,$D10)) -> 48.12 | L10: =IF(OR($G10="",$K10=""),"",$G10-$K10) -> 40.38 | M10: =IF(OR($L10="",$G10=""),"",IFERROR($L10/$G10,"")) -> 0.45627119 | N10: =IF(OR($F10="",$G10=""),"",$G10-$F10) -> -9 | O10: =IF($F10="","",IFERROR($F10/$B10,"")) -> 18.75 | P10: =IF($G10="","",IFERROR($G10/$B10,"")) -> 17.019231
A11: Sam Adams 5.2 | B11: 5.2 | C11: Shore Point | D11: 48.12 | E11: 0 | F11: 90 | G11: 80 | H11: =IF($D11="","",IF(UPPER(Assumptions!$B$6)="Y",$D11-$E11,$D11)) -> 48.12 | I11: =IF(OR($F11="",$H11=""),"",$F11-$H11) -> 41.88 | J11: =IF(OR($I11="",$F11=""),"",IFERROR($I11/$F11,"")) -> 0.46533333 | K11: =IF($D11="","",IF(UPPER(Assumptions!$B$7)="Y",$D11-$E11,$D11)) -> 48.12 | L11: =IF(OR($G11="",$K11=""),"",$G11-$K11) -> 31.88 | M11: =IF(OR($L11="",$G11=""),"",IFERROR($L11/$G11,"")) -> 0.3985 | N11: =IF(OR($F11="",$G11=""),"",$G11-$F11) -> -10 | O11: =IF($F11="","",IFERROR($F11/$B11,"")) -> 17.307692 | P11: =IF($G11="","",IFERROR($G11/$B11,"")) -> 15.384615
A12: Sam Adams 5.2 | B12: 5.2 | C12: Suggested (Boston Beer) | D12: 48.12 | E12: 0 | F12: 73 | G12: 63 | H12: =IF($D12="","",IF(UPPER(Assumptions!$B$6)="Y",$D12-$E12,$D12)) -> 48.12 | I12: =IF(OR($F12="",$H12=""),"",$F12-$H12) -> 24.88 | J12: =IF(OR($I12="",$F12=""),"",IFERROR($I12/$F12,"")) -> 0.34082192 | K12: =IF($D12="","",IF(UPPER(Assumptions!$B$7)="Y",$D12-$E12,$D12)) -> 48.12 | L12: =IF(OR($G12="",$K12=""),"",$G12-$K12) -> 14.88 | M12: =IF(OR($L12="",$G12=""),"",IFERROR($L12/$G12,"")) -> 0.23619048 | N12: =IF(OR($F12="",$G12=""),"",$G12-$F12) -> -10 | O12: =IF($F12="","",IFERROR($F12/$B12,"")) -> 14.038462 | P12: =IF($G12="","",IFERROR($G12/$B12,"")) -> 12.115385 | Q12: Boston Beer suggested price — benchmark, not a distributor.
A13: Twisted Tea 15.5 | B13: 15.5 | C13: Kohler | D13: 114.11 | E13: 0 | F13: 185 | G13: 175 | H13: =IF($D13="","",IF(UPPER(Assumptions!$B$6)="Y",$D13-$E13,$D13)) -> 114.11 | I13: =IF(OR($F13="",$H13=""),"",$F13-$H13) -> 70.89 | J13: =IF(OR($I13="",$F13=""),"",IFERROR($I13/$F13,"")) -> 0.38318919 | K13: =IF($D13="","",IF(UPPER(Assumptions!$B$7)="Y",$D13-$E13,$D13)) -> 114.11 | L13: =IF(OR($G13="",$K13=""),"",$G13-$K13) -> 60.89 | M13: =IF(OR($L13="",$G13=""),"",IFERROR($L13/$G13,"")) -> 0.34794286 | N13: =IF(OR($F13="",$G13=""),"",$G13-$F13) -> -10 | O13: =IF($F13="","",IFERROR($F13/$B13,"")) -> 11.935484 | P13: =IF($G13="","",IFERROR($G13/$B13,"")) -> 11.290323
A14: Twisted Tea 15.5 | B14: 15.5 | C14: Peerless | D14: 114.11 | E14: 0 | F14: 209 | G14: 188 | H14: =IF($D14="","",IF(UPPER(Assumptions!$B$6)="Y",$D14-$E14,$D14)) -> 114.11 | I14: =IF(OR($F14="",$H14=""),"",$F14-$H14) -> 94.89 | J14: =IF(OR($I14="",$F14=""),"",IFERROR($I14/$F14,"")) -> 0.45401914 | K14: =IF($D14="","",IF(UPPER(Assumptions!$B$7)="Y",$D14-$E14,$D14)) -> 114.11 | L14: =IF(OR($G14="",$K14=""),"",$G14-$K14) -> 73.89 | M14: =IF(OR($L14="",$G14=""),"",IFERROR($L14/$G14,"")) -> 0.39303191 | N14: =IF(OR($F14="",$G14=""),"",$G14-$F14) -> -21 | O14: =IF($F14="","",IFERROR($F14/$B14,"")) -> 13.483871 | P14: =IF($G14="","",IFERROR($G14/$B14,"")) -> 12.129032
A15: Twisted Tea 15.5 | B15: 15.5 | C15: Shore Point | D15: 114.11 | E15: 0 | F15: 207 | G15: 188 | H15: =IF($D15="","",IF(UPPER(Assumptions!$B$6)="Y",$D15-$E15,$D15)) -> 114.11 | I15: =IF(OR($F15="",$H15=""),"",$F15-$H15) -> 92.89 | J15: =IF(OR($I15="",$F15=""),"",IFERROR($I15/$F15,"")) -> 0.44874396 | K15: =IF($D15="","",IF(UPPER(Assumptions!$B$7)="Y",$D15-$E15,$D15)) -> 114.11 | L15: =IF(OR($G15="",$K15=""),"",$G15-$K15) -> 73.89 | M15: =IF(OR($L15="",$G15=""),"",IFERROR($L15/$G15,"")) -> 0.39303191 | N15: =IF(OR($F15="",$G15=""),"",$G15-$F15) -> -19 | O15: =IF($F15="","",IFERROR($F15/$B15,"")) -> 13.354839 | P15: =IF($G15="","",IFERROR($G15/$B15,"")) -> 12.129032
A16: Twisted Tea 15.5 | B16: 15.5 | C16: Suggested (Boston Beer) | D16: 114.11 | E16: 0 | F16: 184 | G16: 168 | H16: =IF($D16="","",IF(UPPER(Assumptions!$B$6)="Y",$D16-$E16,$D16)) -> 114.11 | I16: =IF(OR($F16="",$H16=""),"",$F16-$H16) -> 69.89 | J16: =IF(OR($I16="",$F16=""),"",IFERROR($I16/$F16,"")) -> 0.37983696 | K16: =IF($D16="","",IF(UPPER(Assumptions!$B$7)="Y",$D16-$E16,$D16)) -> 114.11 | L16: =IF(OR($G16="",$K16=""),"",$G16-$K16) -> 53.89 | M16: =IF(OR($L16="",$G16=""),"",IFERROR($L16/$G16,"")) -> 0.32077381 | N16: =IF(OR($F16="",$G16=""),"",$G16-$F16) -> -16 | O16: =IF($F16="","",IFERROR($F16/$B16,"")) -> 11.870968 | P16: =IF($G16="","",IFERROR($G16/$B16,"")) -> 10.83871 | Q16: Boston Beer suggested price — benchmark, not a distributor.
A17: Twisted Tea 5.2 | B17: 5.2 | C17: Kohler | D17: 48.12 | E17: 9 | F17: 77 | G17: 58 | H17: =IF($D17="","",IF(UPPER(Assumptions!$B$6)="Y",$D17-$E17,$D17)) -> 48.12 | I17: =IF(OR($F17="",$H17=""),"",$F17-$H17) -> 28.88 | J17: =IF(OR($I17="",$F17=""),"",IFERROR($I17/$F17,"")) -> 0.37506494 | K17: =IF($D17="","",IF(UPPER(Assumptions!$B$7)="Y",$D17-$E17,$D17)) -> 39.12 | L17: =IF(OR($G17="",$K17=""),"",$G17-$K17) -> 18.88 | M17: =IF(OR($L17="",$G17=""),"",IFERROR($L17/$G17,"")) -> 0.32551724 | N17: =IF(OR($F17="",$G17=""),"",$G17-$F17) -> -19 | O17: =IF($F17="","",IFERROR($F17/$B17,"")) -> 14.807692 | P17: =IF($G17="","",IFERROR($G17/$B17,"")) -> 11.153846 | Q17: Source shows best price with a $9.00 DA; DA broken out to col E.
A18: Twisted Tea 5.2 | B18: 5.2 | C18: Peerless | D18: 48.12 | E18: 0 | F18: 97.5 | G18: 88.5 | H18: =IF($D18="","",IF(UPPER(Assumptions!$B$6)="Y",$D18-$E18,$D18)) -> 48.12 | I18: =IF(OR($F18="",$H18=""),"",$F18-$H18) -> 49.38 | J18: =IF(OR($I18="",$F18=""),"",IFERROR($I18/$F18,"")) -> 0.50646154 | K18: =IF($D18="","",IF(UPPER(Assumptions!$B$7)="Y",$D18-$E18,$D18)) -> 48.12 | L18: =IF(OR($G18="",$K18=""),"",$G18-$K18) -> 40.38 | M18: =IF(OR($L18="",$G18=""),"",IFERROR($L18/$G18,"")) -> 0.45627119 | N18: =IF(OR($F18="",$G18=""),"",$G18-$F18) -> -9 | O18: =IF($F18="","",IFERROR($F18/$B18,"")) -> 18.75 | P18: =IF($G18="","",IFERROR($G18/$B18,"")) -> 17.019231 | Q18: Competitor DA unknown — entered as 0; best-price margin is conservative.
A19: Twisted Tea 5.2 | B19: 5.2 | C19: Shore Point | D19: 48.12 | E19: 0 | F19: 90 | G19: 80 | H19: =IF($D19="","",IF(UPPER(Assumptions!$B$6)="Y",$D19-$E19,$D19)) -> 48.12 | I19: =IF(OR($F19="",$H19=""),"",$F19-$H19) -> 41.88 | J19: =IF(OR($I19="",$F19=""),"",IFERROR($I19/$F19,"")) -> 0.46533333 | K19: =IF($D19="","",IF(UPPER(Assumptions!$B$7)="Y",$D19-$E19,$D19)) -> 48.12 | L19: =IF(OR($G19="",$K19=""),"",$G19-$K19) -> 31.88 | M19: =IF(OR($L19="",$G19=""),"",IFERROR($L19/$G19,"")) -> 0.3985 | N19: =IF(OR($F19="",$G19=""),"",$G19-$F19) -> -10 | O19: =IF($F19="","",IFERROR($F19/$B19,"")) -> 17.307692 | P19: =IF($G19="","",IFERROR($G19/$B19,"")) -> 15.384615 | Q19: Competitor DA unknown — entered as 0; best-price margin is conservative.
A20: Twisted Tea 5.2 | B20: 5.2 | C20: Suggested (Boston Beer) | D20: 48.12 | E20: 9 | F20: 77 | G20: 58 | H20: =IF($D20="","",IF(UPPER(Assumptions!$B$6)="Y",$D20-$E20,$D20)) -> 48.12 | I20: =IF(OR($F20="",$H20=""),"",$F20-$H20) -> 28.88 | J20: =IF(OR($I20="",$F20=""),"",IFERROR($I20/$F20,"")) -> 0.37506494 | K20: =IF($D20="","",IF(UPPER(Assumptions!$B$7)="Y",$D20-$E20,$D20)) -> 39.12 | L20: =IF(OR($G20="",$K20=""),"",$G20-$K20) -> 18.88 | M20: =IF(OR($L20="",$G20=""),"",IFERROR($L20/$G20,"")) -> 0.32551724 | N20: =IF(OR($F20="",$G20=""),"",$G20-$F20) -> -19 | O20: =IF($F20="","",IFERROR($F20/$B20,"")) -> 14.807692 | P20: =IF($G20="","",IFERROR($G20/$B20,"")) -> 11.153846 | Q20: Source shows best price with a $9.00 DA; DA broken out to col E.
A21: Angry Orchard 15.5 | B21: 15.5 | C21: Kohler | D21: 114.61 | E21: 0 | F21: 182 | G21: 156 | H21: =IF($D21="","",IF(UPPER(Assumptions!$B$6)="Y",$D21-$E21,$D21)) -> 114.61 | I21: =IF(OR($F21="",$H21=""),"",$F21-$H21) -> 67.39 | J21: =IF(OR($I21="",$F21=""),"",IFERROR($I21/$F21,"")) -> 0.37027473 | K21: =IF($D21="","",IF(UPPER(Assumptions!$B$7)="Y",$D21-$E21,$D21)) -> 114.61 | L21: =IF(OR($G21="",$K21=""),"",$G21-$K21) -> 41.39 | M21: =IF(OR($L21="",$G21=""),"",IFERROR($L21/$G21,"")) -> 0.26532051 | N21: =IF(OR($F21="",$G21=""),"",$G21-$F21) -> -26 | O21: =IF($F21="","",IFERROR($F21/$B21,"")) -> 11.741935 | P21: =IF($G21="","",IFERROR($G21/$B21,"")) -> 10.064516
A22: Angry Orchard 15.5 | B22: 15.5 | C22: Peerless | D22: 114.61 | E22: 0 | F22: 200 | G22: 189 | H22: =IF($D22="","",IF(UPPER(Assumptions!$B$6)="Y",$D22-$E22,$D22)) -> 114.61 | I22: =IF(OR($F22="",$H22=""),"",$F22-$H22) -> 85.39 | J22: =IF(OR($I22="",$F22=""),"",IFERROR($I22/$F22,"")) -> 0.42695 | K22: =IF($D22="","",IF(UPPER(Assumptions!$B$7)="Y",$D22-$E22,$D22)) -> 114.61 | L22: =IF(OR($G22="",$K22=""),"",$G22-$K22) -> 74.39 | M22: =IF(OR($L22="",$G22=""),"",IFERROR($L22/$G22,"")) -> 0.39359788 | N22: =IF(OR($F22="",$G22=""),"",$G22-$F22) -> -11 | O22: =IF($F22="","",IFERROR($F22/$B22,"")) -> 12.903226 | P22: =IF($G22="","",IFERROR($G22/$B22,"")) -> 12.193548
A23: Angry Orchard 15.5 | B23: 15.5 | C23: Shore Point | D23: 114.61 | E23: 0 | F23: 207 | G23: 188 | H23: =IF($D23="","",IF(UPPER(Assumptions!$B$6)="Y",$D23-$E23,$D23)) -> 114.61 | I23: =IF(OR($F23="",$H23=""),"",$F23-$H23) -> 92.39 | J23: =IF(OR($I23="",$F23=""),"",IFERROR($I23/$F23,"")) -> 0.4463285 | K23: =IF($D23="","",IF(UPPER(Assumptions!$B$7)="Y",$D23-$E23,$D23)) -> 114.61 | L23: =IF(OR($G23="",$K23=""),"",$G23-$K23) -> 73.39 | M23: =IF(OR($L23="",$G23=""),"",IFERROR($L23/$G23,"")) -> 0.39037234 | N23: =IF(OR($F23="",$G23=""),"",$G23-$F23) -> -19 | O23: =IF($F23="","",IFERROR($F23/$B23,"")) -> 13.354839 | P23: =IF($G23="","",IFERROR($G23/$B23,"")) -> 12.129032
A24: Angry Orchard 15.5 | B24: 15.5 | C24: Suggested (Boston Beer) | D24: 114.61 | E24: 0 | F24: 185 | G24: 169 | H24: =IF($D24="","",IF(UPPER(Assumptions!$B$6)="Y",$D24-$E24,$D24)) -> 114.61 | I24: =IF(OR($F24="",$H24=""),"",$F24-$H24) -> 70.39 | J24: =IF(OR($I24="",$F24=""),"",IFERROR($I24/$F24,"")) -> 0.38048649 | K24: =IF($D24="","",IF(UPPER(Assumptions!$B$7)="Y",$D24-$E24,$D24)) -> 114.61 | L24: =IF(OR($G24="",$K24=""),"",$G24-$K24) -> 54.39 | M24: =IF(OR($L24="",$G24=""),"",IFERROR($L24/$G24,"")) -> 0.32183432 | N24: =IF(OR($F24="",$G24=""),"",$G24-$F24) -> -16 | O24: =IF($F24="","",IFERROR($F24/$B24,"")) -> 11.935484 | P24: =IF($G24="","",IFERROR($G24/$B24,"")) -> 10.903226 | Q24: Boston Beer suggested price — benchmark, not a distributor.
A25: Angry Orchard 5.2 | B25: 5.2 | C25: Kohler | D25: 48.12 | E25: 0 | F25: 75 | G25: 73 | H25: =IF($D25="","",IF(UPPER(Assumptions!$B$6)="Y",$D25-$E25,$D25)) -> 48.12 | I25: =IF(OR($F25="",$H25=""),"",$F25-$H25) -> 26.88 | J25: =IF(OR($I25="",$F25=""),"",IFERROR($I25/$F25,"")) -> 0.3584 | K25: =IF($D25="","",IF(UPPER(Assumptions!$B$7)="Y",$D25-$E25,$D25)) -> 48.12 | L25: =IF(OR($G25="",$K25=""),"",$G25-$K25) -> 24.88 | M25: =IF(OR($L25="",$G25=""),"",IFERROR($L25/$G25,"")) -> 0.34082192 | N25: =IF(OR($F25="",$G25=""),"",$G25-$F25) -> -2 | O25: =IF($F25="","",IFERROR($F25/$B25,"")) -> 14.423077 | P25: =IF($G25="","",IFERROR($G25/$B25,"")) -> 14.038462
A26: Angry Orchard 5.2 | B26: 5.2 | C26: Peerless | D26: 48.12 | E26: 0 | F26: 95 | G26: 87 | H26: =IF($D26="","",IF(UPPER(Assumptions!$B$6)="Y",$D26-$E26,$D26)) -> 48.12 | I26: =IF(OR($F26="",$H26=""),"",$F26-$H26) -> 46.88 | J26: =IF(OR($I26="",$F26=""),"",IFERROR($I26/$F26,"")) -> 0.49347368 | K26: =IF($D26="","",IF(UPPER(Assumptions!$B$7)="Y",$D26-$E26,$D26)) -> 48.12 | L26: =IF(OR($G26="",$K26=""),"",$G26-$K26) -> 38.88 | M26: =IF(OR($L26="",$G26=""),"",IFERROR($L26/$G26,"")) -> 0.44689655 | N26: =IF(OR($F26="",$G26=""),"",$G26-$F26) -> -8 | O26: =IF($F26="","",IFERROR($F26/$B26,"")) -> 18.269231 | P26: =IF($G26="","",IFERROR($G26/$B26,"")) -> 16.730769
A27: Angry Orchard 5.2 | B27: 5.2 | C27: Shore Point | D27: 48.12 | E27: 0 | F27: 90 | G27: 80 | H27: =IF($D27="","",IF(UPPER(Assumptions!$B$6)="Y",$D27-$E27,$D27)) -> 48.12 | I27: =IF(OR($F27="",$H27=""),"",$F27-$H27) -> 41.88 | J27: =IF(OR($I27="",$F27=""),"",IFERROR($I27/$F27,"")) -> 0.46533333 | K27: =IF($D27="","",IF(UPPER(Assumptions!$B$7)="Y",$D27-$E27,$D27)) -> 48.12 | L27: =IF(OR($G27="",$K27=""),"",$G27-$K27) -> 31.88 | M27: =IF(OR($L27="",$G27=""),"",IFERROR($L27/$G27,"")) -> 0.3985 | N27: =IF(OR($F27="",$G27=""),"",$G27-$F27) -> -10 | O27: =IF($F27="","",IFERROR($F27/$B27,"")) -> 17.307692 | P27: =IF($G27="","",IFERROR($G27/$B27,"")) -> 15.384615
A28: Angry Orchard 5.2 | B28: 5.2 | C28: Suggested (Boston Beer) | D28: 48.12 | E28: 0 | F28: 77 | G28: 73 | H28: =IF($D28="","",IF(UPPER(Assumptions!$B$6)="Y",$D28-$E28,$D28)) -> 48.12 | I28: =IF(OR($F28="",$H28=""),"",$F28-$H28) -> 28.88 | J28: =IF(OR($I28="",$F28=""),"",IFERROR($I28/$F28,"")) -> 0.37506494 | K28: =IF($D28="","",IF(UPPER(Assumptions!$B$7)="Y",$D28-$E28,$D28)) -> 48.12 | L28: =IF(OR($G28="",$K28=""),"",$G28-$K28) -> 24.88 | M28: =IF(OR($L28="",$G28=""),"",IFERROR($L28/$G28,"")) -> 0.34082192 | N28: =IF(OR($F28="",$G28=""),"",$G28-$F28) -> -4 | O28: =IF($F28="","",IFERROR($F28/$B28,"")) -> 14.807692 | P28: =IF($G28="","",IFERROR($G28/$B28,"")) -> 14.038462 | Q28: Boston Beer suggested price — benchmark, not a distributor.
A29: Dogfish Head 15.5 | B29: 15.5 | C29: Kohler | D29: 121.95 | E29: 0 | F29: 185 | G29: 180 | H29: =IF($D29="","",IF(UPPER(Assumptions!$B$6)="Y",$D29-$E29,$D29)) -> 121.95 | I29: =IF(OR($F29="",$H29=""),"",$F29-$H29) -> 63.05 | J29: =IF(OR($I29="",$F29=""),"",IFERROR($I29/$F29,"")) -> 0.34081081 | K29: =IF($D29="","",IF(UPPER(Assumptions!$B$7)="Y",$D29-$E29,$D29)) -> 121.95 | L29: =IF(OR($G29="",$K29=""),"",$G29-$K29) -> 58.05 | M29: =IF(OR($L29="",$G29=""),"",IFERROR($L29/$G29,"")) -> 0.3225 | N29: =IF(OR($F29="",$G29=""),"",$G29-$F29) -> -5 | O29: =IF($F29="","",IFERROR($F29/$B29,"")) -> 11.935484 | P29: =IF($G29="","",IFERROR($G29/$B29,"")) -> 11.612903
A30: Dogfish Head 15.5 | B30: 15.5 | C30: Peerless | D30: 121.95 | E30: 0 | F30: 209 | G30: 188 | H30: =IF($D30="","",IF(UPPER(Assumptions!$B$6)="Y",$D30-$E30,$D30)) -> 121.95 | I30: =IF(OR($F30="",$H30=""),"",$F30-$H30) -> 87.05 | J30: =IF(OR($I30="",$F30=""),"",IFERROR($I30/$F30,"")) -> 0.41650718 | K30: =IF($D30="","",IF(UPPER(Assumptions!$B$7)="Y",$D30-$E30,$D30)) -> 121.95 | L30: =IF(OR($G30="",$K30=""),"",$G30-$K30) -> 66.05 | M30: =IF(OR($L30="",$G30=""),"",IFERROR($L30/$G30,"")) -> 0.35132979 | N30: =IF(OR($F30="",$G30=""),"",$G30-$F30) -> -21 | O30: =IF($F30="","",IFERROR($F30/$B30,"")) -> 13.483871 | P30: =IF($G30="","",IFERROR($G30/$B30,"")) -> 12.129032
A31: Dogfish Head 15.5 | B31: 15.5 | C31: Shore Point | D31: 121.95 | E31: 0 | F31: 203 | G31: 188 | H31: =IF($D31="","",IF(UPPER(Assumptions!$B$6)="Y",$D31-$E31,$D31)) -> 121.95 | I31: =IF(OR($F31="",$H31=""),"",$F31-$H31) -> 81.05 | J31: =IF(OR($I31="",$F31=""),"",IFERROR($I31/$F31,"")) -> 0.39926108 | K31: =IF($D31="","",IF(UPPER(Assumptions!$B$7)="Y",$D31-$E31,$D31)) -> 121.95 | L31: =IF(OR($G31="",$K31=""),"",$G31-$K31) -> 66.05 | M31: =IF(OR($L31="",$G31=""),"",IFERROR($L31/$G31,"")) -> 0.35132979 | N31: =IF(OR($F31="",$G31=""),"",$G31-$F31) -> -15 | O31: =IF($F31="","",IFERROR($F31/$B31,"")) -> 13.096774 | P31: =IF($G31="","",IFERROR($G31/$B31,"")) -> 12.129032
A32: Dogfish Head 15.5 | B32: 15.5 | C32: Suggested (Boston Beer) | D32: 121.95 | E32: 0 | F32: 189 | G32: 161 | H32: =IF($D32="","",IF(UPPER(Assumptions!$B$6)="Y",$D32-$E32,$D32)) -> 121.95 | I32: =IF(OR($F32="",$H32=""),"",$F32-$H32) -> 67.05 | J32: =IF(OR($I32="",$F32=""),"",IFERROR($I32/$F32,"")) -> 0.3547619 | K32: =IF($D32="","",IF(UPPER(Assumptions!$B$7)="Y",$D32-$E32,$D32)) -> 121.95 | L32: =IF(OR($G32="",$K32=""),"",$G32-$K32) -> 39.05 | M32: =IF(OR($L32="",$G32=""),"",IFERROR($L32/$G32,"")) -> 0.24254658 | N32: =IF(OR($F32="",$G32=""),"",$G32-$F32) -> -28 | O32: =IF($F32="","",IFERROR($F32/$B32,"")) -> 12.193548 | P32: =IF($G32="","",IFERROR($G32/$B32,"")) -> 10.387097 | Q32: Boston Beer suggested price — benchmark, not a distributor.
A33: Dogfish Head 5.2 | B33: 5.2 | C33: Kohler | D33: 59.68 | E33: 0 | F33: 90 | G33: 87 | H33: =IF($D33="","",IF(UPPER(Assumptions!$B$6)="Y",$D33-$E33,$D33)) -> 59.68 | I33: =IF(OR($F33="",$H33=""),"",$F33-$H33) -> 30.32 | J33: =IF(OR($I33="",$F33=""),"",IFERROR($I33/$F33,"")) -> 0.33688889 | K33: =IF($D33="","",IF(UPPER(Assumptions!$B$7)="Y",$D33-$E33,$D33)) -> 59.68 | L33: =IF(OR($G33="",$K33=""),"",$G33-$K33) -> 27.32 | M33: =IF(OR($L33="",$G33=""),"",IFERROR($L33/$G33,"")) -> 0.31402299 | N33: =IF(OR($F33="",$G33=""),"",$G33-$F33) -> -3 | O33: =IF($F33="","",IFERROR($F33/$B33,"")) -> 17.307692 | P33: =IF($G33="","",IFERROR($G33/$B33,"")) -> 16.730769
A34: Dogfish Head 5.2 | B34: 5.2 | C34: Peerless | D34: 59.68 | E34: 0 | F34: 97.5 | G34: 88.5 | H34: =IF($D34="","",IF(UPPER(Assumptions!$B$6)="Y",$D34-$E34,$D34)) -> 59.68 | I34: =IF(OR($F34="",$H34=""),"",$F34-$H34) -> 37.82 | J34: =IF(OR($I34="",$F34=""),"",IFERROR($I34/$F34,"")) -> 0.38789744 | K34: =IF($D34="","",IF(UPPER(Assumptions!$B$7)="Y",$D34-$E34,$D34)) -> 59.68 | L34: =IF(OR($G34="",$K34=""),"",$G34-$K34) -> 28.82 | M34: =IF(OR($L34="",$G34=""),"",IFERROR($L34/$G34,"")) -> 0.32564972 | N34: =IF(OR($F34="",$G34=""),"",$G34-$F34) -> -9 | O34: =IF($F34="","",IFERROR($F34/$B34,"")) -> 18.75 | P34: =IF($G34="","",IFERROR($G34/$B34,"")) -> 17.019231
A35: Dogfish Head 5.2 | B35: 5.2 | C35: Shore Point | D35: 59.68 | E35: 0 | F35: 98 | G35: 94 | H35: =IF($D35="","",IF(UPPER(Assumptions!$B$6)="Y",$D35-$E35,$D35)) -> 59.68 | I35: =IF(OR($F35="",$H35=""),"",$F35-$H35) -> 38.32 | J35: =IF(OR($I35="",$F35=""),"",IFERROR($I35/$F35,"")) -> 0.39102041 | K35: =IF($D35="","",IF(UPPER(Assumptions!$B$7)="Y",$D35-$E35,$D35)) -> 59.68 | L35: =IF(OR($G35="",$K35=""),"",$G35-$K35) -> 34.32 | M35: =IF(OR($L35="",$G35=""),"",IFERROR($L35/$G35,"")) -> 0.36510638 | N35: =IF(OR($F35="",$G35=""),"",$G35-$F35) -> -4 | O35: =IF($F35="","",IFERROR($F35/$B35,"")) -> 18.846154 | P35: =IF($G35="","",IFERROR($G35/$B35,"")) -> 18.076923
A36: Dogfish Head 5.2 | B36: 5.2 | C36: Suggested (Boston Beer) | D36: 59.68 | E36: 0 | F36: 87 | G36: 83 | H36: =IF($D36="","",IF(UPPER(Assumptions!$B$6)="Y",$D36-$E36,$D36)) -> 59.68 | I36: =IF(OR($F36="",$H36=""),"",$F36-$H36) -> 27.32 | J36: =IF(OR($I36="",$F36=""),"",IFERROR($I36/$F36,"")) -> 0.31402299 | K36: =IF($D36="","",IF(UPPER(Assumptions!$B$7)="Y",$D36-$E36,$D36)) -> 59.68 | L36: =IF(OR($G36="",$K36=""),"",$G36-$K36) -> 23.32 | M36: =IF(OR($L36="",$G36=""),"",IFERROR($L36/$G36,"")) -> 0.28096386 | N36: =IF(OR($F36="",$G36=""),"",$G36-$F36) -> -4 | O36: =IF($F36="","",IFERROR($F36/$B36,"")) -> 16.730769 | P36: =IF($G36="","",IFERROR($G36/$B36,"")) -> 15.961538 | Q36: Boston Beer suggested price — benchmark, not a distributor.
A37: Truly 15.5 | B37: 15.5 | C37: Kohler | D37: 114.11 | E37: 35.4 | F37: 168 | G37: 115 | H37: =IF($D37="","",IF(UPPER(Assumptions!$B$6)="Y",$D37-$E37,$D37)) -> 114.11 | I37: =IF(OR($F37="",$H37=""),"",$F37-$H37) -> 53.89 | J37: =IF(OR($I37="",$F37=""),"",IFERROR($I37/$F37,"")) -> 0.32077381 | K37: =IF($D37="","",IF(UPPER(Assumptions!$B$7)="Y",$D37-$E37,$D37)) -> 78.71 | L37: =IF(OR($G37="",$K37=""),"",$G37-$K37) -> 36.29 | M37: =IF(OR($L37="",$G37=""),"",IFERROR($L37/$G37,"")) -> 0.31556522 | N37: =IF(OR($F37="",$G37=""),"",$G37-$F37) -> -53 | O37: =IF($F37="","",IFERROR($F37/$B37,"")) -> 10.83871 | P37: =IF($G37="","",IFERROR($G37/$B37,"")) -> 7.4193548 | Q37: Source shows best price with a $35.40 DA; DA broken out to col E.
A38: Truly 15.5 | B38: 15.5 | C38: Peerless | D38: 114.11 | H38: =IF($D38="","",IF(UPPER(Assumptions!$B$6)="Y",$D38-$E38,$D38)) -> 114.11 | I38: =IF(OR($F38="",$H38=""),"",$F38-$H38) | J38: =IF(OR($I38="",$F38=""),"",IFERROR($I38/$F38,"")) | K38: =IF($D38="","",IF(UPPER(Assumptions!$B$7)="Y",$D38-$E38,$D38)) -> 114.11 | L38: =IF(OR($G38="",$K38=""),"",$G38-$K38) | M38: =IF(OR($L38="",$G38=""),"",IFERROR($L38/$G38,"")) | N38: =IF(OR($F38="",$G38=""),"",$G38-$F38) | O38: =IF($F38="","",IFERROR($F38/$B38,"")) | P38: =IF($G38="","",IFERROR($G38/$B38,"")) | Q38: Source shows "NA" — Peerless does not carry this SKU.
A39: Truly 15.5 | B39: 15.5 | C39: Shore Point | D39: 114.11 | E39: 0 | F39: 207 | G39: 188 | H39: =IF($D39="","",IF(UPPER(Assumptions!$B$6)="Y",$D39-$E39,$D39)) -> 114.11 | I39: =IF(OR($F39="",$H39=""),"",$F39-$H39) -> 92.89 | J39: =IF(OR($I39="",$F39=""),"",IFERROR($I39/$F39,"")) -> 0.44874396 | K39: =IF($D39="","",IF(UPPER(Assumptions!$B$7)="Y",$D39-$E39,$D39)) -> 114.11 | L39: =IF(OR($G39="",$K39=""),"",$G39-$K39) -> 73.89 | M39: =IF(OR($L39="",$G39=""),"",IFERROR($L39/$G39,"")) -> 0.39303191 | N39: =IF(OR($F39="",$G39=""),"",$G39-$F39) -> -19 | O39: =IF($F39="","",IFERROR($F39/$B39,"")) -> 13.354839 | P39: =IF($G39="","",IFERROR($G39/$B39,"")) -> 12.129032 | Q39: Competitor DA unknown — entered as 0; best-price margin is conservative.
A40: Truly 15.5 | B40: 15.5 | C40: Suggested (Boston Beer) | D40: 114.11 | E40: 35.4 | F40: 184 | G40: 115 | H40: =IF($D40="","",IF(UPPER(Assumptions!$B$6)="Y",$D40-$E40,$D40)) -> 114.11 | I40: =IF(OR($F40="",$H40=""),"",$F40-$H40) -> 69.89 | J40: =IF(OR($I40="",$F40=""),"",IFERROR($I40/$F40,"")) -> 0.37983696 | K40: =IF($D40="","",IF(UPPER(Assumptions!$B$7)="Y",$D40-$E40,$D40)) -> 78.71 | L40: =IF(OR($G40="",$K40=""),"",$G40-$K40) -> 36.29 | M40: =IF(OR($L40="",$G40=""),"",IFERROR($L40/$G40,"")) -> 0.31556522 | N40: =IF(OR($F40="",$G40=""),"",$G40-$F40) -> -69 | O40: =IF($F40="","",IFERROR($F40/$B40,"")) -> 11.870968 | P40: =IF($G40="","",IFERROR($G40/$B40,"")) -> 7.4193548 | Q40: Source shows best price with a $35.40 DA; DA broken out to col E.
A41: Truly 5.2 | B41: 5.2 | C41: Kohler | D41: 48.12 | E41: 0 | F41: 70 | G41: 68 | H41: =IF($D41="","",IF(UPPER(Assumptions!$B$6)="Y",$D41-$E41,$D41)) -> 48.12 | I41: =IF(OR($F41="",$H41=""),"",$F41-$H41) -> 21.88 | J41: =IF(OR($I41="",$F41=""),"",IFERROR($I41/$F41,"")) -> 0.31257143 | K41: =IF($D41="","",IF(UPPER(Assumptions!$B$7)="Y",$D41-$E41,$D41)) -> 48.12 | L41: =IF(OR($G41="",$K41=""),"",$G41-$K41) -> 19.88 | M41: =IF(OR($L41="",$G41=""),"",IFERROR($L41/$G41,"")) -> 0.29235294 | N41: =IF(OR($F41="",$G41=""),"",$G41-$F41) -> -2 | O41: =IF($F41="","",IFERROR($F41/$B41,"")) -> 13.461538 | P41: =IF($G41="","",IFERROR($G41/$B41,"")) -> 13.076923
A42: Truly 5.2 | B42: 5.2 | C42: Peerless | D42: 48.12 | E42: 0 | F42: 97.5 | G42: 88.5 | H42: =IF($D42="","",IF(UPPER(Assumptions!$B$6)="Y",$D42-$E42,$D42)) -> 48.12 | I42: =IF(OR($F42="",$H42=""),"",$F42-$H42) -> 49.38 | J42: =IF(OR($I42="",$F42=""),"",IFERROR($I42/$F42,"")) -> 0.50646154 | K42: =IF($D42="","",IF(UPPER(Assumptions!$B$7)="Y",$D42-$E42,$D42)) -> 48.12 | L42: =IF(OR($G42="",$K42=""),"",$G42-$K42) -> 40.38 | M42: =IF(OR($L42="",$G42=""),"",IFERROR($L42/$G42,"")) -> 0.45627119 | N42: =IF(OR($F42="",$G42=""),"",$G42-$F42) -> -9 | O42: =IF($F42="","",IFERROR($F42/$B42,"")) -> 18.75 | P42: =IF($G42="","",IFERROR($G42/$B42,"")) -> 17.019231
A43: Truly 5.2 | B43: 5.2 | C43: Shore Point | D43: 48.12 | E43: 0 | F43: 90 | G43: 80 | H43: =IF($D43="","",IF(UPPER(Assumptions!$B$6)="Y",$D43-$E43,$D43)) -> 48.12 | I43: =IF(OR($F43="",$H43=""),"",$F43-$H43) -> 41.88 | J43: =IF(OR($I43="",$F43=""),"",IFERROR($I43/$F43,"")) -> 0.46533333 | K43: =IF($D43="","",IF(UPPER(Assumptions!$B$7)="Y",$D43-$E43,$D43)) -> 48.12 | L43: =IF(OR($G43="",$K43=""),"",$G43-$K43) -> 31.88 | M43: =IF(OR($L43="",$G43=""),"",IFERROR($L43/$G43,"")) -> 0.3985 | N43: =IF(OR($F43="",$G43=""),"",$G43-$F43) -> -10 | O43: =IF($F43="","",IFERROR($F43/$B43,"")) -> 17.307692 | P43: =IF($G43="","",IFERROR($G43/$B43,"")) -> 15.384615
A44: Truly 5.2 | B44: 5.2 | C44: Suggested (Boston Beer) | D44: 48.12 | E44: 0 | F44: 77 | G44: 67 | H44: =IF($D44="","",IF(UPPER(Assumptions!$B$6)="Y",$D44-$E44,$D44)) -> 48.12 | I44: =IF(OR($F44="",$H44=""),"",$F44-$H44) -> 28.88 | J44: =IF(OR($I44="",$F44=""),"",IFERROR($I44/$F44,"")) -> 0.37506494 | K44: =IF($D44="","",IF(UPPER(Assumptions!$B$7)="Y",$D44-$E44,$D44)) -> 48.12 | L44: =IF(OR($G44="",$K44=""),"",$G44-$K44) -> 18.88 | M44: =IF(OR($L44="",$G44=""),"",IFERROR($L44/$G44,"")) -> 0.28179104 | N44: =IF(OR($F44="",$G44=""),"",$G44-$F44) -> -10 | O44: =IF($F44="","",IFERROR($F44/$B44,"")) -> 14.807692 | P44: =IF($G44="","",IFERROR($G44/$B44,"")) -> 12.884615 | Q44: Boston Beer suggested price — benchmark, not a distributor.
A46: Source: Boston_Pricing_Analysis.xlsx, Sheet1 rows 1–11 (current book). DA amounts extracted from the free text in the source best-price cells.

Sheet New Pricing
A1: New Pricing & Margin — by Product and Distributor
A2: New laid-in cost from the source file. Kohler / Peerless / Shore Point new prices are SEEDED with current prices (= hold price, absorb the increase) — overwrite the blue cells with your intended pricing.
A4: Product | B4: Keg Size (Gal) | C4: Distributor | D4: Old Laid-In ($/keg) | E4: New Laid-In ($/keg) | F4: Δ Laid-In ($) | G4: DA ($/keg) | H4: Frontline Price ($/keg) | I4: Best Price ($/keg) | J4: Frontline Cost Basis ($) | K4: Frontline Margin $ | L4: Frontline Margin % | M4: Best-Price Cost Basis ($) | N4: Best-Price Margin $ | O4: Best-Price Margin % | P4: Δ Frontline Margin % vs Current | Q4: Δ Best-Price Margin % vs Current | R4: Best vs Frontline ($) | S4: Notes
A5: Sam Adams 15.5 | B5: 15.5 | C5: Kohler | D5: ='Current Pricing'!$D$5 -> 114.61 | E5: 117.11 | F5: =IF(OR($D5="",$E5=""),"",$E5-$D5) -> 2.5 | G5: 0 | H5: 185 | I5: 175 | J5: =IF($E5="","",IF(UPPER(Assumptions!$B$6)="Y",$E5-$G5,$E5)) -> 117.11 | K5: =IF(OR($H5="",$J5=""),"",$H5-$J5) -> 67.89 | L5: =IF(OR($K5="",$H5=""),"",IFERROR($K5/$H5,"")) -> 0.36697297 | M5: =IF($E5="","",IF(UPPER(Assumptions!$B$7)="Y",$E5-$G5,$E5)) -> 117.11 | N5: =IF(OR($I5="",$M5=""),"",$I5-$M5) -> 57.89 | O5: =IF(OR($N5="",$I5=""),"",IFERROR($N5/$I5,"")) -> 0.3308 | P5: =IF(OR($L5="",'Current Pricing'!$J$5=""),"",$L5-'Current Pricing'!$J$5) -> -0.013513514 | Q5: =IF(OR($O5="",'Current Pricing'!$M$5=""),"",$O5-'Current Pricing'!$M$5) -> -0.014285714 | R5: =IF(OR($H5="",$I5=""),"",$I5-$H5) -> -10 | S5: SEEDED with current price — source gave no new price for this distributor. Edit.
A6: Sam Adams 15.5 | B6: 15.5 | C6: Peerless | D6: ='Current Pricing'!$D$6 -> 114.61 | E6: 117.11 | F6: =IF(OR($D6="",$E6=""),"",$E6-$D6) -> 2.5 | G6: 0 | H6: 209 | I6: 188 | J6: =IF($E6="","",IF(UPPER(Assumptions!$B$6)="Y",$E6-$G6,$E6)) -> 117.11 | K6: =IF(OR($H6="",$J6=""),"",$H6-$J6) -> 91.89 | L6: =IF(OR($K6="",$H6=""),"",IFERROR($K6/$H6,"")) -> 0.43966507 | M6: =IF($E6="","",IF(UPPER(Assumptions!$B$7)="Y",$E6-$G6,$E6)) -> 117.11 | N6: =IF(OR($I6="",$M6=""),"",$I6-$M6) -> 70.89 | O6: =IF(OR($N6="",$I6=""),"",IFERROR($N6/$I6,"")) -> 0.37707447 | P6: =IF(OR($L6="",'Current Pricing'!$J$6=""),"",$L6-'Current Pricing'!$J$6) -> -0.011961722 | Q6: =IF(OR($O6="",'Current Pricing'!$M$6=""),"",$O6-'Current Pricing'!$M$6) -> -0.013297872 | R6: =IF(OR($H6="",$I6=""),"",$I6-$H6) -> -21 | S6: SEEDED with current price — source gave no new price for this distributor. Edit.
A7: Sam Adams 15.5 | B7: 15.5 | C7: Shore Point | D7: ='Current Pricing'!$D$7 -> 114.61 | E7: 117.11 | F7: =IF(OR($D7="",$E7=""),"",$E7-$D7) -> 2.5 | G7: 0 | H7: 207 | I7: 188 | J7: =IF($E7="","",IF(UPPER(Assumptions!$B$6)="Y",$E7-$G7,$E7)) -> 117.11 | K7: =IF(OR($H7="",$J7=""),"",$H7-$J7) -> 89.89 | L7: =IF(OR($K7="",$H7=""),"",IFERROR($K7/$H7,"")) -> 0.43425121 | M7: =IF($E7="","",IF(UPPER(Assumptions!$B$7)="Y",$E7-$G7,$E7)) -> 117.11 | N7: =IF(OR($I7="",$M7=""),"",$I7-$M7) -> 70.89 | O7: =IF(OR($N7="",$I7=""),"",IFERROR($N7/$I7,"")) -> 0.37707447 | P7: =IF(OR($L7="",'Current Pricing'!$J$7=""),"",$L7-'Current Pricing'!$J$7) -> -0.012077295 | Q7: =IF(OR($O7="",'Current Pricing'!$M$7=""),"",$O7-'Current Pricing'!$M$7) -> -0.013297872 | R7: =IF(OR($H7="",$I7=""),"",$I7-$H7) -> -19 | S7: SEEDED with current price — source gave no new price for this distributor. Edit.
A8: Sam Adams 15.5 | B8: 15.5 | C8: Suggested (Boston Beer) | D8: ='Current Pricing'!$D$8 -> 114.61 | E8: 117.11 | F8: =IF(OR($D8="",$E8=""),"",$E8-$D8) -> 2.5 | G8: 0 | H8: 190 | I8: 176 | J8: =IF($E8="","",IF(UPPER(Assumptions!$B$6)="Y",$E8-$G8,$E8)) -> 117.11 | K8: =IF(OR($H8="",$J8=""),"",$H8-$J8) -> 72.89 | L8: =IF(OR($K8="",$H8=""),"",IFERROR($K8/$H8,"")) -> 0.38363158 | M8: =IF($E8="","",IF(UPPER(Assumptions!$B$7)="Y",$E8-$G8,$E8)) -> 117.11 | N8: =IF(OR($I8="",$M8=""),"",$I8-$M8) -> 58.89 | O8: =IF(OR($N8="",$I8=""),"",IFERROR($N8/$I8,"")) -> 0.33460227 | P8: =IF(OR($L8="",'Current Pricing'!$J$8=""),"",$L8-'Current Pricing'!$J$8) -> 0.0031450925 | Q8: =IF(OR($O8="",'Current Pricing'!$M$8=""),"",$O8-'Current Pricing'!$M$8) -> 0.012767953 | R8: =IF(OR($H8="",$I8=""),"",$I8-$H8) -> -14 | S8: New suggested frontline / best price from the source file.
A9: Sam Adams 5.2 | B9: 5.2 | C9: Kohler | D9: ='Current Pricing'!$D$9 -> 48.12 | E9: 49.62 | F9: =IF(OR($D9="",$E9=""),"",$E9-$D9) -> 1.5 | G9: 0 | H9: 80 | I9: 78 | J9: =IF($E9="","",IF(UPPER(Assumptions!$B$6)="Y",$E9-$G9,$E9)) -> 49.62 | K9: =IF(OR($H9="",$J9=""),"",$H9-$J9) -> 30.38 | L9: =IF(OR($K9="",$H9=""),"",IFERROR($K9/$H9,"")) -> 0.37975 | M9: =IF($E9="","",IF(UPPER(Assumptions!$B$7)="Y",$E9-$G9,$E9)) -> 49.62 | N9: =IF(OR($I9="",$M9=""),"",$I9-$M9) -> 28.38 | O9: =IF(OR($N9="",$I9=""),"",IFERROR($N9/$I9,"")) -> 0.36384615 | P9: =IF(OR($L9="",'Current Pricing'!$J$9=""),"",$L9-'Current Pricing'!$J$9) -> -0.01875 | Q9: =IF(OR($O9="",'Current Pricing'!$M$9=""),"",$O9-'Current Pricing'!$M$9) -> -0.019230769 | R9: =IF(OR($H9="",$I9=""),"",$I9-$H9) -> -2 | S9: SEEDED with current price — source gave no new price for this distributor. Edit.
A10: Sam Adams 5.2 | B10: 5.2 | C10: Peerless | D10: ='Current Pricing'!$D$10 -> 48.12 | E10: 49.62 | F10: =IF(OR($D10="",$E10=""),"",$E10-$D10) -> 1.5 | G10: 0 | H10: 97.5 | I10: 88.5 | J10: =IF($E10="","",IF(UPPER(Assumptions!$B$6)="Y",$E10-$G10,$E10)) -> 49.62 | K10: =IF(OR($H10="",$J10=""),"",$H10-$J10) -> 47.88 | L10: =IF(OR($K10="",$H10=""),"",IFERROR($K10/$H10,"")) -> 0.49107692 | M10: =IF($E10="","",IF(UPPER(Assumptions!$B$7)="Y",$E10-$G10,$E10)) -> 49.62 | N10: =IF(OR($I10="",$M10=""),"",$I10-$M10) -> 38.88 | O10: =IF(OR($N10="",$I10=""),"",IFERROR($N10/$I10,"")) -> 0.43932203 | P10: =IF(OR($L10="",'Current Pricing'!$J$10=""),"",$L10-'Current Pricing'!$J$10) -> -0.015384615 | Q10: =IF(OR($O10="",'Current Pricing'!$M$10=""),"",$O10-'Current Pricing'!$M$10) -> -0.016949153 | R10: =IF(OR($H10="",$I10=""),"",$I10-$H10) -> -9 | S10: SEEDED with current price — source gave no new price for this distributor. Edit.
A11: Sam Adams 5.2 | B11: 5.2 | C11: Shore Point | D11: ='Current Pricing'!$D$11 -> 48.12 | E11: 49.62 | F11: =IF(OR($D11="",$E11=""),"",$E11-$D11) -> 1.5 | G11: 0 | H11: 90 | I11: 80 | J11: =IF($E11="","",IF(UPPER(Assumptions!$B$6)="Y",$E11-$G11,$E11)) -> 49.62 | K11: =IF(OR($H11="",$J11=""),"",$H11-$J11) -> 40.38 | L11: =IF(OR($K11="",$H11=""),"",IFERROR($K11/$H11,"")) -> 0.44866667 | M11: =IF($E11="","",IF(UPPER(Assumptions!$B$7)="Y",$E11-$G11,$E11)) -> 49.62 | N11: =IF(OR($I11="",$M11=""),"",$I11-$M11) -> 30.38 | O11: =IF(OR($N11="",$I11=""),"",IFERROR($N11/$I11,"")) -> 0.37975 | P11: =IF(OR($L11="",'Current Pricing'!$J$11=""),"",$L11-'Current Pricing'!$J$11) -> -0.016666667 | Q11: =IF(OR($O11="",'Current Pricing'!$M$11=""),"",$O11-'Current Pricing'!$M$11) -> -0.01875 | R11: =IF(OR($H11="",$I11=""),"",$I11-$H11) -> -10 | S11: SEEDED with current price — source gave no new price for this distributor. Edit.
A12: Sam Adams 5.2 | B12: 5.2 | C12: Suggested (Boston Beer) | D12: ='Current Pricing'!$D$12 -> 48.12 | E12: 49.62 | F12: =IF(OR($D12="",$E12=""),"",$E12-$D12) -> 1.5 | G12: 0 | H12: 79 | I12: 76 | J12: =IF($E12="","",IF(UPPER(Assumptions!$B$6)="Y",$E12-$G12,$E12)) -> 49.62 | K12: =IF(OR($H12="",$J12=""),"",$H12-$J12) -> 29.38 | L12: =IF(OR($K12="",$H12=""),"",IFERROR($K12/$H12,"")) -> 0.37189873 | M12: =IF($E12="","",IF(UPPER(Assumptions!$B$7)="Y",$E12-$G12,$E12)) -> 49.62 | N12: =IF(OR($I12="",$M12=""),"",$I12-$M12) -> 26.38 | O12: =IF(OR($N12="",$I12=""),"",IFERROR($N12/$I12,"")) -> 0.34710526 | P12: =IF(OR($L12="",'Current Pricing'!$J$12=""),"",$L12-'Current Pricing'!$J$12) -> 0.031076816 | Q12: =IF(OR($O12="",'Current Pricing'!$M$12=""),"",$O12-'Current Pricing'!$M$12) -> 0.11091479 | R12: =IF(OR($H12="",$I12=""),"",$I12-$H12) -> -3 | S12: New suggested frontline / best price from the source file.
A13: Twisted Tea 15.5 | B13: 15.5 | C13: Kohler | D13: ='Current Pricing'!$D$13 -> 114.11 | E13: 116.11 | F13: =IF(OR($D13="",$E13=""),"",$E13-$D13) -> 2 | G13: 0 | H13: 185 | I13: 175 | J13: =IF($E13="","",IF(UPPER(Assumptions!$B$6)="Y",$E13-$G13,$E13)) -> 116.11 | K13: =IF(OR($H13="",$J13=""),"",$H13-$J13) -> 68.89 | L13: =IF(OR($K13="",$H13=""),"",IFERROR($K13/$H13,"")) -> 0.37237838 | M13: =IF($E13="","",IF(UPPER(Assumptions!$B$7)="Y",$E13-$G13,$E13)) -> 116.11 | N13: =IF(OR($I13="",$M13=""),"",$I13-$M13) -> 58.89 | O13: =IF(OR($N13="",$I13=""),"",IFERROR($N13/$I13,"")) -> 0.33651429 | P13: =IF(OR($L13="",'Current Pricing'!$J$13=""),"",$L13-'Current Pricing'!$J$13) -> -0.010810811 | Q13: =IF(OR($O13="",'Current Pricing'!$M$13=""),"",$O13-'Current Pricing'!$M$13) -> -0.011428571 | R13: =IF(OR($H13="",$I13=""),"",$I13-$H13) -> -10 | S13: SEEDED with current price — source gave no new price for this distributor. Edit.
A14: Twisted Tea 15.5 | B14: 15.5 | C14: Peerless | D14: ='Current Pricing'!$D$14 -> 114.11 | E14: 116.11 | F14: =IF(OR($D14="",$E14=""),"",$E14-$D14) -> 2 | G14: 0 | H14: 209 | I14: 188 | J14: =IF($E14="","",IF(UPPER(Assumptions!$B$6)="Y",$E14-$G14,$E14)) -> 116.11 | K14: =IF(OR($H14="",$J14=""),"",$H14-$J14) -> 92.89 | L14: =IF(OR($K14="",$H14=""),"",IFERROR($K14/$H14,"")) -> 0.44444976 | M14: =IF($E14="","",IF(UPPER(Assumptions!$B$7)="Y",$E14-$G14,$E14)) -> 116.11 | N14: =IF(OR($I14="",$M14=""),"",$I14-$M14) -> 71.89 | O14: =IF(OR($N14="",$I14=""),"",IFERROR($N14/$I14,"")) -> 0.38239362 | P14: =IF(OR($L14="",'Current Pricing'!$J$14=""),"",$L14-'Current Pricing'!$J$14) -> -0.009569378 | Q14: =IF(OR($O14="",'Current Pricing'!$M$14=""),"",$O14-'Current Pricing'!$M$14) -> -0.010638298 | R14: =IF(OR($H14="",$I14=""),"",$I14-$H14) -> -21 | S14: SEEDED with current price — source gave no new price for this distributor. Edit.
A15: Twisted Tea 15.5 | B15: 15.5 | C15: Shore Point | D15: ='Current Pricing'!$D$15 -> 114.11 | E15: 116.11 | F15: =IF(OR($D15="",$E15=""),"",$E15-$D15) -> 2 | G15: 0 | H15: 207 | I15: 188 | J15: =IF($E15="","",IF(UPPER(Assumptions!$B$6)="Y",$E15-$G15,$E15)) -> 116.11 | K15: =IF(OR($H15="",$J15=""),"",$H15-$J15) -> 90.89 | L15: =IF(OR($K15="",$H15=""),"",IFERROR($K15/$H15,"")) -> 0.43908213 | M15: =IF($E15="","",IF(UPPER(Assumptions!$B$7)="Y",$E15-$G15,$E15)) -> 116.11 | N15: =IF(OR($I15="",$M15=""),"",$I15-$M15) -> 71.89 | O15: =IF(OR($N15="",$I15=""),"",IFERROR($N15/$I15,"")) -> 0.38239362 | P15: =IF(OR($L15="",'Current Pricing'!$J$15=""),"",$L15-'Current Pricing'!$J$15) -> -0.0096618357 | Q15: =IF(OR($O15="",'Current Pricing'!$M$15=""),"",$O15-'Current Pricing'!$M$15) -> -0.010638298 | R15: =IF(OR($H15="",$I15=""),"",$I15-$H15) -> -19 | S15: SEEDED with current price — source gave no new price for this distributor. Edit.
A16: Twisted Tea 15.5 | B16: 15.5 | C16: Suggested (Boston Beer) | D16: ='Current Pricing'!$D$16 -> 114.11 | E16: 116.11 | F16: =IF(OR($D16="",$E16=""),"",$E16-$D16) -> 2 | G16: 0 | H16: 189 | I16: 184 | J16: =IF($E16="","",IF(UPPER(Assumptions!$B$6)="Y",$E16-$G16,$E16)) -> 116.11 | K16: =IF(OR($H16="",$J16=""),"",$H16-$J16) -> 72.89 | L16: =IF(OR($K16="",$H16=""),"",IFERROR($K16/$H16,"")) -> 0.38566138 | M16: =IF($E16="","",IF(UPPER(Assumptions!$B$7)="Y",$E16-$G16,$E16)) -> 116.11 | N16: =IF(OR($I16="",$M16=""),"",$I16-$M16) -> 67.89 | O16: =IF(OR($N16="",$I16=""),"",IFERROR($N16/$I16,"")) -> 0.36896739 | P16: =IF(OR($L16="",'Current Pricing'!$J$16=""),"",$L16-'Current Pricing'!$J$16) -> 0.0058244191 | Q16: =IF(OR($O16="",'Current Pricing'!$M$16=""),"",$O16-'Current Pricing'!$M$16) -> 0.048193582 | R16: =IF(OR($H16="",$I16=""),"",$I16-$H16) -> -5 | S16: New suggested frontline / best price from the source file.
A17: Twisted Tea 5.2 | B17: 5.2 | C17: Kohler | D17: ='Current Pricing'!$D$17 -> 48.12 | E17: 49.62 | F17: =IF(OR($D17="",$E17=""),"",$E17-$D17) -> 1.5 | G17: 9 | H17: 77 | I17: 58 | J17: =IF($E17="","",IF(UPPER(Assumptions!$B$6)="Y",$E17-$G17,$E17)) -> 49.62 | K17: =IF(OR($H17="",$J17=""),"",$H17-$J17) -> 27.38 | L17: =IF(OR($K17="",$H17=""),"",IFERROR($K17/$H17,"")) -> 0.35558442 | M17: =IF($E17="","",IF(UPPER(Assumptions!$B$7)="Y",$E17-$G17,$E17)) -> 40.62 | N17: =IF(OR($I17="",$M17=""),"",$I17-$M17) -> 17.38 | O17: =IF(OR($N17="",$I17=""),"",IFERROR($N17/$I17,"")) -> 0.29965517 | P17: =IF(OR($L17="",'Current Pricing'!$J$17=""),"",$L17-'Current Pricing'!$J$17) -> -0.019480519 | Q17: =IF(OR($O17="",'Current Pricing'!$M$17=""),"",$O17-'Current Pricing'!$M$17) -> -0.025862069 | R17: =IF(OR($H17="",$I17=""),"",$I17-$H17) -> -19 | S17: SEEDED with current price — source gave no new price for this distributor. Edit. Current $9.00 DA carried forward.
A18: Twisted Tea 5.2 | B18: 5.2 | C18: Peerless | D18: ='Current Pricing'!$D$18 -> 48.12 | E18: 49.62 | F18: =IF(OR($D18="",$E18=""),"",$E18-$D18) -> 1.5 | G18: 0 | H18: 97.5 | I18: 88.5 | J18: =IF($E18="","",IF(UPPER(Assumptions!$B$6)="Y",$E18-$G18,$E18)) -> 49.62 | K18: =IF(OR($H18="",$J18=""),"",$H18-$J18) -> 47.88 | L18: =IF(OR($K18="",$H18=""),"",IFERROR($K18/$H18,"")) -> 0.49107692 | M18: =IF($E18="","",IF(UPPER(Assumptions!$B$7)="Y",$E18-$G18,$E18)) -> 49.62 | N18: =IF(OR($I18="",$M18=""),"",$I18-$M18) -> 38.88 | O18: =IF(OR($N18="",$I18=""),"",IFERROR($N18/$I18,"")) -> 0.43932203 | P18: =IF(OR($L18="",'Current Pricing'!$J$18=""),"",$L18-'Current Pricing'!$J$18) -> -0.015384615 | Q18: =IF(OR($O18="",'Current Pricing'!$M$18=""),"",$O18-'Current Pricing'!$M$18) -> -0.016949153 | R18: =IF(OR($H18="",$I18=""),"",$I18-$H18) -> -9 | S18: SEEDED with current price — source gave no new price for this distributor. Edit.
A19: Twisted Tea 5.2 | B19: 5.2 | C19: Shore Point | D19: ='Current Pricing'!$D$19 -> 48.12 | E19: 49.62 | F19: =IF(OR($D19="",$E19=""),"",$E19-$D19) -> 1.5 | G19: 0 | H19: 90 | I19: 80 | J19: =IF($E19="","",IF(UPPER(Assumptions!$B$6)="Y",$E19-$G19,$E19)) -> 49.62 | K19: =IF(OR($H19="",$J19=""),"",$H19-$J19) -> 40.38 | L19: =IF(OR($K19="",$H19=""),"",IFERROR($K19/$H19,"")) -> 0.44866667 | M19: =IF($E19="","",IF(UPPER(Assumptions!$B$7)="Y",$E19-$G19,$E19)) -> 49.62 | N19: =IF(OR($I19="",$M19=""),"",$I19-$M19) -> 30.38 | O19: =IF(OR($N19="",$I19=""),"",IFERROR($N19/$I19,"")) -> 0.37975 | P19: =IF(OR($L19="",'Current Pricing'!$J$19=""),"",$L19-'Current Pricing'!$J$19) -> -0.016666667 | Q19: =IF(OR($O19="",'Current Pricing'!$M$19=""),"",$O19-'Current Pricing'!$M$19) -> -0.01875 | R19: =IF(OR($H19="",$I19=""),"",$I19-$H19) -> -10 | S19: SEEDED with current price — source gave no new price for this distributor. Edit.
A20: Twisted Tea 5.2 | B20: 5.2 | C20: Suggested (Boston Beer) | D20: ='Current Pricing'!$D$20 -> 48.12 | E20: 49.62 | F20: =IF(OR($D20="",$E20=""),"",$E20-$D20) -> 1.5 | G20: 9 | H20: 79 | I20: 61 | J20: =IF($E20="","",IF(UPPER(Assumptions!$B$6)="Y",$E20-$G20,$E20)) -> 49.62 | K20: =IF(OR($H20="",$J20=""),"",$H20-$J20) -> 29.38 | L20: =IF(OR($K20="",$H20=""),"",IFERROR($K20/$H20,"")) -> 0.37189873 | M20: =IF($E20="","",IF(UPPER(Assumptions!$B$7)="Y",$E20-$G20,$E20)) -> 40.62 | N20: =IF(OR($I20="",$M20=""),"",$I20-$M20) -> 20.38 | O20: =IF(OR($N20="",$I20=""),"",IFERROR($N20/$I20,"")) -> 0.33409836 | P20: =IF(OR($L20="",'Current Pricing'!$J$20=""),"",$L20-'Current Pricing'!$J$20) -> -0.0031662009 | Q20: =IF(OR($O20="",'Current Pricing'!$M$20=""),"",$O20-'Current Pricing'!$M$20) -> 0.0085811193 | R20: =IF(OR($H20="",$I20=""),"",$I20-$H20) -> -18 | S20: New suggested frontline / best price from the source file. Source annotates a $9.00 DA — broken out to col G.
A21: Angry Orchard 15.5 | B21: 15.5 | C21: Kohler | D21: ='Current Pricing'!$D$21 -> 114.61 | E21: 117.11 | F21: =IF(OR($D21="",$E21=""),"",$E21-$D21) -> 2.5 | G21: 0 | H21: 182 | I21: 156 | J21: =IF($E21="","",IF(UPPER(Assumptions!$B$6)="Y",$E21-$G21,$E21)) -> 117.11 | K21: =IF(OR($H21="",$J21=""),"",$H21-$J21) -> 64.89 | L21: =IF(OR($K21="",$H21=""),"",IFERROR($K21/$H21,"")) -> 0.35653846 | M21: =IF($E21="","",IF(UPPER(Assumptions!$B$7)="Y",$E21-$G21,$E21)) -> 117.11 | N21: =IF(OR($I21="",$M21=""),"",$I21-$M21) -> 38.89 | O21: =IF(OR($N21="",$I21=""),"",IFERROR($N21/$I21,"")) -> 0.24929487 | P21: =IF(OR($L21="",'Current Pricing'!$J$21=""),"",$L21-'Current Pricing'!$J$21) -> -0.013736264 | Q21: =IF(OR($O21="",'Current Pricing'!$M$21=""),"",$O21-'Current Pricing'!$M$21) -> -0.016025641 | R21: =IF(OR($H21="",$I21=""),"",$I21-$H21) -> -26 | S21: SEEDED with current price — source gave no new price for this distributor. Edit.
A22: Angry Orchard 15.5 | B22: 15.5 | C22: Peerless | D22: ='Current Pricing'!$D$22 -> 114.61 | E22: 117.11 | F22: =IF(OR($D22="",$E22=""),"",$E22-$D22) -> 2.5 | G22: 0 | H22: 200 | I22: 189 | J22: =IF($E22="","",IF(UPPER(Assumptions!$B$6)="Y",$E22-$G22,$E22)) -> 117.11 | K22: =IF(OR($H22="",$J22=""),"",$H22-$J22) -> 82.89 | L22: =IF(OR($K22="",$H22=""),"",IFERROR($K22/$H22,"")) -> 0.41445 | M22: =IF($E22="","",IF(UPPER(Assumptions!$B$7)="Y",$E22-$G22,$E22)) -> 117.11 | N22: =IF(OR($I22="",$M22=""),"",$I22-$M22) -> 71.89 | O22: =IF(OR($N22="",$I22=""),"",IFERROR($N22/$I22,"")) -> 0.38037037 | P22: =IF(OR($L22="",'Current Pricing'!$J$22=""),"",$L22-'Current Pricing'!$J$22) -> -0.0125 | Q22: =IF(OR($O22="",'Current Pricing'!$M$22=""),"",$O22-'Current Pricing'!$M$22) -> -0.013227513 | R22: =IF(OR($H22="",$I22=""),"",$I22-$H22) -> -11 | S22: SEEDED with current price — source gave no new price for this distributor. Edit.
A23: Angry Orchard 15.5 | B23: 15.5 | C23: Shore Point | D23: ='Current Pricing'!$D$23 -> 114.61 | E23: 117.11 | F23: =IF(OR($D23="",$E23=""),"",$E23-$D23) -> 2.5 | G23: 0 | H23: 207 | I23: 188 | J23: =IF($E23="","",IF(UPPER(Assumptions!$B$6)="Y",$E23-$G23,$E23)) -> 117.11 | K23: =IF(OR($H23="",$J23=""),"",$H23-$J23) -> 89.89 | L23: =IF(OR($K23="",$H23=""),"",IFERROR($K23/$H23,"")) -> 0.43425121 | M23: =IF($E23="","",IF(UPPER(Assumptions!$B$7)="Y",$E23-$G23,$E23)) -> 117.11 | N23: =IF(OR($I23="",$M23=""),"",$I23-$M23) -> 70.89 | O23: =IF(OR($N23="",$I23=""),"",IFERROR($N23/$I23,"")) -> 0.37707447 | P23: =IF(OR($L23="",'Current Pricing'!$J$23=""),"",$L23-'Current Pricing'!$J$23) -> -0.012077295 | Q23: =IF(OR($O23="",'Current Pricing'!$M$23=""),"",$O23-'Current Pricing'!$M$23) -> -0.013297872 | R23: =IF(OR($H23="",$I23=""),"",$I23-$H23) -> -19 | S23: SEEDED with current price — source gave no new price for this distributor. Edit.
A24: Angry Orchard 15.5 | B24: 15.5 | C24: Suggested (Boston Beer) | D24: ='Current Pricing'!$D$24 -> 114.61 | E24: 117.11 | F24: =IF(OR($D24="",$E24=""),"",$E24-$D24) -> 2.5 | G24: 0 | H24: 190 | I24: 176 | J24: =IF($E24="","",IF(UPPER(Assumptions!$B$6)="Y",$E24-$G24,$E24)) -> 117.11 | K24: =IF(OR($H24="",$J24=""),"",$H24-$J24) -> 72.89 | L24: =IF(OR($K24="",$H24=""),"",IFERROR($K24/$H24,"")) -> 0.38363158 | M24: =IF($E24="","",IF(UPPER(Assumptions!$B$7)="Y",$E24-$G24,$E24)) -> 117.11 | N24: =IF(OR($I24="",$M24=""),"",$I24-$M24) -> 58.89 | O24: =IF(OR($N24="",$I24=""),"",IFERROR($N24/$I24,"")) -> 0.33460227 | P24: =IF(OR($L24="",'Current Pricing'!$J$24=""),"",$L24-'Current Pricing'!$J$24) -> 0.0031450925 | Q24: =IF(OR($O24="",'Current Pricing'!$M$24=""),"",$O24-'Current Pricing'!$M$24) -> 0.012767953 | R24: =IF(OR($H24="",$I24=""),"",$I24-$H24) -> -14 | S24: New suggested frontline / best price from the source file.
A25: Angry Orchard 5.2 | B25: 5.2 | C25: Kohler | D25: ='Current Pricing'!$D$25 -> 48.12 | E25: 49.62 | F25: =IF(OR($D25="",$E25=""),"",$E25-$D25) -> 1.5 | G25: 0 | H25: 75 | I25: 73 | J25: =IF($E25="","",IF(UPPER(Assumptions!$B$6)="Y",$E25-$G25,$E25)) -> 49.62 | K25: =IF(OR($H25="",$J25=""),"",$H25-$J25) -> 25.38 | L25: =IF(OR($K25="",$H25=""),"",IFERROR($K25/$H25,"")) -> 0.3384 | M25: =IF($E25="","",IF(UPPER(Assumptions!$B$7)="Y",$E25-$G25,$E25)) -> 49.62 | N25: =IF(OR($I25="",$M25=""),"",$I25-$M25) -> 23.38 | O25: =IF(OR($N25="",$I25=""),"",IFERROR($N25/$I25,"")) -> 0.32027397 | P25: =IF(OR($L25="",'Current Pricing'!$J$25=""),"",$L25-'Current Pricing'!$J$25) -> -0.02 | Q25: =IF(OR($O25="",'Current Pricing'!$M$25=""),"",$O25-'Current Pricing'!$M$25) -> -0.020547945 | R25: =IF(OR($H25="",$I25=""),"",$I25-$H25) -> -2 | S25: SEEDED with current price — source gave no new price for this distributor. Edit.
A26: Angry Orchard 5.2 | B26: 5.2 | C26: Peerless | D26: ='Current Pricing'!$D$26 -> 48.12 | E26: 49.62 | F26: =IF(OR($D26="",$E26=""),"",$E26-$D26) -> 1.5 | G26: 0 | H26: 95 | I26: 87 | J26: =IF($E26="","",IF(UPPER(Assumptions!$B$6)="Y",$E26-$G26,$E26)) -> 49.62 | K26: =IF(OR($H26="",$J26=""),"",$H26-$J26) -> 45.38 | L26: =IF(OR($K26="",$H26=""),"",IFERROR($K26/$H26,"")) -> 0.47768421 | M26: =IF($E26="","",IF(UPPER(Assumptions!$B$7)="Y",$E26-$G26,$E26)) -> 49.62 | N26: =IF(OR($I26="",$M26=""),"",$I26-$M26) -> 37.38 | O26: =IF(OR($N26="",$I26=""),"",IFERROR($N26/$I26,"")) -> 0.42965517 | P26: =IF(OR($L26="",'Current Pricing'!$J$26=""),"",$L26-'Current Pricing'!$J$26) -> -0.015789474 | Q26: =IF(OR($O26="",'Current Pricing'!$M$26=""),"",$O26-'Current Pricing'!$M$26) -> -0.017241379 | R26: =IF(OR($H26="",$I26=""),"",$I26-$H26) -> -8 | S26: SEEDED with current price — source gave no new price for this distributor. Edit.
A27: Angry Orchard 5.2 | B27: 5.2 | C27: Shore Point | D27: ='Current Pricing'!$D$27 -> 48.12 | E27: 49.62 | F27: =IF(OR($D27="",$E27=""),"",$E27-$D27) -> 1.5 | G27: 0 | H27: 90 | I27: 80 | J27: =IF($E27="","",IF(UPPER(Assumptions!$B$6)="Y",$E27-$G27,$E27)) -> 49.62 | K27: =IF(OR($H27="",$J27=""),"",$H27-$J27) -> 40.38 | L27: =IF(OR($K27="",$H27=""),"",IFERROR($K27/$H27,"")) -> 0.44866667 | M27: =IF($E27="","",IF(UPPER(Assumptions!$B$7)="Y",$E27-$G27,$E27)) -> 49.62 | N27: =IF(OR($I27="",$M27=""),"",$I27-$M27) -> 30.38 | O27: =IF(OR($N27="",$I27=""),"",IFERROR($N27/$I27,"")) -> 0.37975 | P27: =IF(OR($L27="",'Current Pricing'!$J$27=""),"",$L27-'Current Pricing'!$J$27) -> -0.016666667 | Q27: =IF(OR($O27="",'Current Pricing'!$M$27=""),"",$O27-'Current Pricing'!$M$27) -> -0.01875 | R27: =IF(OR($H27="",$I27=""),"",$I27-$H27) -> -10 | S27: SEEDED with current price — source gave no new price for this distributor. Edit.
A28: Angry Orchard 5.2 | B28: 5.2 | C28: Suggested (Boston Beer) | D28: ='Current Pricing'!$D$28 -> 48.12 | E28: 49.62 | F28: =IF(OR($D28="",$E28=""),"",$E28-$D28) -> 1.5 | G28: 0 | H28: 79 | I28: 76 | J28: =IF($E28="","",IF(UPPER(Assumptions!$B$6)="Y",$E28-$G28,$E28)) -> 49.62 | K28: =IF(OR($H28="",$J28=""),"",$H28-$J28) -> 29.38 | L28: =IF(OR($K28="",$H28=""),"",IFERROR($K28/$H28,"")) -> 0.37189873 | M28: =IF($E28="","",IF(UPPER(Assumptions!$B$7)="Y",$E28-$G28,$E28)) -> 49.62 | N28: =IF(OR($I28="",$M28=""),"",$I28-$M28) -> 26.38 | O28: =IF(OR($N28="",$I28=""),"",IFERROR($N28/$I28,"")) -> 0.34710526 | P28: =IF(OR($L28="",'Current Pricing'!$J$28=""),"",$L28-'Current Pricing'!$J$28) -> -0.0031662009 | Q28: =IF(OR($O28="",'Current Pricing'!$M$28=""),"",$O28-'Current Pricing'!$M$28) -> 0.0062833453 | R28: =IF(OR($H28="",$I28=""),"",$I28-$H28) -> -3 | S28: New suggested frontline / best price from the source file.
A29: Dogfish Head 15.5 | B29: 15.5 | C29: Kohler | D29: ='Current Pricing'!$D$29 -> 121.95 | E29: 124.45 | F29: =IF(OR($D29="",$E29=""),"",$E29-$D29) -> 2.5 | G29: 0 | H29: 185 | I29: 180 | J29: =IF($E29="","",IF(UPPER(Assumptions!$B$6)="Y",$E29-$G29,$E29)) -> 124.45 | K29: =IF(OR($H29="",$J29=""),"",$H29-$J29) -> 60.55 | L29: =IF(OR($K29="",$H29=""),"",IFERROR($K29/$H29,"")) -> 0.3272973 | M29: =IF($E29="","",IF(UPPER(Assumptions!$B$7)="Y",$E29-$G29,$E29)) -> 124.45 | N29: =IF(OR($I29="",$M29=""),"",$I29-$M29) -> 55.55 | O29: =IF(OR($N29="",$I29=""),"",IFERROR($N29/$I29,"")) -> 0.30861111 | P29: =IF(OR($L29="",'Current Pricing'!$J$29=""),"",$L29-'Current Pricing'!$J$29) -> -0.013513514 | Q29: =IF(OR($O29="",'Current Pricing'!$M$29=""),"",$O29-'Current Pricing'!$M$29) -> -0.013888889 | R29: =IF(OR($H29="",$I29=""),"",$I29-$H29) -> -5 | S29: SEEDED with current price — source gave no new price for this distributor. Edit.
A30: Dogfish Head 15.5 | B30: 15.5 | C30: Peerless | D30: ='Current Pricing'!$D$30 -> 121.95 | E30: 124.45 | F30: =IF(OR($D30="",$E30=""),"",$E30-$D30) -> 2.5 | G30: 0 | H30: 209 | I30: 188 | J30: =IF($E30="","",IF(UPPER(Assumptions!$B$6)="Y",$E30-$G30,$E30)) -> 124.45 | K30: =IF(OR($H30="",$J30=""),"",$H30-$J30) -> 84.55 | L30: =IF(OR($K30="",$H30=""),"",IFERROR($K30/$H30,"")) -> 0.40454545 | M30: =IF($E30="","",IF(UPPER(Assumptions!$B$7)="Y",$E30-$G30,$E30)) -> 124.45 | N30: =IF(OR($I30="",$M30=""),"",$I30-$M30) -> 63.55 | O30: =IF(OR($N30="",$I30=""),"",IFERROR($N30/$I30,"")) -> 0.33803191 | P30: =IF(OR($L30="",'Current Pricing'!$J$30=""),"",$L30-'Current Pricing'!$J$30) -> -0.011961722 | Q30: =IF(OR($O30="",'Current Pricing'!$M$30=""),"",$O30-'Current Pricing'!$M$30) -> -0.013297872 | R30: =IF(OR($H30="",$I30=""),"",$I30-$H30) -> -21 | S30: SEEDED with current price — source gave no new price for this distributor. Edit.
A31: Dogfish Head 15.5 | B31: 15.5 | C31: Shore Point | D31: ='Current Pricing'!$D$31 -> 121.95 | E31: 124.45 | F31: =IF(OR($D31="",$E31=""),"",$E31-$D31) -> 2.5 | G31: 0 | H31: 203 | I31: 188 | J31: =IF($E31="","",IF(UPPER(Assumptions!$B$6)="Y",$E31-$G31,$E31)) -> 124.45 | K31: =IF(OR($H31="",$J31=""),"",$H31-$J31) -> 78.55 | L31: =IF(OR($K31="",$H31=""),"",IFERROR($K31/$H31,"")) -> 0.38694581 | M31: =IF($E31="","",IF(UPPER(Assumptions!$B$7)="Y",$E31-$G31,$E31)) -> 124.45 | N31: =IF(OR($I31="",$M31=""),"",$I31-$M31) -> 63.55 | O31: =IF(OR($N31="",$I31=""),"",IFERROR($N31/$I31,"")) -> 0.33803191 | P31: =IF(OR($L31="",'Current Pricing'!$J$31=""),"",$L31-'Current Pricing'!$J$31) -> -0.012315271 | Q31: =IF(OR($O31="",'Current Pricing'!$M$31=""),"",$O31-'Current Pricing'!$M$31) -> -0.013297872 | R31: =IF(OR($H31="",$I31=""),"",$I31-$H31) -> -15 | S31: SEEDED with current price — source gave no new price for this distributor. Edit.
A32: Dogfish Head 15.5 | B32: 15.5 | C32: Suggested (Boston Beer) | D32: ='Current Pricing'!$D$32 -> 121.95 | E32: 124.45 | F32: =IF(OR($D32="",$E32=""),"",$E32-$D32) -> 2.5 | G32: 0 | H32: 194 | I32: 167 | J32: =IF($E32="","",IF(UPPER(Assumptions!$B$6)="Y",$E32-$G32,$E32)) -> 124.45 | K32: =IF(OR($H32="",$J32=""),"",$H32-$J32) -> 69.55 | L32: =IF(OR($K32="",$H32=""),"",IFERROR($K32/$H32,"")) -> 0.35850515 | M32: =IF($E32="","",IF(UPPER(Assumptions!$B$7)="Y",$E32-$G32,$E32)) -> 124.45 | N32: =IF(OR($I32="",$M32=""),"",$I32-$M32) -> 42.55 | O32: =IF(OR($N32="",$I32=""),"",IFERROR($N32/$I32,"")) -> 0.25479042 | P32: =IF(OR($L32="",'Current Pricing'!$J$32=""),"",$L32-'Current Pricing'!$J$32) -> 0.0037432499 | Q32: =IF(OR($O32="",'Current Pricing'!$M$32=""),"",$O32-'Current Pricing'!$M$32) -> 0.012243835 | R32: =IF(OR($H32="",$I32=""),"",$I32-$H32) -> -27 | S32: New suggested frontline / best price from the source file.
A33: Dogfish Head 5.2 | B33: 5.2 | C33: Kohler | D33: ='Current Pricing'!$D$33 -> 59.68 | E33: 61.18 | F33: =IF(OR($D33="",$E33=""),"",$E33-$D33) -> 1.5 | G33: 0 | H33: 90 | I33: 87 | J33: =IF($E33="","",IF(UPPER(Assumptions!$B$6)="Y",$E33-$G33,$E33)) -> 61.18 | K33: =IF(OR($H33="",$J33=""),"",$H33-$J33) -> 28.82 | L33: =IF(OR($K33="",$H33=""),"",IFERROR($K33/$H33,"")) -> 0.32022222 | M33: =IF($E33="","",IF(UPPER(Assumptions!$B$7)="Y",$E33-$G33,$E33)) -> 61.18 | N33: =IF(OR($I33="",$M33=""),"",$I33-$M33) -> 25.82 | O33: =IF(OR($N33="",$I33=""),"",IFERROR($N33/$I33,"")) -> 0.29678161 | P33: =IF(OR($L33="",'Current Pricing'!$J$33=""),"",$L33-'Current Pricing'!$J$33) -> -0.016666667 | Q33: =IF(OR($O33="",'Current Pricing'!$M$33=""),"",$O33-'Current Pricing'!$M$33) -> -0.017241379 | R33: =IF(OR($H33="",$I33=""),"",$I33-$H33) -> -3 | S33: SEEDED with current price — source gave no new price for this distributor. Edit.
A34: Dogfish Head 5.2 | B34: 5.2 | C34: Peerless | D34: ='Current Pricing'!$D$34 -> 59.68 | E34: 61.18 | F34: =IF(OR($D34="",$E34=""),"",$E34-$D34) -> 1.5 | G34: 0 | H34: 97.5 | I34: 88.5 | J34: =IF($E34="","",IF(UPPER(Assumptions!$B$6)="Y",$E34-$G34,$E34)) -> 61.18 | K34: =IF(OR($H34="",$J34=""),"",$H34-$J34) -> 36.32 | L34: =IF(OR($K34="",$H34=""),"",IFERROR($K34/$H34,"")) -> 0.37251282 | M34: =IF($E34="","",IF(UPPER(Assumptions!$B$7)="Y",$E34-$G34,$E34)) -> 61.18 | N34: =IF(OR($I34="",$M34=""),"",$I34-$M34) -> 27.32 | O34: =IF(OR($N34="",$I34=""),"",IFERROR($N34/$I34,"")) -> 0.30870056 | P34: =IF(OR($L34="",'Current Pricing'!$J$34=""),"",$L34-'Current Pricing'!$J$34) -> -0.015384615 | Q34: =IF(OR($O34="",'Current Pricing'!$M$34=""),"",$O34-'Current Pricing'!$M$34) -> -0.016949153 | R34: =IF(OR($H34="",$I34=""),"",$I34-$H34) -> -9 | S34: SEEDED with current price — source gave no new price for this distributor. Edit.
A35: Dogfish Head 5.2 | B35: 5.2 | C35: Shore Point | D35: ='Current Pricing'!$D$35 -> 59.68 | E35: 61.18 | F35: =IF(OR($D35="",$E35=""),"",$E35-$D35) -> 1.5 | G35: 0 | H35: 98 | I35: 94 | J35: =IF($E35="","",IF(UPPER(Assumptions!$B$6)="Y",$E35-$G35,$E35)) -> 61.18 | K35: =IF(OR($H35="",$J35=""),"",$H35-$J35) -> 36.82 | L35: =IF(OR($K35="",$H35=""),"",IFERROR($K35/$H35,"")) -> 0.37571429 | M35: =IF($E35="","",IF(UPPER(Assumptions!$B$7)="Y",$E35-$G35,$E35)) -> 61.18 | N35: =IF(OR($I35="",$M35=""),"",$I35-$M35) -> 32.82 | O35: =IF(OR($N35="",$I35=""),"",IFERROR($N35/$I35,"")) -> 0.34914894 | P35: =IF(OR($L35="",'Current Pricing'!$J$35=""),"",$L35-'Current Pricing'!$J$35) -> -0.015306122 | Q35: =IF(OR($O35="",'Current Pricing'!$M$35=""),"",$O35-'Current Pricing'!$M$35) -> -0.015957447 | R35: =IF(OR($H35="",$I35=""),"",$I35-$H35) -> -4 | S35: SEEDED with current price — source gave no new price for this distributor. Edit.
A36: Dogfish Head 5.2 | B36: 5.2 | C36: Suggested (Boston Beer) | D36: ='Current Pricing'!$D$36 -> 59.68 | E36: 61.18 | F36: =IF(OR($D36="",$E36=""),"",$E36-$D36) -> 1.5 | G36: 0 | H36: 92 | I36: 89 | J36: =IF($E36="","",IF(UPPER(Assumptions!$B$6)="Y",$E36-$G36,$E36)) -> 61.18 | K36: =IF(OR($H36="",$J36=""),"",$H36-$J36) -> 30.82 | L36: =IF(OR($K36="",$H36=""),"",IFERROR($K36/$H36,"")) -> 0.335 | M36: =IF($E36="","",IF(UPPER(Assumptions!$B$7)="Y",$E36-$G36,$E36)) -> 61.18 | N36: =IF(OR($I36="",$M36=""),"",$I36-$M36) -> 27.82 | O36: =IF(OR($N36="",$I36=""),"",IFERROR($N36/$I36,"")) -> 0.31258427 | P36: =IF(OR($L36="",'Current Pricing'!$J$36=""),"",$L36-'Current Pricing'!$J$36) -> 0.020977011 | Q36: =IF(OR($O36="",'Current Pricing'!$M$36=""),"",$O36-'Current Pricing'!$M$36) -> 0.031620414 | R36: =IF(OR($H36="",$I36=""),"",$I36-$H36) -> -3 | S36: New suggested frontline / best price from the source file.
A37: Truly 15.5 | B37: 15.5 | C37: Kohler | D37: ='Current Pricing'!$D$37 -> 114.11 | E37: 116.61 | F37: =IF(OR($D37="",$E37=""),"",$E37-$D37) -> 2.5 | G37: 35.4 | H37: 168 | I37: 115 | J37: =IF($E37="","",IF(UPPER(Assumptions!$B$6)="Y",$E37-$G37,$E37)) -> 116.61 | K37: =IF(OR($H37="",$J37=""),"",$H37-$J37) -> 51.39 | L37: =IF(OR($K37="",$H37=""),"",IFERROR($K37/$H37,"")) -> 0.30589286 | M37: =IF($E37="","",IF(UPPER(Assumptions!$B$7)="Y",$E37-$G37,$E37)) -> 81.21 | N37: =IF(OR($I37="",$M37=""),"",$I37-$M37) -> 33.79 | O37: =IF(OR($N37="",$I37=""),"",IFERROR($N37/$I37,"")) -> 0.29382609 | P37: =IF(OR($L37="",'Current Pricing'!$J$37=""),"",$L37-'Current Pricing'!$J$37) -> -0.014880952 | Q37: =IF(OR($O37="",'Current Pricing'!$M$37=""),"",$O37-'Current Pricing'!$M$37) -> -0.02173913 | R37: =IF(OR($H37="",$I37=""),"",$I37-$H37) -> -53 | S37: SEEDED with current price — source gave no new price for this distributor. Edit. Current $35.40 DA carried forward.
A38: Truly 15.5 | B38: 15.5 | C38: Peerless | D38: ='Current Pricing'!$D$38 -> 114.11 | E38: 116.61 | F38: =IF(OR($D38="",$E38=""),"",$E38-$D38) -> 2.5 | J38: =IF($E38="","",IF(UPPER(Assumptions!$B$6)="Y",$E38-$G38,$E38)) -> 116.61 | K38: =IF(OR($H38="",$J38=""),"",$H38-$J38) | L38: =IF(OR($K38="",$H38=""),"",IFERROR($K38/$H38,"")) | M38: =IF($E38="","",IF(UPPER(Assumptions!$B$7)="Y",$E38-$G38,$E38)) -> 116.61 | N38: =IF(OR($I38="",$M38=""),"",$I38-$M38) | O38: =IF(OR($N38="",$I38=""),"",IFERROR($N38/$I38,"")) | P38: =IF(OR($L38="",'Current Pricing'!$J$38=""),"",$L38-'Current Pricing'!$J$38) | Q38: =IF(OR($O38="",'Current Pricing'!$M$38=""),"",$O38-'Current Pricing'!$M$38) | R38: =IF(OR($H38="",$I38=""),"",$I38-$H38) | S38: Peerless does not carry this SKU ("NA" in source).
A39: Truly 15.5 | B39: 15.5 | C39: Shore Point | D39: ='Current Pricing'!$D$39 -> 114.11 | E39: 116.61 | F39: =IF(OR($D39="",$E39=""),"",$E39-$D39) -> 2.5 | G39: 0 | H39: 207 | I39: 188 | J39: =IF($E39="","",IF(UPPER(Assumptions!$B$6)="Y",$E39-$G39,$E39)) -> 116.61 | K39: =IF(OR($H39="",$J39=""),"",$H39-$J39) -> 90.39 | L39: =IF(OR($K39="",$H39=""),"",IFERROR($K39/$H39,"")) -> 0.43666667 | M39: =IF($E39="","",IF(UPPER(Assumptions!$B$7)="Y",$E39-$G39,$E39)) -> 116.61 | N39: =IF(OR($I39="",$M39=""),"",$I39-$M39) -> 71.39 | O39: =IF(OR($N39="",$I39=""),"",IFERROR($N39/$I39,"")) -> 0.37973404 | P39: =IF(OR($L39="",'Current Pricing'!$J$39=""),"",$L39-'Current Pricing'!$J$39) -> -0.012077295 | Q39: =IF(OR($O39="",'Current Pricing'!$M$39=""),"",$O39-'Current Pricing'!$M$39) -> -0.013297872 | R39: =IF(OR($H39="",$I39=""),"",$I39-$H39) -> -19 | S39: SEEDED with current price — source gave no new price for this distributor. Edit.
A40: Truly 15.5 | B40: 15.5 | C40: Suggested (Boston Beer) | D40: ='Current Pricing'!$D$40 -> 114.11 | E40: 116.61 | F40: =IF(OR($D40="",$E40=""),"",$E40-$D40) -> 2.5 | G40: 35.4 | H40: 189 | I40: 120 | J40: =IF($E40="","",IF(UPPER(Assumptions!$B$6)="Y",$E40-$G40,$E40)) -> 116.61 | K40: =IF(OR($H40="",$J40=""),"",$H40-$J40) -> 72.39 | L40: =IF(OR($K40="",$H40=""),"",IFERROR($K40/$H40,"")) -> 0.38301587 | M40: =IF($E40="","",IF(UPPER(Assumptions!$B$7)="Y",$E40-$G40,$E40)) -> 81.21 | N40: =IF(OR($I40="",$M40=""),"",$I40-$M40) -> 38.79 | O40: =IF(OR($N40="",$I40=""),"",IFERROR($N40/$I40,"")) -> 0.32325 | P40: =IF(OR($L40="",'Current Pricing'!$J$40=""),"",$L40-'Current Pricing'!$J$40) -> 0.0031789165 | Q40: =IF(OR($O40="",'Current Pricing'!$M$40=""),"",$O40-'Current Pricing'!$M$40) -> 0.0076847826 | R40: =IF(OR($H40="",$I40=""),"",$I40-$H40) -> -69 | S40: New suggested frontline / best price from the source file. Source annotates a $35.40 DA — broken out to col G.
A41: Truly 5.2 | B41: 5.2 | C41: Kohler | D41: ='Current Pricing'!$D$41 -> 48.12 | E41: 49.62 | F41: =IF(OR($D41="",$E41=""),"",$E41-$D41) -> 1.5 | G41: 0 | H41: 70 | I41: 68 | J41: =IF($E41="","",IF(UPPER(Assumptions!$B$6)="Y",$E41-$G41,$E41)) -> 49.62 | K41: =IF(OR($H41="",$J41=""),"",$H41-$J41) -> 20.38 | L41: =IF(OR($K41="",$H41=""),"",IFERROR($K41/$H41,"")) -> 0.29114286 | M41: =IF($E41="","",IF(UPPER(Assumptions!$B$7)="Y",$E41-$G41,$E41)) -> 49.62 | N41: =IF(OR($I41="",$M41=""),"",$I41-$M41) -> 18.38 | O41: =IF(OR($N41="",$I41=""),"",IFERROR($N41/$I41,"")) -> 0.27029412 | P41: =IF(OR($L41="",'Current Pricing'!$J$41=""),"",$L41-'Current Pricing'!$J$41) -> -0.021428571 | Q41: =IF(OR($O41="",'Current Pricing'!$M$41=""),"",$O41-'Current Pricing'!$M$41) -> -0.022058824 | R41: =IF(OR($H41="",$I41=""),"",$I41-$H41) -> -2 | S41: SEEDED with current price — source gave no new price for this distributor. Edit.
A42: Truly 5.2 | B42: 5.2 | C42: Peerless | D42: ='Current Pricing'!$D$42 -> 48.12 | E42: 49.62 | F42: =IF(OR($D42="",$E42=""),"",$E42-$D42) -> 1.5 | G42: 0 | H42: 97.5 | I42: 88.5 | J42: =IF($E42="","",IF(UPPER(Assumptions!$B$6)="Y",$E42-$G42,$E42)) -> 49.62 | K42: =IF(OR($H42="",$J42=""),"",$H42-$J42) -> 47.88 | L42: =IF(OR($K42="",$H42=""),"",IFERROR($K42/$H42,"")) -> 0.49107692 | M42: =IF($E42="","",IF(UPPER(Assumptions!$B$7)="Y",$E42-$G42,$E42)) -> 49.62 | N42: =IF(OR($I42="",$M42=""),"",$I42-$M42) -> 38.88 | O42: =IF(OR($N42="",$I42=""),"",IFERROR($N42/$I42,"")) -> 0.43932203 | P42: =IF(OR($L42="",'Current Pricing'!$J$42=""),"",$L42-'Current Pricing'!$J$42) -> -0.015384615 | Q42: =IF(OR($O42="",'Current Pricing'!$M$42=""),"",$O42-'Current Pricing'!$M$42) -> -0.016949153 | R42: =IF(OR($H42="",$I42=""),"",$I42-$H42) -> -9 | S42: SEEDED with current price — source gave no new price for this distributor. Edit.
A43: Truly 5.2 | B43: 5.2 | C43: Shore Point | D43: ='Current Pricing'!$D$43 -> 48.12 | E43: 49.62 | F43: =IF(OR($D43="",$E43=""),"",$E43-$D43) -> 1.5 | G43: 0 | H43: 90 | I43: 80 | J43: =IF($E43="","",IF(UPPER(Assumptions!$B$6)="Y",$E43-$G43,$E43)) -> 49.62 | K43: =IF(OR($H43="",$J43=""),"",$H43-$J43) -> 40.38 | L43: =IF(OR($K43="",$H43=""),"",IFERROR($K43/$H43,"")) -> 0.44866667 | M43: =IF($E43="","",IF(UPPER(Assumptions!$B$7)="Y",$E43-$G43,$E43)) -> 49.62 | N43: =IF(OR($I43="",$M43=""),"",$I43-$M43) -> 30.38 | O43: =IF(OR($N43="",$I43=""),"",IFERROR($N43/$I43,"")) -> 0.37975 | P43: =IF(OR($L43="",'Current Pricing'!$J$43=""),"",$L43-'Current Pricing'!$J$43) -> -0.016666667 | Q43: =IF(OR($O43="",'Current Pricing'!$M$43=""),"",$O43-'Current Pricing'!$M$43) -> -0.01875 | R43: =IF(OR($H43="",$I43=""),"",$I43-$H43) -> -10 | S43: SEEDED with current price — source gave no new price for this distributor. Edit.
A44: Truly 5.2 | B44: 5.2 | C44: Suggested (Boston Beer) | D44: ='Current Pricing'!$D$44 -> 48.12 | E44: 49.62 | F44: =IF(OR($D44="",$E44=""),"",$E44-$D44) -> 1.5 | G44: 0 | H44: 79 | I44: 76 | J44: =IF($E44="","",IF(UPPER(Assumptions!$B$6)="Y",$E44-$G44,$E44)) -> 49.62 | K44: =IF(OR($H44="",$J44=""),"",$H44-$J44) -> 29.38 | L44: =IF(OR($K44="",$H44=""),"",IFERROR($K44/$H44,"")) -> 0.37189873 | M44: =IF($E44="","",IF(UPPER(Assumptions!$B$7)="Y",$E44-$G44,$E44)) -> 49.62 | N44: =IF(OR($I44="",$M44=""),"",$I44-$M44) -> 26.38 | O44: =IF(OR($N44="",$I44=""),"",IFERROR($N44/$I44,"")) -> 0.34710526 | P44: =IF(OR($L44="",'Current Pricing'!$J$44=""),"",$L44-'Current Pricing'!$J$44) -> -0.0031662009 | Q44: =IF(OR($O44="",'Current Pricing'!$M$44=""),"",$O44-'Current Pricing'!$M$44) -> 0.065314218 | R44: =IF(OR($H44="",$I44=""),"",$I44-$H44) -> -3 | S44: New suggested frontline / best price from the source file.
A46: Source: Boston_Pricing_Analysis.xlsx, Sheet1 rows 13–23 (new book). Only new laid-in cost and new SUGGESTED prices exist in the source; distributor new prices are seeded and editable.

Sheet Summary
A1: Summary — Kohler vs the Market, by Product
A2: Every figure links live to Current Pricing / New Pricing. Change a price on those tabs and this tab moves with it.
A4: A. FRONTLINE — CURRENT BOOK
A5: Frontline price and frontline margin % at today's laid-in cost. Positive "Kohler vs" = Kohler is priced ABOVE that distributor.
A6: Product | B6: Keg Size | C6: Kohler Price | D6: Kohler Mgn % | E6: Peerless Price | F6: Peerless Mgn % | G6: Shore Point Price | H6: Shore Pt Mgn % | I6: Suggested Price | J6: Suggested Mgn % | K6: Kohler vs Peerless ($) | L6: Kohler vs Shore Pt ($) | M6: Kohler vs Suggested ($) | N6: Kohler Mgn % vs Competitor Avg
A7: Sam Adams 15.5 | B7: 15.5 | C7: =IF('Current Pricing'!$F$5="","",'Current Pricing'!$F$5) -> 185 | D7: =IF('Current Pricing'!$J$5="","",'Current Pricing'!$J$5) -> 0.38048649 | E7: =IF('Current Pricing'!$F$6="","",'Current Pricing'!$F$6) -> 209 | F7: =IF('Current Pricing'!$J$6="","",'Current Pricing'!$J$6) -> 0.45162679 | G7: =IF('Current Pricing'!$F$7="","",'Current Pricing'!$F$7) -> 207 | H7: =IF('Current Pricing'!$J$7="","",'Current Pricing'!$J$7) -> 0.4463285 | I7: =IF('Current Pricing'!$F$8="","",'Current Pricing'!$F$8) -> 185 | J7: =IF('Current Pricing'!$J$8="","",'Current Pricing'!$J$8) -> 0.38048649 | K7: =IF(OR($C7="",$E7=""),"",$C7-$E7) -> -24 | L7: =IF(OR($C7="",$G7=""),"",$C7-$G7) -> -22 | M7: =IF(OR($C7="",$I7=""),"",$C7-$I7) -> 0 | N7: =IF($D7="","",IFERROR($D7-AVERAGE($F7,$H7),"")) -> -0.068491162
A8: Sam Adams 5.2 | B8: 5.2 | C8: =IF('Current Pricing'!$F$9="","",'Current Pricing'!$F$9) -> 80 | D8: =IF('Current Pricing'!$J$9="","",'Current Pricing'!$J$9) -> 0.3985 | E8: =IF('Current Pricing'!$F$10="","",'Current Pricing'!$F$10) -> 97.5 | F8: =IF('Current Pricing'!$J$10="","",'Current Pricing'!$J$10) -> 0.50646154 | G8: =IF('Current Pricing'!$F$11="","",'Current Pricing'!$F$11) -> 90 | H8: =IF('Current Pricing'!$J$11="","",'Current Pricing'!$J$11) -> 0.46533333 | I8: =IF('Current Pricing'!$F$12="","",'Current Pricing'!$F$12) -> 73 | J8: =IF('Current Pricing'!$J$12="","",'Current Pricing'!$J$12) -> 0.34082192 | K8: =IF(OR($C8="",$E8=""),"",$C8-$E8) -> -17.5 | L8: =IF(OR($C8="",$G8=""),"",$C8-$G8) -> -10 | M8: =IF(OR($C8="",$I8=""),"",$C8-$I8) -> 7 | N8: =IF($D8="","",IFERROR($D8-AVERAGE($F8,$H8),"")) -> -0.087397436
A9: Twisted Tea 15.5 | B9: 15.5 | C9: =IF('Current Pricing'!$F$13="","",'Current Pricing'!$F$13) -> 185 | D9: =IF('Current Pricing'!$J$13="","",'Current Pricing'!$J$13) -> 0.38318919 | E9: =IF('Current Pricing'!$F$14="","",'Current Pricing'!$F$14) -> 209 | F9: =IF('Current Pricing'!$J$14="","",'Current Pricing'!$J$14) -> 0.45401914 | G9: =IF('Current Pricing'!$F$15="","",'Current Pricing'!$F$15) -> 207 | H9: =IF('Current Pricing'!$J$15="","",'Current Pricing'!$J$15) -> 0.44874396 | I9: =IF('Current Pricing'!$F$16="","",'Current Pricing'!$F$16) -> 184 | J9: =IF('Current Pricing'!$J$16="","",'Current Pricing'!$J$16) -> 0.37983696 | K9: =IF(OR($C9="",$E9=""),"",$C9-$E9) -> -24 | L9: =IF(OR($C9="",$G9=""),"",$C9-$G9) -> -22 | M9: =IF(OR($C9="",$I9=""),"",$C9-$I9) -> 1 | N9: =IF($D9="","",IFERROR($D9-AVERAGE($F9,$H9),"")) -> -0.068192361
A10: Twisted Tea 5.2 | B10: 5.2 | C10: =IF('Current Pricing'!$F$17="","",'Current Pricing'!$F$17) -> 77 | D10: =IF('Current Pricing'!$J$17="","",'Current Pricing'!$J$17) -> 0.37506494 | E10: =IF('Current Pricing'!$F$18="","",'Current Pricing'!$F$18) -> 97.5 | F10: =IF('Current Pricing'!$J$18="","",'Current Pricing'!$J$18) -> 0.50646154 | G10: =IF('Current Pricing'!$F$19="","",'Current Pricing'!$F$19) -> 90 | H10: =IF('Current Pricing'!$J$19="","",'Current Pricing'!$J$19) -> 0.46533333 | I10: =IF('Current Pricing'!$F$20="","",'Current Pricing'!$F$20) -> 77 | J10: =IF('Current Pricing'!$J$20="","",'Current Pricing'!$J$20) -> 0.37506494 | K10: =IF(OR($C10="",$E10=""),"",$C10-$E10) -> -20.5 | L10: =IF(OR($C10="",$G10=""),"",$C10-$G10) -> -13 | M10: =IF(OR($C10="",$I10=""),"",$C10-$I10) -> 0 | N10: =IF($D10="","",IFERROR($D10-AVERAGE($F10,$H10),"")) -> -0.1108325
A11: Angry Orchard 15.5 | B11: 15.5 | C11: =IF('Current Pricing'!$F$21="","",'Current Pricing'!$F$21) -> 182 | D11: =IF('Current Pricing'!$J$21="","",'Current Pricing'!$J$21) -> 0.37027473 | E11: =IF('Current Pricing'!$F$22="","",'Current Pricing'!$F$22) -> 200 | F11: =IF('Current Pricing'!$J$22="","",'Current Pricing'!$J$22) -> 0.42695 | G11: =IF('Current Pricing'!$F$23="","",'Current Pricing'!$F$23) -> 207 | H11: =IF('Current Pricing'!$J$23="","",'Current Pricing'!$J$23) -> 0.4463285 | I11: =IF('Current Pricing'!$F$24="","",'Current Pricing'!$F$24) -> 185 | J11: =IF('Current Pricing'!$J$24="","",'Current Pricing'!$J$24) -> 0.38048649 | K11: =IF(OR($C11="",$E11=""),"",$C11-$E11) -> -18 | L11: =IF(OR($C11="",$G11=""),"",$C11-$G11) -> -25 | M11: =IF(OR($C11="",$I11=""),"",$C11-$I11) -> -3 | N11: =IF($D11="","",IFERROR($D11-AVERAGE($F11,$H11),"")) -> -0.066364526
A12: Angry Orchard 5.2 | B12: 5.2 | C12: =IF('Current Pricing'!$F$25="","",'Current Pricing'!$F$25) -> 75 | D12: =IF('Current Pricing'!$J$25="","",'Current Pricing'!$J$25) -> 0.3584 | E12: =IF('Current Pricing'!$F$26="","",'Current Pricing'!$F$26) -> 95 | F12: =IF('Current Pricing'!$J$26="","",'Current Pricing'!$J$26) -> 0.49347368 | G12: =IF('Current Pricing'!$F$27="","",'Current Pricing'!$F$27) -> 90 | H12: =IF('Current Pricing'!$J$27="","",'Current Pricing'!$J$27) -> 0.46533333 | I12: =IF('Current Pricing'!$F$28="","",'Current Pricing'!$F$28) -> 77 | J12: =IF('Current Pricing'!$J$28="","",'Current Pricing'!$J$28) -> 0.37506494 | K12: =IF(OR($C12="",$E12=""),"",$C12-$E12) -> -20 | L12: =IF(OR($C12="",$G12=""),"",$C12-$G12) -> -15 | M12: =IF(OR($C12="",$I12=""),"",$C12-$I12) -> -2 | N12: =IF($D12="","",IFERROR($D12-AVERAGE($F12,$H12),"")) -> -0.12100351
A13: Dogfish Head 15.5 | B13: 15.5 | C13: =IF('Current Pricing'!$F$29="","",'Current Pricing'!$F$29) -> 185 | D13: =IF('Current Pricing'!$J$29="","",'Current Pricing'!$J$29) -> 0.34081081 | E13: =IF('Current Pricing'!$F$30="","",'Current Pricing'!$F$30) -> 209 | F13: =IF('Current Pricing'!$J$30="","",'Current Pricing'!$J$30) -> 0.41650718 | G13: =IF('Current Pricing'!$F$31="","",'Current Pricing'!$F$31) -> 203 | H13: =IF('Current Pricing'!$J$31="","",'Current Pricing'!$J$31) -> 0.39926108 | I13: =IF('Current Pricing'!$F$32="","",'Current Pricing'!$F$32) -> 189 | J13: =IF('Current Pricing'!$J$32="","",'Current Pricing'!$J$32) -> 0.3547619 | K13: =IF(OR($C13="",$E13=""),"",$C13-$E13) -> -24 | L13: =IF(OR($C13="",$G13=""),"",$C13-$G13) -> -18 | M13: =IF(OR($C13="",$I13=""),"",$C13-$I13) -> -4 | N13: =IF($D13="","",IFERROR($D13-AVERAGE($F13,$H13),"")) -> -0.06707332
A14: Dogfish Head 5.2 | B14: 5.2 | C14: =IF('Current Pricing'!$F$33="","",'Current Pricing'!$F$33) -> 90 | D14: =IF('Current Pricing'!$J$33="","",'Current Pricing'!$J$33) -> 0.33688889 | E14: =IF('Current Pricing'!$F$34="","",'Current Pricing'!$F$34) -> 97.5 | F14: =IF('Current Pricing'!$J$34="","",'Current Pricing'!$J$34) -> 0.38789744 | G14: =IF('Current Pricing'!$F$35="","",'Current Pricing'!$F$35) -> 98 | H14: =IF('Current Pricing'!$J$35="","",'Current Pricing'!$J$35) -> 0.39102041 | I14: =IF('Current Pricing'!$F$36="","",'Current Pricing'!$F$36) -> 87 | J14: =IF('Current Pricing'!$J$36="","",'Current Pricing'!$J$36) -> 0.31402299 | K14: =IF(OR($C14="",$E14=""),"",$C14-$E14) -> -7.5 | L14: =IF(OR($C14="",$G14=""),"",$C14-$G14) -> -8 | M14: =IF(OR($C14="",$I14=""),"",$C14-$I14) -> 3 | N14: =IF($D14="","",IFERROR($D14-AVERAGE($F14,$H14),"")) -> -0.052570033
A15: Truly 15.5 | B15: 15.5 | C15: =IF('Current Pricing'!$F$37="","",'Current Pricing'!$F$37) -> 168 | D15: =IF('Current Pricing'!$J$37="","",'Current Pricing'!$J$37) -> 0.32077381 | E15: =IF('Current Pricing'!$F$38="","",'Current Pricing'!$F$38) | F15: =IF('Current Pricing'!$J$38="","",'Current Pricing'!$J$38) | G15: =IF('Current Pricing'!$F$39="","",'Current Pricing'!$F$39) -> 207 | H15: =IF('Current Pricing'!$J$39="","",'Current Pricing'!$J$39) -> 0.44874396 | I15: =IF('Current Pricing'!$F$40="","",'Current Pricing'!$F$40) -> 184 | J15: =IF('Current Pricing'!$J$40="","",'Current Pricing'!$J$40) -> 0.37983696 | K15: =IF(OR($C15="",$E15=""),"",$C15-$E15) | L15: =IF(OR($C15="",$G15=""),"",$C15-$G15) -> -39 | M15: =IF(OR($C15="",$I15=""),"",$C15-$I15) -> -16 | N15: =IF($D15="","",IFERROR($D15-AVERAGE($F15,$H15),"")) -> -0.12797015
A16: Truly 5.2 | B16: 5.2 | C16: =IF('Current Pricing'!$F$41="","",'Current Pricing'!$F$41) -> 70 | D16: =IF('Current Pricing'!$J$41="","",'Current Pricing'!$J$41) -> 0.31257143 | E16: =IF('Current Pricing'!$F$42="","",'Current Pricing'!$F$42) -> 97.5 | F16: =IF('Current Pricing'!$J$42="","",'Current Pricing'!$J$42) -> 0.50646154 | G16: =IF('Current Pricing'!$F$43="","",'Current Pricing'!$F$43) -> 90 | H16: =IF('Current Pricing'!$J$43="","",'Current Pricing'!$J$43) -> 0.46533333 | I16: =IF('Current Pricing'!$F$44="","",'Current Pricing'!$F$44) -> 77 | J16: =IF('Current Pricing'!$J$44="","",'Current Pricing'!$J$44) -> 0.37506494 | K16: =IF(OR($C16="",$E16=""),"",$C16-$E16) -> -27.5 | L16: =IF(OR($C16="",$G16=""),"",$C16-$G16) -> -20 | M16: =IF(OR($C16="",$I16=""),"",$C16-$I16) -> -7 | N16: =IF($D16="","",IFERROR($D16-AVERAGE($F16,$H16),"")) -> -0.17332601
A19: B. BEST PRICE — CURRENT BOOK
A20: Best (promotional) price and margin %, net of DA where one applies. Peerless / Shore Point DA is unknown and set to 0, so their margins here are understated.
A21: Product | B21: Keg Size | C21: Kohler Price | D21: Kohler Mgn % | E21: Peerless Price | F21: Peerless Mgn % | G21: Shore Point Price | H21: Shore Pt Mgn % | I21: Suggested Price | J21: Suggested Mgn % | K21: Kohler vs Peerless ($) | L21: Kohler vs Shore Pt ($) | M21: Kohler vs Suggested ($) | N21: Kohler Mgn % vs Competitor Avg
A22: Sam Adams 15.5 | B22: 15.5 | C22: =IF('Current Pricing'!$G$5="","",'Current Pricing'!$G$5) -> 175 | D22: =IF('Current Pricing'!$M$5="","",'Current Pricing'!$M$5) -> 0.34508571 | E22: =IF('Current Pricing'!$G$6="","",'Current Pricing'!$G$6) -> 188 | F22: =IF('Current Pricing'!$M$6="","",'Current Pricing'!$M$6) -> 0.39037234 | G22: =IF('Current Pricing'!$G$7="","",'Current Pricing'!$G$7) -> 188 | H22: =IF('Current Pricing'!$M$7="","",'Current Pricing'!$M$7) -> 0.39037234 | I22: =IF('Current Pricing'!$G$8="","",'Current Pricing'!$G$8) -> 169 | J22: =IF('Current Pricing'!$M$8="","",'Current Pricing'!$M$8) -> 0.32183432 | K22: =IF(OR($C22="",$E22=""),"",$C22-$E22) -> -13 | L22: =IF(OR($C22="",$G22=""),"",$C22-$G22) -> -13 | M22: =IF(OR($C22="",$I22=""),"",$C22-$I22) -> 6 | N22: =IF($D22="","",IFERROR($D22-AVERAGE($F22,$H22),"")) -> -0.045286626
A23: Sam Adams 5.2 | B23: 5.2 | C23: =IF('Current Pricing'!$G$9="","",'Current Pricing'!$G$9) -> 78 | D23: =IF('Current Pricing'!$M$9="","",'Current Pricing'!$M$9) -> 0.38307692 | E23: =IF('Current Pricing'!$G$10="","",'Current Pricing'!$G$10) -> 88.5 | F23: =IF('Current Pricing'!$M$10="","",'Current Pricing'!$M$10) -> 0.45627119 | G23: =IF('Current Pricing'!$G$11="","",'Current Pricing'!$G$11) -> 80 | H23: =IF('Current Pricing'!$M$11="","",'Current Pricing'!$M$11) -> 0.3985 | I23: =IF('Current Pricing'!$G$12="","",'Current Pricing'!$G$12) -> 63 | J23: =IF('Current Pricing'!$M$12="","",'Current Pricing'!$M$12) -> 0.23619048 | K23: =IF(OR($C23="",$E23=""),"",$C23-$E23) -> -10.5 | L23: =IF(OR($C23="",$G23=""),"",$C23-$G23) -> -2 | M23: =IF(OR($C23="",$I23=""),"",$C23-$I23) -> 15 | N23: =IF($D23="","",IFERROR($D23-AVERAGE($F23,$H23),"")) -> -0.04430867
A24: Twisted Tea 15.5 | B24: 15.5 | C24: =IF('Current Pricing'!$G$13="","",'Current Pricing'!$G$13) -> 175 | D24: =IF('Current Pricing'!$M$13="","",'Current Pricing'!$M$13) -> 0.34794286 | E24: =IF('Current Pricing'!$G$14="","",'Current Pricing'!$G$14) -> 188 | F24: =IF('Current Pricing'!$M$14="","",'Current Pricing'!$M$14) -> 0.39303191 | G24: =IF('Current Pricing'!$G$15="","",'Current Pricing'!$G$15) -> 188 | H24: =IF('Current Pricing'!$M$15="","",'Current Pricing'!$M$15) -> 0.39303191 | I24: =IF('Current Pricing'!$G$16="","",'Current Pricing'!$G$16) -> 168 | J24: =IF('Current Pricing'!$M$16="","",'Current Pricing'!$M$16) -> 0.32077381 | K24: =IF(OR($C24="",$E24=""),"",$C24-$E24) -> -13 | L24: =IF(OR($C24="",$G24=""),"",$C24-$G24) -> -13 | M24: =IF(OR($C24="",$I24=""),"",$C24-$I24) -> 7 | N24: =IF($D24="","",IFERROR($D24-AVERAGE($F24,$H24),"")) -> -0.045089058
A25: Twisted Tea 5.2 | B25: 5.2 | C25: =IF('Current Pricing'!$G$17="","",'Current Pricing'!$G$17) -> 58 | D25: =IF('Current Pricing'!$M$17="","",'Current Pricing'!$M$17) -> 0.32551724 | E25: =IF('Current Pricing'!$G$18="","",'Current Pricing'!$G$18) -> 88.5 | F25: =IF('Current Pricing'!$M$18="","",'Current Pricing'!$M$18) -> 0.45627119 | G25: =IF('Current Pricing'!$G$19="","",'Current Pricing'!$G$19) -> 80 | H25: =IF('Current Pricing'!$M$19="","",'Current Pricing'!$M$19) -> 0.3985 | I25: =IF('Current Pricing'!$G$20="","",'Current Pricing'!$G$20) -> 58 | J25: =IF('Current Pricing'!$M$20="","",'Current Pricing'!$M$20) -> 0.32551724 | K25: =IF(OR($C25="",$E25=""),"",$C25-$E25) -> -30.5 | L25: =IF(OR($C25="",$G25=""),"",$C25-$G25) -> -22 | M25: =IF(OR($C25="",$I25=""),"",$C25-$I25) -> 0 | N25: =IF($D25="","",IFERROR($D25-AVERAGE($F25,$H25),"")) -> -0.10186835
A26: Angry Orchard 15.5 | B26: 15.5 | C26: =IF('Current Pricing'!$G$21="","",'Current Pricing'!$G$21) -> 156 | D26: =IF('Current Pricing'!$M$21="","",'Current Pricing'!$M$21) -> 0.26532051 | E26: =IF('Current Pricing'!$G$22="","",'Current Pricing'!$G$22) -> 189 | F26: =IF('Current Pricing'!$M$22="","",'Current Pricing'!$M$22) -> 0.39359788 | G26: =IF('Current Pricing'!$G$23="","",'Current Pricing'!$G$23) -> 188 | H26: =IF('Current Pricing'!$M$23="","",'Current Pricing'!$M$23) -> 0.39037234 | I26: =IF('Current Pricing'!$G$24="","",'Current Pricing'!$G$24) -> 169 | J26: =IF('Current Pricing'!$M$24="","",'Current Pricing'!$M$24) -> 0.32183432 | K26: =IF(OR($C26="",$E26=""),"",$C26-$E26) -> -33 | L26: =IF(OR($C26="",$G26=""),"",$C26-$G26) -> -32 | M26: =IF(OR($C26="",$I26=""),"",$C26-$I26) -> -13 | N26: =IF($D26="","",IFERROR($D26-AVERAGE($F26,$H26),"")) -> -0.1266646
A27: Angry Orchard 5.2 | B27: 5.2 | C27: =IF('Current Pricing'!$G$25="","",'Current Pricing'!$G$25) -> 73 | D27: =IF('Current Pricing'!$M$25="","",'Current Pricing'!$M$25) -> 0.34082192 | E27: =IF('Current Pricing'!$G$26="","",'Current Pricing'!$G$26) -> 87 | F27: =IF('Current Pricing'!$M$26="","",'Current Pricing'!$M$26) -> 0.44689655 | G27: =IF('Current Pricing'!$G$27="","",'Current Pricing'!$G$27) -> 80 | H27: =IF('Current Pricing'!$M$27="","",'Current Pricing'!$M$27) -> 0.3985 | I27: =IF('Current Pricing'!$G$28="","",'Current Pricing'!$G$28) -> 73 | J27: =IF('Current Pricing'!$M$28="","",'Current Pricing'!$M$28) -> 0.34082192 | K27: =IF(OR($C27="",$E27=""),"",$C27-$E27) -> -14 | L27: =IF(OR($C27="",$G27=""),"",$C27-$G27) -> -7 | M27: =IF(OR($C27="",$I27=""),"",$C27-$I27) -> 0 | N27: =IF($D27="","",IFERROR($D27-AVERAGE($F27,$H27),"")) -> -0.081876358
A28: Dogfish Head 15.5 | B28: 15.5 | C28: =IF('Current Pricing'!$G$29="","",'Current Pricing'!$G$29) -> 180 | D28: =IF('Current Pricing'!$M$29="","",'Current Pricing'!$M$29) -> 0.3225 | E28: =IF('Current Pricing'!$G$30="","",'Current Pricing'!$G$30) -> 188 | F28: =IF('Current Pricing'!$M$30="","",'Current Pricing'!$M$30) -> 0.35132979 | G28: =IF('Current Pricing'!$G$31="","",'Current Pricing'!$G$31) -> 188 | H28: =IF('Current Pricing'!$M$31="","",'Current Pricing'!$M$31) -> 0.35132979 | I28: =IF('Current Pricing'!$G$32="","",'Current Pricing'!$G$32) -> 161 | J28: =IF('Current Pricing'!$M$32="","",'Current Pricing'!$M$32) -> 0.24254658 | K28: =IF(OR($C28="",$E28=""),"",$C28-$E28) -> -8 | L28: =IF(OR($C28="",$G28=""),"",$C28-$G28) -> -8 | M28: =IF(OR($C28="",$I28=""),"",$C28-$I28) -> 19 | N28: =IF($D28="","",IFERROR($D28-AVERAGE($F28,$H28),"")) -> -0.028829787
A29: Dogfish Head 5.2 | B29: 5.2 | C29: =IF('Current Pricing'!$G$33="","",'Current Pricing'!$G$33) -> 87 | D29: =IF('Current Pricing'!$M$33="","",'Current Pricing'!$M$33) -> 0.31402299 | E29: =IF('Current Pricing'!$G$34="","",'Current Pricing'!$G$34) -> 88.5 | F29: =IF('Current Pricing'!$M$34="","",'Current Pricing'!$M$34) -> 0.32564972 | G29: =IF('Current Pricing'!$G$35="","",'Current Pricing'!$G$35) -> 94 | H29: =IF('Current Pricing'!$M$35="","",'Current Pricing'!$M$35) -> 0.36510638 | I29: =IF('Current Pricing'!$G$36="","",'Current Pricing'!$G$36) -> 83 | J29: =IF('Current Pricing'!$M$36="","",'Current Pricing'!$M$36) -> 0.28096386 | K29: =IF(OR($C29="",$E29=""),"",$C29-$E29) -> -1.5 | L29: =IF(OR($C29="",$G29=""),"",$C29-$G29) -> -7 | M29: =IF(OR($C29="",$I29=""),"",$C29-$I29) -> 4 | N29: =IF($D29="","",IFERROR($D29-AVERAGE($F29,$H29),"")) -> -0.031355062
A30: Truly 15.5 | B30: 15.5 | C30: =IF('Current Pricing'!$G$37="","",'Current Pricing'!$G$37) -> 115 | D30: =IF('Current Pricing'!$M$37="","",'Current Pricing'!$M$37) -> 0.31556522 | E30: =IF('Current Pricing'!$G$38="","",'Current Pricing'!$G$38) | F30: =IF('Current Pricing'!$M$38="","",'Current Pricing'!$M$38) | G30: =IF('Current Pricing'!$G$39="","",'Current Pricing'!$G$39) -> 188 | H30: =IF('Current Pricing'!$M$39="","",'Current Pricing'!$M$39) -> 0.39303191 | I30: =IF('Current Pricing'!$G$40="","",'Current Pricing'!$G$40) -> 115 | J30: =IF('Current Pricing'!$M$40="","",'Current Pricing'!$M$40) -> 0.31556522 | K30: =IF(OR($C30="",$E30=""),"",$C30-$E30) | L30: =IF(OR($C30="",$G30=""),"",$C30-$G30) -> -73 | M30: =IF(OR($C30="",$I30=""),"",$C30-$I30) -> 0 | N30: =IF($D30="","",IFERROR($D30-AVERAGE($F30,$H30),"")) -> -0.077466698
A31: Truly 5.2 | B31: 5.2 | C31: =IF('Current Pricing'!$G$41="","",'Current Pricing'!$G$41) -> 68 | D31: =IF('Current Pricing'!$M$41="","",'Current Pricing'!$M$41) -> 0.29235294 | E31: =IF('Current Pricing'!$G$42="","",'Current Pricing'!$G$42) -> 88.5 | F31: =IF('Current Pricing'!$M$42="","",'Current Pricing'!$M$42) -> 0.45627119 | G31: =IF('Current Pricing'!$G$43="","",'Current Pricing'!$G$43) -> 80 | H31: =IF('Current Pricing'!$M$43="","",'Current Pricing'!$M$43) -> 0.3985 | I31: =IF('Current Pricing'!$G$44="","",'Current Pricing'!$G$44) -> 67 | J31: =IF('Current Pricing'!$M$44="","",'Current Pricing'!$M$44) -> 0.28179104 | K31: =IF(OR($C31="",$E31=""),"",$C31-$E31) -> -20.5 | L31: =IF(OR($C31="",$G31=""),"",$C31-$G31) -> -12 | M31: =IF(OR($C31="",$I31=""),"",$C31-$I31) -> 1 | N31: =IF($D31="","",IFERROR($D31-AVERAGE($F31,$H31),"")) -> -0.13503265
A34: C. FRONTLINE — NEW BOOK
A35: Same view at the NEW laid-in cost, using whatever prices are entered on the New Pricing tab (seeded with current prices until you change them).
A36: Product | B36: Keg Size | C36: Kohler Price | D36: Kohler Mgn % | E36: Peerless Price | F36: Peerless Mgn % | G36: Shore Point Price | H36: Shore Pt Mgn % | I36: Suggested Price | J36: Suggested Mgn % | K36: Kohler vs Peerless ($) | L36: Kohler vs Shore Pt ($) | M36: Kohler vs Suggested ($) | N36: Kohler Mgn % vs Competitor Avg
A37: Sam Adams 15.5 | B37: 15.5 | C37: =IF('New Pricing'!$H$5="","",'New Pricing'!$H$5) -> 185 | D37: =IF('New Pricing'!$L$5="","",'New Pricing'!$L$5) -> 0.36697297 | E37: =IF('New Pricing'!$H$6="","",'New Pricing'!$H$6) -> 209 | F37: =IF('New Pricing'!$L$6="","",'New Pricing'!$L$6) -> 0.43966507 | G37: =IF('New Pricing'!$H$7="","",'New Pricing'!$H$7) -> 207 | H37: =IF('New Pricing'!$L$7="","",'New Pricing'!$L$7) -> 0.43425121 | I37: =IF('New Pricing'!$H$8="","",'New Pricing'!$H$8) -> 190 | J37: =IF('New Pricing'!$L$8="","",'New Pricing'!$L$8) -> 0.38363158 | K37: =IF(OR($C37="",$E37=""),"",$C37-$E37) -> -24 | L37: =IF(OR($C37="",$G37=""),"",$C37-$G37) -> -22 | M37: =IF(OR($C37="",$I37=""),"",$C37-$I37) -> -5 | N37: =IF($D37="","",IFERROR($D37-AVERAGE($F37,$H37),"")) -> -0.069985167
A38: Sam Adams 5.2 | B38: 5.2 | C38: =IF('New Pricing'!$H$9="","",'New Pricing'!$H$9) -> 80 | D38: =IF('New Pricing'!$L$9="","",'New Pricing'!$L$9) -> 0.37975 | E38: =IF('New Pricing'!$H$10="","",'New Pricing'!$H$10) -> 97.5 | F38: =IF('New Pricing'!$L$10="","",'New Pricing'!$L$10) -> 0.49107692 | G38: =IF('New Pricing'!$H$11="","",'New Pricing'!$H$11) -> 90 | H38: =IF('New Pricing'!$L$11="","",'New Pricing'!$L$11) -> 0.44866667 | I38: =IF('New Pricing'!$H$12="","",'New Pricing'!$H$12) -> 79 | J38: =IF('New Pricing'!$L$12="","",'New Pricing'!$L$12) -> 0.37189873 | K38: =IF(OR($C38="",$E38=""),"",$C38-$E38) -> -17.5 | L38: =IF(OR($C38="",$G38=""),"",$C38-$G38) -> -10 | M38: =IF(OR($C38="",$I38=""),"",$C38-$I38) -> 1 | N38: =IF($D38="","",IFERROR($D38-AVERAGE($F38,$H38),"")) -> -0.090121795
A39: Twisted Tea 15.5 | B39: 15.5 | C39: =IF('New Pricing'!$H$13="","",'New Pricing'!$H$13) -> 185 | D39: =IF('New Pricing'!$L$13="","",'New Pricing'!$L$13) -> 0.37237838 | E39: =IF('New Pricing'!$H$14="","",'New Pricing'!$H$14) -> 209 | F39: =IF('New Pricing'!$L$14="","",'New Pricing'!$L$14) -> 0.44444976 | G39: =IF('New Pricing'!$H$15="","",'New Pricing'!$H$15) -> 207 | H39: =IF('New Pricing'!$L$15="","",'New Pricing'!$L$15) -> 0.43908213 | I39: =IF('New Pricing'!$H$16="","",'New Pricing'!$H$16) -> 189 | J39: =IF('New Pricing'!$L$16="","",'New Pricing'!$L$16) -> 0.38566138 | K39: =IF(OR($C39="",$E39=""),"",$C39-$E39) -> -24 | L39: =IF(OR($C39="",$G39=""),"",$C39-$G39) -> -22 | M39: =IF(OR($C39="",$I39=""),"",$C39-$I39) -> -4 | N39: =IF($D39="","",IFERROR($D39-AVERAGE($F39,$H39),"")) -> -0.069387565
A40: Twisted Tea 5.2 | B40: 5.2 | C40: =IF('New Pricing'!$H$17="","",'New Pricing'!$H$17) -> 77 | D40: =IF('New Pricing'!$L$17="","",'New Pricing'!$L$17) -> 0.35558442 | E40: =IF('New Pricing'!$H$18="","",'New Pricing'!$H$18) -> 97.5 | F40: =IF('New Pricing'!$L$18="","",'New Pricing'!$L$18) -> 0.49107692 | G40: =IF('New Pricing'!$H$19="","",'New Pricing'!$H$19) -> 90 | H40: =IF('New Pricing'!$L$19="","",'New Pricing'!$L$19) -> 0.44866667 | I40: =IF('New Pricing'!$H$20="","",'New Pricing'!$H$20) -> 79 | J40: =IF('New Pricing'!$L$20="","",'New Pricing'!$L$20) -> 0.37189873 | K40: =IF(OR($C40="",$E40=""),"",$C40-$E40) -> -20.5 | L40: =IF(OR($C40="",$G40=""),"",$C40-$G40) -> -13 | M40: =IF(OR($C40="",$I40=""),"",$C40-$I40) -> -2 | N40: =IF($D40="","",IFERROR($D40-AVERAGE($F40,$H40),"")) -> -0.11428738
A41: Angry Orchard 15.5 | B41: 15.5 | C41: =IF('New Pricing'!$H$21="","",'New Pricing'!$H$21) -> 182 | D41: =IF('New Pricing'!$L$21="","",'New Pricing'!$L$21) -> 0.35653846 | E41: =IF('New Pricing'!$H$22="","",'New Pricing'!$H$22) -> 200 | F41: =IF('New Pricing'!$L$22="","",'New Pricing'!$L$22) -> 0.41445 | G41: =IF('New Pricing'!$H$23="","",'New Pricing'!$H$23) -> 207 | H41: =IF('New Pricing'!$L$23="","",'New Pricing'!$L$23) -> 0.43425121 | I41: =IF('New Pricing'!$H$24="","",'New Pricing'!$H$24) -> 190 | J41: =IF('New Pricing'!$L$24="","",'New Pricing'!$L$24) -> 0.38363158 | K41: =IF(OR($C41="",$E41=""),"",$C41-$E41) -> -18 | L41: =IF(OR($C41="",$G41=""),"",$C41-$G41) -> -25 | M41: =IF(OR($C41="",$I41=""),"",$C41-$I41) -> -8 | N41: =IF($D41="","",IFERROR($D41-AVERAGE($F41,$H41),"")) -> -0.067812142
A42: Angry Orchard 5.2 | B42: 5.2 | C42: =IF('New Pricing'!$H$25="","",'New Pricing'!$H$25) -> 75 | D42: =IF('New Pricing'!$L$25="","",'New Pricing'!$L$25) -> 0.3384 | E42: =IF('New Pricing'!$H$26="","",'New Pricing'!$H$26) -> 95 | F42: =IF('New Pricing'!$L$26="","",'New Pricing'!$L$26) -> 0.47768421 | G42: =IF('New Pricing'!$H$27="","",'New Pricing'!$H$27) -> 90 | H42: =IF('New Pricing'!$L$27="","",'New Pricing'!$L$27) -> 0.44866667 | I42: =IF('New Pricing'!$H$28="","",'New Pricing'!$H$28) -> 79 | J42: =IF('New Pricing'!$L$28="","",'New Pricing'!$L$28) -> 0.37189873 | K42: =IF(OR($C42="",$E42=""),"",$C42-$E42) -> -20 | L42: =IF(OR($C42="",$G42=""),"",$C42-$G42) -> -15 | M42: =IF(OR($C42="",$I42=""),"",$C42-$I42) -> -4 | N42: =IF($D42="","",IFERROR($D42-AVERAGE($F42,$H42),"")) -> -0.12477544
A43: Dogfish Head 15.5 | B43: 15.5 | C43: =IF('New Pricing'!$H$29="","",'New Pricing'!$H$29) -> 185 | D43: =IF('New Pricing'!$L$29="","",'New Pricing'!$L$29) -> 0.3272973 | E43: =IF('New Pricing'!$H$30="","",'New Pricing'!$H$30) -> 209 | F43: =IF('New Pricing'!$L$30="","",'New Pricing'!$L$30) -> 0.40454545 | G43: =IF('New Pricing'!$H$31="","",'New Pricing'!$H$31) -> 203 | H43: =IF('New Pricing'!$L$31="","",'New Pricing'!$L$31) -> 0.38694581 | I43: =IF('New Pricing'!$H$32="","",'New Pricing'!$H$32) -> 194 | J43: =IF('New Pricing'!$L$32="","",'New Pricing'!$L$32) -> 0.35850515 | K43: =IF(OR($C43="",$E43=""),"",$C43-$E43) -> -24 | L43: =IF(OR($C43="",$G43=""),"",$C43-$G43) -> -18 | M43: =IF(OR($C43="",$I43=""),"",$C43-$I43) -> -9 | N43: =IF($D43="","",IFERROR($D43-AVERAGE($F43,$H43),"")) -> -0.068448336
A44: Dogfish Head 5.2 | B44: 5.2 | C44: =IF('New Pricing'!$H$33="","",'New Pricing'!$H$33) -> 90 | D44: =IF('New Pricing'!$L$33="","",'New Pricing'!$L$33) -> 0.32022222 | E44: =IF('New Pricing'!$H$34="","",'New Pricing'!$H$34) -> 97.5 | F44: =IF('New Pricing'!$L$34="","",'New Pricing'!$L$34) -> 0.37251282 | G44: =IF('New Pricing'!$H$35="","",'New Pricing'!$H$35) -> 98 | H44: =IF('New Pricing'!$L$35="","",'New Pricing'!$L$35) -> 0.37571429 | I44: =IF('New Pricing'!$H$36="","",'New Pricing'!$H$36) -> 92 | J44: =IF('New Pricing'!$L$36="","",'New Pricing'!$L$36) -> 0.335 | K44: =IF(OR($C44="",$E44=""),"",$C44-$E44) -> -7.5 | L44: =IF(OR($C44="",$G44=""),"",$C44-$G44) -> -8 | M44: =IF(OR($C44="",$I44=""),"",$C44-$I44) -> -2 | N44: =IF($D44="","",IFERROR($D44-AVERAGE($F44,$H44),"")) -> -0.053891331
A45: Truly 15.5 | B45: 15.5 | C45: =IF('New Pricing'!$H$37="","",'New Pricing'!$H$37) -> 168 | D45: =IF('New Pricing'!$L$37="","",'New Pricing'!$L$37) -> 0.30589286 | E45: =IF('New Pricing'!$H$38="","",'New Pricing'!$H$38) | F45: =IF('New Pricing'!$L$38="","",'New Pricing'!$L$38) | G45: =IF('New Pricing'!$H$39="","",'New Pricing'!$H$39) -> 207 | H45: =IF('New Pricing'!$L$39="","",'New Pricing'!$L$39) -> 0.43666667 | I45: =IF('New Pricing'!$H$40="","",'New Pricing'!$H$40) -> 189 | J45: =IF('New Pricing'!$L$40="","",'New Pricing'!$L$40) -> 0.38301587 | K45: =IF(OR($C45="",$E45=""),"",$C45-$E45) | L45: =IF(OR($C45="",$G45=""),"",$C45-$G45) -> -39 | M45: =IF(OR($C45="",$I45=""),"",$C45-$I45) -> -21 | N45: =IF($D45="","",IFERROR($D45-AVERAGE($F45,$H45),"")) -> -0.13077381
A46: Truly 5.2 | B46: 5.2 | C46: =IF('New Pricing'!$H$41="","",'New Pricing'!$H$41) -> 70 | D46: =IF('New Pricing'!$L$41="","",'New Pricing'!$L$41) -> 0.29114286 | E46: =IF('New Pricing'!$H$42="","",'New Pricing'!$H$42) -> 97.5 | F46: =IF('New Pricing'!$L$42="","",'New Pricing'!$L$42) -> 0.49107692 | G46: =IF('New Pricing'!$H$43="","",'New Pricing'!$H$43) -> 90 | H46: =IF('New Pricing'!$L$43="","",'New Pricing'!$L$43) -> 0.44866667 | I46: =IF('New Pricing'!$H$44="","",'New Pricing'!$H$44) -> 79 | J46: =IF('New Pricing'!$L$44="","",'New Pricing'!$L$44) -> 0.37189873 | K46: =IF(OR($C46="",$E46=""),"",$C46-$E46) -> -27.5 | L46: =IF(OR($C46="",$G46=""),"",$C46-$G46) -> -20 | M46: =IF(OR($C46="",$I46=""),"",$C46-$I46) -> -9 | N46: =IF($D46="","",IFERROR($D46-AVERAGE($F46,$H46),"")) -> -0.17872894
A49: D. BEST PRICE — NEW BOOK
A50: Best price and margin % at the new laid-in cost.
A51: Product | B51: Keg Size | C51: Kohler Price | D51: Kohler Mgn % | E51: Peerless Price | F51: Peerless Mgn % | G51: Shore Point Price | H51: Shore Pt Mgn % | I51: Suggested Price | J51: Suggested Mgn % | K51: Kohler vs Peerless ($) | L51: Kohler vs Shore Pt ($) | M51: Kohler vs Suggested ($) | N51: Kohler Mgn % vs Competitor Avg
A52: Sam Adams 15.5 | B52: 15.5 | C52: =IF('New Pricing'!$I$5="","",'New Pricing'!$I$5) -> 175 | D52: =IF('New Pricing'!$O$5="","",'New Pricing'!$O$5) -> 0.3308 | E52: =IF('New Pricing'!$I$6="","",'New Pricing'!$I$6) -> 188 | F52: =IF('New Pricing'!$O$6="","",'New Pricing'!$O$6) -> 0.37707447 | G52: =IF('New Pricing'!$I$7="","",'New Pricing'!$I$7) -> 188 | H52: =IF('New Pricing'!$O$7="","",'New Pricing'!$O$7) -> 0.37707447 | I52: =IF('New Pricing'!$I$8="","",'New Pricing'!$I$8) -> 176 | J52: =IF('New Pricing'!$O$8="","",'New Pricing'!$O$8) -> 0.33460227 | K52: =IF(OR($C52="",$E52=""),"",$C52-$E52) -> -13 | L52: =IF(OR($C52="",$G52=""),"",$C52-$G52) -> -13 | M52: =IF(OR($C52="",$I52=""),"",$C52-$I52) -> -1 | N52: =IF($D52="","",IFERROR($D52-AVERAGE($F52,$H52),"")) -> -0.046274468
A53: Sam Adams 5.2 | B53: 5.2 | C53: =IF('New Pricing'!$I$9="","",'New Pricing'!$I$9) -> 78 | D53: =IF('New Pricing'!$O$9="","",'New Pricing'!$O$9) -> 0.36384615 | E53: =IF('New Pricing'!$I$10="","",'New Pricing'!$I$10) -> 88.5 | F53: =IF('New Pricing'!$O$10="","",'New Pricing'!$O$10) -> 0.43932203 | G53: =IF('New Pricing'!$I$11="","",'New Pricing'!$I$11) -> 80 | H53: =IF('New Pricing'!$O$11="","",'New Pricing'!$O$11) -> 0.37975 | I53: =IF('New Pricing'!$I$12="","",'New Pricing'!$I$12) -> 76 | J53: =IF('New Pricing'!$O$12="","",'New Pricing'!$O$12) -> 0.34710526 | K53: =IF(OR($C53="",$E53=""),"",$C53-$E53) -> -10.5 | L53: =IF(OR($C53="",$G53=""),"",$C53-$G53) -> -2 | M53: =IF(OR($C53="",$I53=""),"",$C53-$I53) -> 2 | N53: =IF($D53="","",IFERROR($D53-AVERAGE($F53,$H53),"")) -> -0.045689863
A54: Twisted Tea 15.5 | B54: 15.5 | C54: =IF('New Pricing'!$I$13="","",'New Pricing'!$I$13) -> 175 | D54: =IF('New Pricing'!$O$13="","",'New Pricing'!$O$13) -> 0.33651429 | E54: =IF('New Pricing'!$I$14="","",'New Pricing'!$I$14) -> 188 | F54: =IF('New Pricing'!$O$14="","",'New Pricing'!$O$14) -> 0.38239362 | G54: =IF('New Pricing'!$I$15="","",'New Pricing'!$I$15) -> 188 | H54: =IF('New Pricing'!$O$15="","",'New Pricing'!$O$15) -> 0.38239362 | I54: =IF('New Pricing'!$I$16="","",'New Pricing'!$I$16) -> 184 | J54: =IF('New Pricing'!$O$16="","",'New Pricing'!$O$16) -> 0.36896739 | K54: =IF(OR($C54="",$E54=""),"",$C54-$E54) -> -13 | L54: =IF(OR($C54="",$G54=""),"",$C54-$G54) -> -13 | M54: =IF(OR($C54="",$I54=""),"",$C54-$I54) -> -9 | N54: =IF($D54="","",IFERROR($D54-AVERAGE($F54,$H54),"")) -> -0.045879331
A55: Twisted Tea 5.2 | B55: 5.2 | C55: =IF('New Pricing'!$I$17="","",'New Pricing'!$I$17) -> 58 | D55: =IF('New Pricing'!$O$17="","",'New Pricing'!$O$17) -> 0.29965517 | E55: =IF('New Pricing'!$I$18="","",'New Pricing'!$I$18) -> 88.5 | F55: =IF('New Pricing'!$O$18="","",'New Pricing'!$O$18) -> 0.43932203 | G55: =IF('New Pricing'!$I$19="","",'New Pricing'!$I$19) -> 80 | H55: =IF('New Pricing'!$O$19="","",'New Pricing'!$O$19) -> 0.37975 | I55: =IF('New Pricing'!$I$20="","",'New Pricing'!$I$20) -> 61 | J55: =IF('New Pricing'!$O$20="","",'New Pricing'!$O$20) -> 0.33409836 | K55: =IF(OR($C55="",$E55=""),"",$C55-$E55) -> -30.5 | L55: =IF(OR($C55="",$G55=""),"",$C55-$G55) -> -22 | M55: =IF(OR($C55="",$I55=""),"",$C55-$I55) -> -3 | N55: =IF($D55="","",IFERROR($D55-AVERAGE($F55,$H55),"")) -> -0.10988084
A56: Angry Orchard 15.5 | B56: 15.5 | C56: =IF('New Pricing'!$I$21="","",'New Pricing'!$I$21) -> 156 | D56: =IF('New Pricing'!$O$21="","",'New Pricing'!$O$21) -> 0.24929487 | E56: =IF('New Pricing'!$I$22="","",'New Pricing'!$I$22) -> 189 | F56: =IF('New Pricing'!$O$22="","",'New Pricing'!$O$22) -> 0.38037037 | G56: =IF('New Pricing'!$I$23="","",'New Pricing'!$I$23) -> 188 | H56: =IF('New Pricing'!$O$23="","",'New Pricing'!$O$23) -> 0.37707447 | I56: =IF('New Pricing'!$I$24="","",'New Pricing'!$I$24) -> 176 | J56: =IF('New Pricing'!$O$24="","",'New Pricing'!$O$24) -> 0.33460227 | K56: =IF(OR($C56="",$E56=""),"",$C56-$E56) -> -33 | L56: =IF(OR($C56="",$G56=""),"",$C56-$G56) -> -32 | M56: =IF(OR($C56="",$I56=""),"",$C56-$I56) -> -20 | N56: =IF($D56="","",IFERROR($D56-AVERAGE($F56,$H56),"")) -> -0.12942755
A57: Angry Orchard 5.2 | B57: 5.2 | C57: =IF('New Pricing'!$I$25="","",'New Pricing'!$I$25) -> 73 | D57: =IF('New Pricing'!$O$25="","",'New Pricing'!$O$25) -> 0.32027397 | E57: =IF('New Pricing'!$I$26="","",'New Pricing'!$I$26) -> 87 | F57: =IF('New Pricing'!$O$26="","",'New Pricing'!$O$26) -> 0.42965517 | G57: =IF('New Pricing'!$I$27="","",'New Pricing'!$I$27) -> 80 | H57: =IF('New Pricing'!$O$27="","",'New Pricing'!$O$27) -> 0.37975 | I57: =IF('New Pricing'!$I$28="","",'New Pricing'!$I$28) -> 76 | J57: =IF('New Pricing'!$O$28="","",'New Pricing'!$O$28) -> 0.34710526 | K57: =IF(OR($C57="",$E57=""),"",$C57-$E57) -> -14 | L57: =IF(OR($C57="",$G57=""),"",$C57-$G57) -> -7 | M57: =IF(OR($C57="",$I57=""),"",$C57-$I57) -> -3 | N57: =IF($D57="","",IFERROR($D57-AVERAGE($F57,$H57),"")) -> -0.084428614
A58: Dogfish Head 15.5 | B58: 15.5 | C58: =IF('New Pricing'!$I$29="","",'New Pricing'!$I$29) -> 180 | D58: =IF('New Pricing'!$O$29="","",'New Pricing'!$O$29) -> 0.30861111 | E58: =IF('New Pricing'!$I$30="","",'New Pricing'!$I$30) -> 188 | F58: =IF('New Pricing'!$O$30="","",'New Pricing'!$O$30) -> 0.33803191 | G58: =IF('New Pricing'!$I$31="","",'New Pricing'!$I$31) -> 188 | H58: =IF('New Pricing'!$O$31="","",'New Pricing'!$O$31) -> 0.33803191 | I58: =IF('New Pricing'!$I$32="","",'New Pricing'!$I$32) -> 167 | J58: =IF('New Pricing'!$O$32="","",'New Pricing'!$O$32) -> 0.25479042 | K58: =IF(OR($C58="",$E58=""),"",$C58-$E58) -> -8 | L58: =IF(OR($C58="",$G58=""),"",$C58-$G58) -> -8 | M58: =IF(OR($C58="",$I58=""),"",$C58-$I58) -> 13 | N58: =IF($D58="","",IFERROR($D58-AVERAGE($F58,$H58),"")) -> -0.029420804
A59: Dogfish Head 5.2 | B59: 5.2 | C59: =IF('New Pricing'!$I$33="","",'New Pricing'!$I$33) -> 87 | D59: =IF('New Pricing'!$O$33="","",'New Pricing'!$O$33) -> 0.29678161 | E59: =IF('New Pricing'!$I$34="","",'New Pricing'!$I$34) -> 88.5 | F59: =IF('New Pricing'!$O$34="","",'New Pricing'!$O$34) -> 0.30870056 | G59: =IF('New Pricing'!$I$35="","",'New Pricing'!$I$35) -> 94 | H59: =IF('New Pricing'!$O$35="","",'New Pricing'!$O$35) -> 0.34914894 | I59: =IF('New Pricing'!$I$36="","",'New Pricing'!$I$36) -> 89 | J59: =IF('New Pricing'!$O$36="","",'New Pricing'!$O$36) -> 0.31258427 | K59: =IF(OR($C59="",$E59=""),"",$C59-$E59) -> -1.5 | L59: =IF(OR($C59="",$G59=""),"",$C59-$G59) -> -7 | M59: =IF(OR($C59="",$I59=""),"",$C59-$I59) -> -2 | N59: =IF($D59="","",IFERROR($D59-AVERAGE($F59,$H59),"")) -> -0.032143141
A60: Truly 15.5 | B60: 15.5 | C60: =IF('New Pricing'!$I$37="","",'New Pricing'!$I$37) -> 115 | D60: =IF('New Pricing'!$O$37="","",'New Pricing'!$O$37) -> 0.29382609 | E60: =IF('New Pricing'!$I$38="","",'New Pricing'!$I$38) | F60: =IF('New Pricing'!$O$38="","",'New Pricing'!$O$38) | G60: =IF('New Pricing'!$I$39="","",'New Pricing'!$I$39) -> 188 | H60: =IF('New Pricing'!$O$39="","",'New Pricing'!$O$39) -> 0.37973404 | I60: =IF('New Pricing'!$I$40="","",'New Pricing'!$I$40) -> 120 | J60: =IF('New Pricing'!$O$40="","",'New Pricing'!$O$40) -> 0.32325 | K60: =IF(OR($C60="",$E60=""),"",$C60-$E60) | L60: =IF(OR($C60="",$G60=""),"",$C60-$G60) -> -73 | M60: =IF(OR($C60="",$I60=""),"",$C60-$I60) -> -5 | N60: =IF($D60="","",IFERROR($D60-AVERAGE($F60,$H60),"")) -> -0.085907956
A61: Truly 5.2 | B61: 5.2 | C61: =IF('New Pricing'!$I$41="","",'New Pricing'!$I$41) -> 68 | D61: =IF('New Pricing'!$O$41="","",'New Pricing'!$O$41) -> 0.27029412 | E61: =IF('New Pricing'!$I$42="","",'New Pricing'!$I$42) -> 88.5 | F61: =IF('New Pricing'!$O$42="","",'New Pricing'!$O$42) -> 0.43932203 | G61: =IF('New Pricing'!$I$43="","",'New Pricing'!$I$43) -> 80 | H61: =IF('New Pricing'!$O$43="","",'New Pricing'!$O$43) -> 0.37975 | I61: =IF('New Pricing'!$I$44="","",'New Pricing'!$I$44) -> 76 | J61: =IF('New Pricing'!$O$44="","",'New Pricing'!$O$44) -> 0.34710526 | K61: =IF(OR($C61="",$E61=""),"",$C61-$E61) -> -20.5 | L61: =IF(OR($C61="",$G61=""),"",$C61-$G61) -> -12 | M61: =IF(OR($C61="",$I61=""),"",$C61-$I61) -> -8 | N61: =IF($D61="","",IFERROR($D61-AVERAGE($F61,$H61),"")) -> -0.1392419
A64: E. KOHLER MARGIN IMPACT — NEW BOOK vs CURRENT BOOK
A65: What the cost increase does to Kohler at the prices currently entered on the New Pricing tab. Negative = margin lost.
A66: Product | B66: Keg Size | C66: Δ Laid-In ($) | D66: Current FL Price | E66: New FL Price | F66: Current FL Mgn % | G66: New FL Mgn % | H66: Δ FL Mgn % | I66: Current Best Price | J66: New Best Price | K66: Current Best Mgn % | L66: New Best Mgn % | M66: Δ Best Mgn % | N66: FL Price Needed to Hold Current FL Mgn %
A67: Sam Adams 15.5 | B67: 15.5 | C67: ='New Pricing'!$F$5 -> 2.5 | D67: ='Current Pricing'!$F$5 -> 185 | E67: ='New Pricing'!$H$5 -> 185 | F67: ='Current Pricing'!$J$5 -> 0.38048649 | G67: ='New Pricing'!$L$5 -> 0.36697297 | H67: =IF(OR($F67="",$G67=""),"",$G67-$F67) -> -0.013513514 | I67: ='Current Pricing'!$G$5 -> 175 | J67: ='New Pricing'!$I$5 -> 175 | K67: ='Current Pricing'!$M$5 -> 0.34508571 | L67: ='New Pricing'!$O$5 -> 0.3308 | M67: =IF(OR($K67="",$L67=""),"",$L67-$K67) -> -0.014285714 | N67: =IF(OR($F67="",'New Pricing'!$J$5=""),"",IFERROR('New Pricing'!$J$5/(1-$F67),"")) -> 189.03542
A68: Sam Adams 5.2 | B68: 5.2 | C68: ='New Pricing'!$F$9 -> 1.5 | D68: ='Current Pricing'!$F$9 -> 80 | E68: ='New Pricing'!$H$9 -> 80 | F68: ='Current Pricing'!$J$9 -> 0.3985 | G68: ='New Pricing'!$L$9 -> 0.37975 | H68: =IF(OR($F68="",$G68=""),"",$G68-$F68) -> -0.01875 | I68: ='Current Pricing'!$G$9 -> 78 | J68: ='New Pricing'!$I$9 -> 78 | K68: ='Current Pricing'!$M$9 -> 0.38307692 | L68: ='New Pricing'!$O$9 -> 0.36384615 | M68: =IF(OR($K68="",$L68=""),"",$L68-$K68) -> -0.019230769 | N68: =IF(OR($F68="",'New Pricing'!$J$9=""),"",IFERROR('New Pricing'!$J$9/(1-$F68),"")) -> 82.493766
A69: Twisted Tea 15.5 | B69: 15.5 | C69: ='New Pricing'!$F$13 -> 2 | D69: ='Current Pricing'!$F$13 -> 185 | E69: ='New Pricing'!$H$13 -> 185 | F69: ='Current Pricing'!$J$13 -> 0.38318919 | G69: ='New Pricing'!$L$13 -> 0.37237838 | H69: =IF(OR($F69="",$G69=""),"",$G69-$F69) -> -0.010810811 | I69: ='Current Pricing'!$G$13 -> 175 | J69: ='New Pricing'!$I$13 -> 175 | K69: ='Current Pricing'!$M$13 -> 0.34794286 | L69: ='New Pricing'!$O$13 -> 0.33651429 | M69: =IF(OR($K69="",$L69=""),"",$L69-$K69) -> -0.011428571 | N69: =IF(OR($F69="",'New Pricing'!$J$13=""),"",IFERROR('New Pricing'!$J$13/(1-$F69),"")) -> 188.24249
A70: Twisted Tea 5.2 | B70: 5.2 | C70: ='New Pricing'!$F$17 -> 1.5 | D70: ='Current Pricing'!$F$17 -> 77 | E70: ='New Pricing'!$H$17 -> 77 | F70: ='Current Pricing'!$J$17 -> 0.37506494 | G70: ='New Pricing'!$L$17 -> 0.35558442 | H70: =IF(OR($F70="",$G70=""),"",$G70-$F70) -> -0.019480519 | I70: ='Current Pricing'!$G$17 -> 58 | J70: ='New Pricing'!$I$17 -> 58 | K70: ='Current Pricing'!$M$17 -> 0.32551724 | L70: ='New Pricing'!$O$17 -> 0.29965517 | M70: =IF(OR($K70="",$L70=""),"",$L70-$K70) -> -0.025862069 | N70: =IF(OR($F70="",'New Pricing'!$J$17=""),"",IFERROR('New Pricing'!$J$17/(1-$F70),"")) -> 79.400249
A71: Angry Orchard 15.5 | B71: 15.5 | C71: ='New Pricing'!$F$21 -> 2.5 | D71: ='Current Pricing'!$F$21 -> 182 | E71: ='New Pricing'!$H$21 -> 182 | F71: ='Current Pricing'!$J$21 -> 0.37027473 | G71: ='New Pricing'!$L$21 -> 0.35653846 | H71: =IF(OR($F71="",$G71=""),"",$G71-$F71) -> -0.013736264 | I71: ='Current Pricing'!$G$21 -> 156 | J71: ='New Pricing'!$I$21 -> 156 | K71: ='Current Pricing'!$M$21 -> 0.26532051 | L71: ='New Pricing'!$O$21 -> 0.24929487 | M71: =IF(OR($K71="",$L71=""),"",$L71-$K71) -> -0.016025641 | N71: =IF(OR($F71="",'New Pricing'!$J$21=""),"",IFERROR('New Pricing'!$J$21/(1-$F71),"")) -> 185.96999
A72: Angry Orchard 5.2 | B72: 5.2 | C72: ='New Pricing'!$F$25 -> 1.5 | D72: ='Current Pricing'!$F$25 -> 75 | E72: ='New Pricing'!$H$25 -> 75 | F72: ='Current Pricing'!$J$25 -> 0.3584 | G72: ='New Pricing'!$L$25 -> 0.3384 | H72: =IF(OR($F72="",$G72=""),"",$G72-$F72) -> -0.02 | I72: ='Current Pricing'!$G$25 -> 73 | J72: ='New Pricing'!$I$25 -> 73 | K72: ='Current Pricing'!$M$25 -> 0.34082192 | L72: ='New Pricing'!$O$25 -> 0.32027397 | M72: =IF(OR($K72="",$L72=""),"",$L72-$K72) -> -0.020547945 | N72: =IF(OR($F72="",'New Pricing'!$J$25=""),"",IFERROR('New Pricing'!$J$25/(1-$F72),"")) -> 77.337905
A73: Dogfish Head 15.5 | B73: 15.5 | C73: ='New Pricing'!$F$29 -> 2.5 | D73: ='Current Pricing'!$F$29 -> 185 | E73: ='New Pricing'!$H$29 -> 185 | F73: ='Current Pricing'!$J$29 -> 0.34081081 | G73: ='New Pricing'!$L$29 -> 0.3272973 | H73: =IF(OR($F73="",$G73=""),"",$G73-$F73) -> -0.013513514 | I73: ='Current Pricing'!$G$29 -> 180 | J73: ='New Pricing'!$I$29 -> 180 | K73: ='Current Pricing'!$M$29 -> 0.3225 | L73: ='New Pricing'!$O$29 -> 0.30861111 | M73: =IF(OR($K73="",$L73=""),"",$L73-$K73) -> -0.013888889 | N73: =IF(OR($F73="",'New Pricing'!$J$29=""),"",IFERROR('New Pricing'!$J$29/(1-$F73),"")) -> 188.79254
A74: Dogfish Head 5.2 | B74: 5.2 | C74: ='New Pricing'!$F$33 -> 1.5 | D74: ='Current Pricing'!$F$33 -> 90 | E74: ='New Pricing'!$H$33 -> 90 | F74: ='Current Pricing'!$J$33 -> 0.33688889 | G74: ='New Pricing'!$L$33 -> 0.32022222 | H74: =IF(OR($F74="",$G74=""),"",$G74-$F74) -> -0.016666667 | I74: ='Current Pricing'!$G$33 -> 87 | J74: ='New Pricing'!$I$33 -> 87 | K74: ='Current Pricing'!$M$33 -> 0.31402299 | L74: ='New Pricing'!$O$33 -> 0.29678161 | M74: =IF(OR($K74="",$L74=""),"",$L74-$K74) -> -0.017241379 | N74: =IF(OR($F74="",'New Pricing'!$J$33=""),"",IFERROR('New Pricing'!$J$33/(1-$F74),"")) -> 92.262064
A75: Truly 15.5 | B75: 15.5 | C75: ='New Pricing'!$F$37 -> 2.5 | D75: ='Current Pricing'!$F$37 -> 168 | E75: ='New Pricing'!$H$37 -> 168 | F75: ='Current Pricing'!$J$37 -> 0.32077381 | G75: ='New Pricing'!$L$37 -> 0.30589286 | H75: =IF(OR($F75="",$G75=""),"",$G75-$F75) -> -0.014880952 | I75: ='Current Pricing'!$G$37 -> 115 | J75: ='New Pricing'!$I$37 -> 115 | K75: ='Current Pricing'!$M$37 -> 0.31556522 | L75: ='New Pricing'!$O$37 -> 0.29382609 | M75: =IF(OR($K75="",$L75=""),"",$L75-$K75) -> -0.02173913 | N75: =IF(OR($F75="",'New Pricing'!$J$37=""),"",IFERROR('New Pricing'!$J$37/(1-$F75),"")) -> 171.68066
A76: Truly 5.2 | B76: 5.2 | C76: ='New Pricing'!$F$41 -> 1.5 | D76: ='Current Pricing'!$F$41 -> 70 | E76: ='New Pricing'!$H$41 -> 70 | F76: ='Current Pricing'!$J$41 -> 0.31257143 | G76: ='New Pricing'!$L$41 -> 0.29114286 | H76: =IF(OR($F76="",$G76=""),"",$G76-$F76) -> -0.021428571 | I76: ='Current Pricing'!$G$41 -> 68 | J76: ='New Pricing'!$I$41 -> 68 | K76: ='Current Pricing'!$M$41 -> 0.29235294 | L76: ='New Pricing'!$O$41 -> 0.27029412 | M76: =IF(OR($K76="",$L76=""),"",$L76-$K76) -> -0.022058824 | N76: =IF(OR($F76="",'New Pricing'!$J$41=""),"",IFERROR('New Pricing'!$J$41/(1-$F76),"")) -> 72.182045

Sheet Kohler Actuals
A1: Kohler Actuals — What We Really Charged, 7/1/2026 – 8/31/2026
A2: From InvoiceTransReport_GSHARKEY_20260903. Reality check on the pricing file: the realized prices match the Kohler columns in the analysis exactly.
A4: Product | B4: Keg Size (Gal) | C4: Kegs Shipped | D4: Accounts Bought | E4: Weighted Avg Realized $/keg | F4: Frontline Price | G4: Best Price | H4: Realized vs Frontline ($) | I4: % of Kegs at Frontline | J4: % of Kegs at Best Price or Lower | K4: DA ($/keg) | L4: Weighted DA Credit ($/keg) | M4: Effective Cost — Current Laid-In | N4: Realized Margin $ (current cost) | O4: Realized Margin % (current cost) | P4: Effective Cost — New Laid-In | Q4: Realized Margin $ (new cost, price held) | R4: Realized Margin % (new cost, price held) | S4: Margin $ at Risk on This Volume
A5: Sam Adams 15.5 | B5: 15.5 | C5: 1032 | D5: 225 | E5: 180.69 | F5: ='Current Pricing'!$F$5 -> 185 | G5: ='Current Pricing'!$G$5 -> 175 | H5: =IF($F5="","",$E5-$F5) -> -4.31 | I5: 0.3372 | J5: 0.189 | K5: ='Current Pricing'!$E$5 -> 0 | L5: =IF($K5="","",$K5*$J5) -> 0 | M5: =IF('Current Pricing'!$D$5="","",'Current Pricing'!$D$5-$L5) -> 114.61 | N5: =IF($M5="","",$E5-$M5) -> 66.08 | O5: =IF($N5="","",IFERROR($N5/$E5,"")) -> 0.36570923 | P5: =IF('New Pricing'!$E$5="","",'New Pricing'!$E$5-$L5) -> 117.11 | Q5: =IF($P5="","",$E5-$P5) -> 63.58 | R5: =IF($Q5="","",IFERROR($Q5/$E5,"")) -> 0.35187337 | S5: =IF(OR($N5="",$Q5=""),"",($Q5-$N5)*$C5) -> -2580
A6: Sam Adams 5.2 | B6: 5.2 | C6: 617 | D6: 148 | E6: 78.62 | F6: ='Current Pricing'!$F$9 -> 80 | G6: ='Current Pricing'!$G$9 -> 78 | H6: =IF($F6="","",$E6-$F6) -> -1.38 | I6: 0.3096 | J6: 0.6872 | K6: ='Current Pricing'!$E$9 -> 0 | L6: =IF($K6="","",$K6*$J6) -> 0 | M6: =IF('Current Pricing'!$D$9="","",'Current Pricing'!$D$9-$L6) -> 48.12 | N6: =IF($M6="","",$E6-$M6) -> 30.5 | O6: =IF($N6="","",IFERROR($N6/$E6,"")) -> 0.387942 | P6: =IF('New Pricing'!$E$9="","",'New Pricing'!$E$9-$L6) -> 49.62 | Q6: =IF($P6="","",$E6-$P6) -> 29 | R6: =IF($Q6="","",IFERROR($Q6/$E6,"")) -> 0.36886288 | S6: =IF(OR($N6="",$Q6=""),"",($Q6-$N6)*$C6) -> -925.5
A7: Twisted Tea 15.5 | B7: 15.5 | C7: 28 | D7: 13 | E7: 179 | F7: ='Current Pricing'!$F$13 -> 185 | G7: ='Current Pricing'!$G$13 -> 175 | H7: =IF($F7="","",$E7-$F7) -> -6 | I7: 0.3571 | J7: 0.5714 | K7: ='Current Pricing'!$E$13 -> 0 | L7: =IF($K7="","",$K7*$J7) -> 0 | M7: =IF('Current Pricing'!$D$13="","",'Current Pricing'!$D$13-$L7) -> 114.11 | N7: =IF($M7="","",$E7-$M7) -> 64.89 | O7: =IF($N7="","",IFERROR($N7/$E7,"")) -> 0.36251397 | P7: =IF('New Pricing'!$E$13="","",'New Pricing'!$E$13-$L7) -> 116.11 | Q7: =IF($P7="","",$E7-$P7) -> 62.89 | R7: =IF($Q7="","",IFERROR($Q7/$E7,"")) -> 0.35134078 | S7: =IF(OR($N7="",$Q7=""),"",($Q7-$N7)*$C7) -> -56
A8: Twisted Tea 5.2 | B8: 5.2 | C8: 75 | D8: 17 | E8: 64.41 | F8: ='Current Pricing'!$F$17 -> 77 | G8: ='Current Pricing'!$G$17 -> 58 | H8: =IF($F8="","",$E8-$F8) -> -12.59 | I8: 0.2 | J8: 0.6133 | K8: ='Current Pricing'!$E$17 -> 9 | L8: =IF($K8="","",$K8*$J8) -> 5.5197 | M8: =IF('Current Pricing'!$D$17="","",'Current Pricing'!$D$17-$L8) -> 42.6003 | N8: =IF($M8="","",$E8-$M8) -> 21.8097 | O8: =IF($N8="","",IFERROR($N8/$E8,"")) -> 0.33860736 | P8: =IF('New Pricing'!$E$17="","",'New Pricing'!$E$17-$L8) -> 44.1003 | Q8: =IF($P8="","",$E8-$P8) -> 20.3097 | R8: =IF($Q8="","",IFERROR($Q8/$E8,"")) -> 0.31531905 | S8: =IF(OR($N8="",$Q8=""),"",($Q8-$N8)*$C8) -> -112.5
A9: Angry Orchard 15.5 | B9: 15.5 | C9: 151 | D9: 42 | E9: 168.38 | F9: ='Current Pricing'!$F$21 -> 182 | G9: ='Current Pricing'!$G$21 -> 156 | H9: =IF($F9="","",$E9-$F9) -> -13.62 | I9: 0.4305 | J9: 0.4503 | K9: ='Current Pricing'!$E$21 -> 0 | L9: =IF($K9="","",$K9*$J9) -> 0 | M9: =IF('Current Pricing'!$D$21="","",'Current Pricing'!$D$21-$L9) -> 114.61 | N9: =IF($M9="","",$E9-$M9) -> 53.77 | O9: =IF($N9="","",IFERROR($N9/$E9,"")) -> 0.31933721 | P9: =IF('New Pricing'!$E$21="","",'New Pricing'!$E$21-$L9) -> 117.11 | Q9: =IF($P9="","",$E9-$P9) -> 51.27 | R9: =IF($Q9="","",IFERROR($Q9/$E9,"")) -> 0.30448984 | S9: =IF(OR($N9="",$Q9=""),"",($Q9-$N9)*$C9) -> -377.5
A10: Angry Orchard 5.2 | B10: 5.2 | C10: 86 | D10: 25 | E10: 73.84 | F10: ='Current Pricing'!$F$25 -> 75 | G10: ='Current Pricing'!$G$25 -> 73 | H10: =IF($F10="","",$E10-$F10) -> -1.16 | I10: 0.4186 | J10: 0.5814 | K10: ='Current Pricing'!$E$25 -> 0 | L10: =IF($K10="","",$K10*$J10) -> 0 | M10: =IF('Current Pricing'!$D$25="","",'Current Pricing'!$D$25-$L10) -> 48.12 | N10: =IF($M10="","",$E10-$M10) -> 25.72 | O10: =IF($N10="","",IFERROR($N10/$E10,"")) -> 0.34832069 | P10: =IF('New Pricing'!$E$25="","",'New Pricing'!$E$25-$L10) -> 49.62 | Q10: =IF($P10="","",$E10-$P10) -> 24.22 | R10: =IF($Q10="","",IFERROR($Q10/$E10,"")) -> 0.3280065 | S10: =IF(OR($N10="",$Q10=""),"",($Q10-$N10)*$C10) -> -129
A11: Dogfish Head 15.5 | B11: 15.5 | C11: 259 | D11: 72 | E11: 182.14 | F11: ='Current Pricing'!$F$29 -> 185 | G11: ='Current Pricing'!$G$29 -> 180 | H11: =IF($F11="","",$E11-$F11) -> -2.86 | I11: 0.4286 | J11: 0.5714 | K11: ='Current Pricing'!$E$29 -> 0 | L11: =IF($K11="","",$K11*$J11) -> 0 | M11: =IF('Current Pricing'!$D$29="","",'Current Pricing'!$D$29-$L11) -> 121.95 | N11: =IF($M11="","",$E11-$M11) -> 60.19 | O11: =IF($N11="","",IFERROR($N11/$E11,"")) -> 0.33046009 | P11: =IF('New Pricing'!$E$29="","",'New Pricing'!$E$29-$L11) -> 124.45 | Q11: =IF($P11="","",$E11-$P11) -> 57.69 | R11: =IF($Q11="","",IFERROR($Q11/$E11,"")) -> 0.31673438 | S11: =IF(OR($N11="",$Q11=""),"",($Q11-$N11)*$C11) -> -647.5
A12: Dogfish Head 5.2 | B12: 5.2 | C12: 243 | D12: 63 | E12: 88.16 | F12: ='Current Pricing'!$F$33 -> 90 | G12: ='Current Pricing'!$G$33 -> 87 | H12: =IF($F12="","",$E12-$F12) -> -1.84 | I12: 0.3868 | J12: 0.6132 | K12: ='Current Pricing'!$E$33 -> 0 | L12: =IF($K12="","",$K12*$J12) -> 0 | M12: =IF('Current Pricing'!$D$33="","",'Current Pricing'!$D$33-$L12) -> 59.68 | N12: =IF($M12="","",$E12-$M12) -> 28.48 | O12: =IF($N12="","",IFERROR($N12/$E12,"")) -> 0.323049 | P12: =IF('New Pricing'!$E$33="","",'New Pricing'!$E$33-$L12) -> 61.18 | Q12: =IF($P12="","",$E12-$P12) -> 26.98 | R12: =IF($Q12="","",IFERROR($Q12/$E12,"")) -> 0.30603448 | S12: =IF(OR($N12="",$Q12=""),"",($Q12-$N12)*$C12) -> -364.5
A13: Truly 15.5 | B13: 15.5 | C13: 42 | D13: 16 | E13: 120.05 | F13: ='Current Pricing'!$F$37 -> 168 | G13: ='Current Pricing'!$G$37 -> 115 | H13: =IF($F13="","",$E13-$F13) -> -47.95 | I13: 0.0952 | J13: 0.9048 | K13: ='Current Pricing'!$E$37 -> 35.4 | L13: =IF($K13="","",$K13*$J13) -> 32.02992 | M13: =IF('Current Pricing'!$D$37="","",'Current Pricing'!$D$37-$L13) -> 82.08008 | N13: =IF($M13="","",$E13-$M13) -> 37.96992 | O13: =IF($N13="","",IFERROR($N13/$E13,"")) -> 0.31628421 | P13: =IF('New Pricing'!$E$37="","",'New Pricing'!$E$37-$L13) -> 84.58008 | Q13: =IF($P13="","",$E13-$P13) -> 35.46992 | R13: =IF($Q13="","",IFERROR($Q13/$E13,"")) -> 0.29545956 | S13: =IF(OR($N13="",$Q13=""),"",($Q13-$N13)*$C13) -> -105
A14: Truly 5.2 | B14: 5.2 | C14: 33 | D14: 14 | E14: 68.12 | F14: ='Current Pricing'!$F$41 -> 70 | G14: ='Current Pricing'!$G$41 -> 68 | H14: =IF($F14="","",$E14-$F14) -> -1.88 | I14: 0.0606 | J14: 0.9394 | K14: ='Current Pricing'!$E$41 -> 0 | L14: =IF($K14="","",$K14*$J14) -> 0 | M14: =IF('Current Pricing'!$D$41="","",'Current Pricing'!$D$41-$L14) -> 48.12 | N14: =IF($M14="","",$E14-$M14) -> 20 | O14: =IF($N14="","",IFERROR($N14/$E14,"")) -> 0.29359953 | P14: =IF('New Pricing'!$E$41="","",'New Pricing'!$E$41-$L14) -> 49.62 | Q14: =IF($P14="","",$E14-$P14) -> 18.5 | R14: =IF($Q14="","",IFERROR($Q14/$E14,"")) -> 0.27157957 | S14: =IF(OR($N14="",$Q14=""),"",($Q14-$N14)*$C14) -> -49.5
A15: TOTAL | C15: =SUM(C5:C14) -> 2566 | S15: =SUM(S5:S14) -> -5347
A17: Weighted average realized price excludes zero-price lines (18 lines / 21 kegs of samples and comps) and backorder-only lines.
A18: Weighted DA credit = DA x % of kegs sold at best price or lower — i.e. the allowance is credited only against the share of volume that actually moved on the promoted price. Without it, Truly 15.5 reads as a 5% margin product, which is an artefact of ignoring a $35.40 allowance on 90% of its volume.
A19: Margin $ at Risk = (new-cost margin - current-cost margin) x kegs shipped in this two-month window. It is what holding price through the cost increase would have cost on July-August volume, not a forecast.
A20: Sam Adams 15.5 shows only 34% at frontline and 19% at best price because a large share ships at $179 and $181 — intermediate prices between the two, which the pricing analysis does not capture.

Sheet Source Data
A1: Source Data — Boston_Pricing_Analysis.xlsx (unmodified)
A2: Verbatim copy of the original Sheet1, including the DA notes recorded as free text inside price cells. Nothing on this tab feeds the calculations.
B4: Laid In | C4: Frontline Current Suggested | D4: Kohler Current Frontline | E4: Peerless Current Frontline | F4: Shore Point Current Frontline | G4: Suggested Current Best Price | H4: Kohler Current Best Price | I4: Peerless Current Best Price | J4: Shore Point Current Best Price
A5: Sam Adams 15.5 | B5: 114.61 | C5: 185 | D5: 185 | E5: 209 | F5: 207 | G5: 169 | H5: 175 | I5: 188 | J5: 188
A6: Sam Adams 5.2 | B6: 48.12 | C6: 73 | D6: 80 | E6: 97.5 | F6: 90 | G6: 63 | H6: 78 | I6: 88.5 | J6: 80
A7: Twisted Tea 15.5 | B7: 114.11 | C7: 184 | D7: 185 | E7: 209 | F7: 207 | G7: 168 | H7: 175 | I7: 188 | J7: 188
A8: Twisted Tea 5.2 | B8: 48.12 | C8: 77 | D8: 77 | E8: 97.5 | F8: 90 | G8: 58 ($9 DA) | H8: 58 | I8: 88.5 | J8: 80
A9: Angry Orchard 15.5 | B9: 114.61 | C9: 185 | D9: 182 | E9: 200 | F9: 207 | G9: 169 | H9: 156 | I9: 189 | J9: 188
A10: Angry Orchard 5.2 | B10: 48.12 | C10: 77 | D10: 75 | E10: 95 | F10: 90 | G10: 73 | H10: 73 | I10: 87 | J10: 80
A11: Dogfish Head 15.5 | B11: 121.95 | C11: 189 | D11: 185 | E11: 209 | F11: 203 | G11: 161 | H11: 180 | I11: 188 | J11: 188
A12: Dogfish Head 5.2 | B12: 59.68 | C12: 87 | D12: 90 | E12: 97.5 | F12: 98 | G12: 83 | H12: 87 | I12: 88.5 | J12: 94
A13: Truly 15.5 | B13: 114.11 | C13: 184 | D13: 168 | E13: NA | F13: 207 | G13: $115 ($35.40 DA) | H13: 115 | I13: NA | J13: 188
A14: Truly 5.2 | B14: 48.12 | C14: 77 | D14: 70 | E14: 97.5 | F14: 90 | G14: 67 | H14: 68 | I14: 88.5 | J14: 80
B16: New Laid In | C16: Frontline New Suggested Suggested | D16: Kohler New Frontline ? | G16: Suggested New Best Price | H16: Kohler New Best Price ?
A17: Sam Adams 15.5 | B17: 117.11 | C17: 190 | G17: 176
A18: Sam Adams 5.2 | B18: 49.62 | C18: 79 | G18: 76
A19: Twisted Tea 15.5 | B19: 116.11 | C19: 189 | G19: 184
A20: Twisted Tea 5.2 | B20: 49.62 | C20: 79 | G20: $61 ($9 DA)
A21: Angry Orchard 15.5 | B21: 117.11 | C21: 190 | G21: 176
A22: Angry Orchard 5.2 | B22: 49.62 | C22: 79 | G22: 76
A23: Dogfish Head 15.5 | B23: 124.45 | C23: 194 | G23: 167
A24: Dogfish Head 5.2 | B24: 61.18 | C24: 92 | G24: 89
A25: Truly 15.5 | B25: 116.61 | C25: 189 | G25: $120 ($35.40 DA)
A26: Truly 5.2 | B26: 49.62 | C26: 79 | G26: 76
