Workbook

Sheet Summary
A1: Summer of Success 2026 — did it work?
A2: Jun 1 – Aug 31, 2026 vs 2025 · 28 reps · 10 suppliers · 2,016 accounts · built 09/11/2026
A4: THE VERDICT
A5: The incentive did not generate measurable incremental volume or gross profit. It paid for a trend that was already running.
A7: THE TESTS
A8: Test | B8: Result | C8: What it means
A9: 1. Did AMPLIFY growth accelerate when the program started? | B9: ='Acceleration Test'!H7 | C9: No. Already +12% before a dollar was offered.
A10: 1b. Did QUALIFIER volume accelerate? | B10: ='Acceleration Test'!H6 | C10: No — it slowed by nearly three points.
A11: 2. Amplify GP lift vs its own pre-program trajectory | B11: ='Counterfactual'!F12 | C11: Zero, against the amplify payout.
A12: 3. Incented vs the same SUPPLIERS' non-incented brands | B12: ='Control by Supplier'!H13 | C12: The incented book lost to the book with no incentive.
A13: 4. Incented vs non-incented brands in the SAME ACCOUNTS | B13: ='Within-Account Control'!D9 | C13: Same stores, same summer: still no incentive effect.
A14: 5. Did the program build DISTRIBUTION? | B14: ='Distribution'!D7 | C14: Amplify PODs +4.2% — but +5.5% before the program.
A15: 6. Were the qualifier goals set above last year? | B15: ='Goal Design'!$B$147 | C15: No — 9 in 10 sat BELOW the rep's own 2025.
A16: 7. Did payout track performance? | B16: ='Payout vs Performance'!$B$36 | C16: r ≈ 0. Payout did not follow delivery.
A18: THE NUMBERS
A19: Program cases, Jun–Aug | B19: ='Acceleration Test'!F8
A20: vs 2025 | B20: ='Acceleration Test'!G8
A21: Program gross profit, Jun–Aug | B21: ='Acceleration Test'!F13
A22: vs 2025 | B22: ='Acceleration Test'!G13
A23: Gross profit lift vs pre-program trend | B23: ='Counterfactual'!F13
A24: Total payout | B24: =Assumptions!$B$7
A25: Net of payout | B25: ='Counterfactual'!F13-Assumptions!$B$7
A27: WHAT THE PROGRAM CAN HONESTLY CLAIM
A28: Mark Anthony held. Incented White Claw and Cayman Jack fell 5.9% while the same supplier's non-incented brands fell 22.2% — the clearest evidence anywhere here that the incentive changed a rep's behaviour.
A29: No volume was bought with discount. Revenue per case held on every growing amplify brand.
A30: Distribution did not erode. Qualifier PODs fell only 1.2%, matching the control — reps held their accounts. What fell was rate of sale, which is a market result, not an effort one. That is the fair thing to say about the sales team.
A31: Engagement was near-universal: 27 of 28 reps earned something.
A33: AND ONE PLACE IT ACTUALLY WORKED
A34: On-premise — Amplify swing vs its own pre-program rate | B34: ='Channel'!E8
A35: On-premise — Qualifier swing | B35: ='Channel'!E7
A36: On-premise is the only cut in this workbook where the program accelerated — the only positive swings anywhere. It is about 11% of program volume, and even there the incented brands still trailed that channel's non-incented brands.
A37: It is the one version of this incentive the data gives any reason to run again: smaller, and weighted on-premise. See the Channel tab.
A39: THE TWO FINDINGS THAT MATTER FOR 2027
A40: 1. BRAND SELECTION decided the outcome. Boston Beer: the program paid reps to push Twisted Tea (-7,585 cases) and Truly (-3,111), both in structural decline, while Sun Cruiser — no incentive — grew 13,728 cases and $237,182 of GP with the same reps in the same summer.
A41: 2. GOAL DESIGN guaranteed payout regardless. 126 of 137 qualifier goals were set below that rep's own 2025 volume; the aggregate goal asked for 2.5% LESS than last year.
A42: Together they explain the zero correlation between payout and performance: the program paid for goals that were already met, on brands that were already moving — or already falling.
A43: Recommendation: screen candidate brands on their own trailing trajectory before attaching a dollar, and set qualifier goals above prior-year actual. A brand already growing does not need the money; a brand in structural decline will not be saved by it.
A45: AND ONE THING TO WATCH
A46: The amplify gain is concentrated: the top 10 accounts produced 37% of it and the top 100 produced 90%, out of 1,847 accounts buying those brands. Most of it sits in BJ's, Super Wine Warehouse, Beverage Barn, Total Wine and Sam's Club.
A47: Volume in those doors moves on chain decisions and warehouse display buys negotiated above the rep. A per-case incentive paid to 28 reps is not the lever that produced it.
A49: WHAT THIS CANNOT TELL YOU
A50: Whether the payout is Kohler's cost or supplier billback — nothing in the expense tracker names this program.
... A59: Program Brands / Control Brands — the engines. Data - Season / Pre / Control / Accounts — the exports. Replace a Data tab and everything recalculates.

Sheet Assumptions
A1: Assumptions, constants and open items
A2: Blue = typed in. Every other tab is formulas off these cells and the Data tabs.
A4: PROGRAM COST
A5: Tier payouts earned | B5: ='Payout vs Performance'!C33 | C5: Summer_of_Success_Recap_vF.xlsx → Rep Totals
A6: Amplify payouts earned | B6: ='Payout vs Performance'!D33 | C6: Summer_of_Success_Recap_vF.xlsx → Rep Totals
A7: Total payout | B7: =SUM(B5:B6)
A8: Reps earning > $0 / reps in the program | B8: =COUNTIF('Payout vs Performance'!$E$5:$E$32,">0")&" of "&28
A10: PERIODS AND DATA
A11: Pre-program baseline | B11: Jan 1 – May 31, 2026 vs 2025
A12: Program period | B12: Jun 1 – Aug 31, 2026 vs 2025
A13: Control | B13: Jun 1 – Aug 31, brands NOT in Summer of Success
A14: Grain of the source exports | B14: rep × supplier × brand × ACCOUNT × county
A15: Accounts / counties in the program | B15: 2,016 / 9
A16: Payout model | B16: Summer_of_Success_Recap_vF.xlsx (final)
A18: PAYOUT MODEL RULES (from the vF recap)
A19: Qualifier — a rep clears a supplier at 100% of their own personal goal; the tier is then read off the route-volume grid. Tier payouts: T1 $750 · T2 $500 · T3 $250.
A20: Amplify — pays only on cases ABOVE each brand's goal, per brand, at $1/case ($2 for Fever Tree, Mike's Harder, MXD). 90%–99.99% of the qualifier goal earns half rate and no tier; below 90% earns nothing.
A21: Excluded to match the dashboard and the recap: Default, Office Tell Sell, Chris Politano.
A23: ⚠ OPEN ITEMS — these move the cost side, not the lift finding
A24: a) FUNDING — no Summer of Success line appears in supplier-budget/expenses.csv. If the suppliers billback the payout, Kohler's cost is near zero and the finding becomes opportunity cost rather than spend. This is the one open item worth resolving before the meeting.
A25: b) TIER BASIS — the deck writes thresholds as "+25,000 CE's". If "+" means GROWTH over 2025 rather than total 2026 CE, almost no one clears Tier 1 and the tier line largely disappears.
A26: c) PER REP vs HOUSE — summer26/README.txt describes the same grid as a company-wide aggregate; the recap applies it per rep, as instructed.
A27: d) The control set is "brands not in SoS," so it contains non-incented brands from the SAME suppliers and the SAME accounts. That is what makes the within-supplier and within-account tests possible.
A28: e) STILL MISSING — a Jan–May pull of the control set (completes a formal difference-in-differences) and September actuals (tests for pull-forward).
A29: f) The account-level exports total about 0.02% more cases than the brand-level exports for the same window — rounding in RDE's aggregation. It moves nothing in this analysis.

Sheet Acceleration Test
A1: Test 1 — did growth accelerate once the program started?
A2: If the incentive worked, Jun–Aug growth should exceed the Jan–May rate the same brands were already running.
B4: Jan–May 2025 | C4: Jan–May 2026 | D4: Jan–May % | E4: Jun–Aug 2025 | F4: Jun–Aug 2026 | G4: Jun–Aug % | H4: Swing
A5: CASE EQUIVALENTS
A6: Qualifier brands | B6: =SUMIFS('Program Brands'!$J$6:$J$37,'Program Brands'!$A$6:$A$37,"Qualifier") | C6: =SUMIFS('Program Brands'!$K$6:$K$37,'Program Brands'!$A$6:$A$37,"Qualifier") | D6: =IFERROR(C6/B6-1,"") | E6: =SUMIFS('Program Brands'!$D$6:$D$37,'Program Brands'!$A$6:$A$37,"Qualifier") | F6: =SUMIFS('Program Brands'!$E$6:$E$37,'Program Brands'!$A$6:$A$37,"Qualifier") | G6: =IFERROR(F6/E6-1,"") | H6: =IFERROR(G6-D6,"")
A7: Amplify brands | B7: =SUMIFS('Program Brands'!$J$6:$J$37,'Program Brands'!$A$6:$A$37,"Amplify") | C7: =SUMIFS('Program Brands'!$K$6:$K$37,'Program Brands'!$A$6:$A$37,"Amplify") | D7: =IFERROR(C7/B7-1,"") | E7: =SUMIFS('Program Brands'!$D$6:$D$37,'Program Brands'!$A$6:$A$37,"Amplify") | F7: =SUMIFS('Program Brands'!$E$6:$E$37,'Program Brands'!$A$6:$A$37,"Amplify") | G7: =IFERROR(F7/E7-1,"") | H7: =IFERROR(G7-D7,"")
A8: All program brands | B8: =SUM(B6:B7) | C8: =SUM(C6:C7) | D8: =IFERROR(C8/B8-1,"") | E8: =SUM(E6:E7) | F8: =SUM(F6:F7) | G8: =IFERROR(F8/E8-1,"") | H8: =IFERROR(G8-D8,"")
A10: GROSS PROFIT
A11: Qualifier brands | B11: =SUMIFS('Program Brands'!$L$6:$L$37,'Program Brands'!$A$6:$A$37,"Qualifier") | C11: =SUMIFS('Program Brands'!$M$6:$M$37,'Program Brands'!$A$6:$A$37,"Qualifier") | D11: =IFERROR(C11/B11-1,"") | E11: =SUMIFS('Program Brands'!$H$6:$H$37,'Program Brands'!$A$6:$A$37,"Qualifier") | F11: =SUMIFS('Program Brands'!$I$6:$I$37,'Program Brands'!$A$6:$A$37,"Qualifier") | G11: =IFERROR(F11/E11-1,"") | H11: =IFERROR(G11-D11,"")
A12: Amplify brands | B12: =SUMIFS('Program Brands'!$L$6:$L$37,'Program Brands'!$A$6:$A$37,"Amplify") | C12: =SUMIFS('Program Brands'!$M$6:$M$37,'Program Brands'!$A$6:$A$37,"Amplify") | D12: =IFERROR(C12/B12-1,"") | E12: =SUMIFS('Program Brands'!$H$6:$H$37,'Program Brands'!$A$6:$A$37,"Amplify") | F12: =SUMIFS('Program Brands'!$I$6:$I$37,'Program Brands'!$A$6:$A$37,"Amplify") | G12: =IFERROR(F12/E12-1,"") | H12: =IFERROR(G12-D12,"")
A13: All program brands | B13: =SUM(B11:B12) | C13: =SUM(C11:C12) | D13: =IFERROR(C13/B13-1,"") | E13: =SUM(E11:E12) | F13: =SUM(F11:F12) | G13: =IFERROR(F13/E13-1,"") | H13: =IFERROR(G13-D13,"")
A15: HOW TO READ THIS
A16: The Swing column is the test: Jun–Aug growth rate minus Jan–May growth rate. A positive swing is the signature of an incentive that changed behaviour.
A17: Amplify entered the summer already growing double digits and did not speed up. Qualifier volume slowed by nearly three points.
A18: Jan–May and Jun–Aug are different seasons, so each period is measured against its OWN prior year — that removes seasonality from the rates being compared. What it cannot remove is a change in the market between the two windows; the control tabs handle that.

Sheet Counterfactual
A1: Test 2 — measured lift against the pre-program trajectory
A2: Applies each segment's Jan–May growth rate to its Jun–Aug 2025 base. The gap to what actually happened is the lift the program can claim.
B4: Jan–May run rate | C4: Jun–Aug 2025 base | D4: Expected Jun–Aug | E4: Actual Jun–Aug | F4: Lift vs trend
A5: CASE EQUIVALENTS
A6: Qualifier brands | B6: ='Acceleration Test'!D6 | C6: ='Acceleration Test'!E6 | D6: =C6*(1+B6) | E6: ='Acceleration Test'!F6 | F6: =E6-D6
A7: Amplify brands | B7: ='Acceleration Test'!D7 | C7: ='Acceleration Test'!E7 | D7: =C7*(1+B7) | E7: ='Acceleration Test'!F7 | F7: =E7-D7
A8: TOTAL | C8: =SUM(C6:C7) | D8: =SUM(D6:D7) | E8: =SUM(E6:E7) | F8: =SUM(F6:F7)
A10: GROSS PROFIT
A11: Qualifier brands | B11: ='Acceleration Test'!D11 | C11: ='Acceleration Test'!E11 | D11: =C11*(1+B11) | E11: ='Acceleration Test'!F11 | F11: =E11-D11
A12: Amplify brands | B12: ='Acceleration Test'!D12 | C12: ='Acceleration Test'!E12 | D12: =C12*(1+B12) | E12: ='Acceleration Test'!F12 | F12: =E12-D12
A13: TOTAL | C13: =SUM(C11:C12) | D13: =SUM(D11:D12) | E13: =SUM(E11:E12) | F13: =SUM(F11:F12)
A15: THE BOTTOM LINE
A16: Gross profit lift vs pre-program trend | B16: =F13
A17: Case lift vs pre-program trend | B17: =F8
A18: Amplify GP lift alone (what the per-case payout targets) | B18: =F12
A19: Total payout | B19: =Assumptions!$B$7
A20: Net of payout | B20: =F13-Assumptions!$B$7
A21: Return per payout dollar | B21: =IFERROR(F13/Assumptions!$B$7,"")
A23: Read the Amplify line first: it is the segment the per-case payout actually targets, and it landed within a rounding error of the trajectory it was already on.
A24: The Qualifier GP line reads positive, but the GP Bridge and control tabs show why that is not program lift — it is a house-wide margin expansion the non-incented book captured far more of, per case.
A25: A trend extrapolation assumes the Jan–May trajectory would have continued. The control tabs test that assumption directly, and agree.

Sheet Control by Supplier
A1: Test 3 — incented brands vs the SAME supplier's non-incented brands
A2: Jun–Aug, same reps, same window, same pricing environment. The only difference between the two halves is whether a payout was attached.
A4: Supplier | B4: Incented CE 2025 | C4: Incented CE 2026 | D4: Incented % | E4: Not incented CE 2025 | F4: Not incented CE 2026 | G4: Not incented % | H4: Gap (pts) | I4: Incented GP Δ | J4: Not incented GP Δ
A5: Bell's | B5: =SUMIFS('Program Brands'!$D$6:$D$37,'Program Brands'!$B$6:$B$37,$A5) | C5: =SUMIFS('Program Brands'!$E$6:$E$37,'Program Brands'!$B$6:$B$37,$A5) | D5: =IFERROR(C5/B5-1,"") | E5: =SUMIFS('Control Brands'!$C$5:$C$296,'Control Brands'!$A$5:$A$296,$A5) | F5: =SUMIFS('Control Brands'!$D$5:$D$296,'Control Brands'!$A$5:$A$296,$A5) | G5: =IFERROR(F5/E5-1,"") | H5: =IFERROR(D5-G5,"") | I5: =SUMIFS('Program Brands'!$I$6:$I$37,'Program Brands'!$B$6:$B$37,$A5)-SUMIFS('Program Brands'!$H$6:$H$37,'Program Brands'!$B$6:$B$37,$A5) | J5: =SUMIFS('Control Brands'!$H$5:$H$296,'Control Brands'!$A$5:$A$296,$A5)-SUMIFS('Control Brands'!$G$5:$G$296,'Control Brands'!$A$5:$A$296,$A5)
A6: Boston Beer Company | B6: =SUMIFS('Program Brands'!$D$6:$D$37,'Program Brands'!$B$6:$B$37,$A6) | C6: =SUMIFS('Program Brands'!$E$6:$E$37,'Program Brands'!$B$6:$B$37,$A6) | D6: =IFERROR(C6/B6-1,"") | E6: =SUMIFS('Control Brands'!$C$5:$C$296,'Control Brands'!$A$5:$A$296,$A6) | F6: =SUMIFS('Control Brands'!$D$5:$D$296,'Control Brands'!$A$5:$A$296,$A6) | G6: =IFERROR(F6/E6-1,"") | H6: =IFERROR(D6-G6,"") | I6: =SUMIFS('Program Brands'!$I$6:$I$37,'Program Brands'!$B$6:$B$37,$A6)-SUMIFS('Program Brands'!$H$6:$H$37,'Program Brands'!$B$6:$B$37,$A6) | J6: =SUMIFS('Control Brands'!$H$5:$H$296,'Control Brands'!$A$5:$A$296,$A6)-SUMIFS('Control Brands'!$G$5:$G$296,'Control Brands'!$A$5:$A$296,$A6)
A7: Constellation Brands | B7: =SUMIFS('Program Brands'!$D$6:$D$37,'Program Brands'!$B$6:$B$37,$A7) | C7: =SUMIFS('Program Brands'!$E$6:$E$37,'Program Brands'!$B$6:$B$37,$A7) | D7: =IFERROR(C7/B7-1,"") | E7: =SUMIFS('Control Brands'!$C$5:$C$296,'Control Brands'!$A$5:$A$296,$A7) | F7: =SUMIFS('Control Brands'!$D$5:$D$296,'Control Brands'!$A$5:$A$296,$A7) | G7: =IFERROR(F7/E7-1,"") | H7: =IFERROR(D7-G7,"") | I7: =SUMIFS('Program Brands'!$I$6:$I$37,'Program Brands'!$B$6:$B$37,$A7)-SUMIFS('Program Brands'!$H$6:$H$37,'Program Brands'!$B$6:$B$37,$A7) | J7: =SUMIFS('Control Brands'!$H$5:$H$296,'Control Brands'!$A$5:$A$296,$A7)-SUMIFS('Control Brands'!$G$5:$G$296,'Control Brands'!$A$5:$A$296,$A7)
A8: DG Yuengling Inc | B8: =SUMIFS('Program Brands'!$D$6:$D$37,'Program Brands'!$B$6:$B$37,$A8) | C8: =SUMIFS('Program Brands'!$E$6:$E$37,'Program Brands'!$B$6:$B$37,$A8) | D8: =IFERROR(C8/B8-1,"") | E8: =SUMIFS('Control Brands'!$C$5:$C$296,'Control Brands'!$A$5:$A$296,$A8) | F8: =SUMIFS('Control Brands'!$D$5:$D$296,'Control Brands'!$A$5:$A$296,$A8) | G8: =IFERROR(F8/E8-1,"") | H8: =IFERROR(D8-G8,"") | I8: =SUMIFS('Program Brands'!$I$6:$I$37,'Program Brands'!$B$6:$B$37,$A8)-SUMIFS('Program Brands'!$H$6:$H$37,'Program Brands'!$B$6:$B$37,$A8) | J8: =SUMIFS('Control Brands'!$H$5:$H$296,'Control Brands'!$A$5:$A$296,$A8)-SUMIFS('Control Brands'!$G$5:$G$296,'Control Brands'!$A$5:$A$296,$A8)
A9: Heineken USA | B9: =SUMIFS('Program Brands'!$D$6:$D$37,'Program Brands'!$B$6:$B$37,$A9) | C9: =SUMIFS('Program Brands'!$E$6:$E$37,'Program Brands'!$B$6:$B$37,$A9) | D9: =IFERROR(C9/B9-1,"") | E9: =SUMIFS('Control Brands'!$C$5:$C$296,'Control Brands'!$A$5:$A$296,$A9) | F9: =SUMIFS('Control Brands'!$D$5:$D$296,'Control Brands'!$A$5:$A$296,$A9) | G9: =IFERROR(F9/E9-1,"") | H9: =IFERROR(D9-G9,"") | I9: =SUMIFS('Program Brands'!$I$6:$I$37,'Program Brands'!$B$6:$B$37,$A9)-SUMIFS('Program Brands'!$H$6:$H$37,'Program Brands'!$B$6:$B$37,$A9) | J9: =SUMIFS('Control Brands'!$H$5:$H$296,'Control Brands'!$A$5:$A$296,$A9)-SUMIFS('Control Brands'!$G$5:$G$296,'Control Brands'!$A$5:$A$296,$A9)
A10: Mark Anthony | B10: =SUMIFS('Program Brands'!$D$6:$D$37,'Program Brands'!$B$6:$B$37,$A10) | C10: =SUMIFS('Program Brands'!$E$6:$E$37,'Program Brands'!$B$6:$B$37,$A10) | D10: =IFERROR(C10/B10-1,"") | E10: =SUMIFS('Control Brands'!$C$5:$C$296,'Control Brands'!$A$5:$A$296,$A10) | F10: =SUMIFS('Control Brands'!$D$5:$D$296,'Control Brands'!$A$5:$A$296,$A10) | G10: =IFERROR(F10/E10-1,"") | H10: =IFERROR(D10-G10,"") | I10: =SUMIFS('Program Brands'!$I$6:$I$37,'Program Brands'!$B$6:$B$37,$A10)-SUMIFS('Program Brands'!$H$6:$H$37,'Program Brands'!$B$6:$B$37,$A10) | J10: =SUMIFS('Control Brands'!$H$5:$H$296,'Control Brands'!$A$5:$A$296,$A10)-SUMIFS('Control Brands'!$G$5:$G$296,'Control Brands'!$A$5:$A$296,$A10)
A11: MolsonCoors Beverage Company | B11: =SUMIFS('Program Brands'!$D$6:$D$37,'Program Brands'!$B$6:$B$37,$A11) | C11: =SUMIFS('Program Brands'!$E$6:$E$37,'Program Brands'!$B$6:$B$37,$A11) | D11: =IFERROR(C11/B11-1,"") | E11: =SUMIFS('Control Brands'!$C$5:$C$296,'Control Brands'!$A$5:$A$296,$A11) | F11: =SUMIFS('Control Brands'!$D$5:$D$296,'Control Brands'!$A$5:$A$296,$A11) | G11: =IFERROR(F11/E11-1,"") | H11: =IFERROR(D11-G11,"") | I11: =SUMIFS('Program Brands'!$I$6:$I$37,'Program Brands'!$B$6:$B$37,$A11)-SUMIFS('Program Brands'!$H$6:$H$37,'Program Brands'!$B$6:$B$37,$A11) | J11: =SUMIFS('Control Brands'!$H$5:$H$296,'Control Brands'!$A$5:$A$296,$A11)-SUMIFS('Control Brands'!$G$5:$G$296,'Control Brands'!$A$5:$A$296,$A11)
A12: New Belgium Brewing Company | B12: =SUMIFS('Program Brands'!$D$6:$D$37,'Program Brands'!$B$6:$B$37,$A12) | C12: =SUMIFS('Program Brands'!$E$6:$E$37,'Program Brands'!$B$6:$B$37,$A12) | D12: =IFERROR(C12/B12-1,"") | E12: =SUMIFS('Control Brands'!$C$5:$C$296,'Control Brands'!$A$5:$A$296,$A12) | F12: =SUMIFS('Control Brands'!$D$5:$D$296,'Control Brands'!$A$5:$A$296,$A12) | G12: =IFERROR(F12/E12-1,"") | H12: =IFERROR(D12-G12,"") | I12: =SUMIFS('Program Brands'!$I$6:$I$37,'Program Brands'!$B$6:$B$37,$A12)-SUMIFS('Program Brands'!$H$6:$H$37,'Program Brands'!$B$6:$B$37,$A12) | J12: =SUMIFS('Control Brands'!$H$5:$H$296,'Control Brands'!$A$5:$A$296,$A12)-SUMIFS('Control Brands'!$G$5:$G$296,'Control Brands'!$A$5:$A$296,$A12)
A13: WEIGHTED TOTAL | B13: =SUM(B5:B12) | C13: =SUM(C5:C12) | D13: =IFERROR(C13/B13-1,"") | E13: =SUM(E5:E12) | F13: =SUM(F5:F12) | G13: =IFERROR(F13/E13-1,"") | H13: =IFERROR(D13-G13,"") | I13: =SUM(I5:I12) | J13: =SUM(J5:J12)
A15: Only suppliers appearing on both sides are shown — those are the ones where a true within-supplier comparison exists.
A16: A negative gap means that supplier's incented brands did worse than its own non-incented brands over the same three months.
A17: Boston Beer is the finding worth presenting — see the Brand Selection tab.

Sheet Within-Account Control
A1: The tightest control available — same account, same summer, same buyer
A2: Restricted to accounts that bought BOTH incented and non-incented brands. Account mix, rep, channel and geography are all held constant; the only difference is the incentive.
B4: CE 2025 | C4: CE 2026 | D4: Change
A5: Accounts buying on both sides | B5: =COUNTIFS('Data - Accounts'!$E$5:$E$2358,">0",'Data - Accounts'!$I$5:$I$2358,">0")
A7: INCENTED brands in those accounts | B7: =SUMIFS('Data - Accounts'!$E$5:$E$2358,'Data - Accounts'!$E$5:$E$2358,">0",'Data - Accounts'!$I$5:$I$2358,">0") | C7: =SUMIFS('Data - Accounts'!$F$5:$F$2358,'Data - Accounts'!$E$5:$E$2358,">0",'Data - Accounts'!$I$5:$I$2358,">0") | D7: =IFERROR(C7/B7-1,"")
A8: NON-incented brands in the SAME accounts | B8: =SUMIFS('Data - Accounts'!$I$5:$I$2358,'Data - Accounts'!$E$5:$E$2358,">0",'Data - Accounts'!$I$5:$I$2358,">0") | C8: =SUMIFS('Data - Accounts'!$J$5:$J$2358,'Data - Accounts'!$E$5:$E$2358,">0",'Data - Accounts'!$I$5:$I$2358,">0") | D8: =IFERROR(C8/B8-1,"")
A9: Gap | D9: =D7-D8
A11: WHY THIS MATTERS MOST
A12: Every other control in this workbook can be answered with "but those were different accounts." This one cannot. Inside the same 1,704 stores, over the same three months, the brands carrying an incentive performed no better than the brands carrying none.
A13: It is also the fairest test to the sales team: it holds constant everything a rep does not control — which accounts they have, what channel, what geography — and still finds no incentive effect.

Sheet Distribution
A1: Did the program build distribution, or just move cases?
A2: A POD is one account × brand that bought. ΔCE splits into a distribution effect (more or fewer PODs) and a rate-of-sale effect (each POD buying more or less).
B4: PODs 2025 | C4: PODs 2026 | D4: POD % | E4: New PODs | F4: CE from new | G4: Lost PODs | H4: CE from lost | I4: Cases/POD 25 | J4: Cases/POD 26 | K4: Rate % | L4: Distribution effect | M4: Rate-of-sale effect | O4: CE 2025 | P4: CE 2026
A5: JUN–AUG — the program period
A6: Qualifier brands | B6: =SUMIFS('Data - Season'!$K$5:$K$743,'Data - Season'!$B$5:$B$743,"Qualifier") | C6: =SUMIFS('Data - Season'!$L$5:$L$743,'Data - Season'!$B$5:$B$743,"Qualifier") | D6: =IFERROR(C6/B6-1,"") | E6: =SUMIFS('Data - Season'!$M$5:$M$743,'Data - Season'!$B$5:$B$743,"Qualifier") | F6: =SUMIFS('Data - Season'!$N$5:$N$743,'Data - Season'!$B$5:$B$743,"Qualifier") | G6: =SUMIFS('Data - Season'!$O$5:$O$743,'Data - Season'!$B$5:$B$743,"Qualifier") | H6: =SUMIFS('Data - Season'!$P$5:$P$743,'Data - Season'!$B$5:$B$743,"Qualifier") | I6: =IFERROR(O6/B6,"") | J6: =IFERROR(P6/C6,"") | K6: =IFERROR(J6/I6-1,"") | L6: =(C6-B6)*I6 | M6: =C6*(J6-I6) | O6: =SUMIFS('Data - Season'!$E$5:$E$743,'Data - Season'!$B$5:$B$743,"Qualifier") | P6: =SUMIFS('Data - Season'!$F$5:$F$743,'Data - Season'!$B$5:$B$743,"Qualifier")
A7: Amplify brands | B7: =SUMIFS('Data - Season'!$K$5:$K$743,'Data - Season'!$B$5:$B$743,"Amplify") | C7: =SUMIFS('Data - Season'!$L$5:$L$743,'Data - Season'!$B$5:$B$743,"Amplify") | D7: =IFERROR(C7/B7-1,"") | E7: =SUMIFS('Data - Season'!$M$5:$M$743,'Data - Season'!$B$5:$B$743,"Amplify") | F7: =SUMIFS('Data - Season'!$N$5:$N$743,'Data - Season'!$B$5:$B$743,"Amplify") | G7: =SUMIFS('Data - Season'!$O$5:$O$743,'Data - Season'!$B$5:$B$743,"Amplify") | H7: =SUMIFS('Data - Season'!$P$5:$P$743,'Data - Season'!$B$5:$B$743,"Amplify") | I7: =IFERROR(O7/B7,"") | J7: =IFERROR(P7/C7,"") | K7: =IFERROR(J7/I7-1,"") | L7: =(C7-B7)*I7 | M7: =C7*(J7-I7) | O7: =SUMIFS('Data - Season'!$E$5:$E$743,'Data - Season'!$B$5:$B$743,"Amplify") | P7: =SUMIFS('Data - Season'!$F$5:$F$743,'Data - Season'!$B$5:$B$743,"Amplify")
A8: Non-program brands (control) | B8: =SUM('Data - Control'!$I$5:$I$296) | C8: =SUM('Data - Control'!$J$5:$J$296) | D8: =IFERROR(C8/B8-1,"") | E8: =SUM('Data - Control'!$K$5:$K$296) | F8: =SUM('Data - Control'!$L$5:$L$296) | G8: =SUM('Data - Control'!$M$5:$M$296) | H8: =SUM('Data - Control'!$N$5:$N$296) | I8: =IFERROR(O8/B8,"") | J8: =IFERROR(P8/C8,"") | K8: =IFERROR(J8/I8-1,"") | L8: =(C8-B8)*I8 | M8: =C8*(J8-I8) | O8: =SUM('Data - Control'!$C$5:$C$296) | P8: =SUM('Data - Control'!$D$5:$D$296)
A10: JAN–MAY — the same brands, before the program
A11: Qualifier brands | B11: =SUMIFS('Data - Pre'!$J$5:$J$36,'Data - Pre'!$A$5:$A$36,"Qualifier") | C11: =SUMIFS('Data - Pre'!$K$5:$K$36,'Data - Pre'!$A$5:$A$36,"Qualifier") | D11: =IFERROR(C11/B11-1,"") | E11: =SUMIFS('Data - Pre'!$L$5:$L$36,'Data - Pre'!$A$5:$A$36,"Qualifier") | F11: =SUMIFS('Data - Pre'!$M$5:$M$36,'Data - Pre'!$A$5:$A$36,"Qualifier") | G11: =SUMIFS('Data - Pre'!$N$5:$N$36,'Data - Pre'!$A$5:$A$36,"Qualifier") | H11: =SUMIFS('Data - Pre'!$O$5:$O$36,'Data - Pre'!$A$5:$A$36,"Qualifier") | I11: =IFERROR(O11/B11,"") | J11: =IFERROR(P11/C11,"") | K11: =IFERROR(J11/I11-1,"") | L11: =(C11-B11)*I11 | M11: =C11*(J11-I11) | O11: =SUMIFS('Data - Pre'!$D$5:$D$36,'Data - Pre'!$A$5:$A$36,"Qualifier") | P11: =SUMIFS('Data - Pre'!$E$5:$E$36,'Data - Pre'!$A$5:$A$36,"Qualifier")
A12: Amplify brands | B12: =SUMIFS('Data - Pre'!$J$5:$J$36,'Data - Pre'!$A$5:$A$36,"Amplify") | C12: =SUMIFS('Data - Pre'!$K$5:$K$36,'Data - Pre'!$A$5:$A$36,"Amplify") | D12: =IFERROR(C12/B12-1,"") | E12: =SUMIFS('Data - Pre'!$L$5:$L$36,'Data - Pre'!$A$5:$A$36,"Amplify") | F12: =SUMIFS('Data - Pre'!$M$5:$M$36,'Data - Pre'!$A$5:$A$36,"Amplify") | G12: =SUMIFS('Data - Pre'!$N$5:$N$36,'Data - Pre'!$A$5:$A$36,"Amplify") | H12: =SUMIFS('Data - Pre'!$O$5:$O$36,'Data - Pre'!$A$5:$A$36,"Amplify") | I12: =IFERROR(O12/B12,"") | J12: =IFERROR(P12/C12,"") | K12: =IFERROR(J12/I12-1,"") | L12: =(C12-B12)*I12 | M12: =C12*(J12-I12) | O12: =SUMIFS('Data - Pre'!$D$5:$D$36,'Data - Pre'!$A$5:$A$36,"Amplify") | P12: =SUMIFS('Data - Pre'!$E$5:$E$36,'Data - Pre'!$A$5:$A$36,"Amplify")
A14: WHAT THIS SETTLES
A15: Amplify PODs grew 4.2% during the program — but 5.5% in the five months BEFORE it. Distribution growth decelerated, exactly like volume did.
A16: The qualifier decline was NOT lost distribution. PODs fell only 1.2%, the same as the control; what collapsed was rate of sale, from -0.9% pre-program to -4.1% during. Reps held their accounts; the accounts bought less. That is a market result, not an effort one.
A17: Distribution effect = (PODs 2026 − PODs 2025) × cases per POD in 2025. Rate-of-sale effect = PODs 2026 × the change in cases per POD. The two sum to ΔCE.

Sheet Account Concentration
A1: How many accounts actually produced the gain?
A2: AMPLIFY volume only — that is the segment with a positive net change, and the only one where "share of the gain" means anything. Accounts ranked by amplify case gain.
A4: Rank | B4: Account | C4: County | D4: Channel | E4: Rep | F4: Amplify CE 2025 | G4: Amplify CE 2026 | H4: Δ cases | I4: Cumulative Δ | J4: Share of net amplify gain
A5: 1 | B5: ='Data - Accounts'!A5 | C5: ='Data - Accounts'!B5 | D5: ='Data - Accounts'!D5 | E5: ='Data - Accounts'!C5 | F5: ='Data - Accounts'!K5 | G5: ='Data - Accounts'!L5 | H5: =G5-F5 | I5: =SUM($H$5:$H5) | J5: =IFERROR($I5/$B$67,"")
A6: 2 | B6: ='Data - Accounts'!A6 | C6: ='Data - Accounts'!B6 | D6: ='Data - Accounts'!D6 | E6: ='Data - Accounts'!C6 | F6: ='Data - Accounts'!K6 | G6: ='Data - Accounts'!L6 | H6: =G6-F6 | I6: =SUM($H$5:$H6) | J6: =IFERROR($I6/$B$67,"")
A7: 3 | B7: ='Data - Accounts'!A7 | C7: ='Data - Accounts'!B7 | D7: ='Data - Accounts'!D7 | E7: ='Data - Accounts'!C7 | F7: ='Data - Accounts'!K7 | G7: ='Data - Accounts'!L7 | H7: =G7-F7 | I7: =SUM($H$5:$H7) | J7: =IFERROR($I7/$B$67,"")
A8: 4 | B8: ='Data - Accounts'!A8 | C8: ='Data - Accounts'!B8 | D8: ='Data - Accounts'!D8 | E8: ='Data - Accounts'!C8 | F8: ='Data - Accounts'!K8 | G8: ='Data - Accounts'!L8 | H8: =G8-F8 | I8: =SUM($H$5:$H8) | J8: =IFERROR($I8/$B$67,"")
A9: 5 | B9: ='Data - Accounts'!A9 | C9: ='Data - Accounts'!B9 | D9: ='Data - Accounts'!D9 | E9: ='Data - Accounts'!C9 | F9: ='Data - Accounts'!K9 | G9: ='Data - Accounts'!L9 | H9: =G9-F9 | I9: =SUM($H$5:$H9) | J9: =IFERROR($I9/$B$67,"")
A10: 6 | B10: ='Data - Accounts'!A10 | C10: ='Data - Accounts'!B10 | D10: ='Data - Accounts'!D10 | E10: ='Data - Accounts'!C10 | F10: ='Data - Accounts'!K10 | G10: ='Data - Accounts'!L10 | H10: =G10-F10 | I10: =SUM($H$5:$H10) | J10: =IFERROR($I10/$B$67,"")
A11: 7 | B11: ='Data - Accounts'!A11 | C11: ='Data - Accounts'!B11 | D11: ='Data - Accounts'!D11 | E11: ='Data - Accounts'!C11 | F11: ='Data - Accounts'!K11 | G11: ='Data - Accounts'!L11 | H11: =G11-F11 | I11: =SUM($H$5:$H11) | J11: =IFERROR($I11/$B$67,"")
A12: 8 | B12: ='Data - Accounts'!A12 | C12: ='Data - Accounts'!B12 | D12: ='Data - Accounts'!D12 | E12: ='Data - Accounts'!C12 | F12: ='Data - Accounts'!K12 | G12: ='Data - Accounts'!L12 | H12: =G12-F12 | I12: =SUM($H$5:$H12) | J12: =IFERROR($I12/$B$67,"")
A13: 9 | B13: ='Data - Accounts'!A13 | C13: ='Data - Accounts'!B13 | D13: ='Data - Accounts'!D13 | E13: ='Data - Accounts'!C13 | F13: ='Data - Accounts'!K13 | G13: ='Data - Accounts'!L13 | H13: =G13-F13 | I13: =SUM($H$5:$H13) | J13: =IFERROR($I13/$B$67,"")
A14: 10 | B14: ='Data - Accounts'!A14 | C14: ='Data - Accounts'!B14 | D14: ='Data - Accounts'!D14 | E14: ='Data - Accounts'!C14 | F14: ='Data - Accounts'!K14 | G14: ='Data - Accounts'!L14 | H14: =G14-F14 | I14: =SUM($H$5:$H14) | J14: =IFERROR($I14/$B$67,"")
A15: 11 | B15: ='Data - Accounts'!A15 | C15: ='Data - Accounts'!B15 | D15: ='Data - Accounts'!D15 | E15: ='Data - Accounts'!C15 | F15: ='Data - Accounts'!K15 | G15: ='Data - Accounts'!L15 | H15: =G15-F15 | I15: =SUM($H$5:$H15) | J15: =IFERROR($I15/$B$67,"")
A16: 12 | B16: ='Data - Accounts'!A16 | C16: ='Data - Accounts'!B16 | D16: ='Data - Accounts'!D16 | E16: ='Data - Accounts'!C16 | F16: ='Data - Accounts'!K16 | G16: ='Data - Accounts'!L16 | H16: =G16-F16 | I16: =SUM($H$5:$H16) | J16: =IFERROR($I16/$B$67,"")
... A64: 60 | B64: ='Data - Accounts'!A64 | C64: ='Data - Accounts'!B64 | D64: ='Data - Accounts'!D64 | E64: ='Data - Accounts'!C64 | F64: ='Data - Accounts'!K64 | G64: ='Data - Accounts'!L64 | H64: =G64-F64 | I64: =SUM($H$5:$H64) | J64: =IFERROR($I64/$B$67,"")
A66: Net AMPLIFY case gain, all accounts
A67: Net amplify case gain, all accounts | B67: =SUM('Data - Accounts'!$L$5:$L$2358)-SUM('Data - Accounts'!$K$5:$K$2358)
A68: Accounts buying amplify brands | B68: =COUNTIF('Data - Accounts'!$L$5:$L$2358,">0")+COUNTIFS('Data - Accounts'!$L$5:$L$2358,0,'Data - Accounts'!$K$5:$K$2358,">0")
A69: of those, accounts that grew | B69: =COUNTIF('Data - Accounts'!$N$5:$N$2358,">0")
A70: accounts that declined | B70: =COUNTIF('Data - Accounts'!$N$5:$N$2358,"<0")
A71: Top 10 accounts — share of the net amplify gain | B71: =IFERROR(SUM($H$5:$H$14)/$B$67,"")
A72: Top 25 accounts — share of the net amplify gain | B72: =IFERROR(SUM($H$5:$H$29)/$B$67,"")
A73: Top 50 accounts — share of the net amplify gain | B73: =IFERROR(SUM($H$5:$H$54)/$B$67,"")
A74: For contrast — net PROGRAM case change, all accounts | B74: =SUM('Data - Accounts'!$F$5:$F$2358)-SUM('Data - Accounts'!$E$5:$E$2358)
A76: WHAT THIS MEANS
A77: The gain is not broad execution across a route. A handful of large-format accounts — BJ's, Super Wine Warehouse, Beverage Barn, Total Wine, Sam's Club — carry most of it.
A78: Volume in those doors moves on chain decisions and warehouse display buys negotiated above the rep. A per-case incentive paid to 28 reps is not the lever that produced it, and would not reliably reproduce it.
A79: This is also why the program looked better at brand level than it does here: brand totals hide the fact that the growth came from very few doors.
A80: The last line is the reminder that the program as a whole LOST cases. Concentration is measured on amplify because that is the only segment with a gain to concentrate.

Sheet Channel
A1: On-premise vs off-premise — the one place the program shows a pulse
A2: Same acceleration test as Test 1, cut by channel, with each channel's own non-incented brands as the control.
A4: Channel | B4: Segment | C4: Jan–May % | D4: Jun–Aug % | E4: Swing | F4: Jun–Aug CE 2026 | G4: Share of program volume | H4: Control % (same channel) | I4: Gap vs control
A5: Off-premise | B5: Qualifier | C5: =IFERROR(SUMIFS('Data - Channel'!$E$5:$E$19,'Data - Channel'!$A$5:$A$19,"Off-premise",'Data - Channel'!$B$5:$B$19,"Jan–May",'Data - Channel'!$C$5:$C$19,"Qualifier")/SUMIFS('Data - Channel'!$D$5:$D$19,'Data - Channel'!$A$5:$A$19,"Off-premise",'Data - Channel'!$B$5:$B$19,"Jan–May",'Data - Channel'!$C$5:$C$19,"Qualifier")-1,"") | D5: =IFERROR(SUMIFS('Data - Channel'!$E$5:$E$19,'Data - Channel'!$A$5:$A$19,"Off-premise",'Data - Channel'!$B$5:$B$19,"Jun–Aug",'Data - Channel'!$C$5:$C$19,"Qualifier")/SUMIFS('Data - Channel'!$D$5:$D$19,'Data - Channel'!$A$5:$A$19,"Off-premise",'Data - Channel'!$B$5:$B$19,"Jun–Aug",'Data - Channel'!$C$5:$C$19,"Qualifier")-1,"") | E5: =IFERROR(D5-C5,"") | F5: =SUMIFS('Data - Channel'!$E$5:$E$19,'Data - Channel'!$A$5:$A$19,"Off-premise",'Data - Channel'!$B$5:$B$19,"Jun–Aug",'Data - Channel'!$C$5:$C$19,"Qualifier") | G5: =IFERROR(F5/SUM('Data - Accounts'!$F$5:$F$2358),"") | H5: =IFERROR(SUMIFS('Data - Channel'!$E$5:$E$19,'Data - Channel'!$A$5:$A$19,"Off-premise",'Data - Channel'!$B$5:$B$19,"Jun–Aug",'Data - Channel'!$C$5:$C$19,"Control")/SUMIFS('Data - Channel'!$D$5:$D$19,'Data - Channel'!$A$5:$A$19,"Off-premise",'Data - Channel'!$B$5:$B$19,"Jun–Aug",'Data - Channel'!$C$5:$C$19,"Control")-1,"") | I5: =IFERROR(D5-H5,"")
A6: Off-premise | B6: Amplify | C6: =IFERROR(SUMIFS('Data - Channel'!$E$5:$E$19,'Data - Channel'!$A$5:$A$19,"Off-premise",'Data - Channel'!$B$5:$B$19,"Jan–May",'Data - Channel'!$C$5:$C$19,"Amplify")/SUMIFS('Data - Channel'!$D$5:$D$19,'Data - Channel'!$A$5:$A$19,"Off-premise",'Data - Channel'!$B$5:$B$19,"Jan–May",'Data - Channel'!$C$5:$C$19,"Amplify")-1,"") | D6: =IFERROR(SUMIFS('Data - Channel'!$E$5:$E$19,'Data - Channel'!$A$5:$A$19,"Off-premise",'Data - Channel'!$B$5:$B$19,"Jun–Aug",'Data - Channel'!$C$5:$C$19,"Amplify")/SUMIFS('Data - Channel'!$D$5:$D$19,'Data - Channel'!$A$5:$A$19,"Off-premise",'Data - Channel'!$B$5:$B$19,"Jun–Aug",'Data - Channel'!$C$5:$C$19,"Amplify")-1,"") | E6: =IFERROR(D6-C6,"") | F6: =SUMIFS('Data - Channel'!$E$5:$E$19,'Data - Channel'!$A$5:$A$19,"Off-premise",'Data - Channel'!$B$5:$B$19,"Jun–Aug",'Data - Channel'!$C$5:$C$19,"Amplify") | G6: =IFERROR(F6/SUM('Data - Accounts'!$F$5:$F$2358),"") | H6: =IFERROR(SUMIFS('Data - Channel'!$E$5:$E$19,'Data - Channel'!$A$5:$A$19,"Off-premise",'Data - Channel'!$B$5:$B$19,"Jun–Aug",'Data - Channel'!$C$5:$C$19,"Control")/SUMIFS('Data - Channel'!$D$5:$D$19,'Data - Channel'!$A$5:$A$19,"Off-premise",'Data - Channel'!$B$5:$B$19,"Jun–Aug",'Data - Channel'!$C$5:$C$19,"Control")-1,"") | I6: =IFERROR(D6-H6,"")
A7: On-premise | B7: Qualifier | C7: =IFERROR(SUMIFS('Data - Channel'!$E$5:$E$19,'Data - Channel'!$A$5:$A$19,"On-premise",'Data - Channel'!$B$5:$B$19,"Jan–May",'Data - Channel'!$C$5:$C$19,"Qualifier")/SUMIFS('Data - Channel'!$D$5:$D$19,'Data - Channel'!$A$5:$A$19,"On-premise",'Data - Channel'!$B$5:$B$19,"Jan–May",'Data - Channel'!$C$5:$C$19,"Qualifier")-1,"") | D7: =IFERROR(SUMIFS('Data - Channel'!$E$5:$E$19,'Data - Channel'!$A$5:$A$19,"On-premise",'Data - Channel'!$B$5:$B$19,"Jun–Aug",'Data - Channel'!$C$5:$C$19,"Qualifier")/SUMIFS('Data - Channel'!$D$5:$D$19,'Data - Channel'!$A$5:$A$19,"On-premise",'Data - Channel'!$B$5:$B$19,"Jun–Aug",'Data - Channel'!$C$5:$C$19,"Qualifier")-1,"") | E7: =IFERROR(D7-C7,"") | F7: =SUMIFS('Data - Channel'!$E$5:$E$19,'Data - Channel'!$A$5:$A$19,"On-premise",'Data - Channel'!$B$5:$B$19,"Jun–Aug",'Data - Channel'!$C$5:$C$19,"Qualifier") | G7: =IFERROR(F7/SUM('Data - Accounts'!$F$5:$F$2358),"") | H7: =IFERROR(SUMIFS('Data - Channel'!$E$5:$E$19,'Data - Channel'!$A$5:$A$19,"On-premise",'Data - Channel'!$B$5:$B$19,"Jun–Aug",'Data - Channel'!$C$5:$C$19,"Control")/SUMIFS('Data - Channel'!$D$5:$D$19,'Data - Channel'!$A$5:$A$19,"On-premise",'Data - Channel'!$B$5:$B$19,"Jun–Aug",'Data - Channel'!$C$5:$C$19,"Control")-1,"") | I7: =IFERROR(D7-H7,"")
A8: On-premise | B8: Amplify | C8: =IFERROR(SUMIFS('Data - Channel'!$E$5:$E$19,'Data - Channel'!$A$5:$A$19,"On-premise",'Data - Channel'!$B$5:$B$19,"Jan–May",'Data - Channel'!$C$5:$C$19,"Amplify")/SUMIFS('Data - Channel'!$D$5:$D$19,'Data - Channel'!$A$5:$A$19,"On-premise",'Data - Channel'!$B$5:$B$19,"Jan–May",'Data - Channel'!$C$5:$C$19,"Amplify")-1,"") | D8: =IFERROR(SUMIFS('Data - Channel'!$E$5:$E$19,'Data - Channel'!$A$5:$A$19,"On-premise",'Data - Channel'!$B$5:$B$19,"Jun–Aug",'Data - Channel'!$C$5:$C$19,"Amplify")/SUMIFS('Data - Channel'!$D$5:$D$19,'Data - Channel'!$A$5:$A$19,"On-premise",'Data - Channel'!$B$5:$B$19,"Jun–Aug",'Data - Channel'!$C$5:$C$19,"Amplify")-1,"") | E8: =IFERROR(D8-C8,"") | F8: =SUMIFS('Data - Channel'!$E$5:$E$19,'Data - Channel'!$A$5:$A$19,"On-premise",'Data - Channel'!$B$5:$B$19,"Jun–Aug",'Data - Channel'!$C$5:$C$19,"Amplify") | G8: =IFERROR(F8/SUM('Data - Accounts'!$F$5:$F$2358),"") | H8: =IFERROR(SUMIFS('Data - Channel'!$E$5:$E$19,'Data - Channel'!$A$5:$A$19,"On-premise",'Data - Channel'!$B$5:$B$19,"Jun–Aug",'Data - Channel'!$C$5:$C$19,"Control")/SUMIFS('Data - Channel'!$D$5:$D$19,'Data - Channel'!$A$5:$A$19,"On-premise",'Data - Channel'!$B$5:$B$19,"Jun–Aug",'Data - Channel'!$C$5:$C$19,"Control")-1,"") | I8: =IFERROR(D8-H8,"")
A9: Unmatched | B9: Qualifier | C9: =IFERROR(SUMIFS('Data - Channel'!$E$5:$E$19,'Data - Channel'!$A$5:$A$19,"Unmatched",'Data - Channel'!$B$5:$B$19,"Jan–May",'Data - Channel'!$C$5:$C$19,"Qualifier")/SUMIFS('Data - Channel'!$D$5:$D$19,'Data - Channel'!$A$5:$A$19,"Unmatched",'Data - Channel'!$B$5:$B$19,"Jan–May",'Data - Channel'!$C$5:$C$19,"Qualifier")-1,"") | D9: =IFERROR(SUMIFS('Data - Channel'!$E$5:$E$19,'Data - Channel'!$A$5:$A$19,"Unmatched",'Data - Channel'!$B$5:$B$19,"Jun–Aug",'Data - Channel'!$C$5:$C$19,"Qualifier")/SUMIFS('Data - Channel'!$D$5:$D$19,'Data - Channel'!$A$5:$A$19,"Unmatched",'Data - Channel'!$B$5:$B$19,"Jun–Aug",'Data - Channel'!$C$5:$C$19,"Qualifier")-1,"") | E9: =IFERROR(D9-C9,"") | F9: =SUMIFS('Data - Channel'!$E$5:$E$19,'Data - Channel'!$A$5:$A$19,"Unmatched",'Data - Channel'!$B$5:$B$19,"Jun–Aug",'Data - Channel'!$C$5:$C$19,"Qualifier") | G9: =IFERROR(F9/SUM('Data - Accounts'!$F$5:$F$2358),"") | H9: =IFERROR(SUMIFS('Data - Channel'!$E$5:$E$19,'Data - Channel'!$A$5:$A$19,"Unmatched",'Data - Channel'!$B$5:$B$19,"Jun–Aug",'Data - Channel'!$C$5:$C$19,"Control")/SUMIFS('Data - Channel'!$D$5:$D$19,'Data - Channel'!$A$5:$A$19,"Unmatched",'Data - Channel'!$B$5:$B$19,"Jun–Aug",'Data - Channel'!$C$5:$C$19,"Control")-1,"") | I9: =IFERROR(D9-H9,"")
A10: Unmatched | B10: Amplify | C10: =IFERROR(SUMIFS('Data - Channel'!$E$5:$E$19,'Data - Channel'!$A$5:$A$19,"Unmatched",'Data - Channel'!$B$5:$B$19,"Jan–May",'Data - Channel'!$C$5:$C$19,"Amplify")/SUMIFS('Data - Channel'!$D$5:$D$19,'Data - Channel'!$A$5:$A$19,"Unmatched",'Data - Channel'!$B$5:$B$19,"Jan–May",'Data - Channel'!$C$5:$C$19,"Amplify")-1,"") | D10: =IFERROR(SUMIFS('Data - Channel'!$E$5:$E$19,'Data - Channel'!$A$5:$A$19,"Unmatched",'Data - Channel'!$B$5:$B$19,"Jun–Aug",'Data - Channel'!$C$5:$C$19,"Amplify")/SUMIFS('Data - Channel'!$D$5:$D$19,'Data - Channel'!$A$5:$A$19,"Unmatched",'Data - Channel'!$B$5:$B$19,"Jun–Aug",'Data - Channel'!$C$5:$C$19,"Amplify")-1,"") | E10: =IFERROR(D10-C10,"") | F10: =SUMIFS('Data - Channel'!$E$5:$E$19,'Data - Channel'!$A$5:$A$19,"Unmatched",'Data - Channel'!$B$5:$B$19,"Jun–Aug",'Data - Channel'!$C$5:$C$19,"Amplify") | G10: =IFERROR(F10/SUM('Data - Accounts'!$F$5:$F$2358),"") | H10: =IFERROR(SUMIFS('Data - Channel'!$E$5:$E$19,'Data - Channel'!$A$5:$A$19,"Unmatched",'Data - Channel'!$B$5:$B$19,"Jun–Aug",'Data - Channel'!$C$5:$C$19,"Control")/SUMIFS('Data - Channel'!$D$5:$D$19,'Data - Channel'!$A$5:$A$19,"Unmatched",'Data - Channel'!$B$5:$B$19,"Jun–Aug",'Data - Channel'!$C$5:$C$19,"Control")-1,"") | I10: =IFERROR(D10-H10,"")
A12: THE ONE CONSTRUCTIVE FINDING IN THIS WORKBOOK
A13: On-premise is the only cut where the program accelerated. Amplify went from +13.7% pre-program to +18.4% during it, and Qualifier from -3.6% to -0.1% — the only positive swings anywhere in this analysis.
A14: Read it with two caveats. On-premise is about 11% of program volume, so it cannot rescue the total. And even there the incented brands still trailed that channel's non-incented brands, so the acceleration is real but the lead is not.
A15: Off-premise, which is 87% of the volume and where the concentrated large-format gains sit, decelerated in both segments.
A16: This is the part worth testing deliberately in 2027: a smaller, on-premise-weighted program is the one version of this incentive the data gives any reason to believe in.

Sheet County
A1: Did the program work anywhere in particular?
A2: Program vs non-program brands by county, Jun–Aug. The control column is the same county's non-incented volume.
A4: County | B4: Program CE 2025 | C4: Program CE 2026 | D4: Program % | E4: Non-program CE 2025 | F4: Non-program CE 2026 | G4: Non-program % | H4: Gap | I4: Share of program volume
A5: Bergen | B5: =SUMIFS('Data - Accounts'!$E$5:$E$2358,'Data - Accounts'!$B$5:$B$2358,$A5) | C5: =SUMIFS('Data - Accounts'!$F$5:$F$2358,'Data - Accounts'!$B$5:$B$2358,$A5) | D5: =IFERROR(C5/B5-1,"") | E5: =SUMIFS('Data - Accounts'!$I$5:$I$2358,'Data - Accounts'!$B$5:$B$2358,$A5) | F5: =SUMIFS('Data - Accounts'!$J$5:$J$2358,'Data - Accounts'!$B$5:$B$2358,$A5) | G5: =IFERROR(F5/E5-1,"") | H5: =IFERROR(D5-G5,"") | I5: =IFERROR(C5/SUM('Data - Accounts'!$F$5:$F$2358),"")
A6: Essex | B6: =SUMIFS('Data - Accounts'!$E$5:$E$2358,'Data - Accounts'!$B$5:$B$2358,$A6) | C6: =SUMIFS('Data - Accounts'!$F$5:$F$2358,'Data - Accounts'!$B$5:$B$2358,$A6) | D6: =IFERROR(C6/B6-1,"") | E6: =SUMIFS('Data - Accounts'!$I$5:$I$2358,'Data - Accounts'!$B$5:$B$2358,$A6) | F6: =SUMIFS('Data - Accounts'!$J$5:$J$2358,'Data - Accounts'!$B$5:$B$2358,$A6) | G6: =IFERROR(F6/E6-1,"") | H6: =IFERROR(D6-G6,"") | I6: =IFERROR(C6/SUM('Data - Accounts'!$F$5:$F$2358),"")
A7: Hudson | B7: =SUMIFS('Data - Accounts'!$E$5:$E$2358,'Data - Accounts'!$B$5:$B$2358,$A7) | C7: =SUMIFS('Data - Accounts'!$F$5:$F$2358,'Data - Accounts'!$B$5:$B$2358,$A7) | D7: =IFERROR(C7/B7-1,"") | E7: =SUMIFS('Data - Accounts'!$I$5:$I$2358,'Data - Accounts'!$B$5:$B$2358,$A7) | F7: =SUMIFS('Data - Accounts'!$J$5:$J$2358,'Data - Accounts'!$B$5:$B$2358,$A7) | G7: =IFERROR(F7/E7-1,"") | H7: =IFERROR(D7-G7,"") | I7: =IFERROR(C7/SUM('Data - Accounts'!$F$5:$F$2358),"")
A8: Middlesex | B8: =SUMIFS('Data - Accounts'!$E$5:$E$2358,'Data - Accounts'!$B$5:$B$2358,$A8) | C8: =SUMIFS('Data - Accounts'!$F$5:$F$2358,'Data - Accounts'!$B$5:$B$2358,$A8) | D8: =IFERROR(C8/B8-1,"") | E8: =SUMIFS('Data - Accounts'!$I$5:$I$2358,'Data - Accounts'!$B$5:$B$2358,$A8) | F8: =SUMIFS('Data - Accounts'!$J$5:$J$2358,'Data - Accounts'!$B$5:$B$2358,$A8) | G8: =IFERROR(F8/E8-1,"") | H8: =IFERROR(D8-G8,"") | I8: =IFERROR(C8/SUM('Data - Accounts'!$F$5:$F$2358),"")
A9: Morris | B9: =SUMIFS('Data - Accounts'!$E$5:$E$2358,'Data - Accounts'!$B$5:$B$2358,$A9) | C9: =SUMIFS('Data - Accounts'!$F$5:$F$2358,'Data - Accounts'!$B$5:$B$2358,$A9) | D9: =IFERROR(C9/B9-1,"") | E9: =SUMIFS('Data - Accounts'!$I$5:$I$2358,'Data - Accounts'!$B$5:$B$2358,$A9) | F9: =SUMIFS('Data - Accounts'!$J$5:$J$2358,'Data - Accounts'!$B$5:$B$2358,$A9) | G9: =IFERROR(F9/E9-1,"") | H9: =IFERROR(D9-G9,"") | I9: =IFERROR(C9/SUM('Data - Accounts'!$F$5:$F$2358),"")
A10: Passaic | B10: =SUMIFS('Data - Accounts'!$E$5:$E$2358,'Data - Accounts'!$B$5:$B$2358,$A10) | C10: =SUMIFS('Data - Accounts'!$F$5:$F$2358,'Data - Accounts'!$B$5:$B$2358,$A10) | D10: =IFERROR(C10/B10-1,"") | E10: =SUMIFS('Data - Accounts'!$I$5:$I$2358,'Data - Accounts'!$B$5:$B$2358,$A10) | F10: =SUMIFS('Data - Accounts'!$J$5:$J$2358,'Data - Accounts'!$B$5:$B$2358,$A10) | G10: =IFERROR(F10/E10-1,"") | H10: =IFERROR(D10-G10,"") | I10: =IFERROR(C10/SUM('Data - Accounts'!$F$5:$F$2358),"")
A11: Sussex | B11: =SUMIFS('Data - Accounts'!$E$5:$E$2358,'Data - Accounts'!$B$5:$B$2358,$A11) | C11: =SUMIFS('Data - Accounts'!$F$5:$F$2358,'Data - Accounts'!$B$5:$B$2358,$A11) | D11: =IFERROR(C11/B11-1,"") | E11: =SUMIFS('Data - Accounts'!$I$5:$I$2358,'Data - Accounts'!$B$5:$B$2358,$A11) | F11: =SUMIFS('Data - Accounts'!$J$5:$J$2358,'Data - Accounts'!$B$5:$B$2358,$A11) | G11: =IFERROR(F11/E11-1,"") | H11: =IFERROR(D11-G11,"") | I11: =IFERROR(C11/SUM('Data - Accounts'!$F$5:$F$2358),"")
A12: Union | B12: =SUMIFS('Data - Accounts'!$E$5:$E$2358,'Data - Accounts'!$B$5:$B$2358,$A12) | C12: =SUMIFS('Data - Accounts'!$F$5:$F$2358,'Data - Accounts'!$B$5:$B$2358,$A12) | D12: =IFERROR(C12/B12-1,"") | E12: =SUMIFS('Data - Accounts'!$I$5:$I$2358,'Data - Accounts'!$B$5:$B$2358,$A12) | F12: =SUMIFS('Data - Accounts'!$J$5:$J$2358,'Data - Accounts'!$B$5:$B$2358,$A12) | G12: =IFERROR(F12/E12-1,"") | H12: =IFERROR(D12-G12,"") | I12: =IFERROR(C12/SUM('Data - Accounts'!$F$5:$F$2358),"")
A13: Warren | B13: =SUMIFS('Data - Accounts'!$E$5:$E$2358,'Data - Accounts'!$B$5:$B$2358,$A13) | C13: =SUMIFS('Data - Accounts'!$F$5:$F$2358,'Data - Accounts'!$B$5:$B$2358,$A13) | D13: =IFERROR(C13/B13-1,"") | E13: =SUMIFS('Data - Accounts'!$I$5:$I$2358,'Data - Accounts'!$B$5:$B$2358,$A13) | F13: =SUMIFS('Data - Accounts'!$J$5:$J$2358,'Data - Accounts'!$B$5:$B$2358,$A13) | G13: =IFERROR(F13/E13-1,"") | H13: =IFERROR(D13-G13,"") | I13: =IFERROR(C13/SUM('Data - Accounts'!$F$5:$F$2358),"")
A14: TOTAL | B14: =SUM(B5:B13) | C14: =SUM(C5:C13) | D14: =IFERROR(C14/B14-1,"") | E14: =SUM(E5:E13) | F14: =SUM(F5:F13) | G14: =IFERROR(F14/E14-1,"") | H14: =IFERROR(D14-G14,"")
A16: The four counties carrying essentially all the volume — Bergen, Passaic, Morris, Sussex — each trailed their own county's non-incented brands.
A17: Hudson, Union and Essex show big positive percentages on a base of roughly 12,000 cases between them, under 1% of the program. Read the Share column before the Gap column.

Sheet GP Bridge
A1: Where the gross profit change actually came from
A2: ΔGP split three ways: cases sold (Volume), which brands sold (Mix), and gross profit per case within a brand (Rate). Volume is the only one an incentive plausibly drives.
B4: Program brands | C4: Non-program brands (control)
A5: Cases 2025 | B5: =SUM('Program Brands'!$D$6:$D$37) | C5: =SUM('Control Brands'!$C$5:$C$296)
A6: Cases 2026 | B6: =SUM('Program Brands'!$E$6:$E$37) | C6: =SUM('Control Brands'!$D$5:$D$296)
A7: Gross profit 2025 | B7: =SUM('Program Brands'!$H$6:$H$37) | C7: =SUM('Control Brands'!$G$5:$G$296)
A8: Gross profit 2026 | B8: =SUM('Program Brands'!$I$6:$I$37) | C8: =SUM('Control Brands'!$H$5:$H$296)
A9: Actual ΔGP | B9: =B8-B7 | C9: =C8-C7
A11: DECOMPOSED
A12: Volume — cases, at last year's GP/CE | B12: =(B6-B5)*(B7/B5) | C12: =(C6-C5)*(C7/C5)
A13: Mix — which brands sold | B13: =SUM('Program Brands'!$R$6:$R$37)-B6*(B7/B5) | C13: =SUM('Control Brands'!$K$5:$K$296)-C6*(C7/C5)
A14: Rate — GP per case within a brand | B14: =SUM('Program Brands'!$S$6:$S$37) | C14: =SUM('Control Brands'!$L$5:$L$296)
A15: Sum (ties to Actual ΔGP) | B15: =SUM(B12:B14) | C15: =SUM(C12:C14)
A17: RATE EFFECT PER 2026 CASE
A18: Rate effect per case | B18: =IFERROR(B14/B6,"") | C18: =IFERROR(C14/C6,"")
A19: Control advantage per case | B19: =C18-B18
A21: The margin gain was real but house-wide. Per case, the non-incented book captured several times the rate improvement the incented book did, so the program cannot claim it.
A22: Volume is the line an incentive is supposed to move, and on the program brands it is the negative one.
A23: Control mix is large because the non-program book shifted toward higher-margin brands (Sun Cruiser, Sierra Nevada) while low-margin Pabst declined.

Sheet Brand Selection
A1: The variable that decided the outcome — which brands got incented
A2: Every brand of every supplier appearing on both sides, Jun–Aug. INCENTED rows carried a payout; NOT INCENTED rows did not.
A4: Supplier | B4: Incented? | C4: Brand Family | D4: CE 2025 | E4: CE 2026 | F4: Δ cases | G4: Cases % | H4: GP 2025 | I4: GP 2026 | J4: Δ GP | K4: PODs 2026
A5: Bell's | B5: INCENTED | C5: Bell's | D5: =SUMIFS('Program Brands'!$D$6:$D$37,'Program Brands'!$B$6:$B$37,$A5,'Program Brands'!$C$6:$C$37,$C5) | E5: =SUMIFS('Program Brands'!$E$6:$E$37,'Program Brands'!$B$6:$B$37,$A5,'Program Brands'!$C$6:$C$37,$C5) | F5: =E5-D5 | G5: =IFERROR(E5/D5-1,"") | H5: =SUMIFS('Program Brands'!$H$6:$H$37,'Program Brands'!$B$6:$B$37,$A5,'Program Brands'!$C$6:$C$37,$C5) | I5: =SUMIFS('Program Brands'!$I$6:$I$37,'Program Brands'!$B$6:$B$37,$A5,'Program Brands'!$C$6:$C$37,$C5) | J5: =I5-H5 | K5: =SUMIFS('Data - Season'!$L$5:$L$743,'Data - Season'!$C$5:$C$743,$A5,'Data - Season'!$D$5:$D$743,$C5)
A6: Bell's | B6: not incented | C6: Bell's Hearted Family | D6: =SUMIFS('Control Brands'!$C$5:$C$296,'Control Brands'!$A$5:$A$296,$A6,'Control Brands'!$B$5:$B$296,$C6) | E6: =SUMIFS('Control Brands'!$D$5:$D$296,'Control Brands'!$A$5:$A$296,$A6,'Control Brands'!$B$5:$B$296,$C6) | F6: =E6-D6 | G6: =IFERROR(E6/D6-1,"") | H6: =SUMIFS('Control Brands'!$G$5:$G$296,'Control Brands'!$A$5:$A$296,$A6,'Control Brands'!$B$5:$B$296,$C6) | I6: =SUMIFS('Control Brands'!$H$5:$H$296,'Control Brands'!$A$5:$A$296,$A6,'Control Brands'!$B$5:$B$296,$C6) | J6: =I6-H6 | K6: =SUMIFS('Data - Control'!$J$5:$J$296,'Data - Control'!$A$5:$A$296,$A6,'Data - Control'!$B$5:$B$296,$C6)
C7: Bell's — total | D7: =SUM(D5:D6) | E7: =SUM(E5:E6) | F7: =SUM(F5:F6) | H7: =SUM(H5:H6) | I7: =SUM(I5:I6) | J7: =SUM(J5:J6) | K7: =SUM(K5:K6)
A9: Boston Beer Company | B9: INCENTED | C9: Dogfish Head Beer | D9: =SUMIFS('Program Brands'!$D$6:$D$37,'Program Brands'!$B$6:$B$37,$A9,'Program Brands'!$C$6:$C$37,$C9) | E9: =SUMIFS('Program Brands'!$E$6:$E$37,'Program Brands'!$B$6:$B$37,$A9,'Program Brands'!$C$6:$C$37,$C9) | F9: =E9-D9 | G9: =IFERROR(E9/D9-1,"") | H9: =SUMIFS('Program Brands'!$H$6:$H$37,'Program Brands'!$B$6:$B$37,$A9,'Program Brands'!$C$6:$C$37,$C9) | I9: =SUMIFS('Program Brands'!$I$6:$I$37,'Program Brands'!$B$6:$B$37,$A9,'Program Brands'!$C$6:$C$37,$C9) | J9: =I9-H9 | K9: =SUMIFS('Data - Season'!$L$5:$L$743,'Data - Season'!$C$5:$C$743,$A9,'Data - Season'!$D$5:$D$743,$C9)
A10: Boston Beer Company | B10: INCENTED | C10: Dogfish Head Spirits | D10: =SUMIFS('Program Brands'!$D$6:$D$37,'Program Brands'!$B$6:$B$37,$A10,'Program Brands'!$C$6:$C$37,$C10) | E10: =SUMIFS('Program Brands'!$E$6:$E$37,'Program Brands'!$B$6:$B$37,$A10,'Program Brands'!$C$6:$C$37,$C10) | F10: =E10-D10 | G10: =IFERROR(E10/D10-1,"") | H10: =SUMIFS('Program Brands'!$H$6:$H$37,'Program Brands'!$B$6:$B$37,$A10,'Program Brands'!$C$6:$C$37,$C10) | I10: =SUMIFS('Program Brands'!$I$6:$I$37,'Program Brands'!$B$6:$B$37,$A10,'Program Brands'!$C$6:$C$37,$C10) | J10: =I10-H10 | K10: =SUMIFS('Data - Season'!$L$5:$L$743,'Data - Season'!$C$5:$C$743,$A10,'Data - Season'!$D$5:$D$743,$C10)
A11: Boston Beer Company | B11: INCENTED | C11: Truly | D11: =SUMIFS('Program Brands'!$D$6:$D$37,'Program Brands'!$B$6:$B$37,$A11,'Program Brands'!$C$6:$C$37,$C11) | E11: =SUMIFS('Program Brands'!$E$6:$E$37,'Program Brands'!$B$6:$B$37,$A11,'Program Brands'!$C$6:$C$37,$C11) | F11: =E11-D11 | G11: =IFERROR(E11/D11-1,"") | H11: =SUMIFS('Program Brands'!$H$6:$H$37,'Program Brands'!$B$6:$B$37,$A11,'Program Brands'!$C$6:$C$37,$C11) | I11: =SUMIFS('Program Brands'!$I$6:$I$37,'Program Brands'!$B$6:$B$37,$A11,'Program Brands'!$C$6:$C$37,$C11) | J11: =I11-H11 | K11: =SUMIFS('Data - Season'!$L$5:$L$743,'Data - Season'!$C$5:$C$743,$A11,'Data - Season'!$D$5:$D$743,$C11)
A12: Boston Beer Company | B12: INCENTED | C12: Twisted Tea | D12: =SUMIFS('Program Brands'!$D$6:$D$37,'Program Brands'!$B$6:$B$37,$A12,'Program Brands'!$C$6:$C$37,$C12) | E12: =SUMIFS('Program Brands'!$E$6:$E$37,'Program Brands'!$B$6:$B$37,$A12,'Program Brands'!$C$6:$C$37,$C12) | F12: =E12-D12 | G12: =IFERROR(E12/D12-1,"") | H12: =SUMIFS('Program Brands'!$H$6:$H$37,'Program Brands'!$B$6:$B$37,$A12,'Program Brands'!$C$6:$C$37,$C12) | I12: =SUMIFS('Program Brands'!$I$6:$I$37,'Program Brands'!$B$6:$B$37,$A12,'Program Brands'!$C$6:$C$37,$C12) | J12: =I12-H12 | K12: =SUMIFS('Data - Season'!$L$5:$L$743,'Data - Season'!$C$5:$C$743,$A12,'Data - Season'!$D$5:$D$743,$C12)
A13: Boston Beer Company | B13: not incented | C13: Angry Orchard | D13: =SUMIFS('Control Brands'!$C$5:$C$296,'Control Brands'!$A$5:$A$296,$A13,'Control Brands'!$B$5:$B$296,$C13) | E13: =SUMIFS('Control Brands'!$D$5:$D$296,'Control Brands'!$A$5:$A$296,$A13,'Control Brands'!$B$5:$B$296,$C13) | F13: =E13-D13 | G13: =IFERROR(E13/D13-1,"") | H13: =SUMIFS('Control Brands'!$G$5:$G$296,'Control Brands'!$A$5:$A$296,$A13,'Control Brands'!$B$5:$B$296,$C13) | I13: =SUMIFS('Control Brands'!$H$5:$H$296,'Control Brands'!$A$5:$A$296,$A13,'Control Brands'!$B$5:$B$296,$C13) | J13: =I13-H13 | K13: =SUMIFS('Data - Control'!$J$5:$J$296,'Data - Control'!$A$5:$A$296,$A13,'Data - Control'!$B$5:$B$296,$C13)
A14: Boston Beer Company | B14: not incented | C14: Coney Island | D14: =SUMIFS('Control Brands'!$C$5:$C$296,'Control Brands'!$A$5:$A$296,$A14,'Control Brands'!$B$5:$B$296,$C14) | E14: =SUMIFS('Control Brands'!$D$5:$D$296,'Control Brands'!$A$5:$A$296,$A14,'Control Brands'!$B$5:$B$296,$C14) | F14: =E14-D14 | G14: =IFERROR(E14/D14-1,"") | H14: =SUMIFS('Control Brands'!$G$5:$G$296,'Control Brands'!$A$5:$A$296,$A14,'Control Brands'!$B$5:$B$296,$C14) | I14: =SUMIFS('Control Brands'!$H$5:$H$296,'Control Brands'!$A$5:$A$296,$A14,'Control Brands'!$B$5:$B$296,$C14) | J14: =I14-H14 | K14: =SUMIFS('Data - Control'!$J$5:$J$296,'Data - Control'!$A$5:$A$296,$A14,'Data - Control'!$B$5:$B$296,$C14)
A15: Boston Beer Company | B15: not incented | C15: Hard Mountain Dew | D15: =SUMIFS('Control Brands'!$C$5:$C$296,'Control Brands'!$A$5:$A$296,$A15,'Control Brands'!$B$5:$B$296,$C15) | E15: =SUMIFS('Control Brands'!$D$5:$D$296,'Control Brands'!$A$5:$A$296,$A15,'Control Brands'!$B$5:$B$296,$C15) | F15: =E15-D15 | G15: =IFERROR(E15/D15-1,"") | H15: =SUMIFS('Control Brands'!$G$5:$G$296,'Control Brands'!$A$5:$A$296,$A15,'Control Brands'!$B$5:$B$296,$C15) | I15: =SUMIFS('Control Brands'!$H$5:$H$296,'Control Brands'!$A$5:$A$296,$A15,'Control Brands'!$B$5:$B$296,$C15) | J15: =I15-H15 | K15: =SUMIFS('Data - Control'!$J$5:$J$296,'Data - Control'!$A$5:$A$296,$A15,'Data - Control'!$B$5:$B$296,$C15)
A16: Boston Beer Company | B16: not incented | C16: Lytt | D16: =SUMIFS('Control Brands'!$C$5:$C$296,'Control Brands'!$A$5:$A$296,$A16,'Control Brands'!$B$5:$B$296,$C16) | E16: =SUMIFS('Control Brands'!$D$5:$D$296,'Control Brands'!$A$5:$A$296,$A16,'Control Brands'!$B$5:$B$296,$C16) | F16: =E16-D16 | G16: =IFERROR(E16/D16-1,"") | H16: =SUMIFS('Control Brands'!$G$5:$G$296,'Control Brands'!$A$5:$A$296,$A16,'Control Brands'!$B$5:$B$296,$C16) | I16: =SUMIFS('Control Brands'!$H$5:$H$296,'Control Brands'!$A$5:$A$296,$A16,'Control Brands'!$B$5:$B$296,$C16) | J16: =I16-H16 | K16: =SUMIFS('Data - Control'!$J$5:$J$296,'Data - Control'!$A$5:$A$296,$A16,'Data - Control'!$B$5:$B$296,$C16)
A17: Boston Beer Company | B17: not incented | C17: Samuel Adams | D17: =SUMIFS('Control Brands'!$C$5:$C$296,'Control Brands'!$A$5:$A$296,$A17,'Control Brands'!$B$5:$B$296,$C17) | E17: =SUMIFS('Control Brands'!$D$5:$D$296,'Control Brands'!$A$5:$A$296,$A17,'Control Brands'!$B$5:$B$296,$C17) | F17: =E17-D17 | G17: =IFERROR(E17/D17-1,"") | H17: =SUMIFS('Control Brands'!$G$5:$G$296,'Control Brands'!$A$5:$A$296,$A17,'Control Brands'!$B$5:$B$296,$C17) | I17: =SUMIFS('Control Brands'!$H$5:$H$296,'Control Brands'!$A$5:$A$296,$A17,'Control Brands'!$B$5:$B$296,$C17) | J17: =I17-H17 | K17: =SUMIFS('Data - Control'!$J$5:$J$296,'Data - Control'!$A$5:$A$296,$A17,'Data - Control'!$B$5:$B$296,$C17)
A18: Boston Beer Company | B18: not incented | C18: Sinless Vodka Cocktail | D18: =SUMIFS('Control Brands'!$C$5:$C$296,'Control Brands'!$A$5:$A$296,$A18,'Control Brands'!$B$5:$B$296,$C18) | E18: =SUMIFS('Control Brands'!$D$5:$D$296,'Control Brands'!$A$5:$A$296,$A18,'Control Brands'!$B$5:$B$296,$C18) | F18: =E18-D18 | G18: =IFERROR(E18/D18-1,"") | H18: =SUMIFS('Control Brands'!$G$5:$G$296,'Control Brands'!$A$5:$A$296,$A18,'Control Brands'!$B$5:$B$296,$C18) | I18: =SUMIFS('Control Brands'!$H$5:$H$296,'Control Brands'!$A$5:$A$296,$A18,'Control Brands'!$B$5:$B$296,$C18) | J18: =I18-H18 | K18: =SUMIFS('Data - Control'!$J$5:$J$296,'Data - Control'!$A$5:$A$296,$A18,'Data - Control'!$B$5:$B$296,$C18)
A19: Boston Beer Company | B19: not incented | C19: Sun Cruiser | D19: =SUMIFS('Control Brands'!$C$5:$C$296,'Control Brands'!$A$5:$A$296,$A19,'Control Brands'!$B$5:$B$296,$C19) | E19: =SUMIFS('Control Brands'!$D$5:$D$296,'Control Brands'!$A$5:$A$296,$A19,'Control Brands'!$B$5:$B$296,$C19) | F19: =E19-D19 | G19: =IFERROR(E19/D19-1,"") | H19: =SUMIFS('Control Brands'!$G$5:$G$296,'Control Brands'!$A$5:$A$296,$A19,'Control Brands'!$B$5:$B$296,$C19) | I19: =SUMIFS('Control Brands'!$H$5:$H$296,'Control Brands'!$A$5:$A$296,$A19,'Control Brands'!$B$5:$B$296,$C19) | J19: =I19-H19 | K19: =SUMIFS('Data - Control'!$J$5:$J$296,'Data - Control'!$A$5:$A$296,$A19,'Data - Control'!$B$5:$B$296,$C19)
C20: Boston Beer Company — total | D20: =SUM(D9:D19) | E20: =SUM(E9:E19) | F20: =SUM(F9:F19) | H20: =SUM(H9:H19) | I20: =SUM(I9:I19) | J20: =SUM(J9:J19) | K20: =SUM(K9:K19)
A22: New Belgium Brewing Company | B22: INCENTED | C22: Fat Tire Family | D22: =SUMIFS('Program Brands'!$D$6:$D$37,'Program Brands'!$B$6:$B$37,$A22,'Program Brands'!$C$6:$C$37,$C22) | E22: =SUMIFS('Program Brands'!$E$6:$E$37,'Program Brands'!$B$6:$B$37,$A22,'Program Brands'!$C$6:$C$37,$C22) | F22: =E22-D22 | G22: =IFERROR(E22/D22-1,"") | H22: =SUMIFS('Program Brands'!$H$6:$H$37,'Program Brands'!$B$6:$B$37,$A22,'Program Brands'!$C$6:$C$37,$C22) | I22: =SUMIFS('Program Brands'!$I$6:$I$37,'Program Brands'!$B$6:$B$37,$A22,'Program Brands'!$C$6:$C$37,$C22) | J22: =I22-H22 | K22: =SUMIFS('Data - Season'!$L$5:$L$743,'Data - Season'!$C$5:$C$743,$A22,'Data - Season'!$D$5:$D$743,$C22)
A23: New Belgium Brewing Company | B23: INCENTED | C23: Kirin Ichiban | D23: =SUMIFS('Program Brands'!$D$6:$D$37,'Program Brands'!$B$6:$B$37,$A23,'Program Brands'!$C$6:$C$37,$C23) | E23: =SUMIFS('Program Brands'!$E$6:$E$37,'Program Brands'!$B$6:$B$37,$A23,'Program Brands'!$C$6:$C$37,$C23) | F23: =E23-D23 | G23: =IFERROR(E23/D23-1,"") | H23: =SUMIFS('Program Brands'!$H$6:$H$37,'Program Brands'!$B$6:$B$37,$A23,'Program Brands'!$C$6:$C$37,$C23) | I23: =SUMIFS('Program Brands'!$I$6:$I$37,'Program Brands'!$B$6:$B$37,$A23,'Program Brands'!$C$6:$C$37,$C23) | J23: =I23-H23 | K23: =SUMIFS('Data - Season'!$L$5:$L$743,'Data - Season'!$C$5:$C$743,$A23,'Data - Season'!$D$5:$D$743,$C23)
A24: New Belgium Brewing Company | B24: INCENTED | C24: Voodoo Family | D24: =SUMIFS('Program Brands'!$D$6:$D$37,'Program Brands'!$B$6:$B$37,$A24,'Program Brands'!$C$6:$C$37,$C24) | E24: =SUMIFS('Program Brands'!$E$6:$E$37,'Program Brands'!$B$6:$B$37,$A24,'Program Brands'!$C$6:$C$37,$C24) | F24: =E24-D24 | G24: =IFERROR(E24/D24-1,"") | H24: =SUMIFS('Program Brands'!$H$6:$H$37,'Program Brands'!$B$6:$B$37,$A24,'Program Brands'!$C$6:$C$37,$C24) | I24: =SUMIFS('Program Brands'!$I$6:$I$37,'Program Brands'!$B$6:$B$37,$A24,'Program Brands'!$C$6:$C$37,$C24) | J24: =I24-H24 | K24: =SUMIFS('Data - Season'!$L$5:$L$743,'Data - Season'!$C$5:$C$743,$A24,'Data - Season'!$D$5:$D$743,$C24)
A25: New Belgium Brewing Company | B25: not incented | C25: Kirin Light | D25: =SUMIFS('Control Brands'!$C$5:$C$296,'Control Brands'!$A$5:$A$296,$A25,'Control Brands'!$B$5:$B$296,$C25) | E25: =SUMIFS('Control Brands'!$D$5:$D$296,'Control Brands'!$A$5:$A$296,$A25,'Control Brands'!$B$5:$B$296,$C25) | F25: =E25-D25 | G25: =IFERROR(E25/D25-1,"") | H25: =SUMIFS('Control Brands'!$G$5:$G$296,'Control Brands'!$A$5:$A$296,$A25,'Control Brands'!$B$5:$B$296,$C25) | I25: =SUMIFS('Control Brands'!$H$5:$H$296,'Control Brands'!$A$5:$A$296,$A25,'Control Brands'!$B$5:$B$296,$C25) | J25: =I25-H25 | K25: =SUMIFS('Data - Control'!$J$5:$J$296,'Data - Control'!$A$5:$A$296,$A25,'Data - Control'!$B$5:$B$296,$C25)
A26: New Belgium Brewing Company | B26: not incented | C26: Lightstrike | D26: =SUMIFS('Control Brands'!$C$5:$C$296,'Control Brands'!$A$5:$A$296,$A26,'Control Brands'!$B$5:$B$296,$C26) | E26: =SUMIFS('Control Brands'!$D$5:$D$296,'Control Brands'!$A$5:$A$296,$A26,'Control Brands'!$B$5:$B$296,$C26) | F26: =E26-D26 | G26: =IFERROR(E26/D26-1,"") | H26: =SUMIFS('Control Brands'!$G$5:$G$296,'Control Brands'!$A$5:$A$296,$A26,'Control Brands'!$B$5:$B$296,$C26) | I26: =SUMIFS('Control Brands'!$H$5:$H$296,'Control Brands'!$A$5:$A$296,$A26,'Control Brands'!$B$5:$B$296,$C26) | J26: =I26-H26 | K26: =SUMIFS('Data - Control'!$J$5:$J$296,'Data - Control'!$A$5:$A$296,$A26,'Data - Control'!$B$5:$B$296,$C26)
A27: New Belgium Brewing Company | B27: not incented | C27: New Belgium Brewing Company | D27: =SUMIFS('Control Brands'!$C$5:$C$296,'Control Brands'!$A$5:$A$296,$A27,'Control Brands'!$B$5:$B$296,$C27) | E27: =SUMIFS('Control Brands'!$D$5:$D$296,'Control Brands'!$A$5:$A$296,$A27,'Control Brands'!$B$5:$B$296,$C27) | F27: =E27-D27 | G27: =IFERROR(E27/D27-1,"") | H27: =SUMIFS('Control Brands'!$G$5:$G$296,'Control Brands'!$A$5:$A$296,$A27,'Control Brands'!$B$5:$B$296,$C27) | I27: =SUMIFS('Control Brands'!$H$5:$H$296,'Control Brands'!$A$5:$A$296,$A27,'Control Brands'!$B$5:$B$296,$C27) | J27: =I27-H27 | K27: =SUMIFS('Data - Control'!$J$5:$J$296,'Data - Control'!$A$5:$A$296,$A27,'Data - Control'!$B$5:$B$296,$C27)
A28: New Belgium Brewing Company | B28: not incented | C28: Voodoo Hardcharged | D28: =SUMIFS('Control Brands'!$C$5:$C$296,'Control Brands'!$A$5:$A$296,$A28,'Control Brands'!$B$5:$B$296,$C28) | E28: =SUMIFS('Control Brands'!$D$5:$D$296,'Control Brands'!$A$5:$A$296,$A28,'Control Brands'!$B$5:$B$296,$C28) | F28: =E28-D28 | G28: =IFERROR(E28/D28-1,"") | H28: =SUMIFS('Control Brands'!$G$5:$G$296,'Control Brands'!$A$5:$A$296,$A28,'Control Brands'!$B$5:$B$296,$C28) | I28: =SUMIFS('Control Brands'!$H$5:$H$296,'Control Brands'!$A$5:$A$296,$A28,'Control Brands'!$B$5:$B$296,$C28) | J28: =I28-H28 | K28: =SUMIFS('Data - Control'!$J$5:$J$296,'Data - Control'!$A$5:$A$296,$A28,'Data - Control'!$B$5:$B$296,$C28)
C29: New Belgium Brewing Company — total | D29: =SUM(D22:D28) | E29: =SUM(E22:E28) | F29: =SUM(F22:F28) | H29: =SUM(H22:H28) | I29: =SUM(I22:I28) | J29: =SUM(J22:J28) | K29: =SUM(K22:K28)
A31: Heineken USA | B31: INCENTED | C31: Heineken 0.0 | D31: =SUMIFS('Program Brands'!$D$6:$D$37,'Program Brands'!$B$6:$B$37,$A31,'Program Brands'!$C$6:$C$37,$C31) | E31: =SUMIFS('Program Brands'!$E$6:$E$37,'Program Brands'!$B$6:$B$37,$A31,'Program Brands'!$C$6:$C$37,$C31) | F31: =E31-D31 | G31: =IFERROR(E31/D31-1,"") | H31: =SUMIFS('Program Brands'!$H$6:$H$37,'Program Brands'!$B$6:$B$37,$A31,'Program Brands'!$C$6:$C$37,$C31) | I31: =SUMIFS('Program Brands'!$I$6:$I$37,'Program Brands'!$B$6:$B$37,$A31,'Program Brands'!$C$6:$C$37,$C31) | J31: =I31-H31 | K31: =SUMIFS('Data - Season'!$L$5:$L$743,'Data - Season'!$C$5:$C$743,$A31,'Data - Season'!$D$5:$D$743,$C31)
A32: Heineken USA | B32: INCENTED | C32: Heineken Light | D32: =SUMIFS('Program Brands'!$D$6:$D$37,'Program Brands'!$B$6:$B$37,$A32,'Program Brands'!$C$6:$C$37,$C32) | E32: =SUMIFS('Program Brands'!$E$6:$E$37,'Program Brands'!$B$6:$B$37,$A32,'Program Brands'!$C$6:$C$37,$C32) | F32: =E32-D32 | G32: =IFERROR(E32/D32-1,"") | H32: =SUMIFS('Program Brands'!$H$6:$H$37,'Program Brands'!$B$6:$B$37,$A32,'Program Brands'!$C$6:$C$37,$C32) | I32: =SUMIFS('Program Brands'!$I$6:$I$37,'Program Brands'!$B$6:$B$37,$A32,'Program Brands'!$C$6:$C$37,$C32) | J32: =I32-H32 | K32: =SUMIFS('Data - Season'!$L$5:$L$743,'Data - Season'!$C$5:$C$743,$A32,'Data - Season'!$D$5:$D$743,$C32)
A33: Heineken USA | B33: INCENTED | C33: Heineken USA | D33: =SUMIFS('Program Brands'!$D$6:$D$37,'Program Brands'!$B$6:$B$37,$A33,'Program Brands'!$C$6:$C$37,$C33) | E33: =SUMIFS('Program Brands'!$E$6:$E$37,'Program Brands'!$B$6:$B$37,$A33,'Program Brands'!$C$6:$C$37,$C33) | F33: =E33-D33 | G33: =IFERROR(E33/D33-1,"") | H33: =SUMIFS('Program Brands'!$H$6:$H$37,'Program Brands'!$B$6:$B$37,$A33,'Program Brands'!$C$6:$C$37,$C33) | I33: =SUMIFS('Program Brands'!$I$6:$I$37,'Program Brands'!$B$6:$B$37,$A33,'Program Brands'!$C$6:$C$37,$C33) | J33: =I33-H33 | K33: =SUMIFS('Data - Season'!$L$5:$L$743,'Data - Season'!$C$5:$C$743,$A33,'Data - Season'!$D$5:$D$743,$C33)
A34: Heineken USA | B34: not incented | C34: Amstel | D34: =SUMIFS('Control Brands'!$C$5:$C$296,'Control Brands'!$A$5:$A$296,$A34,'Control Brands'!$B$5:$B$296,$C34) | E34: =SUMIFS('Control Brands'!$D$5:$D$296,'Control Brands'!$A$5:$A$296,$A34,'Control Brands'!$B$5:$B$296,$C34) | F34: =E34-D34 | G34: =IFERROR(E34/D34-1,"") | H34: =SUMIFS('Control Brands'!$G$5:$G$296,'Control Brands'!$A$5:$A$296,$A34,'Control Brands'!$B$5:$B$296,$C34) | I34: =SUMIFS('Control Brands'!$H$5:$H$296,'Control Brands'!$A$5:$A$296,$A34,'Control Brands'!$B$5:$B$296,$C34) | J34: =I34-H34 | K34: =SUMIFS('Data - Control'!$J$5:$J$296,'Data - Control'!$A$5:$A$296,$A34,'Data - Control'!$B$5:$B$296,$C34)
A35: Heineken USA | B35: not incented | C35: Buckler | D35: =SUMIFS('Control Brands'!$C$5:$C$296,'Control Brands'!$A$5:$A$296,$A35,'Control Brands'!$B$5:$B$296,$C35) | E35: =SUMIFS('Control Brands'!$D$5:$D$296,'Control Brands'!$A$5:$A$296,$A35,'Control Brands'!$B$5:$B$296,$C35) | F35: =E35-D35 | G35: =IFERROR(E35/D35-1,"") | H35: =SUMIFS('Control Brands'!$G$5:$G$296,'Control Brands'!$A$5:$A$296,$A35,'Control Brands'!$B$5:$B$296,$C35) | I35: =SUMIFS('Control Brands'!$H$5:$H$296,'Control Brands'!$A$5:$A$296,$A35,'Control Brands'!$B$5:$B$296,$C35) | J35: =I35-H35 | K35: =SUMIFS('Data - Control'!$J$5:$J$296,'Data - Control'!$A$5:$A$296,$A35,'Data - Control'!$B$5:$B$296,$C35)
A36: Heineken USA | B36: not incented | C36: Carta Blanca | D36: =SUMIFS('Control Brands'!$C$5:$C$296,'Control Brands'!$A$5:$A$296,$A36,'Control Brands'!$B$5:$B$296,$C36) | E36: =SUMIFS('Control Brands'!$D$5:$D$296,'Control Brands'!$A$5:$A$296,$A36,'Control Brands'!$B$5:$B$296,$C36) | F36: =E36-D36 | G36: =IFERROR(E36/D36-1,"") | H36: =SUMIFS('Control Brands'!$G$5:$G$296,'Control Brands'!$A$5:$A$296,$A36,'Control Brands'!$B$5:$B$296,$C36) | I36: =SUMIFS('Control Brands'!$H$5:$H$296,'Control Brands'!$A$5:$A$296,$A36,'Control Brands'!$B$5:$B$296,$C36) | J36: =I36-H36 | K36: =SUMIFS('Data - Control'!$J$5:$J$296,'Data - Control'!$A$5:$A$296,$A36,'Data - Control'!$B$5:$B$296,$C36)
A37: Heineken USA | B37: not incented | C37: Dos Equis | D37: =SUMIFS('Control Brands'!$C$5:$C$296,'Control Brands'!$A$5:$A$296,$A37,'Control Brands'!$B$5:$B$296,$C37) | E37: =SUMIFS('Control Brands'!$D$5:$D$296,'Control Brands'!$A$5:$A$296,$A37,'Control Brands'!$B$5:$B$296,$C37) | F37: =E37-D37 | G37: =IFERROR(E37/D37-1,"") | H37: =SUMIFS('Control Brands'!$G$5:$G$296,'Control Brands'!$A$5:$A$296,$A37,'Control Brands'!$B$5:$B$296,$C37) | I37: =SUMIFS('Control Brands'!$H$5:$H$296,'Control Brands'!$A$5:$A$296,$A37,'Control Brands'!$B$5:$B$296,$C37) | J37: =I37-H37 | K37: =SUMIFS('Data - Control'!$J$5:$J$296,'Data - Control'!$A$5:$A$296,$A37,'Data - Control'!$B$5:$B$296,$C37)
A38: Heineken USA | B38: not incented | C38: Heineken 0.0 Ultimate | D38: =SUMIFS('Control Brands'!$C$5:$C$296,'Control Brands'!$A$5:$A$296,$A38,'Control Brands'!$B$5:$B$296,$C38) | E38: =SUMIFS('Control Brands'!$D$5:$D$296,'Control Brands'!$A$5:$A$296,$A38,'Control Brands'!$B$5:$B$296,$C38) | F38: =E38-D38 | G38: =IFERROR(E38/D38-1,"") | H38: =SUMIFS('Control Brands'!$G$5:$G$296,'Control Brands'!$A$5:$A$296,$A38,'Control Brands'!$B$5:$B$296,$C38) | I38: =SUMIFS('Control Brands'!$H$5:$H$296,'Control Brands'!$A$5:$A$296,$A38,'Control Brands'!$B$5:$B$296,$C38) | J38: =I38-H38 | K38: =SUMIFS('Data - Control'!$J$5:$J$296,'Data - Control'!$A$5:$A$296,$A38,'Data - Control'!$B$5:$B$296,$C38)
A39: Heineken USA | B39: not incented | C39: Heineken Silver | D39: =SUMIFS('Control Brands'!$C$5:$C$296,'Control Brands'!$A$5:$A$296,$A39,'Control Brands'!$B$5:$B$296,$C39) | E39: =SUMIFS('Control Brands'!$D$5:$D$296,'Control Brands'!$A$5:$A$296,$A39,'Control Brands'!$B$5:$B$296,$C39) | F39: =E39-D39 | G39: =IFERROR(E39/D39-1,"") | H39: =SUMIFS('Control Brands'!$G$5:$G$296,'Control Brands'!$A$5:$A$296,$A39,'Control Brands'!$B$5:$B$296,$C39) | I39: =SUMIFS('Control Brands'!$H$5:$H$296,'Control Brands'!$A$5:$A$296,$A39,'Control Brands'!$B$5:$B$296,$C39) | J39: =I39-H39 | K39: =SUMIFS('Data - Control'!$J$5:$J$296,'Data - Control'!$A$5:$A$296,$A39,'Data - Control'!$B$5:$B$296,$C39)
A40: Heineken USA | B40: not incented | C40: Murphy's | D40: =SUMIFS('Control Brands'!$C$5:$C$296,'Control Brands'!$A$5:$A$296,$A40,'Control Brands'!$B$5:$B$296,$C40) | E40: =SUMIFS('Control Brands'!$D$5:$D$296,'Control Brands'!$A$5:$A$296,$A40,'Control Brands'!$B$5:$B$296,$C40) | F40: =E40-D40 | G40: =IFERROR(E40/D40-1,"") | H40: =SUMIFS('Control Brands'!$G$5:$G$296,'Control Brands'!$A$5:$A$296,$A40,'Control Brands'!$B$5:$B$296,$C40) | I40: =SUMIFS('Control Brands'!$H$5:$H$296,'Control Brands'!$A$5:$A$296,$A40,'Control Brands'!$B$5:$B$296,$C40) | J40: =I40-H40 | K40: =SUMIFS('Data - Control'!$J$5:$J$296,'Data - Control'!$A$5:$A$296,$A40,'Data - Control'!$B$5:$B$296,$C40)
A41: Heineken USA | B41: not incented | C41: Newcastle | D41: =SUMIFS('Control Brands'!$C$5:$C$296,'Control Brands'!$A$5:$A$296,$A41,'Control Brands'!$B$5:$B$296,$C41) | E41: =SUMIFS('Control Brands'!$D$5:$D$296,'Control Brands'!$A$5:$A$296,$A41,'Control Brands'!$B$5:$B$296,$C41) | F41: =E41-D41 | G41: =IFERROR(E41/D41-1,"") | H41: =SUMIFS('Control Brands'!$G$5:$G$296,'Control Brands'!$A$5:$A$296,$A41,'Control Brands'!$B$5:$B$296,$C41) | I41: =SUMIFS('Control Brands'!$H$5:$H$296,'Control Brands'!$A$5:$A$296,$A41,'Control Brands'!$B$5:$B$296,$C41) | J41: =I41-H41 | K41: =SUMIFS('Data - Control'!$J$5:$J$296,'Data - Control'!$A$5:$A$296,$A41,'Data - Control'!$B$5:$B$296,$C41)
A42: Heineken USA | B42: not incented | C42: Prestige Lager | D42: =SUMIFS('Control Brands'!$C$5:$C$296,'Control Brands'!$A$5:$A$296,$A42,'Control Brands'!$B$5:$B$296,$C42) | E42: =SUMIFS('Control Brands'!$D$5:$D$296,'Control Brands'!$A$5:$A$296,$A42,'Control Brands'!$B$5:$B$296,$C42) | F42: =E42-D42 | G42: =IFERROR(E42/D42-1,"") | H42: =SUMIFS('Control Brands'!$G$5:$G$296,'Control Brands'!$A$5:$A$296,$A42,'Control Brands'!$B$5:$B$296,$C42) | I42: =SUMIFS('Control Brands'!$H$5:$H$296,'Control Brands'!$A$5:$A$296,$A42,'Control Brands'!$B$5:$B$296,$C42) | J42: =I42-H42 | K42: =SUMIFS('Data - Control'!$J$5:$J$296,'Data - Control'!$A$5:$A$296,$A42,'Data - Control'!$B$5:$B$296,$C42)
A43: Heineken USA | B43: not incented | C43: Red Stripe | D43: =SUMIFS('Control Brands'!$C$5:$C$296,'Control Brands'!$A$5:$A$296,$A43,'Control Brands'!$B$5:$B$296,$C43) | E43: =SUMIFS('Control Brands'!$D$5:$D$296,'Control Brands'!$A$5:$A$296,$A43,'Control Brands'!$B$5:$B$296,$C43) | F43: =E43-D43 | G43: =IFERROR(E43/D43-1,"") | H43: =SUMIFS('Control Brands'!$G$5:$G$296,'Control Brands'!$A$5:$A$296,$A43,'Control Brands'!$B$5:$B$296,$C43) | I43: =SUMIFS('Control Brands'!$H$5:$H$296,'Control Brands'!$A$5:$A$296,$A43,'Control Brands'!$B$5:$B$296,$C43) | J43: =I43-H43 | K43: =SUMIFS('Data - Control'!$J$5:$J$296,'Data - Control'!$A$5:$A$296,$A43,'Data - Control'!$B$5:$B$296,$C43)
A44: Heineken USA | B44: not incented | C44: Strongbow | D44: =SUMIFS('Control Brands'!$C$5:$C$296,'Control Brands'!$A$5:$A$296,$A44,'Control Brands'!$B$5:$B$296,$C44) | E44: =SUMIFS('Control Brands'!$D$5:$D$296,'Control Brands'!$A$5:$A$296,$A44,'Control Brands'!$B$5:$B$296,$C44) | F44: =E44-D44 | G44: =IFERROR(E44/D44-1,"") | H44: =SUMIFS('Control Brands'!$G$5:$G$296,'Control Brands'!$A$5:$A$296,$A44,'Control Brands'!$B$5:$B$296,$C44) | I44: =SUMIFS('Control Brands'!$H$5:$H$296,'Control Brands'!$A$5:$A$296,$A44,'Control Brands'!$B$5:$B$296,$C44) | J44: =I44-H44 | K44: =SUMIFS('Data - Control'!$J$5:$J$296,'Data - Control'!$A$5:$A$296,$A44,'Data - Control'!$B$5:$B$296,$C44)
A45: Heineken USA | B45: not incented | C45: Tecate | D45: =SUMIFS('Control Brands'!$C$5:$C$296,'Control Brands'!$A$5:$A$296,$A45,'Control Brands'!$B$5:$B$296,$C45) | E45: =SUMIFS('Control Brands'!$D$5:$D$296,'Control Brands'!$A$5:$A$296,$A45,'Control Brands'!$B$5:$B$296,$C45) | F45: =E45-D45 | G45: =IFERROR(E45/D45-1,"") | H45: =SUMIFS('Control Brands'!$G$5:$G$296,'Control Brands'!$A$5:$A$296,$A45,'Control Brands'!$B$5:$B$296,$C45) | I45: =SUMIFS('Control Brands'!$H$5:$H$296,'Control Brands'!$A$5:$A$296,$A45,'Control Brands'!$B$5:$B$296,$C45) | J45: =I45-H45 | K45: =SUMIFS('Data - Control'!$J$5:$J$296,'Data - Control'!$A$5:$A$296,$A45,'Data - Control'!$B$5:$B$296,$C45)
C46: Heineken USA — total | D46: =SUM(D31:D45) | E46: =SUM(E31:E45) | F46: =SUM(F31:F45) | H46: =SUM(H31:H45) | I46: =SUM(I31:I45) | J46: =SUM(J31:J45) | K46: =SUM(K31:K45)
A48: MolsonCoors Beverage Company | B48: INCENTED | C48: Blue Moon | D48: =SUMIFS('Program Brands'!$D$6:$D$37,'Program Brands'!$B$6:$B$37,$A48,'Program Brands'!$C$6:$C$37,$C48) | E48: =SUMIFS('Program Brands'!$E$6:$E$37,'Program Brands'!$B$6:$B$37,$A48,'Program Brands'!$C$6:$C$37,$C48) | F48: =E48-D48 | G48: =IFERROR(E48/D48-1,"") | H48: =SUMIFS('Program Brands'!$H$6:$H$37,'Program Brands'!$B$6:$B$37,$A48,'Program Brands'!$C$6:$C$37,$C48) | I48: =SUMIFS('Program Brands'!$I$6:$I$37,'Program Brands'!$B$6:$B$37,$A48,'Program Brands'!$C$6:$C$37,$C48) | J48: =I48-H48 | K48: =SUMIFS('Data - Season'!$L$5:$L$743,'Data - Season'!$C$5:$C$743,$A48,'Data - Season'!$D$5:$D$743,$C48)
A49: MolsonCoors Beverage Company | B49: INCENTED | C49: Coors | D49: =SUMIFS('Program Brands'!$D$6:$D$37,'Program Brands'!$B$6:$B$37,$A49,'Program Brands'!$C$6:$C$37,$C49) | E49: =SUMIFS('Program Brands'!$E$6:$E$37,'Program Brands'!$B$6:$B$37,$A49,'Program Brands'!$C$6:$C$37,$C49) | F49: =E49-D49 | G49: =IFERROR(E49/D49-1,"") | H49: =SUMIFS('Program Brands'!$H$6:$H$37,'Program Brands'!$B$6:$B$37,$A49,'Program Brands'!$C$6:$C$37,$C49) | I49: =SUMIFS('Program Brands'!$I$6:$I$37,'Program Brands'!$B$6:$B$37,$A49,'Program Brands'!$C$6:$C$37,$C49) | J49: =I49-H49 | K49: =SUMIFS('Data - Season'!$L$5:$L$743,'Data - Season'!$C$5:$C$743,$A49,'Data - Season'!$D$5:$D$743,$C49)
A50: MolsonCoors Beverage Company | B50: INCENTED | C50: Coors Light | D50: =SUMIFS('Program Brands'!$D$6:$D$37,'Program Brands'!$B$6:$B$37,$A50,'Program Brands'!$C$6:$C$37,$C50) | E50: =SUMIFS('Program Brands'!$E$6:$E$37,'Program Brands'!$B$6:$B$37,$A50,'Program Brands'!$C$6:$C$37,$C50) | F50: =E50-D50 | G50: =IFERROR(E50/D50-1,"") | H50: =SUMIFS('Program Brands'!$H$6:$H$37,'Program Brands'!$B$6:$B$37,$A50,'Program Brands'!$C$6:$C$37,$C50) | I50: =SUMIFS('Program Brands'!$I$6:$I$37,'Program Brands'!$B$6:$B$37,$A50,'Program Brands'!$C$6:$C$37,$C50) | J50: =I50-H50 | K50: =SUMIFS('Data - Season'!$L$5:$L$743,'Data - Season'!$C$5:$C$743,$A50,'Data - Season'!$D$5:$D$743,$C50)
A51: MolsonCoors Beverage Company | B51: INCENTED | C51: Fever Tree | D51: =SUMIFS('Program Brands'!$D$6:$D$37,'Program Brands'!$B$6:$B$37,$A51,'Program Brands'!$C$6:$C$37,$C51) | E51: =SUMIFS('Program Brands'!$E$6:$E$37,'Program Brands'!$B$6:$B$37,$A51,'Program Brands'!$C$6:$C$37,$C51) | F51: =E51-D51 | G51: =IFERROR(E51/D51-1,"") | H51: =SUMIFS('Program Brands'!$H$6:$H$37,'Program Brands'!$B$6:$B$37,$A51,'Program Brands'!$C$6:$C$37,$C51) | I51: =SUMIFS('Program Brands'!$I$6:$I$37,'Program Brands'!$B$6:$B$37,$A51,'Program Brands'!$C$6:$C$37,$C51) | J51: =I51-H51 | K51: =SUMIFS('Data - Season'!$L$5:$L$743,'Data - Season'!$C$5:$C$743,$A51,'Data - Season'!$D$5:$D$743,$C51)
A52: MolsonCoors Beverage Company | B52: INCENTED | C52: Lite | D52: =SUMIFS('Program Brands'!$D$6:$D$37,'Program Brands'!$B$6:$B$37,$A52,'Program Brands'!$C$6:$C$37,$C52) | E52: =SUMIFS('Program Brands'!$E$6:$E$37,'Program Brands'!$B$6:$B$37,$A52,'Program Brands'!$C$6:$C$37,$C52) | F52: =E52-D52 | G52: =IFERROR(E52/D52-1,"") | H52: =SUMIFS('Program Brands'!$H$6:$H$37,'Program Brands'!$B$6:$B$37,$A52,'Program Brands'!$C$6:$C$37,$C52) | I52: =SUMIFS('Program Brands'!$I$6:$I$37,'Program Brands'!$B$6:$B$37,$A52,'Program Brands'!$C$6:$C$37,$C52) | J52: =I52-H52 | K52: =SUMIFS('Data - Season'!$L$5:$L$743,'Data - Season'!$C$5:$C$743,$A52,'Data - Season'!$D$5:$D$743,$C52)
A53: MolsonCoors Beverage Company | B53: INCENTED | C53: Peroni | D53: =SUMIFS('Program Brands'!$D$6:$D$37,'Program Brands'!$B$6:$B$37,$A53,'Program Brands'!$C$6:$C$37,$C53) | E53: =SUMIFS('Program Brands'!$E$6:$E$37,'Program Brands'!$B$6:$B$37,$A53,'Program Brands'!$C$6:$C$37,$C53) | F53: =E53-D53 | G53: =IFERROR(E53/D53-1,"") | H53: =SUMIFS('Program Brands'!$H$6:$H$37,'Program Brands'!$B$6:$B$37,$A53,'Program Brands'!$C$6:$C$37,$C53) | I53: =SUMIFS('Program Brands'!$I$6:$I$37,'Program Brands'!$B$6:$B$37,$A53,'Program Brands'!$C$6:$C$37,$C53) | J53: =I53-H53 | K53: =SUMIFS('Data - Season'!$L$5:$L$743,'Data - Season'!$C$5:$C$743,$A53,'Data - Season'!$D$5:$D$743,$C53)
A54: MolsonCoors Beverage Company | B54: not incented | C54: Aguila | D54: =SUMIFS('Control Brands'!$C$5:$C$296,'Control Brands'!$A$5:$A$296,$A54,'Control Brands'!$B$5:$B$296,$C54) | E54: =SUMIFS('Control Brands'!$D$5:$D$296,'Control Brands'!$A$5:$A$296,$A54,'Control Brands'!$B$5:$B$296,$C54) | F54: =E54-D54 | G54: =IFERROR(E54/D54-1,"") | H54: =SUMIFS('Control Brands'!$G$5:$G$296,'Control Brands'!$A$5:$A$296,$A54,'Control Brands'!$B$5:$B$296,$C54) | I54: =SUMIFS('Control Brands'!$H$5:$H$296,'Control Brands'!$A$5:$A$296,$A54,'Control Brands'!$B$5:$B$296,$C54) | J54: =I54-H54 | K54: =SUMIFS('Data - Control'!$J$5:$J$296,'Data - Control'!$A$5:$A$296,$A54,'Data - Control'!$B$5:$B$296,$C54)
A55: MolsonCoors Beverage Company | B55: not incented | C55: Arnold Palmer | D55: =SUMIFS('Control Brands'!$C$5:$C$296,'Control Brands'!$A$5:$A$296,$A55,'Control Brands'!$B$5:$B$296,$C55) | E55: =SUMIFS('Control Brands'!$D$5:$D$296,'Control Brands'!$A$5:$A$296,$A55,'Control Brands'!$B$5:$B$296,$C55) | F55: =E55-D55 | G55: =IFERROR(E55/D55-1,"") | H55: =SUMIFS('Control Brands'!$G$5:$G$296,'Control Brands'!$A$5:$A$296,$A55,'Control Brands'!$B$5:$B$296,$C55) | I55: =SUMIFS('Control Brands'!$H$5:$H$296,'Control Brands'!$A$5:$A$296,$A55,'Control Brands'!$B$5:$B$296,$C55) | J55: =I55-H55 | K55: =SUMIFS('Data - Control'!$J$5:$J$296,'Data - Control'!$A$5:$A$296,$A55,'Data - Control'!$B$5:$B$296,$C55)
A56: MolsonCoors Beverage Company | B56: not incented | C56: Coors 0.0 | D56: =SUMIFS('Control Brands'!$C$5:$C$296,'Control Brands'!$A$5:$A$296,$A56,'Control Brands'!$B$5:$B$296,$C56) | E56: =SUMIFS('Control Brands'!$D$5:$D$296,'Control Brands'!$A$5:$A$296,$A56,'Control Brands'!$B$5:$B$296,$C56) | F56: =E56-D56 | G56: =IFERROR(E56/D56-1,"") | H56: =SUMIFS('Control Brands'!$G$5:$G$296,'Control Brands'!$A$5:$A$296,$A56,'Control Brands'!$B$5:$B$296,$C56) | I56: =SUMIFS('Control Brands'!$H$5:$H$296,'Control Brands'!$A$5:$A$296,$A56,'Control Brands'!$B$5:$B$296,$C56) | J56: =I56-H56 | K56: =SUMIFS('Data - Control'!$J$5:$J$296,'Data - Control'!$A$5:$A$296,$A56,'Data - Control'!$B$5:$B$296,$C56)
A57: MolsonCoors Beverage Company | B57: not incented | C57: Coors Edge | D57: =SUMIFS('Control Brands'!$C$5:$C$296,'Control Brands'!$A$5:$A$296,$A57,'Control Brands'!$B$5:$B$296,$C57) | E57: =SUMIFS('Control Brands'!$D$5:$D$296,'Control Brands'!$A$5:$A$296,$A57,'Control Brands'!$B$5:$B$296,$C57) | F57: =E57-D57 | G57: =IFERROR(E57/D57-1,"") | H57: =SUMIFS('Control Brands'!$G$5:$G$296,'Control Brands'!$A$5:$A$296,$A57,'Control Brands'!$B$5:$B$296,$C57) | I57: =SUMIFS('Control Brands'!$H$5:$H$296,'Control Brands'!$A$5:$A$296,$A57,'Control Brands'!$B$5:$B$296,$C57) | J57: =I57-H57 | K57: =SUMIFS('Data - Control'!$J$5:$J$296,'Data - Control'!$A$5:$A$296,$A57,'Data - Control'!$B$5:$B$296,$C57)
A58: MolsonCoors Beverage Company | B58: not incented | C58: Cusquena | D58: =SUMIFS('Control Brands'!$C$5:$C$296,'Control Brands'!$A$5:$A$296,$A58,'Control Brands'!$B$5:$B$296,$C58) | E58: =SUMIFS('Control Brands'!$D$5:$D$296,'Control Brands'!$A$5:$A$296,$A58,'Control Brands'!$B$5:$B$296,$C58) | F58: =E58-D58 | G58: =IFERROR(E58/D58-1,"") | H58: =SUMIFS('Control Brands'!$G$5:$G$296,'Control Brands'!$A$5:$A$296,$A58,'Control Brands'!$B$5:$B$296,$C58) | I58: =SUMIFS('Control Brands'!$H$5:$H$296,'Control Brands'!$A$5:$A$296,$A58,'Control Brands'!$B$5:$B$296,$C58) | J58: =I58-H58 | K58: =SUMIFS('Data - Control'!$J$5:$J$296,'Data - Control'!$A$5:$A$296,$A58,'Data - Control'!$B$5:$B$296,$C58)
A59: MolsonCoors Beverage Company | B59: not incented | C59: Fosters | D59: =SUMIFS('Control Brands'!$C$5:$C$296,'Control Brands'!$A$5:$A$296,$A59,'Control Brands'!$B$5:$B$296,$C59) | E59: =SUMIFS('Control Brands'!$D$5:$D$296,'Control Brands'!$A$5:$A$296,$A59,'Control Brands'!$B$5:$B$296,$C59) | F59: =E59-D59 | G59: =IFERROR(E59/D59-1,"") | H59: =SUMIFS('Control Brands'!$G$5:$G$296,'Control Brands'!$A$5:$A$296,$A59,'Control Brands'!$B$5:$B$296,$C59) | I59: =SUMIFS('Control Brands'!$H$5:$H$296,'Control Brands'!$A$5:$A$296,$A59,'Control Brands'!$B$5:$B$296,$C59) | J59: =I59-H59 | K59: =SUMIFS('Data - Control'!$J$5:$J$296,'Data - Control'!$A$5:$A$296,$A59,'Data - Control'!$B$5:$B$296,$C59)
A60: MolsonCoors Beverage Company | B60: not incented | C60: George Killian's | D60: =SUMIFS('Control Brands'!$C$5:$C$296,'Control Brands'!$A$5:$A$296,$A60,'Control Brands'!$B$5:$B$296,$C60) | E60: =SUMIFS('Control Brands'!$D$5:$D$296,'Control Brands'!$A$5:$A$296,$A60,'Control Brands'!$B$5:$B$296,$C60) | F60: =E60-D60 | G60: =IFERROR(E60/D60-1,"") | H60: =SUMIFS('Control Brands'!$G$5:$G$296,'Control Brands'!$A$5:$A$296,$A60,'Control Brands'!$B$5:$B$296,$C60) | I60: =SUMIFS('Control Brands'!$H$5:$H$296,'Control Brands'!$A$5:$A$296,$A60,'Control Brands'!$B$5:$B$296,$C60) | J60: =I60-H60 | K60: =SUMIFS('Data - Control'!$J$5:$J$296,'Data - Control'!$A$5:$A$296,$A60,'Data - Control'!$B$5:$B$296,$C60)
A61: MolsonCoors Beverage Company | B61: not incented | C61: Grolsch | D61: =SUMIFS('Control Brands'!$C$5:$C$296,'Control Brands'!$A$5:$A$296,$A61,'Control Brands'!$B$5:$B$296,$C61) | E61: =SUMIFS('Control Brands'!$D$5:$D$296,'Control Brands'!$A$5:$A$296,$A61,'Control Brands'!$B$5:$B$296,$C61) | F61: =E61-D61 | G61: =IFERROR(E61/D61-1,"") | H61: =SUMIFS('Control Brands'!$G$5:$G$296,'Control Brands'!$A$5:$A$296,$A61,'Control Brands'!$B$5:$B$296,$C61) | I61: =SUMIFS('Control Brands'!$H$5:$H$296,'Control Brands'!$A$5:$A$296,$A61,'Control Brands'!$B$5:$B$296,$C61) | J61: =I61-H61 | K61: =SUMIFS('Data - Control'!$J$5:$J$296,'Data - Control'!$A$5:$A$296,$A61,'Data - Control'!$B$5:$B$296,$C61)
A62: MolsonCoors Beverage Company | B62: not incented | C62: Hamm's | D62: =SUMIFS('Control Brands'!$C$5:$C$296,'Control Brands'!$A$5:$A$296,$A62,'Control Brands'!$B$5:$B$296,$C62) | E62: =SUMIFS('Control Brands'!$D$5:$D$296,'Control Brands'!$A$5:$A$296,$A62,'Control Brands'!$B$5:$B$296,$C62) | F62: =E62-D62 | G62: =IFERROR(E62/D62-1,"") | H62: =SUMIFS('Control Brands'!$G$5:$G$296,'Control Brands'!$A$5:$A$296,$A62,'Control Brands'!$B$5:$B$296,$C62) | I62: =SUMIFS('Control Brands'!$H$5:$H$296,'Control Brands'!$A$5:$A$296,$A62,'Control Brands'!$B$5:$B$296,$C62) | J62: =I62-H62 | K62: =SUMIFS('Data - Control'!$J$5:$J$296,'Data - Control'!$A$5:$A$296,$A62,'Data - Control'!$B$5:$B$296,$C62)
A63: MolsonCoors Beverage Company | B63: not incented | C63: Happy Thursday Spiked Refresher | D63: =SUMIFS('Control Brands'!$C$5:$C$296,'Control Brands'!$A$5:$A$296,$A63,'Control Brands'!$B$5:$B$296,$C63) | E63: =SUMIFS('Control Brands'!$D$5:$D$296,'Control Brands'!$A$5:$A$296,$A63,'Control Brands'!$B$5:$B$296,$C63) | F63: =E63-D63 | G63: =IFERROR(E63/D63-1,"") | H63: =SUMIFS('Control Brands'!$G$5:$G$296,'Control Brands'!$A$5:$A$296,$A63,'Control Brands'!$B$5:$B$296,$C63) | I63: =SUMIFS('Control Brands'!$H$5:$H$296,'Control Brands'!$A$5:$A$296,$A63,'Control Brands'!$B$5:$B$296,$C63) | J63: =I63-H63 | K63: =SUMIFS('Data - Control'!$J$5:$J$296,'Data - Control'!$A$5:$A$296,$A63,'Data - Control'!$B$5:$B$296,$C63)
A64: MolsonCoors Beverage Company | B64: not incented | C64: Keystone | D64: =SUMIFS('Control Brands'!$C$5:$C$296,'Control Brands'!$A$5:$A$296,$A64,'Control Brands'!$B$5:$B$296,$C64) | E64: =SUMIFS('Control Brands'!$D$5:$D$296,'Control Brands'!$A$5:$A$296,$A64,'Control Brands'!$B$5:$B$296,$C64) | F64: =E64-D64 | G64: =IFERROR(E64/D64-1,"") | H64: =SUMIFS('Control Brands'!$G$5:$G$296,'Control Brands'!$A$5:$A$296,$A64,'Control Brands'!$B$5:$B$296,$C64) | I64: =SUMIFS('Control Brands'!$H$5:$H$296,'Control Brands'!$A$5:$A$296,$A64,'Control Brands'!$B$5:$B$296,$C64) | J64: =I64-H64 | K64: =SUMIFS('Data - Control'!$J$5:$J$296,'Data - Control'!$A$5:$A$296,$A64,'Data - Control'!$B$5:$B$296,$C64)
A65: MolsonCoors Beverage Company | B65: not incented | C65: Leinenkugel | D65: =SUMIFS('Control Brands'!$C$5:$C$296,'Control Brands'!$A$5:$A$296,$A65,'Control Brands'!$B$5:$B$296,$C65) | E65: =SUMIFS('Control Brands'!$D$5:$D$296,'Control Brands'!$A$5:$A$296,$A65,'Control Brands'!$B$5:$B$296,$C65) | F65: =E65-D65 | G65: =IFERROR(E65/D65-1,"") | H65: =SUMIFS('Control Brands'!$G$5:$G$296,'Control Brands'!$A$5:$A$296,$A65,'Control Brands'!$B$5:$B$296,$C65) | I65: =SUMIFS('Control Brands'!$H$5:$H$296,'Control Brands'!$A$5:$A$296,$A65,'Control Brands'!$B$5:$B$296,$C65) | J65: =I65-H65 | K65: =SUMIFS('Data - Control'!$J$5:$J$296,'Data - Control'!$A$5:$A$296,$A65,'Data - Control'!$B$5:$B$296,$C65)
... A84: MolsonCoors Beverage Company | B84: not incented | C84: Vizzy | D84: =SUMIFS('Control Brands'!$C$5:$C$296,'Control Brands'!$A$5:$A$296,$A84,'Control Brands'!$B$5:$B$296,$C84) | E84: =SUMIFS('Control Brands'!$D$5:$D$296,'Control Brands'!$A$5:$A$296,$A84,'Control Brands'!$B$5:$B$296,$C84) | F84: =E84-D84 | G84: =IFERROR(E84/D84-1,"") | H84: =SUMIFS('Control Brands'!$G$5:$G$296,'Control Brands'!$A$5:$A$296,$A84,'Control Brands'!$B$5:$B$296,$C84) | I84: =SUMIFS('Control Brands'!$H$5:$H$296,'Control Brands'!$A$5:$A$296,$A84,'Control Brands'!$B$5:$B$296,$C84) | J84: =I84-H84 | K84: =SUMIFS('Data - Control'!$J$5:$J$296,'Data - Control'!$A$5:$A$296,$A84,'Data - Control'!$B$5:$B$296,$C84)
C85: MolsonCoors Beverage Company — total | D85: =SUM(D48:D84) | E85: =SUM(E48:E84) | F85: =SUM(F48:F84) | H85: =SUM(H48:H84) | I85: =SUM(I48:I84) | J85: =SUM(J48:J84) | K85: =SUM(K48:K84)
A87: DG Yuengling Inc | B87: INCENTED | C87: Yuengling Flight | D87: =SUMIFS('Program Brands'!$D$6:$D$37,'Program Brands'!$B$6:$B$37,$A87,'Program Brands'!$C$6:$C$37,$C87) | E87: =SUMIFS('Program Brands'!$E$6:$E$37,'Program Brands'!$B$6:$B$37,$A87,'Program Brands'!$C$6:$C$37,$C87) | F87: =E87-D87 | G87: =IFERROR(E87/D87-1,"") | H87: =SUMIFS('Program Brands'!$H$6:$H$37,'Program Brands'!$B$6:$B$37,$A87,'Program Brands'!$C$6:$C$37,$C87) | I87: =SUMIFS('Program Brands'!$I$6:$I$37,'Program Brands'!$B$6:$B$37,$A87,'Program Brands'!$C$6:$C$37,$C87) | J87: =I87-H87 | K87: =SUMIFS('Data - Season'!$L$5:$L$743,'Data - Season'!$C$5:$C$743,$A87,'Data - Season'!$D$5:$D$743,$C87)
A88: DG Yuengling Inc | B88: INCENTED | C88: Yuengling Lager | D88: =SUMIFS('Program Brands'!$D$6:$D$37,'Program Brands'!$B$6:$B$37,$A88,'Program Brands'!$C$6:$C$37,$C88) | E88: =SUMIFS('Program Brands'!$E$6:$E$37,'Program Brands'!$B$6:$B$37,$A88,'Program Brands'!$C$6:$C$37,$C88) | F88: =E88-D88 | G88: =IFERROR(E88/D88-1,"") | H88: =SUMIFS('Program Brands'!$H$6:$H$37,'Program Brands'!$B$6:$B$37,$A88,'Program Brands'!$C$6:$C$37,$C88) | I88: =SUMIFS('Program Brands'!$I$6:$I$37,'Program Brands'!$B$6:$B$37,$A88,'Program Brands'!$C$6:$C$37,$C88) | J88: =I88-H88 | K88: =SUMIFS('Data - Season'!$L$5:$L$743,'Data - Season'!$C$5:$C$743,$A88,'Data - Season'!$D$5:$D$743,$C88)
A89: DG Yuengling Inc | B89: INCENTED | C89: Yuengling Light Lager | D89: =SUMIFS('Program Brands'!$D$6:$D$37,'Program Brands'!$B$6:$B$37,$A89,'Program Brands'!$C$6:$C$37,$C89) | E89: =SUMIFS('Program Brands'!$E$6:$E$37,'Program Brands'!$B$6:$B$37,$A89,'Program Brands'!$C$6:$C$37,$C89) | F89: =E89-D89 | G89: =IFERROR(E89/D89-1,"") | H89: =SUMIFS('Program Brands'!$H$6:$H$37,'Program Brands'!$B$6:$B$37,$A89,'Program Brands'!$C$6:$C$37,$C89) | I89: =SUMIFS('Program Brands'!$I$6:$I$37,'Program Brands'!$B$6:$B$37,$A89,'Program Brands'!$C$6:$C$37,$C89) | J89: =I89-H89 | K89: =SUMIFS('Data - Season'!$L$5:$L$743,'Data - Season'!$C$5:$C$743,$A89,'Data - Season'!$D$5:$D$743,$C89)
A90: DG Yuengling Inc | B90: not incented | C90: Dg Yuengling Inc | D90: =SUMIFS('Control Brands'!$C$5:$C$296,'Control Brands'!$A$5:$A$296,$A90,'Control Brands'!$B$5:$B$296,$C90) | E90: =SUMIFS('Control Brands'!$D$5:$D$296,'Control Brands'!$A$5:$A$296,$A90,'Control Brands'!$B$5:$B$296,$C90) | F90: =E90-D90 | G90: =IFERROR(E90/D90-1,"") | H90: =SUMIFS('Control Brands'!$G$5:$G$296,'Control Brands'!$A$5:$A$296,$A90,'Control Brands'!$B$5:$B$296,$C90) | I90: =SUMIFS('Control Brands'!$H$5:$H$296,'Control Brands'!$A$5:$A$296,$A90,'Control Brands'!$B$5:$B$296,$C90) | J90: =I90-H90 | K90: =SUMIFS('Data - Control'!$J$5:$J$296,'Data - Control'!$A$5:$A$296,$A90,'Data - Control'!$B$5:$B$296,$C90)
A91: DG Yuengling Inc | B91: not incented | C91: Yuengling Black & Tan | D91: =SUMIFS('Control Brands'!$C$5:$C$296,'Control Brands'!$A$5:$A$296,$A91,'Control Brands'!$B$5:$B$296,$C91) | E91: =SUMIFS('Control Brands'!$D$5:$D$296,'Control Brands'!$A$5:$A$296,$A91,'Control Brands'!$B$5:$B$296,$C91) | F91: =E91-D91 | G91: =IFERROR(E91/D91-1,"") | H91: =SUMIFS('Control Brands'!$G$5:$G$296,'Control Brands'!$A$5:$A$296,$A91,'Control Brands'!$B$5:$B$296,$C91) | I91: =SUMIFS('Control Brands'!$H$5:$H$296,'Control Brands'!$A$5:$A$296,$A91,'Control Brands'!$B$5:$B$296,$C91) | J91: =I91-H91 | K91: =SUMIFS('Data - Control'!$J$5:$J$296,'Data - Control'!$A$5:$A$296,$A91,'Data - Control'!$B$5:$B$296,$C91)
A92: DG Yuengling Inc | B92: not incented | C92: Yuengling Golden Pilsner | D92: =SUMIFS('Control Brands'!$C$5:$C$296,'Control Brands'!$A$5:$A$296,$A92,'Control Brands'!$B$5:$B$296,$C92) | E92: =SUMIFS('Control Brands'!$D$5:$D$296,'Control Brands'!$A$5:$A$296,$A92,'Control Brands'!$B$5:$B$296,$C92) | F92: =E92-D92 | G92: =IFERROR(E92/D92-1,"") | H92: =SUMIFS('Control Brands'!$G$5:$G$296,'Control Brands'!$A$5:$A$296,$A92,'Control Brands'!$B$5:$B$296,$C92) | I92: =SUMIFS('Control Brands'!$H$5:$H$296,'Control Brands'!$A$5:$A$296,$A92,'Control Brands'!$B$5:$B$296,$C92) | J92: =I92-H92 | K92: =SUMIFS('Data - Control'!$J$5:$J$296,'Data - Control'!$A$5:$A$296,$A92,'Data - Control'!$B$5:$B$296,$C92)
A93: DG Yuengling Inc | B93: not incented | C93: Yuengling Oktoberfest | D93: =SUMIFS('Control Brands'!$C$5:$C$296,'Control Brands'!$A$5:$A$296,$A93,'Control Brands'!$B$5:$B$296,$C93) | E93: =SUMIFS('Control Brands'!$D$5:$D$296,'Control Brands'!$A$5:$A$296,$A93,'Control Brands'!$B$5:$B$296,$C93) | F93: =E93-D93 | G93: =IFERROR(E93/D93-1,"") | H93: =SUMIFS('Control Brands'!$G$5:$G$296,'Control Brands'!$A$5:$A$296,$A93,'Control Brands'!$B$5:$B$296,$C93) | I93: =SUMIFS('Control Brands'!$H$5:$H$296,'Control Brands'!$A$5:$A$296,$A93,'Control Brands'!$B$5:$B$296,$C93) | J93: =I93-H93 | K93: =SUMIFS('Data - Control'!$J$5:$J$296,'Data - Control'!$A$5:$A$296,$A93,'Data - Control'!$B$5:$B$296,$C93)
A94: DG Yuengling Inc | B94: not incented | C94: Yuengling Premium | D94: =SUMIFS('Control Brands'!$C$5:$C$296,'Control Brands'!$A$5:$A$296,$A94,'Control Brands'!$B$5:$B$296,$C94) | E94: =SUMIFS('Control Brands'!$D$5:$D$296,'Control Brands'!$A$5:$A$296,$A94,'Control Brands'!$B$5:$B$296,$C94) | F94: =E94-D94 | G94: =IFERROR(E94/D94-1,"") | H94: =SUMIFS('Control Brands'!$G$5:$G$296,'Control Brands'!$A$5:$A$296,$A94,'Control Brands'!$B$5:$B$296,$C94) | I94: =SUMIFS('Control Brands'!$H$5:$H$296,'Control Brands'!$A$5:$A$296,$A94,'Control Brands'!$B$5:$B$296,$C94) | J94: =I94-H94 | K94: =SUMIFS('Data - Control'!$J$5:$J$296,'Data - Control'!$A$5:$A$296,$A94,'Data - Control'!$B$5:$B$296,$C94)
A95: DG Yuengling Inc | B95: not incented | C95: Yuengling Premium Light | D95: =SUMIFS('Control Brands'!$C$5:$C$296,'Control Brands'!$A$5:$A$296,$A95,'Control Brands'!$B$5:$B$296,$C95) | E95: =SUMIFS('Control Brands'!$D$5:$D$296,'Control Brands'!$A$5:$A$296,$A95,'Control Brands'!$B$5:$B$296,$C95) | F95: =E95-D95 | G95: =IFERROR(E95/D95-1,"") | H95: =SUMIFS('Control Brands'!$G$5:$G$296,'Control Brands'!$A$5:$A$296,$A95,'Control Brands'!$B$5:$B$296,$C95) | I95: =SUMIFS('Control Brands'!$H$5:$H$296,'Control Brands'!$A$5:$A$296,$A95,'Control Brands'!$B$5:$B$296,$C95) | J95: =I95-H95 | K95: =SUMIFS('Data - Control'!$J$5:$J$296,'Data - Control'!$A$5:$A$296,$A95,'Data - Control'!$B$5:$B$296,$C95)
C96: DG Yuengling Inc — total | D96: =SUM(D87:D95) | E96: =SUM(E87:E95) | F96: =SUM(F87:F95) | H96: =SUM(H87:H95) | I96: =SUM(I87:I95) | J96: =SUM(J87:J95) | K96: =SUM(K87:K95)
A98: Constellation Brands | B98: INCENTED | C98: Corona Extra | D98: =SUMIFS('Program Brands'!$D$6:$D$37,'Program Brands'!$B$6:$B$37,$A98,'Program Brands'!$C$6:$C$37,$C98) | E98: =SUMIFS('Program Brands'!$E$6:$E$37,'Program Brands'!$B$6:$B$37,$A98,'Program Brands'!$C$6:$C$37,$C98) | F98: =E98-D98 | G98: =IFERROR(E98/D98-1,"") | H98: =SUMIFS('Program Brands'!$H$6:$H$37,'Program Brands'!$B$6:$B$37,$A98,'Program Brands'!$C$6:$C$37,$C98) | I98: =SUMIFS('Program Brands'!$I$6:$I$37,'Program Brands'!$B$6:$B$37,$A98,'Program Brands'!$C$6:$C$37,$C98) | J98: =I98-H98 | K98: =SUMIFS('Data - Season'!$L$5:$L$743,'Data - Season'!$C$5:$C$743,$A98,'Data - Season'!$D$5:$D$743,$C98)
A99: Constellation Brands | B99: INCENTED | C99: Corona Premier | D99: =SUMIFS('Program Brands'!$D$6:$D$37,'Program Brands'!$B$6:$B$37,$A99,'Program Brands'!$C$6:$C$37,$C99) | E99: =SUMIFS('Program Brands'!$E$6:$E$37,'Program Brands'!$B$6:$B$37,$A99,'Program Brands'!$C$6:$C$37,$C99) | F99: =E99-D99 | G99: =IFERROR(E99/D99-1,"") | H99: =SUMIFS('Program Brands'!$H$6:$H$37,'Program Brands'!$B$6:$B$37,$A99,'Program Brands'!$C$6:$C$37,$C99) | I99: =SUMIFS('Program Brands'!$I$6:$I$37,'Program Brands'!$B$6:$B$37,$A99,'Program Brands'!$C$6:$C$37,$C99) | J99: =I99-H99 | K99: =SUMIFS('Data - Season'!$L$5:$L$743,'Data - Season'!$C$5:$C$743,$A99,'Data - Season'!$D$5:$D$743,$C99)
A100: Constellation Brands | B100: INCENTED | C100: Modelo Chelada | D100: =SUMIFS('Program Brands'!$D$6:$D$37,'Program Brands'!$B$6:$B$37,$A100,'Program Brands'!$C$6:$C$37,$C100) | E100: =SUMIFS('Program Brands'!$E$6:$E$37,'Program Brands'!$B$6:$B$37,$A100,'Program Brands'!$C$6:$C$37,$C100) | F100: =E100-D100 | G100: =IFERROR(E100/D100-1,"") | H100: =SUMIFS('Program Brands'!$H$6:$H$37,'Program Brands'!$B$6:$B$37,$A100,'Program Brands'!$C$6:$C$37,$C100) | I100: =SUMIFS('Program Brands'!$I$6:$I$37,'Program Brands'!$B$6:$B$37,$A100,'Program Brands'!$C$6:$C$37,$C100) | J100: =I100-H100 | K100: =SUMIFS('Data - Season'!$L$5:$L$743,'Data - Season'!$C$5:$C$743,$A100,'Data - Season'!$D$5:$D$743,$C100)
A101: Constellation Brands | B101: INCENTED | C101: Modelo Especial | D101: =SUMIFS('Program Brands'!$D$6:$D$37,'Program Brands'!$B$6:$B$37,$A101,'Program Brands'!$C$6:$C$37,$C101) | E101: =SUMIFS('Program Brands'!$E$6:$E$37,'Program Brands'!$B$6:$B$37,$A101,'Program Brands'!$C$6:$C$37,$C101) | F101: =E101-D101 | G101: =IFERROR(E101/D101-1,"") | H101: =SUMIFS('Program Brands'!$H$6:$H$37,'Program Brands'!$B$6:$B$37,$A101,'Program Brands'!$C$6:$C$37,$C101) | I101: =SUMIFS('Program Brands'!$I$6:$I$37,'Program Brands'!$B$6:$B$37,$A101,'Program Brands'!$C$6:$C$37,$C101) | J101: =I101-H101 | K101: =SUMIFS('Data - Season'!$L$5:$L$743,'Data - Season'!$C$5:$C$743,$A101,'Data - Season'!$D$5:$D$743,$C101)
A102: Constellation Brands | B102: INCENTED | C102: Pacifico | D102: =SUMIFS('Program Brands'!$D$6:$D$37,'Program Brands'!$B$6:$B$37,$A102,'Program Brands'!$C$6:$C$37,$C102) | E102: =SUMIFS('Program Brands'!$E$6:$E$37,'Program Brands'!$B$6:$B$37,$A102,'Program Brands'!$C$6:$C$37,$C102) | F102: =E102-D102 | G102: =IFERROR(E102/D102-1,"") | H102: =SUMIFS('Program Brands'!$H$6:$H$37,'Program Brands'!$B$6:$B$37,$A102,'Program Brands'!$C$6:$C$37,$C102) | I102: =SUMIFS('Program Brands'!$I$6:$I$37,'Program Brands'!$B$6:$B$37,$A102,'Program Brands'!$C$6:$C$37,$C102) | J102: =I102-H102 | K102: =SUMIFS('Data - Season'!$L$5:$L$743,'Data - Season'!$C$5:$C$743,$A102,'Data - Season'!$D$5:$D$743,$C102)
A103: Constellation Brands | B103: INCENTED | C103: Victoria | D103: =SUMIFS('Program Brands'!$D$6:$D$37,'Program Brands'!$B$6:$B$37,$A103,'Program Brands'!$C$6:$C$37,$C103) | E103: =SUMIFS('Program Brands'!$E$6:$E$37,'Program Brands'!$B$6:$B$37,$A103,'Program Brands'!$C$6:$C$37,$C103) | F103: =E103-D103 | G103: =IFERROR(E103/D103-1,"") | H103: =SUMIFS('Program Brands'!$H$6:$H$37,'Program Brands'!$B$6:$B$37,$A103,'Program Brands'!$C$6:$C$37,$C103) | I103: =SUMIFS('Program Brands'!$I$6:$I$37,'Program Brands'!$B$6:$B$37,$A103,'Program Brands'!$C$6:$C$37,$C103) | J103: =I103-H103 | K103: =SUMIFS('Data - Season'!$L$5:$L$743,'Data - Season'!$C$5:$C$743,$A103,'Data - Season'!$D$5:$D$743,$C103)
A104: Constellation Brands | B104: not incented | C104: Corona Familiar | D104: =SUMIFS('Control Brands'!$C$5:$C$296,'Control Brands'!$A$5:$A$296,$A104,'Control Brands'!$B$5:$B$296,$C104) | E104: =SUMIFS('Control Brands'!$D$5:$D$296,'Control Brands'!$A$5:$A$296,$A104,'Control Brands'!$B$5:$B$296,$C104) | F104: =E104-D104 | G104: =IFERROR(E104/D104-1,"") | H104: =SUMIFS('Control Brands'!$G$5:$G$296,'Control Brands'!$A$5:$A$296,$A104,'Control Brands'!$B$5:$B$296,$C104) | I104: =SUMIFS('Control Brands'!$H$5:$H$296,'Control Brands'!$A$5:$A$296,$A104,'Control Brands'!$B$5:$B$296,$C104) | J104: =I104-H104 | K104: =SUMIFS('Data - Control'!$J$5:$J$296,'Data - Control'!$A$5:$A$296,$A104,'Data - Control'!$B$5:$B$296,$C104)
A105: Constellation Brands | B105: not incented | C105: Corona Light | D105: =SUMIFS('Control Brands'!$C$5:$C$296,'Control Brands'!$A$5:$A$296,$A105,'Control Brands'!$B$5:$B$296,$C105) | E105: =SUMIFS('Control Brands'!$D$5:$D$296,'Control Brands'!$A$5:$A$296,$A105,'Control Brands'!$B$5:$B$296,$C105) | F105: =E105-D105 | G105: =IFERROR(E105/D105-1,"") | H105: =SUMIFS('Control Brands'!$G$5:$G$296,'Control Brands'!$A$5:$A$296,$A105,'Control Brands'!$B$5:$B$296,$C105) | I105: =SUMIFS('Control Brands'!$H$5:$H$296,'Control Brands'!$A$5:$A$296,$A105,'Control Brands'!$B$5:$B$296,$C105) | J105: =I105-H105 | K105: =SUMIFS('Data - Control'!$J$5:$J$296,'Data - Control'!$A$5:$A$296,$A105,'Data - Control'!$B$5:$B$296,$C105)
A106: Constellation Brands | B106: not incented | C106: Corona NA | D106: =SUMIFS('Control Brands'!$C$5:$C$296,'Control Brands'!$A$5:$A$296,$A106,'Control Brands'!$B$5:$B$296,$C106) | E106: =SUMIFS('Control Brands'!$D$5:$D$296,'Control Brands'!$A$5:$A$296,$A106,'Control Brands'!$B$5:$B$296,$C106) | F106: =E106-D106 | G106: =IFERROR(E106/D106-1,"") | H106: =SUMIFS('Control Brands'!$G$5:$G$296,'Control Brands'!$A$5:$A$296,$A106,'Control Brands'!$B$5:$B$296,$C106) | I106: =SUMIFS('Control Brands'!$H$5:$H$296,'Control Brands'!$A$5:$A$296,$A106,'Control Brands'!$B$5:$B$296,$C106) | J106: =I106-H106 | K106: =SUMIFS('Data - Control'!$J$5:$J$296,'Data - Control'!$A$5:$A$296,$A106,'Data - Control'!$B$5:$B$296,$C106)
A107: Constellation Brands | B107: not incented | C107: Corona Refresca | D107: =SUMIFS('Control Brands'!$C$5:$C$296,'Control Brands'!$A$5:$A$296,$A107,'Control Brands'!$B$5:$B$296,$C107) | E107: =SUMIFS('Control Brands'!$D$5:$D$296,'Control Brands'!$A$5:$A$296,$A107,'Control Brands'!$B$5:$B$296,$C107) | F107: =E107-D107 | G107: =IFERROR(E107/D107-1,"") | H107: =SUMIFS('Control Brands'!$G$5:$G$296,'Control Brands'!$A$5:$A$296,$A107,'Control Brands'!$B$5:$B$296,$C107) | I107: =SUMIFS('Control Brands'!$H$5:$H$296,'Control Brands'!$A$5:$A$296,$A107,'Control Brands'!$B$5:$B$296,$C107) | J107: =I107-H107 | K107: =SUMIFS('Data - Control'!$J$5:$J$296,'Data - Control'!$A$5:$A$296,$A107,'Data - Control'!$B$5:$B$296,$C107)
A108: Constellation Brands | B108: not incented | C108: Corona Sunbrew | D108: =SUMIFS('Control Brands'!$C$5:$C$296,'Control Brands'!$A$5:$A$296,$A108,'Control Brands'!$B$5:$B$296,$C108) | E108: =SUMIFS('Control Brands'!$D$5:$D$296,'Control Brands'!$A$5:$A$296,$A108,'Control Brands'!$B$5:$B$296,$C108) | F108: =E108-D108 | G108: =IFERROR(E108/D108-1,"") | H108: =SUMIFS('Control Brands'!$G$5:$G$296,'Control Brands'!$A$5:$A$296,$A108,'Control Brands'!$B$5:$B$296,$C108) | I108: =SUMIFS('Control Brands'!$H$5:$H$296,'Control Brands'!$A$5:$A$296,$A108,'Control Brands'!$B$5:$B$296,$C108) | J108: =I108-H108 | K108: =SUMIFS('Data - Control'!$J$5:$J$296,'Data - Control'!$A$5:$A$296,$A108,'Data - Control'!$B$5:$B$296,$C108)
A109: Constellation Brands | B109: not incented | C109: Modelo Aquas Frescas | D109: =SUMIFS('Control Brands'!$C$5:$C$296,'Control Brands'!$A$5:$A$296,$A109,'Control Brands'!$B$5:$B$296,$C109) | E109: =SUMIFS('Control Brands'!$D$5:$D$296,'Control Brands'!$A$5:$A$296,$A109,'Control Brands'!$B$5:$B$296,$C109) | F109: =E109-D109 | G109: =IFERROR(E109/D109-1,"") | H109: =SUMIFS('Control Brands'!$G$5:$G$296,'Control Brands'!$A$5:$A$296,$A109,'Control Brands'!$B$5:$B$296,$C109) | I109: =SUMIFS('Control Brands'!$H$5:$H$296,'Control Brands'!$A$5:$A$296,$A109,'Control Brands'!$B$5:$B$296,$C109) | J109: =I109-H109 | K109: =SUMIFS('Data - Control'!$J$5:$J$296,'Data - Control'!$A$5:$A$296,$A109,'Data - Control'!$B$5:$B$296,$C109)
A110: Constellation Brands | B110: not incented | C110: Modelo Negra | D110: =SUMIFS('Control Brands'!$C$5:$C$296,'Control Brands'!$A$5:$A$296,$A110,'Control Brands'!$B$5:$B$296,$C110) | E110: =SUMIFS('Control Brands'!$D$5:$D$296,'Control Brands'!$A$5:$A$296,$A110,'Control Brands'!$B$5:$B$296,$C110) | F110: =E110-D110 | G110: =IFERROR(E110/D110-1,"") | H110: =SUMIFS('Control Brands'!$G$5:$G$296,'Control Brands'!$A$5:$A$296,$A110,'Control Brands'!$B$5:$B$296,$C110) | I110: =SUMIFS('Control Brands'!$H$5:$H$296,'Control Brands'!$A$5:$A$296,$A110,'Control Brands'!$B$5:$B$296,$C110) | J110: =I110-H110 | K110: =SUMIFS('Data - Control'!$J$5:$J$296,'Data - Control'!$A$5:$A$296,$A110,'Data - Control'!$B$5:$B$296,$C110)
A111: Constellation Brands | B111: not incented | C111: Modelo Oro | D111: =SUMIFS('Control Brands'!$C$5:$C$296,'Control Brands'!$A$5:$A$296,$A111,'Control Brands'!$B$5:$B$296,$C111) | E111: =SUMIFS('Control Brands'!$D$5:$D$296,'Control Brands'!$A$5:$A$296,$A111,'Control Brands'!$B$5:$B$296,$C111) | F111: =E111-D111 | G111: =IFERROR(E111/D111-1,"") | H111: =SUMIFS('Control Brands'!$G$5:$G$296,'Control Brands'!$A$5:$A$296,$A111,'Control Brands'!$B$5:$B$296,$C111) | I111: =SUMIFS('Control Brands'!$H$5:$H$296,'Control Brands'!$A$5:$A$296,$A111,'Control Brands'!$B$5:$B$296,$C111) | J111: =I111-H111 | K111: =SUMIFS('Data - Control'!$J$5:$J$296,'Data - Control'!$A$5:$A$296,$A111,'Data - Control'!$B$5:$B$296,$C111)
A112: Constellation Brands | B112: not incented | C112: The Drop | D112: =SUMIFS('Control Brands'!$C$5:$C$296,'Control Brands'!$A$5:$A$296,$A112,'Control Brands'!$B$5:$B$296,$C112) | E112: =SUMIFS('Control Brands'!$D$5:$D$296,'Control Brands'!$A$5:$A$296,$A112,'Control Brands'!$B$5:$B$296,$C112) | F112: =E112-D112 | G112: =IFERROR(E112/D112-1,"") | H112: =SUMIFS('Control Brands'!$G$5:$G$296,'Control Brands'!$A$5:$A$296,$A112,'Control Brands'!$B$5:$B$296,$C112) | I112: =SUMIFS('Control Brands'!$H$5:$H$296,'Control Brands'!$A$5:$A$296,$A112,'Control Brands'!$B$5:$B$296,$C112) | J112: =I112-H112 | K112: =SUMIFS('Data - Control'!$J$5:$J$296,'Data - Control'!$A$5:$A$296,$A112,'Data - Control'!$B$5:$B$296,$C112)
C113: Constellation Brands — total | D113: =SUM(D98:D112) | E113: =SUM(E98:E112) | F113: =SUM(F98:F112) | H113: =SUM(H98:H112) | I113: =SUM(I98:I112) | J113: =SUM(J98:J112) | K113: =SUM(K98:K112)
A115: Mark Anthony | B115: INCENTED | C115: Cayman Jack | D115: =SUMIFS('Program Brands'!$D$6:$D$37,'Program Brands'!$B$6:$B$37,$A115,'Program Brands'!$C$6:$C$37,$C115) | E115: =SUMIFS('Program Brands'!$E$6:$E$37,'Program Brands'!$B$6:$B$37,$A115,'Program Brands'!$C$6:$C$37,$C115) | F115: =E115-D115 | G115: =IFERROR(E115/D115-1,"") | H115: =SUMIFS('Program Brands'!$H$6:$H$37,'Program Brands'!$B$6:$B$37,$A115,'Program Brands'!$C$6:$C$37,$C115) | I115: =SUMIFS('Program Brands'!$I$6:$I$37,'Program Brands'!$B$6:$B$37,$A115,'Program Brands'!$C$6:$C$37,$C115) | J115: =I115-H115 | K115: =SUMIFS('Data - Season'!$L$5:$L$743,'Data - Season'!$C$5:$C$743,$A115,'Data - Season'!$D$5:$D$743,$C115)
A116: Mark Anthony | B116: INCENTED | C116: Mike's Harder | D116: =SUMIFS('Program Brands'!$D$6:$D$37,'Program Brands'!$B$6:$B$37,$A116,'Program Brands'!$C$6:$C$37,$C116) | E116: =SUMIFS('Program Brands'!$E$6:$E$37,'Program Brands'!$B$6:$B$37,$A116,'Program Brands'!$C$6:$C$37,$C116) | F116: =E116-D116 | G116: =IFERROR(E116/D116-1,"") | H116: =SUMIFS('Program Brands'!$H$6:$H$37,'Program Brands'!$B$6:$B$37,$A116,'Program Brands'!$C$6:$C$37,$C116) | I116: =SUMIFS('Program Brands'!$I$6:$I$37,'Program Brands'!$B$6:$B$37,$A116,'Program Brands'!$C$6:$C$37,$C116) | J116: =I116-H116 | K116: =SUMIFS('Data - Season'!$L$5:$L$743,'Data - Season'!$C$5:$C$743,$A116,'Data - Season'!$D$5:$D$743,$C116)
A117: Mark Anthony | B117: INCENTED | C117: Mxd Cocktails | D117: =SUMIFS('Program Brands'!$D$6:$D$37,'Program Brands'!$B$6:$B$37,$A117,'Program Brands'!$C$6:$C$37,$C117) | E117: =SUMIFS('Program Brands'!$E$6:$E$37,'Program Brands'!$B$6:$B$37,$A117,'Program Brands'!$C$6:$C$37,$C117) | F117: =E117-D117 | G117: =IFERROR(E117/D117-1,"") | H117: =SUMIFS('Program Brands'!$H$6:$H$37,'Program Brands'!$B$6:$B$37,$A117,'Program Brands'!$C$6:$C$37,$C117) | I117: =SUMIFS('Program Brands'!$I$6:$I$37,'Program Brands'!$B$6:$B$37,$A117,'Program Brands'!$C$6:$C$37,$C117) | J117: =I117-H117 | K117: =SUMIFS('Data - Season'!$L$5:$L$743,'Data - Season'!$C$5:$C$743,$A117,'Data - Season'!$D$5:$D$743,$C117)
A118: Mark Anthony | B118: INCENTED | C118: White Claw | D118: =SUMIFS('Program Brands'!$D$6:$D$37,'Program Brands'!$B$6:$B$37,$A118,'Program Brands'!$C$6:$C$37,$C118) | E118: =SUMIFS('Program Brands'!$E$6:$E$37,'Program Brands'!$B$6:$B$37,$A118,'Program Brands'!$C$6:$C$37,$C118) | F118: =E118-D118 | G118: =IFERROR(E118/D118-1,"") | H118: =SUMIFS('Program Brands'!$H$6:$H$37,'Program Brands'!$B$6:$B$37,$A118,'Program Brands'!$C$6:$C$37,$C118) | I118: =SUMIFS('Program Brands'!$I$6:$I$37,'Program Brands'!$B$6:$B$37,$A118,'Program Brands'!$C$6:$C$37,$C118) | J118: =I118-H118 | K118: =SUMIFS('Data - Season'!$L$5:$L$743,'Data - Season'!$C$5:$C$743,$A118,'Data - Season'!$D$5:$D$743,$C118)
A119: Mark Anthony | B119: not incented | C119: Dillon's Cocktails | D119: =SUMIFS('Control Brands'!$C$5:$C$296,'Control Brands'!$A$5:$A$296,$A119,'Control Brands'!$B$5:$B$296,$C119) | E119: =SUMIFS('Control Brands'!$D$5:$D$296,'Control Brands'!$A$5:$A$296,$A119,'Control Brands'!$B$5:$B$296,$C119) | F119: =E119-D119 | G119: =IFERROR(E119/D119-1,"") | H119: =SUMIFS('Control Brands'!$G$5:$G$296,'Control Brands'!$A$5:$A$296,$A119,'Control Brands'!$B$5:$B$296,$C119) | I119: =SUMIFS('Control Brands'!$H$5:$H$296,'Control Brands'!$A$5:$A$296,$A119,'Control Brands'!$B$5:$B$296,$C119) | J119: =I119-H119 | K119: =SUMIFS('Data - Control'!$J$5:$J$296,'Data - Control'!$A$5:$A$296,$A119,'Data - Control'!$B$5:$B$296,$C119)
A120: Mark Anthony | B120: not incented | C120: Mike's Hard Dirty Lemonade | D120: =SUMIFS('Control Brands'!$C$5:$C$296,'Control Brands'!$A$5:$A$296,$A120,'Control Brands'!$B$5:$B$296,$C120) | E120: =SUMIFS('Control Brands'!$D$5:$D$296,'Control Brands'!$A$5:$A$296,$A120,'Control Brands'!$B$5:$B$296,$C120) | F120: =E120-D120 | G120: =IFERROR(E120/D120-1,"") | H120: =SUMIFS('Control Brands'!$G$5:$G$296,'Control Brands'!$A$5:$A$296,$A120,'Control Brands'!$B$5:$B$296,$C120) | I120: =SUMIFS('Control Brands'!$H$5:$H$296,'Control Brands'!$A$5:$A$296,$A120,'Control Brands'!$B$5:$B$296,$C120) | J120: =I120-H120 | K120: =SUMIFS('Data - Control'!$J$5:$J$296,'Data - Control'!$A$5:$A$296,$A120,'Data - Control'!$B$5:$B$296,$C120)
A121: Mark Anthony | B121: not incented | C121: Mike's Hard Lemonade | D121: =SUMIFS('Control Brands'!$C$5:$C$296,'Control Brands'!$A$5:$A$296,$A121,'Control Brands'!$B$5:$B$296,$C121) | E121: =SUMIFS('Control Brands'!$D$5:$D$296,'Control Brands'!$A$5:$A$296,$A121,'Control Brands'!$B$5:$B$296,$C121) | F121: =E121-D121 | G121: =IFERROR(E121/D121-1,"") | H121: =SUMIFS('Control Brands'!$G$5:$G$296,'Control Brands'!$A$5:$A$296,$A121,'Control Brands'!$B$5:$B$296,$C121) | I121: =SUMIFS('Control Brands'!$H$5:$H$296,'Control Brands'!$A$5:$A$296,$A121,'Control Brands'!$B$5:$B$296,$C121) | J121: =I121-H121 | K121: =SUMIFS('Data - Control'!$J$5:$J$296,'Data - Control'!$A$5:$A$296,$A121,'Data - Control'!$B$5:$B$296,$C121)
A122: Mark Anthony | B122: not incented | C122: Ole | D122: =SUMIFS('Control Brands'!$C$5:$C$296,'Control Brands'!$A$5:$A$296,$A122,'Control Brands'!$B$5:$B$296,$C122) | E122: =SUMIFS('Control Brands'!$D$5:$D$296,'Control Brands'!$A$5:$A$296,$A122,'Control Brands'!$B$5:$B$296,$C122) | F122: =E122-D122 | G122: =IFERROR(E122/D122-1,"") | H122: =SUMIFS('Control Brands'!$G$5:$G$296,'Control Brands'!$A$5:$A$296,$A122,'Control Brands'!$B$5:$B$296,$C122) | I122: =SUMIFS('Control Brands'!$H$5:$H$296,'Control Brands'!$A$5:$A$296,$A122,'Control Brands'!$B$5:$B$296,$C122) | J122: =I122-H122 | K122: =SUMIFS('Data - Control'!$J$5:$J$296,'Data - Control'!$A$5:$A$296,$A122,'Data - Control'!$B$5:$B$296,$C122)
C123: Mark Anthony — total | D123: =SUM(D115:D122) | E123: =SUM(E115:E122) | F123: =SUM(F115:F122) | H123: =SUM(H115:H122) | I123: =SUM(I115:I122) | J123: =SUM(J115:J122) | K123: =SUM(K115:K122)
A125: Boston Beer is the case to present. The program pointed reps at Twisted Tea and Truly — both in decline — while Sun Cruiser, carrying no incentive, grew by more cases than the incented brands lost.
A126: Mark Anthony is the mirror image and the program's one clear win: incented brands held while the same supplier's non-incented brands fell more than twenty points further.
A127: Filter column B to compare the two halves of any supplier.

Sheet Goal Design
A1: Were the goals ever hard? — qualifier goal vs the rep's own prior-year volume
A2: A goal set below last year's actual pays for maintenance. Goal is typed from goals.csv; both actuals are live SUMIFS off Data - Season.
A4: Rep | B4: Manager | C4: Supplier | D4: 2026 qualifier goal | E4: Rep's own 2025 CE | F4: Goal vs 2025 | G4: Goal below 2025? | H4: 2026 actual CE | I4: % to goal | J4: Cleared? | K4: 2026 vs 2025 | L4: At or below LY? | M4: Within 1% of LY?
A5: Alisa Acciardi | B5: Mike Kennedy | C5: Constellation Brands | D5: 453 | E5: =SUMIFS('Data - Season'!$E$5:$E$743,'Data - Season'!$A$5:$A$743,$A5,'Data - Season'!$C$5:$C$743,$C5,'Data - Season'!$B$5:$B$743,"Qualifier") | F5: =IFERROR($D5/$E5-1,"") | G5: =IF($D5<$E5,"YES — below LY","no") | H5: =SUMIFS('Data - Season'!$F$5:$F$743,'Data - Season'!$A$5:$A$743,$A5,'Data - Season'!$C$5:$C$743,$C5,'Data - Season'!$B$5:$B$743,"Qualifier") | I5: =IFERROR($H5/$D5,"") | J5: =IF($H5>=$D5,"cleared","missed") | K5: =IFERROR($H5/$E5-1,"") | L5: =IF($D5<=$E5,"at or below","above") | M5: =IF(AND($E5>0,ABS($D5/$E5-1)<=0.01),"within 1%","")
A6: Alisa Acciardi | B6: Mike Kennedy | C6: DG Yuengling Inc | D6: 19 | E6: =SUMIFS('Data - Season'!$E$5:$E$743,'Data - Season'!$A$5:$A$743,$A6,'Data - Season'!$C$5:$C$743,$C6,'Data - Season'!$B$5:$B$743,"Qualifier") | F6: =IFERROR($D6/$E6-1,"") | G6: =IF($D6<$E6,"YES — below LY","no") | H6: =SUMIFS('Data - Season'!$F$5:$F$743,'Data - Season'!$A$5:$A$743,$A6,'Data - Season'!$C$5:$C$743,$C6,'Data - Season'!$B$5:$B$743,"Qualifier") | I6: =IFERROR($H6/$D6,"") | J6: =IF($H6>=$D6,"cleared","missed") | K6: =IFERROR($H6/$E6-1,"") | L6: =IF($D6<=$E6,"at or below","above") | M6: =IF(AND($E6>0,ABS($D6/$E6-1)<=0.01),"within 1%","")
A7: Alisa Acciardi | B7: Mike Kennedy | C7: Heineken USA | D7: 149 | E7: =SUMIFS('Data - Season'!$E$5:$E$743,'Data - Season'!$A$5:$A$743,$A7,'Data - Season'!$C$5:$C$743,$C7,'Data - Season'!$B$5:$B$743,"Qualifier") | F7: =IFERROR($D7/$E7-1,"") | G7: =IF($D7<$E7,"YES — below LY","no") | H7: =SUMIFS('Data - Season'!$F$5:$F$743,'Data - Season'!$A$5:$A$743,$A7,'Data - Season'!$C$5:$C$743,$C7,'Data - Season'!$B$5:$B$743,"Qualifier") | I7: =IFERROR($H7/$D7,"") | J7: =IF($H7>=$D7,"cleared","missed") | K7: =IFERROR($H7/$E7-1,"") | L7: =IF($D7<=$E7,"at or below","above") | M7: =IF(AND($E7>0,ABS($D7/$E7-1)<=0.01),"within 1%","")
A8: Alisa Acciardi | B8: Mike Kennedy | C8: Mark Anthony | D8: 80 | E8: =SUMIFS('Data - Season'!$E$5:$E$743,'Data - Season'!$A$5:$A$743,$A8,'Data - Season'!$C$5:$C$743,$C8,'Data - Season'!$B$5:$B$743,"Qualifier") | F8: =IFERROR($D8/$E8-1,"") | G8: =IF($D8<$E8,"YES — below LY","no") | H8: =SUMIFS('Data - Season'!$F$5:$F$743,'Data - Season'!$A$5:$A$743,$A8,'Data - Season'!$C$5:$C$743,$C8,'Data - Season'!$B$5:$B$743,"Qualifier") | I8: =IFERROR($H8/$D8,"") | J8: =IF($H8>=$D8,"cleared","missed") | K8: =IFERROR($H8/$E8-1,"") | L8: =IF($D8<=$E8,"at or below","above") | M8: =IF(AND($E8>0,ABS($D8/$E8-1)<=0.01),"within 1%","")
A9: Alisa Acciardi | B9: Mike Kennedy | C9: MolsonCoors Beverage Company | D9: 491 | E9: =SUMIFS('Data - Season'!$E$5:$E$743,'Data - Season'!$A$5:$A$743,$A9,'Data - Season'!$C$5:$C$743,$C9,'Data - Season'!$B$5:$B$743,"Qualifier") | F9: =IFERROR($D9/$E9-1,"") | G9: =IF($D9<$E9,"YES — below LY","no") | H9: =SUMIFS('Data - Season'!$F$5:$F$743,'Data - Season'!$A$5:$A$743,$A9,'Data - Season'!$C$5:$C$743,$C9,'Data - Season'!$B$5:$B$743,"Qualifier") | I9: =IFERROR($H9/$D9,"") | J9: =IF($H9>=$D9,"cleared","missed") | K9: =IFERROR($H9/$E9-1,"") | L9: =IF($D9<=$E9,"at or below","above") | M9: =IF(AND($E9>0,ABS($D9/$E9-1)<=0.01),"within 1%","")
A10: Allison Scott | B10: Chris McCrohan | C10: Boston Beer Company | D10: 265 | E10: =SUMIFS('Data - Season'!$E$5:$E$743,'Data - Season'!$A$5:$A$743,$A10,'Data - Season'!$C$5:$C$743,$C10,'Data - Season'!$B$5:$B$743,"Qualifier") | F10: =IFERROR($D10/$E10-1,"") | G10: =IF($D10<$E10,"YES — below LY","no") | H10: =SUMIFS('Data - Season'!$F$5:$F$743,'Data - Season'!$A$5:$A$743,$A10,'Data - Season'!$C$5:$C$743,$C10,'Data - Season'!$B$5:$B$743,"Qualifier") | I10: =IFERROR($H10/$D10,"") | J10: =IF($H10>=$D10,"cleared","missed") | K10: =IFERROR($H10/$E10-1,"") | L10: =IF($D10<=$E10,"at or below","above") | M10: =IF(AND($E10>0,ABS($D10/$E10-1)<=0.01),"within 1%","")
A11: Allison Scott | B11: Chris McCrohan | C11: Constellation Brands | D11: 7193 | E11: =SUMIFS('Data - Season'!$E$5:$E$743,'Data - Season'!$A$5:$A$743,$A11,'Data - Season'!$C$5:$C$743,$C11,'Data - Season'!$B$5:$B$743,"Qualifier") | F11: =IFERROR($D11/$E11-1,"") | G11: =IF($D11<$E11,"YES — below LY","no") | H11: =SUMIFS('Data - Season'!$F$5:$F$743,'Data - Season'!$A$5:$A$743,$A11,'Data - Season'!$C$5:$C$743,$C11,'Data - Season'!$B$5:$B$743,"Qualifier") | I11: =IFERROR($H11/$D11,"") | J11: =IF($H11>=$D11,"cleared","missed") | K11: =IFERROR($H11/$E11-1,"") | L11: =IF($D11<=$E11,"at or below","above") | M11: =IF(AND($E11>0,ABS($D11/$E11-1)<=0.01),"within 1%","")
A12: Allison Scott | B12: Chris McCrohan | C12: DG Yuengling Inc | D12: 2762 | E12: =SUMIFS('Data - Season'!$E$5:$E$743,'Data - Season'!$A$5:$A$743,$A12,'Data - Season'!$C$5:$C$743,$C12,'Data - Season'!$B$5:$B$743,"Qualifier") | F12: =IFERROR($D12/$E12-1,"") | G12: =IF($D12<$E12,"YES — below LY","no") | H12: =SUMIFS('Data - Season'!$F$5:$F$743,'Data - Season'!$A$5:$A$743,$A12,'Data - Season'!$C$5:$C$743,$C12,'Data - Season'!$B$5:$B$743,"Qualifier") | I12: =IFERROR($H12/$D12,"") | J12: =IF($H12>=$D12,"cleared","missed") | K12: =IFERROR($H12/$E12-1,"") | L12: =IF($D12<=$E12,"at or below","above") | M12: =IF(AND($E12>0,ABS($D12/$E12-1)<=0.01),"within 1%","")
A13: Allison Scott | B13: Chris McCrohan | C13: Heineken USA | D13: 1846 | E13: =SUMIFS('Data - Season'!$E$5:$E$743,'Data - Season'!$A$5:$A$743,$A13,'Data - Season'!$C$5:$C$743,$C13,'Data - Season'!$B$5:$B$743,"Qualifier") | F13: =IFERROR($D13/$E13-1,"") | G13: =IF($D13<$E13,"YES — below LY","no") | H13: =SUMIFS('Data - Season'!$F$5:$F$743,'Data - Season'!$A$5:$A$743,$A13,'Data - Season'!$C$5:$C$743,$C13,'Data - Season'!$B$5:$B$743,"Qualifier") | I13: =IFERROR($H13/$D13,"") | J13: =IF($H13>=$D13,"cleared","missed") | K13: =IFERROR($H13/$E13-1,"") | L13: =IF($D13<=$E13,"at or below","above") | M13: =IF(AND($E13>0,ABS($D13/$E13-1)<=0.01),"within 1%","")
A14: Allison Scott | B14: Chris McCrohan | C14: Mark Anthony | D14: 940 | E14: =SUMIFS('Data - Season'!$E$5:$E$743,'Data - Season'!$A$5:$A$743,$A14,'Data - Season'!$C$5:$C$743,$C14,'Data - Season'!$B$5:$B$743,"Qualifier") | F14: =IFERROR($D14/$E14-1,"") | G14: =IF($D14<$E14,"YES — below LY","no") | H14: =SUMIFS('Data - Season'!$F$5:$F$743,'Data - Season'!$A$5:$A$743,$A14,'Data - Season'!$C$5:$C$743,$C14,'Data - Season'!$B$5:$B$743,"Qualifier") | I14: =IFERROR($H14/$D14,"") | J14: =IF($H14>=$D14,"cleared","missed") | K14: =IFERROR($H14/$E14-1,"") | L14: =IF($D14<=$E14,"at or below","above") | M14: =IF(AND($E14>0,ABS($D14/$E14-1)<=0.01),"within 1%","")
A15: Allison Scott | B15: Chris McCrohan | C15: MolsonCoors Beverage Company | D15: 12865 | E15: =SUMIFS('Data - Season'!$E$5:$E$743,'Data - Season'!$A$5:$A$743,$A15,'Data - Season'!$C$5:$C$743,$C15,'Data - Season'!$B$5:$B$743,"Qualifier") | F15: =IFERROR($D15/$E15-1,"") | G15: =IF($D15<$E15,"YES — below LY","no") | H15: =SUMIFS('Data - Season'!$F$5:$F$743,'Data - Season'!$A$5:$A$743,$A15,'Data - Season'!$C$5:$C$743,$C15,'Data - Season'!$B$5:$B$743,"Qualifier") | I15: =IFERROR($H15/$D15,"") | J15: =IF($H15>=$D15,"cleared","missed") | K15: =IFERROR($H15/$E15-1,"") | L15: =IF($D15<=$E15,"at or below","above") | M15: =IF(AND($E15>0,ABS($D15/$E15-1)<=0.01),"within 1%","")
A16: Anthony Palmisano | B16: Chris McCrohan | C16: Boston Beer Company | D16: 4450 | E16: =SUMIFS('Data - Season'!$E$5:$E$743,'Data - Season'!$A$5:$A$743,$A16,'Data - Season'!$C$5:$C$743,$C16,'Data - Season'!$B$5:$B$743,"Qualifier") | F16: =IFERROR($D16/$E16-1,"") | G16: =IF($D16<$E16,"YES — below LY","no") | H16: =SUMIFS('Data - Season'!$F$5:$F$743,'Data - Season'!$A$5:$A$743,$A16,'Data - Season'!$C$5:$C$743,$C16,'Data - Season'!$B$5:$B$743,"Qualifier") | I16: =IFERROR($H16/$D16,"") | J16: =IF($H16>=$D16,"cleared","missed") | K16: =IFERROR($H16/$E16-1,"") | L16: =IF($D16<=$E16,"at or below","above") | M16: =IF(AND($E16>0,ABS($D16/$E16-1)<=0.01),"within 1%","")
... A74: Jim Heaney | B74: Denise Montes | C74: MolsonCoors Beverage Company | D74: 21984 | E74: =SUMIFS('Data - Season'!$E$5:$E$743,'Data - Season'!$A$5:$A$743,$A74,'Data - Season'!$C$5:$C$743,$C74,'Data - Season'!$B$5:$B$743,"Qualifier") | F74: =IFERROR($D74/$E74-1,"") | G74: =IF($D74<$E74,"YES — below LY","no") | H74: =SUMIFS('Data - Season'!$F$5:$F$743,'Data - Season'!$A$5:$A$743,$A74,'Data - Season'!$C$5:$C$743,$C74,'Data - Season'!$B$5:$B$743,"Qualifier") | I74: =IFERROR($H74/$D74,"") | J74: =IF($H74>=$D74,"cleared","missed") | K74: =IFERROR($H74/$E74-1,"") | L74: =IF($D74<=$E74,"at or below","above") | M74: =IF(AND($E74>0,ABS($D74/$E74-1)<=0.01),"within 1%","")
A75: John Neukum | C75: Boston Beer Company | D75: 1220 | E75: =SUMIFS('Data - Season'!$E$5:$E$743,'Data - Season'!$A$5:$A$743,$A75,'Data - Season'!$C$5:$C$743,$C75,'Data - Season'!$B$5:$B$743,"Qualifier") | F75: =IFERROR($D75/$E75-1,"") | G75: =IF($D75<$E75,"YES — below LY","no") | H75: =SUMIFS('Data - Season'!$F$5:$F$743,'Data - Season'!$A$5:$A$743,$A75,'Data - Season'!$C$5:$C$743,$C75,'Data - Season'!$B$5:$B$743,"Qualifier") | I75: =IFERROR($H75/$D75,"") | J75: =IF($H75>=$D75,"cleared","missed") | K75: =IFERROR($H75/$E75-1,"") | L75: =IF($D75<=$E75,"at or below","above") | M75: =IF(AND($E75>0,ABS($D75/$E75-1)<=0.01),"within 1%","")
A76: John Neukum | C76: Constellation Brands | D76: 115716 | E76: =SUMIFS('Data - Season'!$E$5:$E$743,'Data - Season'!$A$5:$A$743,$A76,'Data - Season'!$C$5:$C$743,$C76,'Data - Season'!$B$5:$B$743,"Qualifier") | F76: =IFERROR($D76/$E76-1,"") | G76: =IF($D76<$E76,"YES — below LY","no") | H76: =SUMIFS('Data - Season'!$F$5:$F$743,'Data - Season'!$A$5:$A$743,$A76,'Data - Season'!$C$5:$C$743,$C76,'Data - Season'!$B$5:$B$743,"Qualifier") | I76: =IFERROR($H76/$D76,"") | J76: =IF($H76>=$D76,"cleared","missed") | K76: =IFERROR($H76/$E76-1,"") | L76: =IF($D76<=$E76,"at or below","above") | M76: =IF(AND($E76>0,ABS($D76/$E76-1)<=0.01),"within 1%","")
A77: John Neukum | C77: DG Yuengling Inc | D77: 3930 | E77: =SUMIFS('Data - Season'!$E$5:$E$743,'Data - Season'!$A$5:$A$743,$A77,'Data - Season'!$C$5:$C$743,$C77,'Data - Season'!$B$5:$B$743,"Qualifier") | F77: =IFERROR($D77/$E77-1,"") | G77: =IF($D77<$E77,"YES — below LY","no") | H77: =SUMIFS('Data - Season'!$F$5:$F$743,'Data - Season'!$A$5:$A$743,$A77,'Data - Season'!$C$5:$C$743,$C77,'Data - Season'!$B$5:$B$743,"Qualifier") | I77: =IFERROR($H77/$D77,"") | J77: =IF($H77>=$D77,"cleared","missed") | K77: =IFERROR($H77/$E77-1,"") | L77: =IF($D77<=$E77,"at or below","above") | M77: =IF(AND($E77>0,ABS($D77/$E77-1)<=0.01),"within 1%","")
A78: John Neukum | C78: Heineken USA | D78: 15101 | E78: =SUMIFS('Data - Season'!$E$5:$E$743,'Data - Season'!$A$5:$A$743,$A78,'Data - Season'!$C$5:$C$743,$C78,'Data - Season'!$B$5:$B$743,"Qualifier") | F78: =IFERROR($D78/$E78-1,"") | G78: =IF($D78<$E78,"YES — below LY","no") | H78: =SUMIFS('Data - Season'!$F$5:$F$743,'Data - Season'!$A$5:$A$743,$A78,'Data - Season'!$C$5:$C$743,$C78,'Data - Season'!$B$5:$B$743,"Qualifier") | I78: =IFERROR($H78/$D78,"") | J78: =IF($H78>=$D78,"cleared","missed") | K78: =IFERROR($H78/$E78-1,"") | L78: =IF($D78<=$E78,"at or below","above") | M78: =IF(AND($E78>0,ABS($D78/$E78-1)<=0.01),"within 1%","")
A79: John Neukum | C79: Mark Anthony | D79: 4633 | E79: =SUMIFS('Data - Season'!$E$5:$E$743,'Data - Season'!$A$5:$A$743,$A79,'Data - Season'!$C$5:$C$743,$C79,'Data - Season'!$B$5:$B$743,"Qualifier") | F79: =IFERROR($D79/$E79-1,"") | G79: =IF($D79<$E79,"YES — below LY","no") | H79: =SUMIFS('Data - Season'!$F$5:$F$743,'Data - Season'!$A$5:$A$743,$A79,'Data - Season'!$C$5:$C$743,$C79,'Data - Season'!$B$5:$B$743,"Qualifier") | I79: =IFERROR($H79/$D79,"") | J79: =IF($H79>=$D79,"cleared","missed") | K79: =IFERROR($H79/$E79-1,"") | L79: =IF($D79<=$E79,"at or below","above") | M79: =IF(AND($E79>0,ABS($D79/$E79-1)<=0.01),"within 1%","")
A80: John Neukum | C80: MolsonCoors Beverage Company | D80: 20735 | E80: =SUMIFS('Data - Season'!$E$5:$E$743,'Data - Season'!$A$5:$A$743,$A80,'Data - Season'!$C$5:$C$743,$C80,'Data - Season'!$B$5:$B$743,"Qualifier") | F80: =IFERROR($D80/$E80-1,"") | G80: =IF($D80<$E80,"YES — below LY","no") | H80: =SUMIFS('Data - Season'!$F$5:$F$743,'Data - Season'!$A$5:$A$743,$A80,'Data - Season'!$C$5:$C$743,$C80,'Data - Season'!$B$5:$B$743,"Qualifier") | I80: =IFERROR($H80/$D80,"") | J80: =IF($H80>=$D80,"cleared","missed") | K80: =IFERROR($H80/$E80-1,"") | L80: =IF($D80<=$E80,"at or below","above") | M80: =IF(AND($E80>0,ABS($D80/$E80-1)<=0.01),"within 1%","")
A81: John O'Donoghue | B81: Mike Kennedy | C81: Constellation Brands | D81: 233 | E81: =SUMIFS('Data - Season'!$E$5:$E$743,'Data - Season'!$A$5:$A$743,$A81,'Data - Season'!$C$5:$C$743,$C81,'Data - Season'!$B$5:$B$743,"Qualifier") | F81: =IFERROR($D81/$E81-1,"") | G81: =IF($D81<$E81,"YES — below LY","no") | H81: =SUMIFS('Data - Season'!$F$5:$F$743,'Data - Season'!$A$5:$A$743,$A81,'Data - Season'!$C$5:$C$743,$C81,'Data - Season'!$B$5:$B$743,"Qualifier") | I81: =IFERROR($H81/$D81,"") | J81: =IF($H81>=$D81,"cleared","missed") | K81: =IFERROR($H81/$E81-1,"") | L81: =IF($D81<=$E81,"at or below","above") | M81: =IF(AND($E81>0,ABS($D81/$E81-1)<=0.01),"within 1%","")
A82: John O'Donoghue | B82: Mike Kennedy | C82: Mark Anthony | D82: 14 | E82: =SUMIFS('Data - Season'!$E$5:$E$743,'Data - Season'!$A$5:$A$743,$A82,'Data - Season'!$C$5:$C$743,$C82,'Data - Season'!$B$5:$B$743,"Qualifier") | F82: =IFERROR($D82/$E82-1,"") | G82: =IF($D82<$E82,"YES — below LY","no") | H82: =SUMIFS('Data - Season'!$F$5:$F$743,'Data - Season'!$A$5:$A$743,$A82,'Data - Season'!$C$5:$C$743,$C82,'Data - Season'!$B$5:$B$743,"Qualifier") | I82: =IFERROR($H82/$D82,"") | J82: =IF($H82>=$D82,"cleared","missed") | K82: =IFERROR($H82/$E82-1,"") | L82: =IF($D82<=$E82,"at or below","above") | M82: =IF(AND($E82>0,ABS($D82/$E82-1)<=0.01),"within 1%","")
A83: Klejdi Lamo | B83: Paul Deady | C83: Boston Beer Company | D83: 4900 | E83: =SUMIFS('Data - Season'!$E$5:$E$743,'Data - Season'!$A$5:$A$743,$A83,'Data - Season'!$C$5:$C$743,$C83,'Data - Season'!$B$5:$B$743,"Qualifier") | F83: =IFERROR($D83/$E83-1,"") | G83: =IF($D83<$E83,"YES — below LY","no") | H83: =SUMIFS('Data - Season'!$F$5:$F$743,'Data - Season'!$A$5:$A$743,$A83,'Data - Season'!$C$5:$C$743,$C83,'Data - Season'!$B$5:$B$743,"Qualifier") | I83: =IFERROR($H83/$D83,"") | J83: =IF($H83>=$D83,"cleared","missed") | K83: =IFERROR($H83/$E83-1,"") | L83: =IF($D83<=$E83,"at or below","above") | M83: =IF(AND($E83>0,ABS($D83/$E83-1)<=0.01),"within 1%","")
A84: Klejdi Lamo | B84: Paul Deady | C84: Constellation Brands | D84: 25364 | E84: =SUMIFS('Data - Season'!$E$5:$E$743,'Data - Season'!$A$5:$A$743,$A84,'Data - Season'!$C$5:$C$743,$C84,'Data - Season'!$B$5:$B$743,"Qualifier") | F84: =IFERROR($D84/$E84-1,"") | G84: =IF($D84<$E84,"YES — below LY","no") | H84: =SUMIFS('Data - Season'!$F$5:$F$743,'Data - Season'!$A$5:$A$743,$A84,'Data - Season'!$C$5:$C$743,$C84,'Data - Season'!$B$5:$B$743,"Qualifier") | I84: =IFERROR($H84/$D84,"") | J84: =IF($H84>=$D84,"cleared","missed") | K84: =IFERROR($H84/$E84-1,"") | L84: =IF($D84<=$E84,"at or below","above") | M84: =IF(AND($E84>0,ABS($D84/$E84-1)<=0.01),"within 1%","")
A85: Klejdi Lamo | B85: Paul Deady | C85: DG Yuengling Inc | D85: 4063 | E85: =SUMIFS('Data - Season'!$E$5:$E$743,'Data - Season'!$A$5:$A$743,$A85,'Data - Season'!$C$5:$C$743,$C85,'Data - Season'!$B$5:$B$743,"Qualifier") | F85: =IFERROR($D85/$E85-1,"") | G85: =IF($D85<$E85,"YES — below LY","no") | H85: =SUMIFS('Data - Season'!$F$5:$F$743,'Data - Season'!$A$5:$A$743,$A85,'Data - Season'!$C$5:$C$743,$C85,'Data - Season'!$B$5:$B$743,"Qualifier") | I85: =IFERROR($H85/$D85,"") | J85: =IF($H85>=$D85,"cleared","missed") | K85: =IFERROR($H85/$E85-1,"") | L85: =IF($D85<=$E85,"at or below","above") | M85: =IF(AND($E85>0,ABS($D85/$E85-1)<=0.01),"within 1%","")
A86: Klejdi Lamo | B86: Paul Deady | C86: Heineken USA | D86: 190 | E86: =SUMIFS('Data - Season'!$E$5:$E$743,'Data - Season'!$A$5:$A$743,$A86,'Data - Season'!$C$5:$C$743,$C86,'Data - Season'!$B$5:$B$743,"Qualifier") | F86: =IFERROR($D86/$E86-1,"") | G86: =IF($D86<$E86,"YES — below LY","no") | H86: =SUMIFS('Data - Season'!$F$5:$F$743,'Data - Season'!$A$5:$A$743,$A86,'Data - Season'!$C$5:$C$743,$C86,'Data - Season'!$B$5:$B$743,"Qualifier") | I86: =IFERROR($H86/$D86,"") | J86: =IF($H86>=$D86,"cleared","missed") | K86: =IFERROR($H86/$E86-1,"") | L86: =IF($D86<=$E86,"at or below","above") | M86: =IF(AND($E86>0,ABS($D86/$E86-1)<=0.01),"within 1%","")
A87: Klejdi Lamo | B87: Paul Deady | C87: Mark Anthony | D87: 8451 | E87: =SUMIFS('Data - Season'!$E$5:$E$743,'Data - Season'!$A$5:$A$743,$A87,'Data - Season'!$C$5:$C$743,$C87,'Data - Season'!$B$5:$B$743,"Qualifier") | F87: =IFERROR($D87/$E87-1,"") | G87: =IF($D87<$E87,"YES — below LY","no") | H87: =SUMIFS('Data - Season'!$F$5:$F$743,'Data - Season'!$A$5:$A$743,$A87,'Data - Season'!$C$5:$C$743,$C87,'Data - Season'!$B$5:$B$743,"Qualifier") | I87: =IFERROR($H87/$D87,"") | J87: =IF($H87>=$D87,"cleared","missed") | K87: =IFERROR($H87/$E87-1,"") | L87: =IF($D87<=$E87,"at or below","above") | M87: =IF(AND($E87>0,ABS($D87/$E87-1)<=0.01),"within 1%","")
A88: Klejdi Lamo | B88: Paul Deady | C88: MolsonCoors Beverage Company | D88: 27752 | E88: =SUMIFS('Data - Season'!$E$5:$E$743,'Data - Season'!$A$5:$A$743,$A88,'Data - Season'!$C$5:$C$743,$C88,'Data - Season'!$B$5:$B$743,"Qualifier") | F88: =IFERROR($D88/$E88-1,"") | G88: =IF($D88<$E88,"YES — below LY","no") | H88: =SUMIFS('Data - Season'!$F$5:$F$743,'Data - Season'!$A$5:$A$743,$A88,'Data - Season'!$C$5:$C$743,$C88,'Data - Season'!$B$5:$B$743,"Qualifier") | I88: =IFERROR($H88/$D88,"") | J88: =IF($H88>=$D88,"cleared","missed") | K88: =IFERROR($H88/$E88-1,"") | L88: =IF($D88<=$E88,"at or below","above") | M88: =IF(AND($E88>0,ABS($D88/$E88-1)<=0.01),"within 1%","")
A89: Matt Powierski | B89: Denise Montes | C89: Boston Beer Company | D89: 2250 | E89: =SUMIFS('Data - Season'!$E$5:$E$743,'Data - Season'!$A$5:$A$743,$A89,'Data - Season'!$C$5:$C$743,$C89,'Data - Season'!$B$5:$B$743,"Qualifier") | F89: =IFERROR($D89/$E89-1,"") | G89: =IF($D89<$E89,"YES — below LY","no") | H89: =SUMIFS('Data - Season'!$F$5:$F$743,'Data - Season'!$A$5:$A$743,$A89,'Data - Season'!$C$5:$C$743,$C89,'Data - Season'!$B$5:$B$743,"Qualifier") | I89: =IFERROR($H89/$D89,"") | J89: =IF($H89>=$D89,"cleared","missed") | K89: =IFERROR($H89/$E89-1,"") | L89: =IF($D89<=$E89,"at or below","above") | M89: =IF(AND($E89>0,ABS($D89/$E89-1)<=0.01),"within 1%","")
A90: Matt Powierski | B90: Denise Montes | C90: Constellation Brands | D90: 32540 | E90: =SUMIFS('Data - Season'!$E$5:$E$743,'Data - Season'!$A$5:$A$743,$A90,'Data - Season'!$C$5:$C$743,$C90,'Data - Season'!$B$5:$B$743,"Qualifier") | F90: =IFERROR($D90/$E90-1,"") | G90: =IF($D90<$E90,"YES — below LY","no") | H90: =SUMIFS('Data - Season'!$F$5:$F$743,'Data - Season'!$A$5:$A$743,$A90,'Data - Season'!$C$5:$C$743,$C90,'Data - Season'!$B$5:$B$743,"Qualifier") | I90: =IFERROR($H90/$D90,"") | J90: =IF($H90>=$D90,"cleared","missed") | K90: =IFERROR($H90/$E90-1,"") | L90: =IF($D90<=$E90,"at or below","above") | M90: =IF(AND($E90>0,ABS($D90/$E90-1)<=0.01),"within 1%","")
A91: Matt Powierski | B91: Denise Montes | C91: DG Yuengling Inc | D91: 1270 | E91: =SUMIFS('Data - Season'!$E$5:$E$743,'Data - Season'!$A$5:$A$743,$A91,'Data - Season'!$C$5:$C$743,$C91,'Data - Season'!$B$5:$B$743,"Qualifier") | F91: =IFERROR($D91/$E91-1,"") | G91: =IF($D91<$E91,"YES — below LY","no") | H91: =SUMIFS('Data - Season'!$F$5:$F$743,'Data - Season'!$A$5:$A$743,$A91,'Data - Season'!$C$5:$C$743,$C91,'Data - Season'!$B$5:$B$743,"Qualifier") | I91: =IFERROR($H91/$D91,"") | J91: =IF($H91>=$D91,"cleared","missed") | K91: =IFERROR($H91/$E91-1,"") | L91: =IF($D91<=$E91,"at or below","above") | M91: =IF(AND($E91>0,ABS($D91/$E91-1)<=0.01),"within 1%","")
A92: Matt Powierski | B92: Denise Montes | C92: Heineken USA | D92: 6888 | E92: =SUMIFS('Data - Season'!$E$5:$E$743,'Data - Season'!$A$5:$A$743,$A92,'Data - Season'!$C$5:$C$743,$C92,'Data - Season'!$B$5:$B$743,"Qualifier") | F92: =IFERROR($D92/$E92-1,"") | G92: =IF($D92<$E92,"YES — below LY","no") | H92: =SUMIFS('Data - Season'!$F$5:$F$743,'Data - Season'!$A$5:$A$743,$A92,'Data - Season'!$C$5:$C$743,$C92,'Data - Season'!$B$5:$B$743,"Qualifier") | I92: =IFERROR($H92/$D92,"") | J92: =IF($H92>=$D92,"cleared","missed") | K92: =IFERROR($H92/$E92-1,"") | L92: =IF($D92<=$E92,"at or below","above") | M92: =IF(AND($E92>0,ABS($D92/$E92-1)<=0.01),"within 1%","")
... A141: Shane Barreca | B141: Paul Deady | C141: MolsonCoors Beverage Company | D141: 33742 | E141: =SUMIFS('Data - Season'!$E$5:$E$743,'Data - Season'!$A$5:$A$743,$A141,'Data - Season'!$C$5:$C$743,$C141,'Data - Season'!$B$5:$B$743,"Qualifier") | F141: =IFERROR($D141/$E141-1,"") | G141: =IF($D141<$E141,"YES — below LY","no") | H141: =SUMIFS('Data - Season'!$F$5:$F$743,'Data - Season'!$A$5:$A$743,$A141,'Data - Season'!$C$5:$C$743,$C141,'Data - Season'!$B$5:$B$743,"Qualifier") | I141: =IFERROR($H141/$D141,"") | J141: =IF($H141>=$D141,"cleared","missed") | K141: =IFERROR($H141/$E141-1,"") | L141: =IF($D141<=$E141,"at or below","above") | M141: =IF(AND($E141>0,ABS($D141/$E141-1)<=0.01),"within 1%","")
A142: TOTAL | D142: =SUM(D5:D141) | E142: =SUM(E5:E141) | F142: =IFERROR(D142/E142-1,"") | H142: =SUM(H5:H141) | K142: =IFERROR(H142/E142-1,"")
A144: HOW THE GOALS WERE SET
A145: Qualifier goals with a prior-year comparison | B145: =COUNT($D$5:$D$141)
A146: set BELOW the rep's own 2025 volume | B146: =COUNTIF($G$5:$G$141,"YES*")
A147: set AT or below it | B147: =COUNTIF($L$5:$L$141,"at or below")
A148: set within 1% of it — effectively last year's number | B148: =COUNTIF($M$5:$M$141,"within 1%")
A149: share of all qualifier goals | B149: =IFERROR(COUNTIF($G$5:$G$141,"YES*")/COUNT($D$5:$D$141),"")
A150: Aggregate goal vs the same reps' 2025 volume | B150: =F142
A151: Sub-2025 goals that were CLEARED and paid | B151: =COUNTIFS($G$5:$G$141,"YES*",$J$5:$J$141,"cleared")
A152: their 2026 volume vs their own 2025 | B152: =IFERROR(SUMIFS($H$5:$H$141,$G$5:$G$141,"YES*",$J$5:$J$141,"cleared")/SUMIFS($E$5:$E$141,$G$5:$G$141,"YES*",$J$5:$J$141,"cleared")-1,"")
A154: The qualifier half of this program was designed to pay for decline: in aggregate the goals asked for less volume than the same reps delivered in 2025, and nine in ten individual goals sat below that rep's own prior-year number.
A155: A sizeable block was not merely below last year but AT it — set within 1% of the rep's own 2025 figure, and in fifteen cases within two cases of it. Those goals were prior-year volume restated as a target.
A156: The sub-2025 goals that cleared delivered volume flat to last year — and earned tier payouts for it. That is a goal-setting outcome, not a rep-performance one.
A157: This is the cheapest thing to fix for 2027, and it is independent of brand selection: a goal below last year cannot produce incremental volume no matter which brand carries it.

Sheet Payout vs Performance
A1: Did the reps who earned the most actually deliver the most?
A2: Payout columns are the vF recap. Volume and POD columns are live off Data - Accounts and Data - Season. "Their own control" is that rep's non-incented volume.
A4: Rep | B4: Manager | C4: Tier payout | D4: Amplify payout | E4: Total payout | F4: Program CE 2025 | G4: Program CE 2026 | H4: Program % | I4: Their own control % | J4: Gap vs own control | K4: PODs 2025 | L4: PODs 2026 | M4: POD %
A5: Dave Ehlers | B5: Mike Engel | C5: 4250 | D5: 3461 | E5: =C5+D5 | F5: =SUMIFS('Data - Accounts'!$E$5:$E$2358,'Data - Accounts'!$C$5:$C$2358,$A5) | G5: =SUMIFS('Data - Accounts'!$F$5:$F$2358,'Data - Accounts'!$C$5:$C$2358,$A5) | H5: =IFERROR(G5/F5-1,"") | I5: =IFERROR(SUMIFS('Data - Accounts'!$J$5:$J$2358,'Data - Accounts'!$C$5:$C$2358,$A5)/SUMIFS('Data - Accounts'!$I$5:$I$2358,'Data - Accounts'!$C$5:$C$2358,$A5)-1,"") | J5: =IFERROR(H5-I5,"") | K5: 35 | L5: 36 | M5: =IFERROR(L5/K5-1,"")
A6: Shane Barreca | B6: Paul Deady | C6: 3000 | D6: 2869 | E6: =C6+D6 | F6: =SUMIFS('Data - Accounts'!$E$5:$E$2358,'Data - Accounts'!$C$5:$C$2358,$A6) | G6: =SUMIFS('Data - Accounts'!$F$5:$F$2358,'Data - Accounts'!$C$5:$C$2358,$A6) | H6: =IFERROR(G6/F6-1,"") | I6: =IFERROR(SUMIFS('Data - Accounts'!$J$5:$J$2358,'Data - Accounts'!$C$5:$C$2358,$A6)/SUMIFS('Data - Accounts'!$I$5:$I$2358,'Data - Accounts'!$C$5:$C$2358,$A6)-1,"") | J6: =IFERROR(H6-I6,"") | K6: 29 | L6: 29 | M6: =IFERROR(L6/K6-1,"")
A7: Javier Melo | B7: Denise Montes | C7: 2500 | D7: 1615.5 | E7: =C7+D7 | F7: =SUMIFS('Data - Accounts'!$E$5:$E$2358,'Data - Accounts'!$C$5:$C$2358,$A7) | G7: =SUMIFS('Data - Accounts'!$F$5:$F$2358,'Data - Accounts'!$C$5:$C$2358,$A7) | H7: =IFERROR(G7/F7-1,"") | I7: =IFERROR(SUMIFS('Data - Accounts'!$J$5:$J$2358,'Data - Accounts'!$C$5:$C$2358,$A7)/SUMIFS('Data - Accounts'!$I$5:$I$2358,'Data - Accounts'!$C$5:$C$2358,$A7)-1,"") | J7: =IFERROR(H7-I7,"") | K7: 64 | L7: 66 | M7: =IFERROR(L7/K7-1,"")
A8: Matt Powierski | B8: Denise Montes | C8: 2000 | D8: 1736 | E8: =C8+D8 | F8: =SUMIFS('Data - Accounts'!$E$5:$E$2358,'Data - Accounts'!$C$5:$C$2358,$A8) | G8: =SUMIFS('Data - Accounts'!$F$5:$F$2358,'Data - Accounts'!$C$5:$C$2358,$A8) | H8: =IFERROR(G8/F8-1,"") | I8: =IFERROR(SUMIFS('Data - Accounts'!$J$5:$J$2358,'Data - Accounts'!$C$5:$C$2358,$A8)/SUMIFS('Data - Accounts'!$I$5:$I$2358,'Data - Accounts'!$C$5:$C$2358,$A8)-1,"") | J8: =IFERROR(H8-I8,"") | K8: 56 | L8: 59 | M8: =IFERROR(L8/K8-1,"")
A9: Mike Ast | B9: Paul Deady | C9: 2500 | D9: 928.5 | E9: =C9+D9 | F9: =SUMIFS('Data - Accounts'!$E$5:$E$2358,'Data - Accounts'!$C$5:$C$2358,$A9) | G9: =SUMIFS('Data - Accounts'!$F$5:$F$2358,'Data - Accounts'!$C$5:$C$2358,$A9) | H9: =IFERROR(G9/F9-1,"") | I9: =IFERROR(SUMIFS('Data - Accounts'!$J$5:$J$2358,'Data - Accounts'!$C$5:$C$2358,$A9)/SUMIFS('Data - Accounts'!$I$5:$I$2358,'Data - Accounts'!$C$5:$C$2358,$A9)-1,"") | J9: =IFERROR(H9-I9,"") | K9: 43 | L9: 44 | M9: =IFERROR(L9/K9-1,"")
A10: Dan Lagala | B10: Mike Engel | C10: 1250 | D10: 1823 | E10: =C10+D10 | F10: =SUMIFS('Data - Accounts'!$E$5:$E$2358,'Data - Accounts'!$C$5:$C$2358,$A10) | G10: =SUMIFS('Data - Accounts'!$F$5:$F$2358,'Data - Accounts'!$C$5:$C$2358,$A10) | H10: =IFERROR(G10/F10-1,"") | I10: =IFERROR(SUMIFS('Data - Accounts'!$J$5:$J$2358,'Data - Accounts'!$C$5:$C$2358,$A10)/SUMIFS('Data - Accounts'!$I$5:$I$2358,'Data - Accounts'!$C$5:$C$2358,$A10)-1,"") | J10: =IFERROR(H10-I10,"") | K10: 104 | L10: 95 | M10: =IFERROR(L10/K10-1,"")
A11: Phil Ernst | B11: Mike Engel | C11: 1500 | D11: 1443 | E11: =C11+D11 | F11: =SUMIFS('Data - Accounts'!$E$5:$E$2358,'Data - Accounts'!$C$5:$C$2358,$A11) | G11: =SUMIFS('Data - Accounts'!$F$5:$F$2358,'Data - Accounts'!$C$5:$C$2358,$A11) | H11: =IFERROR(G11/F11-1,"") | I11: =IFERROR(SUMIFS('Data - Accounts'!$J$5:$J$2358,'Data - Accounts'!$C$5:$C$2358,$A11)/SUMIFS('Data - Accounts'!$I$5:$I$2358,'Data - Accounts'!$C$5:$C$2358,$A11)-1,"") | J11: =IFERROR(H11-I11,"") | K11: 27 | L11: 26 | M11: =IFERROR(L11/K11-1,"")
A12: Nick Melissari | B12: Chris McCrohan | C12: 1750 | D12: 1129 | E12: =C12+D12 | F12: =SUMIFS('Data - Accounts'!$E$5:$E$2358,'Data - Accounts'!$C$5:$C$2358,$A12) | G12: =SUMIFS('Data - Accounts'!$F$5:$F$2358,'Data - Accounts'!$C$5:$C$2358,$A12) | H12: =IFERROR(G12/F12-1,"") | I12: =IFERROR(SUMIFS('Data - Accounts'!$J$5:$J$2358,'Data - Accounts'!$C$5:$C$2358,$A12)/SUMIFS('Data - Accounts'!$I$5:$I$2358,'Data - Accounts'!$C$5:$C$2358,$A12)-1,"") | J12: =IFERROR(H12-I12,"") | K12: 170 | L12: 173 | M12: =IFERROR(L12/K12-1,"")
A13: Allison Scott | B13: Chris McCrohan | C13: 1750 | D13: 816 | E13: =C13+D13 | F13: =SUMIFS('Data - Accounts'!$E$5:$E$2358,'Data - Accounts'!$C$5:$C$2358,$A13) | G13: =SUMIFS('Data - Accounts'!$F$5:$F$2358,'Data - Accounts'!$C$5:$C$2358,$A13) | H13: =IFERROR(G13/F13-1,"") | I13: =IFERROR(SUMIFS('Data - Accounts'!$J$5:$J$2358,'Data - Accounts'!$C$5:$C$2358,$A13)/SUMIFS('Data - Accounts'!$I$5:$I$2358,'Data - Accounts'!$C$5:$C$2358,$A13)-1,"") | J13: =IFERROR(H13-I13,"") | K13: 117 | L13: 117 | M13: =IFERROR(L13/K13-1,"")
A14: Klejdi Lamo | B14: Paul Deady | C14: 1500 | D14: 909.5 | E14: =C14+D14 | F14: =SUMIFS('Data - Accounts'!$E$5:$E$2358,'Data - Accounts'!$C$5:$C$2358,$A14) | G14: =SUMIFS('Data - Accounts'!$F$5:$F$2358,'Data - Accounts'!$C$5:$C$2358,$A14) | H14: =IFERROR(G14/F14-1,"") | I14: =IFERROR(SUMIFS('Data - Accounts'!$J$5:$J$2358,'Data - Accounts'!$C$5:$C$2358,$A14)/SUMIFS('Data - Accounts'!$I$5:$I$2358,'Data - Accounts'!$C$5:$C$2358,$A14)-1,"") | J14: =IFERROR(H14-I14,"") | K14: 28 | L14: 28 | M14: =IFERROR(L14/K14-1,"")
A15: John Neukum | C15: 0 | D15: 2373.5 | E15: =C15+D15 | F15: =SUMIFS('Data - Accounts'!$E$5:$E$2358,'Data - Accounts'!$C$5:$C$2358,$A15) | G15: =SUMIFS('Data - Accounts'!$F$5:$F$2358,'Data - Accounts'!$C$5:$C$2358,$A15) | H15: =IFERROR(G15/F15-1,"") | I15: =IFERROR(SUMIFS('Data - Accounts'!$J$5:$J$2358,'Data - Accounts'!$C$5:$C$2358,$A15)/SUMIFS('Data - Accounts'!$I$5:$I$2358,'Data - Accounts'!$C$5:$C$2358,$A15)-1,"") | J15: =IFERROR(H15-I15,"") | K15: 4 | L15: 5 | M15: =IFERROR(L15/K15-1,"")
A16: Anthony Palmisano | B16: Chris McCrohan | C16: 1250 | D16: 941 | E16: =C16+D16 | F16: =SUMIFS('Data - Accounts'!$E$5:$E$2358,'Data - Accounts'!$C$5:$C$2358,$A16) | G16: =SUMIFS('Data - Accounts'!$F$5:$F$2358,'Data - Accounts'!$C$5:$C$2358,$A16) | H16: =IFERROR(G16/F16-1,"") | I16: =IFERROR(SUMIFS('Data - Accounts'!$J$5:$J$2358,'Data - Accounts'!$C$5:$C$2358,$A16)/SUMIFS('Data - Accounts'!$I$5:$I$2358,'Data - Accounts'!$C$5:$C$2358,$A16)-1,"") | J16: =IFERROR(H16-I16,"") | K16: 71 | L16: 77 | M16: =IFERROR(L16/K16-1,"")
A17: Chris Payton | B17: Mike Engel | C17: 1250 | D17: 910.5 | E17: =C17+D17 | F17: =SUMIFS('Data - Accounts'!$E$5:$E$2358,'Data - Accounts'!$C$5:$C$2358,$A17) | G17: =SUMIFS('Data - Accounts'!$F$5:$F$2358,'Data - Accounts'!$C$5:$C$2358,$A17) | H17: =IFERROR(G17/F17-1,"") | I17: =IFERROR(SUMIFS('Data - Accounts'!$J$5:$J$2358,'Data - Accounts'!$C$5:$C$2358,$A17)/SUMIFS('Data - Accounts'!$I$5:$I$2358,'Data - Accounts'!$C$5:$C$2358,$A17)-1,"") | J17: =IFERROR(H17-I17,"") | K17: 59 | L17: 60 | M17: =IFERROR(L17/K17-1,"")
A18: Derrick Laws | B18: Denise Montes | C18: 500 | D18: 844.5 | E18: =C18+D18 | F18: =SUMIFS('Data - Accounts'!$E$5:$E$2358,'Data - Accounts'!$C$5:$C$2358,$A18) | G18: =SUMIFS('Data - Accounts'!$F$5:$F$2358,'Data - Accounts'!$C$5:$C$2358,$A18) | H18: =IFERROR(G18/F18-1,"") | I18: =IFERROR(SUMIFS('Data - Accounts'!$J$5:$J$2358,'Data - Accounts'!$C$5:$C$2358,$A18)/SUMIFS('Data - Accounts'!$I$5:$I$2358,'Data - Accounts'!$C$5:$C$2358,$A18)-1,"") | J18: =IFERROR(H18-I18,"") | K18: 42 | L18: 44 | M18: =IFERROR(L18/K18-1,"")
A19: Jayson Romine | B19: Paul Deady | C19: 500 | D19: 767 | E19: =C19+D19 | F19: =SUMIFS('Data - Accounts'!$E$5:$E$2358,'Data - Accounts'!$C$5:$C$2358,$A19) | G19: =SUMIFS('Data - Accounts'!$F$5:$F$2358,'Data - Accounts'!$C$5:$C$2358,$A19) | H19: =IFERROR(G19/F19-1,"") | I19: =IFERROR(SUMIFS('Data - Accounts'!$J$5:$J$2358,'Data - Accounts'!$C$5:$C$2358,$A19)/SUMIFS('Data - Accounts'!$I$5:$I$2358,'Data - Accounts'!$C$5:$C$2358,$A19)-1,"") | J19: =IFERROR(H19-I19,"") | K19: 33 | L19: 35 | M19: =IFERROR(L19/K19-1,"")
A20: Pablo Lopez | B20: Denise Montes | C20: 500 | D20: 756.5 | E20: =C20+D20 | F20: =SUMIFS('Data - Accounts'!$E$5:$E$2358,'Data - Accounts'!$C$5:$C$2358,$A20) | G20: =SUMIFS('Data - Accounts'!$F$5:$F$2358,'Data - Accounts'!$C$5:$C$2358,$A20) | H20: =IFERROR(G20/F20-1,"") | I20: =IFERROR(SUMIFS('Data - Accounts'!$J$5:$J$2358,'Data - Accounts'!$C$5:$C$2358,$A20)/SUMIFS('Data - Accounts'!$I$5:$I$2358,'Data - Accounts'!$C$5:$C$2358,$A20)-1,"") | J20: =IFERROR(H20-I20,"") | K20: 77 | L20: 78 | M20: =IFERROR(L20/K20-1,"")
A21: Robin Feldman | B21: Chris McCrohan | C21: 500 | D21: 374.5 | E21: =C21+D21 | F21: =SUMIFS('Data - Accounts'!$E$5:$E$2358,'Data - Accounts'!$C$5:$C$2358,$A21) | G21: =SUMIFS('Data - Accounts'!$F$5:$F$2358,'Data - Accounts'!$C$5:$C$2358,$A21) | H21: =IFERROR(G21/F21-1,"") | I21: =IFERROR(SUMIFS('Data - Accounts'!$J$5:$J$2358,'Data - Accounts'!$C$5:$C$2358,$A21)/SUMIFS('Data - Accounts'!$I$5:$I$2358,'Data - Accounts'!$C$5:$C$2358,$A21)-1,"") | J21: =IFERROR(H21-I21,"") | K21: 191 | L21: 191 | M21: =IFERROR(L21/K21-1,"")
A22: Jim Heaney | B22: Denise Montes | C22: 0 | D22: 810.5 | E22: =C22+D22 | F22: =SUMIFS('Data - Accounts'!$E$5:$E$2358,'Data - Accounts'!$C$5:$C$2358,$A22) | G22: =SUMIFS('Data - Accounts'!$F$5:$F$2358,'Data - Accounts'!$C$5:$C$2358,$A22) | H22: =IFERROR(G22/F22-1,"") | I22: =IFERROR(SUMIFS('Data - Accounts'!$J$5:$J$2358,'Data - Accounts'!$C$5:$C$2358,$A22)/SUMIFS('Data - Accounts'!$I$5:$I$2358,'Data - Accounts'!$C$5:$C$2358,$A22)-1,"") | J22: =IFERROR(H22-I22,"") | K22: 44 | L22: 42 | M22: =IFERROR(L22/K22-1,"")
A23: Paul Mclaughlin | B23: Chris McCrohan | C23: 500 | D23: 267.5 | E23: =C23+D23 | F23: =SUMIFS('Data - Accounts'!$E$5:$E$2358,'Data - Accounts'!$C$5:$C$2358,$A23) | G23: =SUMIFS('Data - Accounts'!$F$5:$F$2358,'Data - Accounts'!$C$5:$C$2358,$A23) | H23: =IFERROR(G23/F23-1,"") | I23: =IFERROR(SUMIFS('Data - Accounts'!$J$5:$J$2358,'Data - Accounts'!$C$5:$C$2358,$A23)/SUMIFS('Data - Accounts'!$I$5:$I$2358,'Data - Accounts'!$C$5:$C$2358,$A23)-1,"") | J23: =IFERROR(H23-I23,"") | K23: 122 | L23: 123 | M23: =IFERROR(L23/K23-1,"")
A24: Dylan Rubino | B24: Mike Kennedy | C24: 0 | D24: 698 | E24: =C24+D24 | F24: =SUMIFS('Data - Accounts'!$E$5:$E$2358,'Data - Accounts'!$C$5:$C$2358,$A24) | G24: =SUMIFS('Data - Accounts'!$F$5:$F$2358,'Data - Accounts'!$C$5:$C$2358,$A24) | H24: =IFERROR(G24/F24-1,"") | I24: =IFERROR(SUMIFS('Data - Accounts'!$J$5:$J$2358,'Data - Accounts'!$C$5:$C$2358,$A24)/SUMIFS('Data - Accounts'!$I$5:$I$2358,'Data - Accounts'!$C$5:$C$2358,$A24)-1,"") | J24: =IFERROR(H24-I24,"") | K24: 119 | L24: 126 | M24: =IFERROR(L24/K24-1,"")
A25: Michael Harboy | B25: Mike Kennedy | C25: 0 | D25: 372.5 | E25: =C25+D25 | F25: =SUMIFS('Data - Accounts'!$E$5:$E$2358,'Data - Accounts'!$C$5:$C$2358,$A25) | G25: =SUMIFS('Data - Accounts'!$F$5:$F$2358,'Data - Accounts'!$C$5:$C$2358,$A25) | H25: =IFERROR(G25/F25-1,"") | I25: =IFERROR(SUMIFS('Data - Accounts'!$J$5:$J$2358,'Data - Accounts'!$C$5:$C$2358,$A25)/SUMIFS('Data - Accounts'!$I$5:$I$2358,'Data - Accounts'!$C$5:$C$2358,$A25)-1,"") | J25: =IFERROR(H25-I25,"") | K25: 25 | L25: 32 | M25: =IFERROR(L25/K25-1,"")
A26: Alex Rodriguez | B26: Mike Kennedy | C26: 0 | D26: 297 | E26: =C26+D26 | F26: =SUMIFS('Data - Accounts'!$E$5:$E$2358,'Data - Accounts'!$C$5:$C$2358,$A26) | G26: =SUMIFS('Data - Accounts'!$F$5:$F$2358,'Data - Accounts'!$C$5:$C$2358,$A26) | H26: =IFERROR(G26/F26-1,"") | I26: =IFERROR(SUMIFS('Data - Accounts'!$J$5:$J$2358,'Data - Accounts'!$C$5:$C$2358,$A26)/SUMIFS('Data - Accounts'!$I$5:$I$2358,'Data - Accounts'!$C$5:$C$2358,$A26)-1,"") | J26: =IFERROR(H26-I26,"") | K26: 31 | L26: 38 | M26: =IFERROR(L26/K26-1,"")
A27: Brian Sengebush | B27: Chris McCrohan | C27: 0 | D27: 252 | E27: =C27+D27 | F27: =SUMIFS('Data - Accounts'!$E$5:$E$2358,'Data - Accounts'!$C$5:$C$2358,$A27) | G27: =SUMIFS('Data - Accounts'!$F$5:$F$2358,'Data - Accounts'!$C$5:$C$2358,$A27) | H27: =IFERROR(G27/F27-1,"") | I27: =IFERROR(SUMIFS('Data - Accounts'!$J$5:$J$2358,'Data - Accounts'!$C$5:$C$2358,$A27)/SUMIFS('Data - Accounts'!$I$5:$I$2358,'Data - Accounts'!$C$5:$C$2358,$A27)-1,"") | J27: =IFERROR(H27-I27,"") | K27: 123 | L27: 117 | M27: =IFERROR(L27/K27-1,"")
... A32: Hakan Sadik | B32: Mike Kennedy | C32: 0 | D32: 0 | E32: =C32+D32 | F32: =SUMIFS('Data - Accounts'!$E$5:$E$2358,'Data - Accounts'!$C$5:$C$2358,$A32) | G32: =SUMIFS('Data - Accounts'!$F$5:$F$2358,'Data - Accounts'!$C$5:$C$2358,$A32) | H32: =IFERROR(G32/F32-1,"") | I32: =IFERROR(SUMIFS('Data - Accounts'!$J$5:$J$2358,'Data - Accounts'!$C$5:$C$2358,$A32)/SUMIFS('Data - Accounts'!$I$5:$I$2358,'Data - Accounts'!$C$5:$C$2358,$A32)-1,"") | J32: =IFERROR(H32-I32,"") | K32: 46 | L32: 42 | M32: =IFERROR(L32/K32-1,"")
A33: TOTAL | C33: =SUM(C5:C32) | D33: =SUM(D5:D32) | E33: =SUM(E5:E32) | F33: =SUM(F5:F32) | G33: =SUM(G5:G32) | H33: =IFERROR(G33/F33-1,"") | K33: =SUM(K5:K32) | L33: =SUM(L5:L32)
A35: DOES PAYOUT TRACK PERFORMANCE?
A36: Correlation: payout earned vs program volume growth | B36: =IFERROR(CORREL($E$5:$E$32,$H$5:$H$32),"")
A37: Correlation: payout earned vs gap over that rep's own control | B37: =IFERROR(CORREL($E$5:$E$32,$J$5:$J$32),"")
A39: Both correlations sit at roughly zero. The reps who earned the most were not the reps who grew the most, and were not the reps who beat their own non-incented book.
A40: That is what you would expect when payout is driven by how each rep's goal was set rather than by what they delivered — see the Goal Design tab.
A41: It is not a criticism of the sales team. It says the program did not reward the behaviour it was meant to reward.

Sheet Program Brands
A1: Program brands — both periods, brand level
A2: SUMIFS off Data - Season and Data - Pre. Feeds the Acceleration Test, Counterfactual, Distribution and GP Bridge tabs.
D4: JUN–AUG (program period) | J4: JAN–MAY (pre-program) | N4: PER-CASE ECONOMICS, JUN–AUG | R4: GP BRIDGE INPUTS | T4: ACCELERATION
A5: Segment | B5: Supplier | C5: Brand Family | D5: CE 2025 | E5: CE 2026 | F5: Rev 2025 | G5: Rev 2026 | H5: GP 2025 | I5: GP 2026 | J5: CE 2025 | K5: CE 2026 | L5: GP 2025 | M5: GP 2026 | N5: GP/CE 2025 | O5: GP/CE 2026 | P5: Rev/CE 2025 | Q5: Rev/CE 2026 | R5: GP26 at LY rate | S5: Rate effect | T5: Cases % Jun–Aug | U5: Cases % Jan–May | V5: Swing
A6: Amplify | B6: Bell's | C6: Bell's | D6: =SUMIFS('Data - Season'!$E$5:$E$743,'Data - Season'!$B$5:$B$743,$A6,'Data - Season'!$C$5:$C$743,$B6,'Data - Season'!$D$5:$D$743,$C6) | E6: =SUMIFS('Data - Season'!$F$5:$F$743,'Data - Season'!$B$5:$B$743,$A6,'Data - Season'!$C$5:$C$743,$B6,'Data - Season'!$D$5:$D$743,$C6) | F6: =SUMIFS('Data - Season'!$G$5:$G$743,'Data - Season'!$B$5:$B$743,$A6,'Data - Season'!$C$5:$C$743,$B6,'Data - Season'!$D$5:$D$743,$C6) | G6: =SUMIFS('Data - Season'!$H$5:$H$743,'Data - Season'!$B$5:$B$743,$A6,'Data - Season'!$C$5:$C$743,$B6,'Data - Season'!$D$5:$D$743,$C6) | H6: =SUMIFS('Data - Season'!$I$5:$I$743,'Data - Season'!$B$5:$B$743,$A6,'Data - Season'!$C$5:$C$743,$B6,'Data - Season'!$D$5:$D$743,$C6) | I6: =SUMIFS('Data - Season'!$J$5:$J$743,'Data - Season'!$B$5:$B$743,$A6,'Data - Season'!$C$5:$C$743,$B6,'Data - Season'!$D$5:$D$743,$C6) | J6: =SUMIFS('Data - Pre'!$D$5:$D$36,'Data - Pre'!$A$5:$A$36,$A6,'Data - Pre'!$B$5:$B$36,$B6,'Data - Pre'!$C$5:$C$36,$C6) | K6: =SUMIFS('Data - Pre'!$E$5:$E$36,'Data - Pre'!$A$5:$A$36,$A6,'Data - Pre'!$B$5:$B$36,$B6,'Data - Pre'!$C$5:$C$36,$C6) | L6: =SUMIFS('Data - Pre'!$H$5:$H$36,'Data - Pre'!$A$5:$A$36,$A6,'Data - Pre'!$B$5:$B$36,$B6,'Data - Pre'!$C$5:$C$36,$C6) | M6: =SUMIFS('Data - Pre'!$I$5:$I$36,'Data - Pre'!$A$5:$A$36,$A6,'Data - Pre'!$B$5:$B$36,$B6,'Data - Pre'!$C$5:$C$36,$C6) | N6: =IFERROR($H6/$D6,0) | O6: =IFERROR($I6/$E6,0) | P6: =IFERROR($F6/$D6,0) | Q6: =IFERROR($G6/$E6,0) | R6: =$E6*$N6 | S6: =$E6*($O6-$N6) | T6: =IFERROR($E6/$D6-1,"") | U6: =IFERROR($K6/$J6-1,"") | V6: =IFERROR($T6-$U6,"")
A7: Amplify | B7: Boston Beer Company | C7: Dogfish Head Beer | D7: =SUMIFS('Data - Season'!$E$5:$E$743,'Data - Season'!$B$5:$B$743,$A7,'Data - Season'!$C$5:$C$743,$B7,'Data - Season'!$D$5:$D$743,$C7) | E7: =SUMIFS('Data - Season'!$F$5:$F$743,'Data - Season'!$B$5:$B$743,$A7,'Data - Season'!$C$5:$C$743,$B7,'Data - Season'!$D$5:$D$743,$C7) | F7: =SUMIFS('Data - Season'!$G$5:$G$743,'Data - Season'!$B$5:$B$743,$A7,'Data - Season'!$C$5:$C$743,$B7,'Data - Season'!$D$5:$D$743,$C7) | G7: =SUMIFS('Data - Season'!$H$5:$H$743,'Data - Season'!$B$5:$B$743,$A7,'Data - Season'!$C$5:$C$743,$B7,'Data - Season'!$D$5:$D$743,$C7) | H7: =SUMIFS('Data - Season'!$I$5:$I$743,'Data - Season'!$B$5:$B$743,$A7,'Data - Season'!$C$5:$C$743,$B7,'Data - Season'!$D$5:$D$743,$C7) | I7: =SUMIFS('Data - Season'!$J$5:$J$743,'Data - Season'!$B$5:$B$743,$A7,'Data - Season'!$C$5:$C$743,$B7,'Data - Season'!$D$5:$D$743,$C7) | J7: =SUMIFS('Data - Pre'!$D$5:$D$36,'Data - Pre'!$A$5:$A$36,$A7,'Data - Pre'!$B$5:$B$36,$B7,'Data - Pre'!$C$5:$C$36,$C7) | K7: =SUMIFS('Data - Pre'!$E$5:$E$36,'Data - Pre'!$A$5:$A$36,$A7,'Data - Pre'!$B$5:$B$36,$B7,'Data - Pre'!$C$5:$C$36,$C7) | L7: =SUMIFS('Data - Pre'!$H$5:$H$36,'Data - Pre'!$A$5:$A$36,$A7,'Data - Pre'!$B$5:$B$36,$B7,'Data - Pre'!$C$5:$C$36,$C7) | M7: =SUMIFS('Data - Pre'!$I$5:$I$36,'Data - Pre'!$A$5:$A$36,$A7,'Data - Pre'!$B$5:$B$36,$B7,'Data - Pre'!$C$5:$C$36,$C7) | N7: =IFERROR($H7/$D7,0) | O7: =IFERROR($I7/$E7,0) | P7: =IFERROR($F7/$D7,0) | Q7: =IFERROR($G7/$E7,0) | R7: =$E7*$N7 | S7: =$E7*($O7-$N7) | T7: =IFERROR($E7/$D7-1,"") | U7: =IFERROR($K7/$J7-1,"") | V7: =IFERROR($T7-$U7,"")
A8: Amplify | B8: Boston Beer Company | C8: Dogfish Head Spirits | D8: =SUMIFS('Data - Season'!$E$5:$E$743,'Data - Season'!$B$5:$B$743,$A8,'Data - Season'!$C$5:$C$743,$B8,'Data - Season'!$D$5:$D$743,$C8) | E8: =SUMIFS('Data - Season'!$F$5:$F$743,'Data - Season'!$B$5:$B$743,$A8,'Data - Season'!$C$5:$C$743,$B8,'Data - Season'!$D$5:$D$743,$C8) | F8: =SUMIFS('Data - Season'!$G$5:$G$743,'Data - Season'!$B$5:$B$743,$A8,'Data - Season'!$C$5:$C$743,$B8,'Data - Season'!$D$5:$D$743,$C8) | G8: =SUMIFS('Data - Season'!$H$5:$H$743,'Data - Season'!$B$5:$B$743,$A8,'Data - Season'!$C$5:$C$743,$B8,'Data - Season'!$D$5:$D$743,$C8) | H8: =SUMIFS('Data - Season'!$I$5:$I$743,'Data - Season'!$B$5:$B$743,$A8,'Data - Season'!$C$5:$C$743,$B8,'Data - Season'!$D$5:$D$743,$C8) | I8: =SUMIFS('Data - Season'!$J$5:$J$743,'Data - Season'!$B$5:$B$743,$A8,'Data - Season'!$C$5:$C$743,$B8,'Data - Season'!$D$5:$D$743,$C8) | J8: =SUMIFS('Data - Pre'!$D$5:$D$36,'Data - Pre'!$A$5:$A$36,$A8,'Data - Pre'!$B$5:$B$36,$B8,'Data - Pre'!$C$5:$C$36,$C8) | K8: =SUMIFS('Data - Pre'!$E$5:$E$36,'Data - Pre'!$A$5:$A$36,$A8,'Data - Pre'!$B$5:$B$36,$B8,'Data - Pre'!$C$5:$C$36,$C8) | L8: =SUMIFS('Data - Pre'!$H$5:$H$36,'Data - Pre'!$A$5:$A$36,$A8,'Data - Pre'!$B$5:$B$36,$B8,'Data - Pre'!$C$5:$C$36,$C8) | M8: =SUMIFS('Data - Pre'!$I$5:$I$36,'Data - Pre'!$A$5:$A$36,$A8,'Data - Pre'!$B$5:$B$36,$B8,'Data - Pre'!$C$5:$C$36,$C8) | N8: =IFERROR($H8/$D8,0) | O8: =IFERROR($I8/$E8,0) | P8: =IFERROR($F8/$D8,0) | Q8: =IFERROR($G8/$E8,0) | R8: =$E8*$N8 | S8: =$E8*($O8-$N8) | T8: =IFERROR($E8/$D8-1,"") | U8: =IFERROR($K8/$J8-1,"") | V8: =IFERROR($T8-$U8,"")
A9: Amplify | B9: Cape May | C9: Cape May | D9: =SUMIFS('Data - Season'!$E$5:$E$743,'Data - Season'!$B$5:$B$743,$A9,'Data - Season'!$C$5:$C$743,$B9,'Data - Season'!$D$5:$D$743,$C9) | E9: =SUMIFS('Data - Season'!$F$5:$F$743,'Data - Season'!$B$5:$B$743,$A9,'Data - Season'!$C$5:$C$743,$B9,'Data - Season'!$D$5:$D$743,$C9) | F9: =SUMIFS('Data - Season'!$G$5:$G$743,'Data - Season'!$B$5:$B$743,$A9,'Data - Season'!$C$5:$C$743,$B9,'Data - Season'!$D$5:$D$743,$C9) | G9: =SUMIFS('Data - Season'!$H$5:$H$743,'Data - Season'!$B$5:$B$743,$A9,'Data - Season'!$C$5:$C$743,$B9,'Data - Season'!$D$5:$D$743,$C9) | H9: =SUMIFS('Data - Season'!$I$5:$I$743,'Data - Season'!$B$5:$B$743,$A9,'Data - Season'!$C$5:$C$743,$B9,'Data - Season'!$D$5:$D$743,$C9) | I9: =SUMIFS('Data - Season'!$J$5:$J$743,'Data - Season'!$B$5:$B$743,$A9,'Data - Season'!$C$5:$C$743,$B9,'Data - Season'!$D$5:$D$743,$C9) | J9: =SUMIFS('Data - Pre'!$D$5:$D$36,'Data - Pre'!$A$5:$A$36,$A9,'Data - Pre'!$B$5:$B$36,$B9,'Data - Pre'!$C$5:$C$36,$C9) | K9: =SUMIFS('Data - Pre'!$E$5:$E$36,'Data - Pre'!$A$5:$A$36,$A9,'Data - Pre'!$B$5:$B$36,$B9,'Data - Pre'!$C$5:$C$36,$C9) | L9: =SUMIFS('Data - Pre'!$H$5:$H$36,'Data - Pre'!$A$5:$A$36,$A9,'Data - Pre'!$B$5:$B$36,$B9,'Data - Pre'!$C$5:$C$36,$C9) | M9: =SUMIFS('Data - Pre'!$I$5:$I$36,'Data - Pre'!$A$5:$A$36,$A9,'Data - Pre'!$B$5:$B$36,$B9,'Data - Pre'!$C$5:$C$36,$C9) | N9: =IFERROR($H9/$D9,0) | O9: =IFERROR($I9/$E9,0) | P9: =IFERROR($F9/$D9,0) | Q9: =IFERROR($G9/$E9,0) | R9: =$E9*$N9 | S9: =$E9*($O9-$N9) | T9: =IFERROR($E9/$D9-1,"") | U9: =IFERROR($K9/$J9-1,"") | V9: =IFERROR($T9-$U9,"")
A10: Amplify | B10: Constellation Brands | C10: Corona Premier | D10: =SUMIFS('Data - Season'!$E$5:$E$743,'Data - Season'!$B$5:$B$743,$A10,'Data - Season'!$C$5:$C$743,$B10,'Data - Season'!$D$5:$D$743,$C10) | E10: =SUMIFS('Data - Season'!$F$5:$F$743,'Data - Season'!$B$5:$B$743,$A10,'Data - Season'!$C$5:$C$743,$B10,'Data - Season'!$D$5:$D$743,$C10) | F10: =SUMIFS('Data - Season'!$G$5:$G$743,'Data - Season'!$B$5:$B$743,$A10,'Data - Season'!$C$5:$C$743,$B10,'Data - Season'!$D$5:$D$743,$C10) | G10: =SUMIFS('Data - Season'!$H$5:$H$743,'Data - Season'!$B$5:$B$743,$A10,'Data - Season'!$C$5:$C$743,$B10,'Data - Season'!$D$5:$D$743,$C10) | H10: =SUMIFS('Data - Season'!$I$5:$I$743,'Data - Season'!$B$5:$B$743,$A10,'Data - Season'!$C$5:$C$743,$B10,'Data - Season'!$D$5:$D$743,$C10) | I10: =SUMIFS('Data - Season'!$J$5:$J$743,'Data - Season'!$B$5:$B$743,$A10,'Data - Season'!$C$5:$C$743,$B10,'Data - Season'!$D$5:$D$743,$C10) | J10: =SUMIFS('Data - Pre'!$D$5:$D$36,'Data - Pre'!$A$5:$A$36,$A10,'Data - Pre'!$B$5:$B$36,$B10,'Data - Pre'!$C$5:$C$36,$C10) | K10: =SUMIFS('Data - Pre'!$E$5:$E$36,'Data - Pre'!$A$5:$A$36,$A10,'Data - Pre'!$B$5:$B$36,$B10,'Data - Pre'!$C$5:$C$36,$C10) | L10: =SUMIFS('Data - Pre'!$H$5:$H$36,'Data - Pre'!$A$5:$A$36,$A10,'Data - Pre'!$B$5:$B$36,$B10,'Data - Pre'!$C$5:$C$36,$C10) | M10: =SUMIFS('Data - Pre'!$I$5:$I$36,'Data - Pre'!$A$5:$A$36,$A10,'Data - Pre'!$B$5:$B$36,$B10,'Data - Pre'!$C$5:$C$36,$C10) | N10: =IFERROR($H10/$D10,0) | O10: =IFERROR($I10/$E10,0) | P10: =IFERROR($F10/$D10,0) | Q10: =IFERROR($G10/$E10,0) | R10: =$E10*$N10 | S10: =$E10*($O10-$N10) | T10: =IFERROR($E10/$D10-1,"") | U10: =IFERROR($K10/$J10-1,"") | V10: =IFERROR($T10-$U10,"")
A11: Amplify | B11: Constellation Brands | C11: Modelo Chelada | D11: =SUMIFS('Data - Season'!$E$5:$E$743,'Data - Season'!$B$5:$B$743,$A11,'Data - Season'!$C$5:$C$743,$B11,'Data - Season'!$D$5:$D$743,$C11) | E11: =SUMIFS('Data - Season'!$F$5:$F$743,'Data - Season'!$B$5:$B$743,$A11,'Data - Season'!$C$5:$C$743,$B11,'Data - Season'!$D$5:$D$743,$C11) | F11: =SUMIFS('Data - Season'!$G$5:$G$743,'Data - Season'!$B$5:$B$743,$A11,'Data - Season'!$C$5:$C$743,$B11,'Data - Season'!$D$5:$D$743,$C11) | G11: =SUMIFS('Data - Season'!$H$5:$H$743,'Data - Season'!$B$5:$B$743,$A11,'Data - Season'!$C$5:$C$743,$B11,'Data - Season'!$D$5:$D$743,$C11) | H11: =SUMIFS('Data - Season'!$I$5:$I$743,'Data - Season'!$B$5:$B$743,$A11,'Data - Season'!$C$5:$C$743,$B11,'Data - Season'!$D$5:$D$743,$C11) | I11: =SUMIFS('Data - Season'!$J$5:$J$743,'Data - Season'!$B$5:$B$743,$A11,'Data - Season'!$C$5:$C$743,$B11,'Data - Season'!$D$5:$D$743,$C11) | J11: =SUMIFS('Data - Pre'!$D$5:$D$36,'Data - Pre'!$A$5:$A$36,$A11,'Data - Pre'!$B$5:$B$36,$B11,'Data - Pre'!$C$5:$C$36,$C11) | K11: =SUMIFS('Data - Pre'!$E$5:$E$36,'Data - Pre'!$A$5:$A$36,$A11,'Data - Pre'!$B$5:$B$36,$B11,'Data - Pre'!$C$5:$C$36,$C11) | L11: =SUMIFS('Data - Pre'!$H$5:$H$36,'Data - Pre'!$A$5:$A$36,$A11,'Data - Pre'!$B$5:$B$36,$B11,'Data - Pre'!$C$5:$C$36,$C11) | M11: =SUMIFS('Data - Pre'!$I$5:$I$36,'Data - Pre'!$A$5:$A$36,$A11,'Data - Pre'!$B$5:$B$36,$B11,'Data - Pre'!$C$5:$C$36,$C11) | N11: =IFERROR($H11/$D11,0) | O11: =IFERROR($I11/$E11,0) | P11: =IFERROR($F11/$D11,0) | Q11: =IFERROR($G11/$E11,0) | R11: =$E11*$N11 | S11: =$E11*($O11-$N11) | T11: =IFERROR($E11/$D11-1,"") | U11: =IFERROR($K11/$J11-1,"") | V11: =IFERROR($T11-$U11,"")
A12: Amplify | B12: Constellation Brands | C12: Pacifico | D12: =SUMIFS('Data - Season'!$E$5:$E$743,'Data - Season'!$B$5:$B$743,$A12,'Data - Season'!$C$5:$C$743,$B12,'Data - Season'!$D$5:$D$743,$C12) | E12: =SUMIFS('Data - Season'!$F$5:$F$743,'Data - Season'!$B$5:$B$743,$A12,'Data - Season'!$C$5:$C$743,$B12,'Data - Season'!$D$5:$D$743,$C12) | F12: =SUMIFS('Data - Season'!$G$5:$G$743,'Data - Season'!$B$5:$B$743,$A12,'Data - Season'!$C$5:$C$743,$B12,'Data - Season'!$D$5:$D$743,$C12) | G12: =SUMIFS('Data - Season'!$H$5:$H$743,'Data - Season'!$B$5:$B$743,$A12,'Data - Season'!$C$5:$C$743,$B12,'Data - Season'!$D$5:$D$743,$C12) | H12: =SUMIFS('Data - Season'!$I$5:$I$743,'Data - Season'!$B$5:$B$743,$A12,'Data - Season'!$C$5:$C$743,$B12,'Data - Season'!$D$5:$D$743,$C12) | I12: =SUMIFS('Data - Season'!$J$5:$J$743,'Data - Season'!$B$5:$B$743,$A12,'Data - Season'!$C$5:$C$743,$B12,'Data - Season'!$D$5:$D$743,$C12) | J12: =SUMIFS('Data - Pre'!$D$5:$D$36,'Data - Pre'!$A$5:$A$36,$A12,'Data - Pre'!$B$5:$B$36,$B12,'Data - Pre'!$C$5:$C$36,$C12) | K12: =SUMIFS('Data - Pre'!$E$5:$E$36,'Data - Pre'!$A$5:$A$36,$A12,'Data - Pre'!$B$5:$B$36,$B12,'Data - Pre'!$C$5:$C$36,$C12) | L12: =SUMIFS('Data - Pre'!$H$5:$H$36,'Data - Pre'!$A$5:$A$36,$A12,'Data - Pre'!$B$5:$B$36,$B12,'Data - Pre'!$C$5:$C$36,$C12) | M12: =SUMIFS('Data - Pre'!$I$5:$I$36,'Data - Pre'!$A$5:$A$36,$A12,'Data - Pre'!$B$5:$B$36,$B12,'Data - Pre'!$C$5:$C$36,$C12) | N12: =IFERROR($H12/$D12,0) | O12: =IFERROR($I12/$E12,0) | P12: =IFERROR($F12/$D12,0) | Q12: =IFERROR($G12/$E12,0) | R12: =$E12*$N12 | S12: =$E12*($O12-$N12) | T12: =IFERROR($E12/$D12-1,"") | U12: =IFERROR($K12/$J12-1,"") | V12: =IFERROR($T12-$U12,"")
A13: Amplify | B13: Constellation Brands | C13: Victoria | D13: =SUMIFS('Data - Season'!$E$5:$E$743,'Data - Season'!$B$5:$B$743,$A13,'Data - Season'!$C$5:$C$743,$B13,'Data - Season'!$D$5:$D$743,$C13) | E13: =SUMIFS('Data - Season'!$F$5:$F$743,'Data - Season'!$B$5:$B$743,$A13,'Data - Season'!$C$5:$C$743,$B13,'Data - Season'!$D$5:$D$743,$C13) | F13: =SUMIFS('Data - Season'!$G$5:$G$743,'Data - Season'!$B$5:$B$743,$A13,'Data - Season'!$C$5:$C$743,$B13,'Data - Season'!$D$5:$D$743,$C13) | G13: =SUMIFS('Data - Season'!$H$5:$H$743,'Data - Season'!$B$5:$B$743,$A13,'Data - Season'!$C$5:$C$743,$B13,'Data - Season'!$D$5:$D$743,$C13) | H13: =SUMIFS('Data - Season'!$I$5:$I$743,'Data - Season'!$B$5:$B$743,$A13,'Data - Season'!$C$5:$C$743,$B13,'Data - Season'!$D$5:$D$743,$C13) | I13: =SUMIFS('Data - Season'!$J$5:$J$743,'Data - Season'!$B$5:$B$743,$A13,'Data - Season'!$C$5:$C$743,$B13,'Data - Season'!$D$5:$D$743,$C13) | J13: =SUMIFS('Data - Pre'!$D$5:$D$36,'Data - Pre'!$A$5:$A$36,$A13,'Data - Pre'!$B$5:$B$36,$B13,'Data - Pre'!$C$5:$C$36,$C13) | K13: =SUMIFS('Data - Pre'!$E$5:$E$36,'Data - Pre'!$A$5:$A$36,$A13,'Data - Pre'!$B$5:$B$36,$B13,'Data - Pre'!$C$5:$C$36,$C13) | L13: =SUMIFS('Data - Pre'!$H$5:$H$36,'Data - Pre'!$A$5:$A$36,$A13,'Data - Pre'!$B$5:$B$36,$B13,'Data - Pre'!$C$5:$C$36,$C13) | M13: =SUMIFS('Data - Pre'!$I$5:$I$36,'Data - Pre'!$A$5:$A$36,$A13,'Data - Pre'!$B$5:$B$36,$B13,'Data - Pre'!$C$5:$C$36,$C13) | N13: =IFERROR($H13/$D13,0) | O13: =IFERROR($I13/$E13,0) | P13: =IFERROR($F13/$D13,0) | Q13: =IFERROR($G13/$E13,0) | R13: =$E13*$N13 | S13: =$E13*($O13-$N13) | T13: =IFERROR($E13/$D13-1,"") | U13: =IFERROR($K13/$J13-1,"") | V13: =IFERROR($T13-$U13,"")
A14: Amplify | B14: DG Yuengling Inc | C14: Yuengling Flight | D14: =SUMIFS('Data - Season'!$E$5:$E$743,'Data - Season'!$B$5:$B$743,$A14,'Data - Season'!$C$5:$C$743,$B14,'Data - Season'!$D$5:$D$743,$C14) | E14: =SUMIFS('Data - Season'!$F$5:$F$743,'Data - Season'!$B$5:$B$743,$A14,'Data - Season'!$C$5:$C$743,$B14,'Data - Season'!$D$5:$D$743,$C14) | F14: =SUMIFS('Data - Season'!$G$5:$G$743,'Data - Season'!$B$5:$B$743,$A14,'Data - Season'!$C$5:$C$743,$B14,'Data - Season'!$D$5:$D$743,$C14) | G14: =SUMIFS('Data - Season'!$H$5:$H$743,'Data - Season'!$B$5:$B$743,$A14,'Data - Season'!$C$5:$C$743,$B14,'Data - Season'!$D$5:$D$743,$C14) | H14: =SUMIFS('Data - Season'!$I$5:$I$743,'Data - Season'!$B$5:$B$743,$A14,'Data - Season'!$C$5:$C$743,$B14,'Data - Season'!$D$5:$D$743,$C14) | I14: =SUMIFS('Data - Season'!$J$5:$J$743,'Data - Season'!$B$5:$B$743,$A14,'Data - Season'!$C$5:$C$743,$B14,'Data - Season'!$D$5:$D$743,$C14) | J14: =SUMIFS('Data - Pre'!$D$5:$D$36,'Data - Pre'!$A$5:$A$36,$A14,'Data - Pre'!$B$5:$B$36,$B14,'Data - Pre'!$C$5:$C$36,$C14) | K14: =SUMIFS('Data - Pre'!$E$5:$E$36,'Data - Pre'!$A$5:$A$36,$A14,'Data - Pre'!$B$5:$B$36,$B14,'Data - Pre'!$C$5:$C$36,$C14) | L14: =SUMIFS('Data - Pre'!$H$5:$H$36,'Data - Pre'!$A$5:$A$36,$A14,'Data - Pre'!$B$5:$B$36,$B14,'Data - Pre'!$C$5:$C$36,$C14) | M14: =SUMIFS('Data - Pre'!$I$5:$I$36,'Data - Pre'!$A$5:$A$36,$A14,'Data - Pre'!$B$5:$B$36,$B14,'Data - Pre'!$C$5:$C$36,$C14) | N14: =IFERROR($H14/$D14,0) | O14: =IFERROR($I14/$E14,0) | P14: =IFERROR($F14/$D14,0) | Q14: =IFERROR($G14/$E14,0) | R14: =$E14*$N14 | S14: =$E14*($O14-$N14) | T14: =IFERROR($E14/$D14-1,"") | U14: =IFERROR($K14/$J14-1,"") | V14: =IFERROR($T14-$U14,"")
A15: Amplify | B15: DG Yuengling Inc | C15: Yuengling Light Lager | D15: =SUMIFS('Data - Season'!$E$5:$E$743,'Data - Season'!$B$5:$B$743,$A15,'Data - Season'!$C$5:$C$743,$B15,'Data - Season'!$D$5:$D$743,$C15) | E15: =SUMIFS('Data - Season'!$F$5:$F$743,'Data - Season'!$B$5:$B$743,$A15,'Data - Season'!$C$5:$C$743,$B15,'Data - Season'!$D$5:$D$743,$C15) | F15: =SUMIFS('Data - Season'!$G$5:$G$743,'Data - Season'!$B$5:$B$743,$A15,'Data - Season'!$C$5:$C$743,$B15,'Data - Season'!$D$5:$D$743,$C15) | G15: =SUMIFS('Data - Season'!$H$5:$H$743,'Data - Season'!$B$5:$B$743,$A15,'Data - Season'!$C$5:$C$743,$B15,'Data - Season'!$D$5:$D$743,$C15) | H15: =SUMIFS('Data - Season'!$I$5:$I$743,'Data - Season'!$B$5:$B$743,$A15,'Data - Season'!$C$5:$C$743,$B15,'Data - Season'!$D$5:$D$743,$C15) | I15: =SUMIFS('Data - Season'!$J$5:$J$743,'Data - Season'!$B$5:$B$743,$A15,'Data - Season'!$C$5:$C$743,$B15,'Data - Season'!$D$5:$D$743,$C15) | J15: =SUMIFS('Data - Pre'!$D$5:$D$36,'Data - Pre'!$A$5:$A$36,$A15,'Data - Pre'!$B$5:$B$36,$B15,'Data - Pre'!$C$5:$C$36,$C15) | K15: =SUMIFS('Data - Pre'!$E$5:$E$36,'Data - Pre'!$A$5:$A$36,$A15,'Data - Pre'!$B$5:$B$36,$B15,'Data - Pre'!$C$5:$C$36,$C15) | L15: =SUMIFS('Data - Pre'!$H$5:$H$36,'Data - Pre'!$A$5:$A$36,$A15,'Data - Pre'!$B$5:$B$36,$B15,'Data - Pre'!$C$5:$C$36,$C15) | M15: =SUMIFS('Data - Pre'!$I$5:$I$36,'Data - Pre'!$A$5:$A$36,$A15,'Data - Pre'!$B$5:$B$36,$B15,'Data - Pre'!$C$5:$C$36,$C15) | N15: =IFERROR($H15/$D15,0) | O15: =IFERROR($I15/$E15,0) | P15: =IFERROR($F15/$D15,0) | Q15: =IFERROR($G15/$E15,0) | R15: =$E15*$N15 | S15: =$E15*($O15-$N15) | T15: =IFERROR($E15/$D15-1,"") | U15: =IFERROR($K15/$J15-1,"") | V15: =IFERROR($T15-$U15,"")
A16: Amplify | B16: Heineken USA | C16: Heineken 0.0 | D16: =SUMIFS('Data - Season'!$E$5:$E$743,'Data - Season'!$B$5:$B$743,$A16,'Data - Season'!$C$5:$C$743,$B16,'Data - Season'!$D$5:$D$743,$C16) | E16: =SUMIFS('Data - Season'!$F$5:$F$743,'Data - Season'!$B$5:$B$743,$A16,'Data - Season'!$C$5:$C$743,$B16,'Data - Season'!$D$5:$D$743,$C16) | F16: =SUMIFS('Data - Season'!$G$5:$G$743,'Data - Season'!$B$5:$B$743,$A16,'Data - Season'!$C$5:$C$743,$B16,'Data - Season'!$D$5:$D$743,$C16) | G16: =SUMIFS('Data - Season'!$H$5:$H$743,'Data - Season'!$B$5:$B$743,$A16,'Data - Season'!$C$5:$C$743,$B16,'Data - Season'!$D$5:$D$743,$C16) | H16: =SUMIFS('Data - Season'!$I$5:$I$743,'Data - Season'!$B$5:$B$743,$A16,'Data - Season'!$C$5:$C$743,$B16,'Data - Season'!$D$5:$D$743,$C16) | I16: =SUMIFS('Data - Season'!$J$5:$J$743,'Data - Season'!$B$5:$B$743,$A16,'Data - Season'!$C$5:$C$743,$B16,'Data - Season'!$D$5:$D$743,$C16) | J16: =SUMIFS('Data - Pre'!$D$5:$D$36,'Data - Pre'!$A$5:$A$36,$A16,'Data - Pre'!$B$5:$B$36,$B16,'Data - Pre'!$C$5:$C$36,$C16) | K16: =SUMIFS('Data - Pre'!$E$5:$E$36,'Data - Pre'!$A$5:$A$36,$A16,'Data - Pre'!$B$5:$B$36,$B16,'Data - Pre'!$C$5:$C$36,$C16) | L16: =SUMIFS('Data - Pre'!$H$5:$H$36,'Data - Pre'!$A$5:$A$36,$A16,'Data - Pre'!$B$5:$B$36,$B16,'Data - Pre'!$C$5:$C$36,$C16) | M16: =SUMIFS('Data - Pre'!$I$5:$I$36,'Data - Pre'!$A$5:$A$36,$A16,'Data - Pre'!$B$5:$B$36,$B16,'Data - Pre'!$C$5:$C$36,$C16) | N16: =IFERROR($H16/$D16,0) | O16: =IFERROR($I16/$E16,0) | P16: =IFERROR($F16/$D16,0) | Q16: =IFERROR($G16/$E16,0) | R16: =$E16*$N16 | S16: =$E16*($O16-$N16) | T16: =IFERROR($E16/$D16-1,"") | U16: =IFERROR($K16/$J16-1,"") | V16: =IFERROR($T16-$U16,"")
A17: Amplify | B17: Heineken USA | C17: Heineken Light | D17: =SUMIFS('Data - Season'!$E$5:$E$743,'Data - Season'!$B$5:$B$743,$A17,'Data - Season'!$C$5:$C$743,$B17,'Data - Season'!$D$5:$D$743,$C17) | E17: =SUMIFS('Data - Season'!$F$5:$F$743,'Data - Season'!$B$5:$B$743,$A17,'Data - Season'!$C$5:$C$743,$B17,'Data - Season'!$D$5:$D$743,$C17) | F17: =SUMIFS('Data - Season'!$G$5:$G$743,'Data - Season'!$B$5:$B$743,$A17,'Data - Season'!$C$5:$C$743,$B17,'Data - Season'!$D$5:$D$743,$C17) | G17: =SUMIFS('Data - Season'!$H$5:$H$743,'Data - Season'!$B$5:$B$743,$A17,'Data - Season'!$C$5:$C$743,$B17,'Data - Season'!$D$5:$D$743,$C17) | H17: =SUMIFS('Data - Season'!$I$5:$I$743,'Data - Season'!$B$5:$B$743,$A17,'Data - Season'!$C$5:$C$743,$B17,'Data - Season'!$D$5:$D$743,$C17) | I17: =SUMIFS('Data - Season'!$J$5:$J$743,'Data - Season'!$B$5:$B$743,$A17,'Data - Season'!$C$5:$C$743,$B17,'Data - Season'!$D$5:$D$743,$C17) | J17: =SUMIFS('Data - Pre'!$D$5:$D$36,'Data - Pre'!$A$5:$A$36,$A17,'Data - Pre'!$B$5:$B$36,$B17,'Data - Pre'!$C$5:$C$36,$C17) | K17: =SUMIFS('Data - Pre'!$E$5:$E$36,'Data - Pre'!$A$5:$A$36,$A17,'Data - Pre'!$B$5:$B$36,$B17,'Data - Pre'!$C$5:$C$36,$C17) | L17: =SUMIFS('Data - Pre'!$H$5:$H$36,'Data - Pre'!$A$5:$A$36,$A17,'Data - Pre'!$B$5:$B$36,$B17,'Data - Pre'!$C$5:$C$36,$C17) | M17: =SUMIFS('Data - Pre'!$I$5:$I$36,'Data - Pre'!$A$5:$A$36,$A17,'Data - Pre'!$B$5:$B$36,$B17,'Data - Pre'!$C$5:$C$36,$C17) | N17: =IFERROR($H17/$D17,0) | O17: =IFERROR($I17/$E17,0) | P17: =IFERROR($F17/$D17,0) | Q17: =IFERROR($G17/$E17,0) | R17: =$E17*$N17 | S17: =$E17*($O17-$N17) | T17: =IFERROR($E17/$D17-1,"") | U17: =IFERROR($K17/$J17-1,"") | V17: =IFERROR($T17-$U17,"")
... A37: Qualifier | B37: MolsonCoors Beverage Company | C37: Lite | D37: =SUMIFS('Data - Season'!$E$5:$E$743,'Data - Season'!$B$5:$B$743,$A37,'Data - Season'!$C$5:$C$743,$B37,'Data - Season'!$D$5:$D$743,$C37) | E37: =SUMIFS('Data - Season'!$F$5:$F$743,'Data - Season'!$B$5:$B$743,$A37,'Data - Season'!$C$5:$C$743,$B37,'Data - Season'!$D$5:$D$743,$C37) | F37: =SUMIFS('Data - Season'!$G$5:$G$743,'Data - Season'!$B$5:$B$743,$A37,'Data - Season'!$C$5:$C$743,$B37,'Data - Season'!$D$5:$D$743,$C37) | G37: =SUMIFS('Data - Season'!$H$5:$H$743,'Data - Season'!$B$5:$B$743,$A37,'Data - Season'!$C$5:$C$743,$B37,'Data - Season'!$D$5:$D$743,$C37) | H37: =SUMIFS('Data - Season'!$I$5:$I$743,'Data - Season'!$B$5:$B$743,$A37,'Data - Season'!$C$5:$C$743,$B37,'Data - Season'!$D$5:$D$743,$C37) | I37: =SUMIFS('Data - Season'!$J$5:$J$743,'Data - Season'!$B$5:$B$743,$A37,'Data - Season'!$C$5:$C$743,$B37,'Data - Season'!$D$5:$D$743,$C37) | J37: =SUMIFS('Data - Pre'!$D$5:$D$36,'Data - Pre'!$A$5:$A$36,$A37,'Data - Pre'!$B$5:$B$36,$B37,'Data - Pre'!$C$5:$C$36,$C37) | K37: =SUMIFS('Data - Pre'!$E$5:$E$36,'Data - Pre'!$A$5:$A$36,$A37,'Data - Pre'!$B$5:$B$36,$B37,'Data - Pre'!$C$5:$C$36,$C37) | L37: =SUMIFS('Data - Pre'!$H$5:$H$36,'Data - Pre'!$A$5:$A$36,$A37,'Data - Pre'!$B$5:$B$36,$B37,'Data - Pre'!$C$5:$C$36,$C37) | M37: =SUMIFS('Data - Pre'!$I$5:$I$36,'Data - Pre'!$A$5:$A$36,$A37,'Data - Pre'!$B$5:$B$36,$B37,'Data - Pre'!$C$5:$C$36,$C37) | N37: =IFERROR($H37/$D37,0) | O37: =IFERROR($I37/$E37,0) | P37: =IFERROR($F37/$D37,0) | Q37: =IFERROR($G37/$E37,0) | R37: =$E37*$N37 | S37: =$E37*($O37-$N37) | T37: =IFERROR($E37/$D37-1,"") | U37: =IFERROR($K37/$J37-1,"") | V37: =IFERROR($T37-$U37,"")
A38: TOTAL | D38: =SUM(D6:D37) | E38: =SUM(E6:E37) | F38: =SUM(F6:F37) | G38: =SUM(G6:G37) | H38: =SUM(H6:H37) | I38: =SUM(I6:I37) | J38: =SUM(J6:J37) | K38: =SUM(K6:K37) | ... M38: =SUM(M6:M37) | R38: =SUM(R6:R37) | S38: =SUM(S6:S37)

Sheet Control Brands
A1: Non-program brands — Jun–Aug, brand level
A2: The control set: every brand NOT in Summer of Success. SUMIFS off Data - Control.
A4: Supplier | B4: Brand Family | C4: CE 2025 | D4: CE 2026 | E4: Rev 2025 | F4: Rev 2026 | G4: GP 2025 | H4: GP 2026 | I4: GP/CE 2025 | J4: GP/CE 2026 | K4: GP26 at LY rate | L4: Rate effect | M4: Cases %
A5: 1925 Spirits LLC | B5: Leyenda 1925 | C5: =SUMIFS('Data - Control'!$C$5:$C$296,'Data - Control'!$A$5:$A$296,$A5,'Data - Control'!$B$5:$B$296,$B5) | D5: =SUMIFS('Data - Control'!$D$5:$D$296,'Data - Control'!$A$5:$A$296,$A5,'Data - Control'!$B$5:$B$296,$B5) | E5: =SUMIFS('Data - Control'!$E$5:$E$296,'Data - Control'!$A$5:$A$296,$A5,'Data - Control'!$B$5:$B$296,$B5) | F5: =SUMIFS('Data - Control'!$F$5:$F$296,'Data - Control'!$A$5:$A$296,$A5,'Data - Control'!$B$5:$B$296,$B5) | G5: =SUMIFS('Data - Control'!$G$5:$G$296,'Data - Control'!$A$5:$A$296,$A5,'Data - Control'!$B$5:$B$296,$B5) | H5: =SUMIFS('Data - Control'!$H$5:$H$296,'Data - Control'!$A$5:$A$296,$A5,'Data - Control'!$B$5:$B$296,$B5) | I5: =IFERROR($G5/$C5,0) | J5: =IFERROR($H5/$D5,0) | K5: =$D5*$I5 | L5: =$D5*($J5-$I5) | M5: =IFERROR($D5/$C5-1,"")
A6: 2 Towns Ciderhouse | B6: Craftwell | C6: =SUMIFS('Data - Control'!$C$5:$C$296,'Data - Control'!$A$5:$A$296,$A6,'Data - Control'!$B$5:$B$296,$B6) | D6: =SUMIFS('Data - Control'!$D$5:$D$296,'Data - Control'!$A$5:$A$296,$A6,'Data - Control'!$B$5:$B$296,$B6) | E6: =SUMIFS('Data - Control'!$E$5:$E$296,'Data - Control'!$A$5:$A$296,$A6,'Data - Control'!$B$5:$B$296,$B6) | F6: =SUMIFS('Data - Control'!$F$5:$F$296,'Data - Control'!$A$5:$A$296,$A6,'Data - Control'!$B$5:$B$296,$B6) | G6: =SUMIFS('Data - Control'!$G$5:$G$296,'Data - Control'!$A$5:$A$296,$A6,'Data - Control'!$B$5:$B$296,$B6) | H6: =SUMIFS('Data - Control'!$H$5:$H$296,'Data - Control'!$A$5:$A$296,$A6,'Data - Control'!$B$5:$B$296,$B6) | I6: =IFERROR($G6/$C6,0) | J6: =IFERROR($H6/$D6,0) | K6: =$D6*$I6 | L6: =$D6*($J6-$I6) | M6: =IFERROR($D6/$C6-1,"")
A7: Alias Brew Works | B7: Alias Brew Works | C7: =SUMIFS('Data - Control'!$C$5:$C$296,'Data - Control'!$A$5:$A$296,$A7,'Data - Control'!$B$5:$B$296,$B7) | D7: =SUMIFS('Data - Control'!$D$5:$D$296,'Data - Control'!$A$5:$A$296,$A7,'Data - Control'!$B$5:$B$296,$B7) | E7: =SUMIFS('Data - Control'!$E$5:$E$296,'Data - Control'!$A$5:$A$296,$A7,'Data - Control'!$B$5:$B$296,$B7) | F7: =SUMIFS('Data - Control'!$F$5:$F$296,'Data - Control'!$A$5:$A$296,$A7,'Data - Control'!$B$5:$B$296,$B7) | G7: =SUMIFS('Data - Control'!$G$5:$G$296,'Data - Control'!$A$5:$A$296,$A7,'Data - Control'!$B$5:$B$296,$B7) | H7: =SUMIFS('Data - Control'!$H$5:$H$296,'Data - Control'!$A$5:$A$296,$A7,'Data - Control'!$B$5:$B$296,$B7) | I7: =IFERROR($G7/$C7,0) | J7: =IFERROR($H7/$D7,0) | K7: =$D7*$I7 | L7: =$D7*($J7-$I7) | M7: =IFERROR($D7/$C7-1,"")
A8: Alte Beverage | B8: Alte Beverage | C8: =SUMIFS('Data - Control'!$C$5:$C$296,'Data - Control'!$A$5:$A$296,$A8,'Data - Control'!$B$5:$B$296,$B8) | D8: =SUMIFS('Data - Control'!$D$5:$D$296,'Data - Control'!$A$5:$A$296,$A8,'Data - Control'!$B$5:$B$296,$B8) | E8: =SUMIFS('Data - Control'!$E$5:$E$296,'Data - Control'!$A$5:$A$296,$A8,'Data - Control'!$B$5:$B$296,$B8) | F8: =SUMIFS('Data - Control'!$F$5:$F$296,'Data - Control'!$A$5:$A$296,$A8,'Data - Control'!$B$5:$B$296,$B8) | G8: =SUMIFS('Data - Control'!$G$5:$G$296,'Data - Control'!$A$5:$A$296,$A8,'Data - Control'!$B$5:$B$296,$B8) | H8: =SUMIFS('Data - Control'!$H$5:$H$296,'Data - Control'!$A$5:$A$296,$A8,'Data - Control'!$B$5:$B$296,$B8) | I8: =IFERROR($G8/$C8,0) | J8: =IFERROR($H8/$D8,0) | K8: =$D8*$I8 | L8: =$D8*($J8-$I8) | M8: =IFERROR($D8/$C8-1,"")
A9: American Fruits | B9: American Fruit | C9: =SUMIFS('Data - Control'!$C$5:$C$296,'Data - Control'!$A$5:$A$296,$A9,'Data - Control'!$B$5:$B$296,$B9) | D9: =SUMIFS('Data - Control'!$D$5:$D$296,'Data - Control'!$A$5:$A$296,$A9,'Data - Control'!$B$5:$B$296,$B9) | E9: =SUMIFS('Data - Control'!$E$5:$E$296,'Data - Control'!$A$5:$A$296,$A9,'Data - Control'!$B$5:$B$296,$B9) | F9: =SUMIFS('Data - Control'!$F$5:$F$296,'Data - Control'!$A$5:$A$296,$A9,'Data - Control'!$B$5:$B$296,$B9) | G9: =SUMIFS('Data - Control'!$G$5:$G$296,'Data - Control'!$A$5:$A$296,$A9,'Data - Control'!$B$5:$B$296,$B9) | H9: =SUMIFS('Data - Control'!$H$5:$H$296,'Data - Control'!$A$5:$A$296,$A9,'Data - Control'!$B$5:$B$296,$B9) | I9: =IFERROR($G9/$C9,0) | J9: =IFERROR($H9/$D9,0) | K9: =$D9*$I9 | L9: =$D9*($J9-$I9) | M9: =IFERROR($D9/$C9-1,"")
A10: Artisanal Imports | B10: Palma | C10: =SUMIFS('Data - Control'!$C$5:$C$296,'Data - Control'!$A$5:$A$296,$A10,'Data - Control'!$B$5:$B$296,$B10) | D10: =SUMIFS('Data - Control'!$D$5:$D$296,'Data - Control'!$A$5:$A$296,$A10,'Data - Control'!$B$5:$B$296,$B10) | E10: =SUMIFS('Data - Control'!$E$5:$E$296,'Data - Control'!$A$5:$A$296,$A10,'Data - Control'!$B$5:$B$296,$B10) | F10: =SUMIFS('Data - Control'!$F$5:$F$296,'Data - Control'!$A$5:$A$296,$A10,'Data - Control'!$B$5:$B$296,$B10) | G10: =SUMIFS('Data - Control'!$G$5:$G$296,'Data - Control'!$A$5:$A$296,$A10,'Data - Control'!$B$5:$B$296,$B10) | H10: =SUMIFS('Data - Control'!$H$5:$H$296,'Data - Control'!$A$5:$A$296,$A10,'Data - Control'!$B$5:$B$296,$B10) | I10: =IFERROR($G10/$C10,0) | J10: =IFERROR($H10/$D10,0) | K10: =$D10*$I10 | L10: =$D10*($J10-$I10) | M10: =IFERROR($D10/$C10-1,"")
A11: Artisanal Imports | B11: Tona | C11: =SUMIFS('Data - Control'!$C$5:$C$296,'Data - Control'!$A$5:$A$296,$A11,'Data - Control'!$B$5:$B$296,$B11) | D11: =SUMIFS('Data - Control'!$D$5:$D$296,'Data - Control'!$A$5:$A$296,$A11,'Data - Control'!$B$5:$B$296,$B11) | E11: =SUMIFS('Data - Control'!$E$5:$E$296,'Data - Control'!$A$5:$A$296,$A11,'Data - Control'!$B$5:$B$296,$B11) | F11: =SUMIFS('Data - Control'!$F$5:$F$296,'Data - Control'!$A$5:$A$296,$A11,'Data - Control'!$B$5:$B$296,$B11) | G11: =SUMIFS('Data - Control'!$G$5:$G$296,'Data - Control'!$A$5:$A$296,$A11,'Data - Control'!$B$5:$B$296,$B11) | H11: =SUMIFS('Data - Control'!$H$5:$H$296,'Data - Control'!$A$5:$A$296,$A11,'Data - Control'!$B$5:$B$296,$B11) | I11: =IFERROR($G11/$C11,0) | J11: =IFERROR($H11/$D11,0) | K11: =$D11*$I11 | L11: =$D11*($J11-$I11) | M11: =IFERROR($D11/$C11-1,"")
A12: Athletic Brewing Company | B12: Athletic | C12: =SUMIFS('Data - Control'!$C$5:$C$296,'Data - Control'!$A$5:$A$296,$A12,'Data - Control'!$B$5:$B$296,$B12) | D12: =SUMIFS('Data - Control'!$D$5:$D$296,'Data - Control'!$A$5:$A$296,$A12,'Data - Control'!$B$5:$B$296,$B12) | E12: =SUMIFS('Data - Control'!$E$5:$E$296,'Data - Control'!$A$5:$A$296,$A12,'Data - Control'!$B$5:$B$296,$B12) | F12: =SUMIFS('Data - Control'!$F$5:$F$296,'Data - Control'!$A$5:$A$296,$A12,'Data - Control'!$B$5:$B$296,$B12) | G12: =SUMIFS('Data - Control'!$G$5:$G$296,'Data - Control'!$A$5:$A$296,$A12,'Data - Control'!$B$5:$B$296,$B12) | H12: =SUMIFS('Data - Control'!$H$5:$H$296,'Data - Control'!$A$5:$A$296,$A12,'Data - Control'!$B$5:$B$296,$B12) | I12: =IFERROR($G12/$C12,0) | J12: =IFERROR($H12/$D12,0) | K12: =$D12*$I12 | L12: =$D12*($J12-$I12) | M12: =IFERROR($D12/$C12-1,"")
A13: BJ'S Private Label Brew | B13: BJ'S Private Label Brewa | C13: =SUMIFS('Data - Control'!$C$5:$C$296,'Data - Control'!$A$5:$A$296,$A13,'Data - Control'!$B$5:$B$296,$B13) | D13: =SUMIFS('Data - Control'!$D$5:$D$296,'Data - Control'!$A$5:$A$296,$A13,'Data - Control'!$B$5:$B$296,$B13) | E13: =SUMIFS('Data - Control'!$E$5:$E$296,'Data - Control'!$A$5:$A$296,$A13,'Data - Control'!$B$5:$B$296,$B13) | F13: =SUMIFS('Data - Control'!$F$5:$F$296,'Data - Control'!$A$5:$A$296,$A13,'Data - Control'!$B$5:$B$296,$B13) | G13: =SUMIFS('Data - Control'!$G$5:$G$296,'Data - Control'!$A$5:$A$296,$A13,'Data - Control'!$B$5:$B$296,$B13) | H13: =SUMIFS('Data - Control'!$H$5:$H$296,'Data - Control'!$A$5:$A$296,$A13,'Data - Control'!$B$5:$B$296,$B13) | I13: =IFERROR($G13/$C13,0) | J13: =IFERROR($H13/$D13,0) | K13: =$D13*$I13 | L13: =$D13*($J13-$I13) | M13: =IFERROR($D13/$C13-1,"")
A14: Bardstown Bourbon Co | B14: Bardstown Bourbon | C14: =SUMIFS('Data - Control'!$C$5:$C$296,'Data - Control'!$A$5:$A$296,$A14,'Data - Control'!$B$5:$B$296,$B14) | D14: =SUMIFS('Data - Control'!$D$5:$D$296,'Data - Control'!$A$5:$A$296,$A14,'Data - Control'!$B$5:$B$296,$B14) | E14: =SUMIFS('Data - Control'!$E$5:$E$296,'Data - Control'!$A$5:$A$296,$A14,'Data - Control'!$B$5:$B$296,$B14) | F14: =SUMIFS('Data - Control'!$F$5:$F$296,'Data - Control'!$A$5:$A$296,$A14,'Data - Control'!$B$5:$B$296,$B14) | G14: =SUMIFS('Data - Control'!$G$5:$G$296,'Data - Control'!$A$5:$A$296,$A14,'Data - Control'!$B$5:$B$296,$B14) | H14: =SUMIFS('Data - Control'!$H$5:$H$296,'Data - Control'!$A$5:$A$296,$A14,'Data - Control'!$B$5:$B$296,$B14) | I14: =IFERROR($G14/$C14,0) | J14: =IFERROR($H14/$D14,0) | K14: =$D14*$I14 | L14: =$D14*($J14-$I14) | M14: =IFERROR($D14/$C14-1,"")
A15: Bardstown Bourbon Co | B15: Bardstown Green River | C15: =SUMIFS('Data - Control'!$C$5:$C$296,'Data - Control'!$A$5:$A$296,$A15,'Data - Control'!$B$5:$B$296,$B15) | D15: =SUMIFS('Data - Control'!$D$5:$D$296,'Data - Control'!$A$5:$A$296,$A15,'Data - Control'!$B$5:$B$296,$B15) | E15: =SUMIFS('Data - Control'!$E$5:$E$296,'Data - Control'!$A$5:$A$296,$A15,'Data - Control'!$B$5:$B$296,$B15) | F15: =SUMIFS('Data - Control'!$F$5:$F$296,'Data - Control'!$A$5:$A$296,$A15,'Data - Control'!$B$5:$B$296,$B15) | G15: =SUMIFS('Data - Control'!$G$5:$G$296,'Data - Control'!$A$5:$A$296,$A15,'Data - Control'!$B$5:$B$296,$B15) | H15: =SUMIFS('Data - Control'!$H$5:$H$296,'Data - Control'!$A$5:$A$296,$A15,'Data - Control'!$B$5:$B$296,$B15) | I15: =IFERROR($G15/$C15,0) | J15: =IFERROR($H15/$D15,0) | K15: =$D15*$I15 | L15: =$D15*($J15-$I15) | M15: =IFERROR($D15/$C15-1,"")
A16: Barn Brew Co | B16: Barn Brew | C16: =SUMIFS('Data - Control'!$C$5:$C$296,'Data - Control'!$A$5:$A$296,$A16,'Data - Control'!$B$5:$B$296,$B16) | D16: =SUMIFS('Data - Control'!$D$5:$D$296,'Data - Control'!$A$5:$A$296,$A16,'Data - Control'!$B$5:$B$296,$B16) | E16: =SUMIFS('Data - Control'!$E$5:$E$296,'Data - Control'!$A$5:$A$296,$A16,'Data - Control'!$B$5:$B$296,$B16) | F16: =SUMIFS('Data - Control'!$F$5:$F$296,'Data - Control'!$A$5:$A$296,$A16,'Data - Control'!$B$5:$B$296,$B16) | G16: =SUMIFS('Data - Control'!$G$5:$G$296,'Data - Control'!$A$5:$A$296,$A16,'Data - Control'!$B$5:$B$296,$B16) | H16: =SUMIFS('Data - Control'!$H$5:$H$296,'Data - Control'!$A$5:$A$296,$A16,'Data - Control'!$B$5:$B$296,$B16) | I16: =IFERROR($G16/$C16,0) | J16: =IFERROR($H16/$D16,0) | K16: =$D16*$I16 | L16: =$D16*($J16-$I16) | M16: =IFERROR($D16/$C16-1,"")
... A296: XYZ Beverage | B296: Press | C296: =SUMIFS('Data - Control'!$C$5:$C$296,'Data - Control'!$A$5:$A$296,$A296,'Data - Control'!$B$5:$B$296,$B296) | D296: =SUMIFS('Data - Control'!$D$5:$D$296,'Data - Control'!$A$5:$A$296,$A296,'Data - Control'!$B$5:$B$296,$B296) | E296: =SUMIFS('Data - Control'!$E$5:$E$296,'Data - Control'!$A$5:$A$296,$A296,'Data - Control'!$B$5:$B$296,$B296) | F296: =SUMIFS('Data - Control'!$F$5:$F$296,'Data - Control'!$A$5:$A$296,$A296,'Data - Control'!$B$5:$B$296,$B296) | G296: =SUMIFS('Data - Control'!$G$5:$G$296,'Data - Control'!$A$5:$A$296,$A296,'Data - Control'!$B$5:$B$296,$B296) | H296: =SUMIFS('Data - Control'!$H$5:$H$296,'Data - Control'!$A$5:$A$296,$A296,'Data - Control'!$B$5:$B$296,$B296) | I296: =IFERROR($G296/$C296,0) | J296: =IFERROR($H296/$D296,0) | K296: =$D296*$I296 | L296: =$D296*($J296-$I296) | M296: =IFERROR($D296/$C296-1,"")
A297: TOTAL | C297: =SUM(C5:C296) | D297: =SUM(D5:D296) | E297: =SUM(E5:E296) | F297: =SUM(F5:F296) | G297: =SUM(G5:G296) | H297: =SUM(H5:H296) | K297: =SUM(K5:K296) | L297: =SUM(L5:L296)

Sheet Data - Season
A1: Source data — Season
A2: Program brands, 6/1–8/31 (2026 vs 2025), summed to rep × segment × supplier × brand, with account-derived POD counts · Source: RDE_2026_Summer_of_Success_52.csv
A4: Rep | B4: Segment | C4: Supplier | D4: Brand Family | E4: CE 2025 | F4: CE 2026 | G4: Revenue 2025 | H4: Revenue 2026 | I4: GP 2025 | J4: GP 2026 | K4: PODs 2025 | L4: PODs 2026 | M4: New PODs | N4: CE from new | O4: Lost PODs | P4: CE from lost
A5: Alex Rodriguez | B5: Amplify | C5: Sapporo | D5: Sapporo | E5: 576 | F5: 876 | G5: 18621 | H5: 28010.25 | I5: 4531.14 | J5: 6891.31 | K5: 31 | L5: 38 | M5: 11 | N5: 158 | O5: 4 | P5: 33
A6: Alisa Acciardi | B6: Amplify | C6: Boston Beer Company | D6: Dogfish Head Beer | E6: 6 | F6: 2 | G6: 239.8 | H6: 73.6 | I6: 64.57 | J6: 23.84 | K6: 1 | L6: 1 | M6: 0 | N6: 0 | O6: 0 | P6: 0
A7: Alisa Acciardi | B7: Amplify | C7: Cape May | D7: Cape May | E7: 8 | F7: 0 | G7: 316.5 | H7: 0 | I7: 108.67 | J7: 0 | K7: 2 | L7: 0 | M7: 0 | N7: 0 | O7: 2 | P7: 8
A8: Alisa Acciardi | B8: Amplify | C8: Constellation Brands | D8: Corona Premier | E8: 7 | F8: 6 | G8: 212.25 | H8: 158.4 | I8: 38.36 | J8: 41.29 | K8: 1 | L8: 1 | M8: 0 | N8: 0 | O8: 0 | P8: 0
A9: Alisa Acciardi | B9: Amplify | C9: Constellation Brands | D9: Modelo Chelada | E9: 51 | F9: 31 | G9: 1571.4 | H9: 967.75 | I9: 373.99 | J9: 252.09 | K9: 2 | L9: 2 | M9: 0 | N9: 0 | O9: 0 | P9: 0
A10: Alisa Acciardi | B10: Amplify | C10: Constellation Brands | D10: Pacifico | E10: 34 | F10: 8 | G10: 1035 | H10: 233.8 | I10: 240.96 | J10: 54.57 | K10: 1 | L10: 1 | M10: 0 | N10: 0 | O10: 0 | P10: 0
A11: Alisa Acciardi | B11: Amplify | C11: Constellation Brands | D11: Victoria | E11: 5 | F11: 9 | G11: 151.35 | H11: 277 | I11: 33.29 | J11: 63.24 | K11: 2 | L11: 2 | M11: 0 | N11: 0 | O11: 0 | P11: 0
A12: Alisa Acciardi | B12: Amplify | C12: DG Yuengling Inc | D12: Yuengling Flight | E12: 2 | F12: 2 | G12: 46.05 | H12: 42.2 | I12: 12.51 | J12: 10.05 | K12: 1 | L12: 1 | M12: 0 | N12: 0 | O12: 0 | P12: 0
A13: Alisa Acciardi | B13: Amplify | C13: DG Yuengling Inc | D13: Yuengling Light Lager | E13: 1 | F13: 2 | G13: 27 | H13: 42.2 | I13: 7.89 | J13: 10.02 | K13: 1 | L13: 1 | M13: 0 | N13: 0 | O13: 0 | P13: 0
A14: Alisa Acciardi | B14: Amplify | C14: Heineken USA | D14: Heineken 0.0 | E14: 9 | F14: 3 | G14: 282.15 | H14: 94.05 | I14: 74.88 | J14: 24.96 | K14: 2 | L14: 1 | M14: 0 | N14: 0 | O14: 1 | P14: 3
A15: Alisa Acciardi | B15: Amplify | C15: Heineken USA | D15: Heineken Light | E15: 19 | F15: 12 | G15: 603.7 | H15: 379.15 | I15: 152.03 | J15: 93.87 | K15: 2 | L15: 2 | M15: 0 | N15: 0 | O15: 0 | P15: 0
A16: Alisa Acciardi | B16: Amplify | C16: Mark Anthony | D16: Cayman Jack | E16: 5 | F16: 3 | G16: 155 | H16: 92.75 | I16: 37.65 | J16: 22.34 | K16: 1 | L16: 1 | M16: 0 | N16: 0 | O16: 0 | P16: 0
... A743: Shane Barreca | B743: Qualifier | C743: MolsonCoors Beverage Company | D743: Lite | E743: 15846 | F743: 14416 | G743: 338790.3 | H743: 318528.85 | I743: 78091.39 | J743: 75992.8 | K743: 28 | L743: 26 | M743: 0 | N743: 0 | O743: 2 | P743: 22
A745: Blue = from the RDE export, summed to segment × supplier × brand. The export itself is one row per rep × brand × ACCOUNT; no tab reads it at that grain, so it is summed here.
A746: POD = a point of distribution, one account × brand that bought. New / lost are measured at that grain, and the counts are additive across brands, which is why they can live on this tab and still roll up correctly.
A747: Account-grain analysis runs off the Data - Accounts tab instead.

Sheet Data - Pre
A1: Source data — Pre
A2: Program brands, 1/1–5/31 (2026 vs 2025) — pre-program baseline · Source: RDE_2026_Summer_of_Success_Jan__May_1.csv
A4: Segment | B4: Supplier | C4: Brand Family | D4: CE 2025 | E4: CE 2026 | F4: Revenue 2025 | G4: Revenue 2026 | H4: GP 2025 | I4: GP 2026 | J4: PODs 2025 | K4: PODs 2026 | L4: New PODs | M4: CE from new | N4: Lost PODs | O4: CE from lost
A5: Amplify | B5: Bell's | C5: Bell's | D5: 339 | E5: 642 | F5: 11761.15 | G5: 19507.6 | H5: 3630.5 | I5: 4883.72 | J5: 53 | K5: 49 | L5: 14 | M5: 438 | N5: 18 | O5: 57
A6: Amplify | B6: Boston Beer Company | C6: Dogfish Head Beer | D6: 14075 | E6: 14348 | F6: 504774.39 | G6: 504142.11 | H6: 131621.17 | I6: 128721.57 | J6: 580 | K6: 584 | L6: 94 | M6: 770 | N6: 90 | O6: 583
A7: Amplify | B7: Boston Beer Company | C7: Dogfish Head Spirits | D7: 1894 | E7: 1820 | F7: 102250.97 | G7: 90439.45 | H7: 39851.26 | I7: 31020.25 | J7: 112 | K7: 122 | L7: 42 | M7: 296 | N7: 32 | O7: 229
A8: Amplify | B8: Cape May | C8: Cape May | D8: 10157 | E8: 10352 | F8: 409580.01 | G8: 412420.06 | H8: 119246.62 | I8: 119479.5 | J8: 311 | K8: 329 | L8: 74 | M8: 910 | N8: 56 | O8: 406
A9: Amplify | B9: Constellation Brands | C9: Corona Premier | D9: 11387 | E9: 10572 | F9: 354677.53 | G9: 288577.15 | H9: 80869.84 | I9: 69688.7 | J9: 526 | K9: 464 | L9: 71 | M9: 341 | N9: 133 | O9: 519
A10: Amplify | B10: Constellation Brands | C10: Modelo Chelada | D10: 26948 | E10: 34538 | F10: 834793.6 | G10: 1060327.7 | H10: 211754.67 | I10: 263732.29 | J10: 431 | K10: 444 | L10: 30 | M10: 444 | N10: 17 | O10: 174
A11: Amplify | B11: Constellation Brands | C11: Pacifico | D11: 10533 | E11: 13329 | F11: 325545.1 | G11: 412489.75 | H11: 75921.61 | I11: 96456.25 | J11: 487 | K11: 509 | L11: 111 | M11: 829 | N11: 89 | O11: 345
A12: Amplify | B12: Constellation Brands | C12: Victoria | D12: 21044 | E12: 25253 | F12: 634688.9 | G12: 761409.95 | H12: 149923.11 | I12: 180910.75 | J12: 371 | K12: 399 | L12: 54 | M12: 538 | N12: 26 | O12: 208
A13: Amplify | B13: DG Yuengling Inc | C13: Yuengling Flight | D13: 3113 | E13: 3199 | F13: 72006.5 | G13: 74629.01 | H13: 20518.48 | I13: 21443.11 | J13: 210 | K13: 233 | L13: 71 | M13: 182 | N13: 48 | O13: 183
A14: Amplify | B14: DG Yuengling Inc | C14: Yuengling Light Lager | D14: 2738 | E14: 2612 | F14: 63781.56 | G14: 60600.03 | H14: 17501.9 | I14: 16258.59 | J14: 150 | K14: 164 | L14: 38 | M14: 159 | N14: 24 | O14: 56
A15: Amplify | B15: Heineken USA | C15: Heineken 0.0 | D15: 10097 | E15: 9458 | F15: 340246.85 | G15: 320164.4 | H15: 91362.33 | I15: 87095.68 | J15: 754 | K15: 770 | L15: 118 | M15: 555 | N15: 102 | O15: 732
A16: Amplify | B16: Heineken USA | C16: Heineken Light | D16: 12726 | E16: 11640 | F16: 400028.45 | G16: 365349.9 | H16: 97501.41 | I16: 88658.97 | J16: 504 | K16: 457 | L16: 72 | M16: 364 | N16: 119 | O16: 793
... A36: Qualifier | B36: MolsonCoors Beverage Company | C36: Lite | D36: 184909 | E36: 188262 | F36: 3999586.3 | G36: 4080313.7 | H36: 959196.18 | I36: 970730.04 | J36: 1093 | K36: 1107 | L36: 87 | M36: 4812 | N36: 73 | O36: 904
A38: Blue = from the RDE export, summed to segment × supplier × brand. The export itself is one row per rep × brand × ACCOUNT; no tab reads it at that grain, so it is summed here.
A39: POD = a point of distribution, one account × brand that bought. New / lost are measured at that grain, and the counts are additive across brands, which is why they can live on this tab and still roll up correctly.
A40: Account-grain analysis runs off the Data - Accounts tab instead.

Sheet Data - Control
A1: Source data — Control
A2: Brands NOT in Summer of Success, 6/1–8/31 (2026 vs 2025) · Source: RDE_2026_..._Brands_Not_Included_in_SoS_1.csv
A4: Supplier | B4: Brand Family | C4: CE 2025 | D4: CE 2026 | E4: Revenue 2025 | F4: Revenue 2026 | G4: GP 2025 | H4: GP 2026 | I4: PODs 2025 | J4: PODs 2026 | K4: New PODs | L4: CE from new | M4: Lost PODs | N4: CE from lost
A5: 1925 Spirits LLC | B5: Leyenda 1925 | C5: 0 | D5: 11 | E5: 0 | F5: 22539.14 | G5: 0 | H5: 6420.16 | I5: 0 | J5: 10 | K5: 10 | L5: 11 | M5: 0 | N5: 0
A6: 2 Towns Ciderhouse | B6: Craftwell | C6: 2 | D6: 0 | E6: 164 | F6: 0 | G6: 47.26 | H6: 0 | I6: 2 | J6: 0 | K6: 0 | L6: 0 | M6: 2 | N6: 2
A7: Alias Brew Works | B7: Alias Brew Works | C7: 250 | D7: 0 | E7: 10532 | F7: 0 | G7: 2785.45 | H7: 0 | I7: 22 | J7: 0 | K7: 0 | L7: 0 | M7: 22 | N7: 251
A8: Alte Beverage | B8: Alte Beverage | C8: 0 | D8: 42 | E8: 0 | F8: 3984 | G8: 0 | H8: 1470.66 | I8: 0 | J8: 15 | K8: 15 | L8: 42 | M8: 0 | N8: 0
A9: American Fruits | B9: American Fruit | C9: 6 | D9: 5 | E9: 1590 | F9: 900 | G9: 460.88 | H9: 284.76 | I9: 4 | J9: 5 | K9: 3 | L9: 3 | M9: 2 | N9: 3
A10: Artisanal Imports | B10: Palma | C10: 2006 | D10: 925 | E10: 58338.32 | F10: 23888.25 | G10: 15328.33 | H10: 4364.2 | I10: 70 | J10: 45 | K10: 11 | L10: 80 | M10: 36 | N10: 531
A11: Artisanal Imports | B11: Tona | C11: 1465 | D11: 960 | E11: 41646 | F11: 28242 | G11: 11602.85 | H11: 8420.3 | I11: 75 | J11: 81 | K11: 32 | L11: 268 | M11: 26 | N11: 311
A12: Athletic Brewing Company | B12: Athletic | C12: 6309 | D12: 6840 | E12: 195603.7 | F12: 210942.89 | G12: 46975.7 | H12: 50377.99 | I12: 276 | J12: 300 | K12: 80 | L12: 887 | M12: 56 | N12: 426
A13: BJ'S Private Label Brew | B13: BJ'S Private Label Brewa | C13: 851 | D13: 904 | E13: 14704.24 | F13: 17866.83 | G13: 3273.68 | H13: 4178.7 | I13: 6 | J13: 8 | K13: 4 | L13: 29 | M13: 2 | N13: 9
A14: Bardstown Bourbon Co | B14: Bardstown Bourbon | C14: 94 | D14: 63 | E14: 59574.9 | F14: 37875.75 | G14: 17009.19 | H14: 11018.75 | I14: 47 | J14: 40 | K14: 13 | L14: 19 | M14: 20 | N14: 28
A15: Bardstown Bourbon Co | B15: Bardstown Green River | C15: 32 | D15: 51 | E15: 16250.28 | F15: 18716.8 | G15: 4971.8 | H15: 5946.06 | I15: 16 | J15: 35 | K15: 25 | L15: 36 | M15: 6 | N15: 11
A16: Barn Brew Co | B16: Barn Brew | C16: 165 | D16: 117 | E16: 10210 | F16: 6814 | G16: 2665.44 | H16: 2134.28 | I16: 36 | J16: 16 | K16: 7 | L16: 16 | M16: 27 | N16: 82
... A296: XYZ Beverage | B296: Press | C296: 125 | D296: 0 | E296: 3141 | F296: 0 | G296: 232.25 | H296: 0 | I296: 10 | J296: 0 | K296: 0 | L296: 0 | M296: 10 | N296: 125
A298: Blue = from the RDE export, summed to supplier × brand. The export itself is one row per rep × brand × ACCOUNT; no tab reads it at that grain, so it is summed here.
A299: POD = a point of distribution, one account × brand that bought. New / lost are measured at that grain, and the counts are additive across brands, which is why they can live on this tab and still roll up correctly.
A300: Account-grain analysis runs off the Data - Accounts tab instead.

Sheet Data - Accounts
A1: Source data — accounts
A2: One row per account, 6/1–8/31. Program and non-program volume side by side. Sorted by program case gain, biggest first. · Source: all three RDE exports
A4: Account | B4: County | C4: Rep | D4: Channel | E4: Program CE 2025 | F4: Program CE 2026 | G4: Program GP 2025 | H4: Program GP 2026 | I4: Non-program CE 2025 | J4: Non-program CE 2026 | K4: Amplify CE 2025 | L4: Amplify CE 2026 | M4: Program Δ cases | N4: Amplify Δ cases
A5: 31019 Bj's Warehouse E Rutherfo | B5: Bergen | C5: John Neukum | D5: Off-premise | E5: 94432 | F5: 86573 | G5: 561240.04 | H5: 529082.94 | I5: 4706 | J5: 4798 | K5: 7088 | L5: 9982 | M5: =F5-E5 | N5: =L5-K5
A6: 20106 Super Wine Warehse(P)Pate | B6: Passaic | C6: Phil Ernst | D6: Off-premise | E6: 19588 | F6: 21892 | G6: 127699.52 | H6: 133675.72 | I6: 2323 | J6: 2220 | K6: 1941 | L6: 3787 | M6: =F6-E6 | N6: =L6-K6
A7: 67004 Beverage Barn (A) | B7: Bergen | C7: Shane Barreca | D7: Off-premise | E7: 7816 | F7: 9192 | G7: 45214.2 | H7: 55274.42 | I7: 2198 | J7: 2999 | K7: 1891 | L7: 3211 | M7: =F7-E7 | N7: =L7-K7
A8: 14007 Total Wine & More (Totowa) | B8: Passaic | C8: Dave Ehlers | D8: Off-premise | E8: 20953 | F8: 24507 | G8: 134387.57 | H8: 162555.79 | I8: 8120 | J8: 8175 | K8: 3216 | L8: 4003 | M8: =F8-E8 | N8: =L8-K8
A9: 31060 Bottle Republic (Rutherford) | B9: Bergen | C9: Matt Powierski | D9: Off-premise | E9: 0 | F9: 2754 | G9: 0 | H9: 18613.97 | I9: 0 | J9: 1259 | K9: 0 | L9: 687 | M9: =F9-E9 | N9: =L9-K9
A10: 201026 Sam's Club (Secaucus) | B10: Hudson | C10: John Neukum | D10: Off-premise | E10: 0 | F10: 500 | G10: 0 | H10: 2515 | I10: 0 | J10: 100 | K10: 0 | L10: 500 | M10: =F10-E10 | N10: =L10-K10
A11: 190917 Shop Rite Liq (A)Wharton | B11: Morris | C11: Klejdi Lamo | D11: Off-premise | E11: 11629 | F11: 11707 | G11: 69910.65 | H11: 73850.25 | I11: 4559 | J11: 4799 | K11: 1706 | L11: 2137 | M11: =F11-E11 | N11: =L11-K11
A12: 58001 Total Wine & More (River Edge) | B12: Bergen | C12: Dave Ehlers | D12: Off-premise | E12: 23412 | F12: 23346 | G12: 147833.77 | H12: 148881.17 | I12: 11097 | J12: 10698 | K12: 3975 | L12: 4357 | M12: =F12-E12 | N12: =L12-K12
A13: 25045 Clifton Disc Liq (A) | B13: Passaic | C13: Chris Payton | D13: Off-premise | E13: 14017 | F13: 12713 | G13: 93239.12 | H13: 86593.19 | I13: 1932 | J13: 1919 | K13: 1680 | L13: 2005 | M13: =F13-E13 | N13: =L13-K13
A14: 92011 Bottle King (A) Ramsey | B14: Bergen | C14: Shane Barreca | D14: Off-premise | E14: 16201 | F14: 16102 | G14: 97199.36 | H14: 99665.33 | I14: 6561 | J14: 7298 | K14: 2529 | L14: 2830 | M14: =F14-E14 | N14: =L14-K14
A15: 56008 Bergenfield Liq & Fw | B15: Bergen | C15: Dave Ehlers | D15: Off-premise | E15: 4503 | F15: 5325 | G15: 30149.36 | H15: 35741.29 | I15: 589 | J15: 800 | K15: 827 | L15: 1105 | M15: =F15-E15 | N15: =L15-K15
A16: 49045 Liquor World | B16: Bergen | C16: Dan Lagala | D16: Off-premise | E16: 4620 | F16: 4889 | G16: 26395.26 | H16: 27930.6 | I16: 703 | J16: 764 | K16: 693 | L16: 967 | M16: =F16-E16 | N16: =L16-K16
... A2358: 14001 Wine & Bev. Depot (A) | B2358: Passaic | C2358: Jim Heaney | D2358: Off-premise | E2358: 4390 | F2358: 0 | G2358: 29001.78 | H2358: 0 | I2358: 972 | J2358: 0 | K2358: 511 | L2358: 0 | M2358: =F2358-E2358 | N2358: =L2358-K2358
A2360: Every account maps to exactly one rep and one county in these exports — checked, not assumed — so this tab is an exact re-grouping, not an approximation.
A2361: An account with zero in the non-program columns bought only incented brands, and vice versa. The Within-Account Control tab uses only accounts with volume on both sides.
A2362: Sorted by AMPLIFY case gain, biggest first — that is the order the Account Concentration tab reads. Concentration is only meaningful on a segment whose net change is positive, and the program total is negative.
A2363: Channel is joined from territory-accounts/ in this repo on the leading customer number. Accounts on neither roster are carried as Unmatched — about 2% of volume — rather than guessed at.

Sheet Data - Channel
A1: Source data — channel
A2: Channel × segment × period. Channel joined from territory-accounts/ on customer number. · Source: all three RDE exports + this repo's territory rosters
A4: Channel | B4: Period | C4: Segment | D4: CE 2025 | E4: CE 2026 | F4: Revenue 2025 | G4: Revenue 2026 | H4: GP 2025 | I4: GP 2026
A5: Off-premise | B5: Jun–Aug | C5: Qualifier | D5: 1270979 | E5: 1195151 | F5: 35973923 | G5: 34138772 | H5: 8185449.4 | I5: 7927089.3
A6: Off-premise | B6: Jun–Aug | C6: Amplify | D6: 199974 | E6: 222382 | F6: 5975744.3 | G6: 6562970.6 | H6: 1458666.3 | I6: 1598498
A7: Off-premise | B7: Jan–May | C7: Qualifier | D7: 1432953 | E7: 1400105 | F7: 40431053 | G7: 39374729 | H7: 9429096.6 | I7: 9127051.6
A8: Off-premise | B8: Jan–May | C8: Amplify | D8: 221681 | E8: 248581 | F8: 6565888.8 | G8: 7299804.9 | H8: 1620419 | I8: 1782484.4
A9: Off-premise | B9: Jun–Aug | C9: Control | D9: 394391 | E9: 383792 | F9: 11305595 | G9: 11318823 | H9: 2870046.9 | I9: 3109773.7
A10: On-premise | B10: Jun–Aug | C10: Qualifier | D10: 158230 | E10: 158046 | F10: 4290825.2 | G10: 4318523.1 | H10: 1151961.9 | I10: 1162903.1
A11: On-premise | B11: Jun–Aug | C11: Amplify | D11: 16950 | E11: 20071 | F11: 558827.78 | G11: 659213.49 | H11: 146782.85 | I11: 175701.29
A12: On-premise | B12: Jan–May | C12: Qualifier | D12: 245942 | E12: 236968 | F12: 6605427.8 | G12: 6399737.4 | H12: 1793799.6 | I12: 1745068.3
A13: On-premise | B13: Jan–May | C13: Amplify | D13: 25272 | E13: 28729 | F13: 833816.97 | G13: 945175.46 | H13: 218916.05 | I13: 250311.72
A14: On-premise | B14: Jun–Aug | C14: Control | D14: 51584 | E14: 53871 | F14: 1645739.5 | G14: 1728443.3 | H14: 448446.75 | I14: 477398.97
A15: Unmatched | B15: Jun–Aug | C15: Qualifier | D15: 24699 | E15: 25199 | F15: 735905.29 | G15: 760912.15 | H15: 189250.5 | I15: 198215.93
A16: Unmatched | B16: Jun–Aug | C16: Amplify | D16: 4929 | E16: 4993 | F16: 155231.1 | G16: 156414.33 | H16: 40388.01 | I16: 41125.95
... A19: Unmatched | B19: Jun–Aug | C19: Control | D19: 20505 | E19: 18877 | F19: 591936.5 | G19: 547870.61 | H19: 154303.25 | I19: 144419.94
A21: Unmatched = accounts on neither territory roster, about 2% of volume. Shown rather than dropped so the channel rows still add to the program total.
