Workbook

Sheet Master - US vs THEM
A1: Brand Family | B1: County | C1: Territory ID | D1: In Territory? | E1: Blacklist Status | F1: Final Determination | G1: Lookup Key (helper)
A2: {=INDEX('[1]Brand Family Territory (Enc)'!$A$2:$A$296,INT((ROW()-2)/10)+1)} -> Angry Orchard | B2: {=INDEX('Whitelist (Blackout Reverse)'!$B$1:$K$1,MOD(ROW()-2,10)+1)} -> BERGEN | C2: =VLOOKUP(A2,'[1]Brand Family Territory (Enc)'!$A$2:$B$296,2,FALSE) -> Core Market | D2: =IF(COUNTIFS('[1]Brand Family Territories (Enc)'!$B$2:$B$62,C2,'[1]Brand Family Territories (Enc)'!$C$2:$C$62,B2)>0,1,IF(AND(LEFT(B2,6)="MORRIS",COUNTIFS('[1]Brand Family Territories (Enc)'!$B$2:$B$62,C2,'[1]Brand Family Territories (Enc)'!$C$2:$C$62,"Morri")>0),"Unk",0)) -> 1 | E2: =IFERROR(INDEX('Blackout Brand Fam Areas (Enc)'!$D$6:$D$998,MATCH(UPPER(A2)&"|"&UPPER(B2),'Blackout Brand Fam Areas (Enc)'!$G$6:$G$998,0)),"No Match") -> No Match | F2: =IF(D2="Unk","Ambiguous (Source Truncated)",IF(E2="Inactive","THEM",IF(D2=1,"US",IF(D2="N/A","No Territory Data","THEM")))) -> US | G2: =A2&"|"&B2 -> Angry Orchard|BERGEN
A3: {=INDEX('[1]Brand Family Territory (Enc)'!$A$2:$A$296,INT((ROW()-2)/10)+1)} -> Angry Orchard | B3: {=INDEX('Whitelist (Blackout Reverse)'!$B$1:$K$1,MOD(ROW()-2,10)+1)} -> PASSAIC | C3: =VLOOKUP(A3,'[1]Brand Family Territory (Enc)'!$A$2:$B$296,2,FALSE) -> Core Market | D3: =IF(COUNTIFS('[1]Brand Family Territories (Enc)'!$B$2:$B$62,C3,'[1]Brand Family Territories (Enc)'!$C$2:$C$62,B3)>0,1,IF(AND(LEFT(B3,6)="MORRIS",COUNTIFS('[1]Brand Family Territories (Enc)'!$B$2:$B$62,C3,'[1]Brand Family Territories (Enc)'!$C$2:$C$62,"Morri")>0),"Unk",0)) -> 1 | E3: =IFERROR(INDEX('Blackout Brand Fam Areas (Enc)'!$D$6:$D$998,MATCH(UPPER(A3)&"|"&UPPER(B3),'Blackout Brand Fam Areas (Enc)'!$G$6:$G$998,0)),"No Match") -> No Match | F3: =IF(D3="Unk","Ambiguous (Source Truncated)",IF(E3="Inactive","THEM",IF(D3=1,"US",IF(D3="N/A","No Territory Data","THEM")))) -> US | G3: =A3&"|"&B3 -> Angry Orchard|PASSAIC
A4: {=INDEX('[1]Brand Family Territory (Enc)'!$A$2:$A$296,INT((ROW()-2)/10)+1)} -> Angry Orchard | B4: {=INDEX('Whitelist (Blackout Reverse)'!$B$1:$K$1,MOD(ROW()-2,10)+1)} -> PASSAIC-FF | C4: =VLOOKUP(A4,'[1]Brand Family Territory (Enc)'!$A$2:$B$296,2,FALSE) -> Core Market | D4: =IF(COUNTIFS('[1]Brand Family Territories (Enc)'!$B$2:$B$62,C4,'[1]Brand Family Territories (Enc)'!$C$2:$C$62,B4)>0,1,IF(AND(LEFT(B4,6)="MORRIS",COUNTIFS('[1]Brand Family Territories (Enc)'!$B$2:$B$62,C4,'[1]Brand Family Territories (Enc)'!$C$2:$C$62,"Morri")>0),"Unk",0)) -> 1 | E4: =IFERROR(INDEX('Blackout Brand Fam Areas (Enc)'!$D$6:$D$998,MATCH(UPPER(A4)&"|"&UPPER(B4),'Blackout Brand Fam Areas (Enc)'!$G$6:$G$998,0)),"No Match") -> No Match | F4: =IF(D4="Unk","Ambiguous (Source Truncated)",IF(E4="Inactive","THEM",IF(D4=1,"US",IF(D4="N/A","No Territory Data","THEM")))) -> US | G4: =A4&"|"&B4 -> Angry Orchard|PASSAIC-FF
A5: {=INDEX('[1]Brand Family Territory (Enc)'!$A$2:$A$296,INT((ROW()-2)/10)+1)} -> Angry Orchard | B5: {=INDEX('Whitelist (Blackout Reverse)'!$B$1:$K$1,MOD(ROW()-2,10)+1)} -> ESSEX | C5: =VLOOKUP(A5,'[1]Brand Family Territory (Enc)'!$A$2:$B$296,2,FALSE) -> Core Market | D5: =IF(COUNTIFS('[1]Brand Family Territories (Enc)'!$B$2:$B$62,C5,'[1]Brand Family Territories (Enc)'!$C$2:$C$62,B5)>0,1,IF(AND(LEFT(B5,6)="MORRIS",COUNTIFS('[1]Brand Family Territories (Enc)'!$B$2:$B$62,C5,'[1]Brand Family Territories (Enc)'!$C$2:$C$62,"Morri")>0),"Unk",0)) -> 0 | E5: =IFERROR(INDEX('Blackout Brand Fam Areas (Enc)'!$D$6:$D$998,MATCH(UPPER(A5)&"|"&UPPER(B5),'Blackout Brand Fam Areas (Enc)'!$G$6:$G$998,0)),"No Match") -> Inactive | F5: =IF(D5="Unk","Ambiguous (Source Truncated)",IF(E5="Inactive","THEM",IF(D5=1,"US",IF(D5="N/A","No Territory Data","THEM")))) -> THEM | G5: =A5&"|"&B5 -> Angry Orchard|ESSEX
A6: {=INDEX('[1]Brand Family Territory (Enc)'!$A$2:$A$296,INT((ROW()-2)/10)+1)} -> Angry Orchard | B6: {=INDEX('Whitelist (Blackout Reverse)'!$B$1:$K$1,MOD(ROW()-2,10)+1)} -> HUDSON | C6: =VLOOKUP(A6,'[1]Brand Family Territory (Enc)'!$A$2:$B$296,2,FALSE) -> Core Market | D6: =IF(COUNTIFS('[1]Brand Family Territories (Enc)'!$B$2:$B$62,C6,'[1]Brand Family Territories (Enc)'!$C$2:$C$62,B6)>0,1,IF(AND(LEFT(B6,6)="MORRIS",COUNTIFS('[1]Brand Family Territories (Enc)'!$B$2:$B$62,C6,'[1]Brand Family Territories (Enc)'!$C$2:$C$62,"Morri")>0),"Unk",0)) -> 0 | E6: =IFERROR(INDEX('Blackout Brand Fam Areas (Enc)'!$D$6:$D$998,MATCH(UPPER(A6)&"|"&UPPER(B6),'Blackout Brand Fam Areas (Enc)'!$G$6:$G$998,0)),"No Match") -> Inactive | F6: =IF(D6="Unk","Ambiguous (Source Truncated)",IF(E6="Inactive","THEM",IF(D6=1,"US",IF(D6="N/A","No Territory Data","THEM")))) -> THEM | G6: =A6&"|"&B6 -> Angry Orchard|HUDSON
A7: {=INDEX('[1]Brand Family Territory (Enc)'!$A$2:$A$296,INT((ROW()-2)/10)+1)} -> Angry Orchard | B7: {=INDEX('Whitelist (Blackout Reverse)'!$B$1:$K$1,MOD(ROW()-2,10)+1)} -> UNION | C7: =VLOOKUP(A7,'[1]Brand Family Territory (Enc)'!$A$2:$B$296,2,FALSE) -> Core Market | D7: =IF(COUNTIFS('[1]Brand Family Territories (Enc)'!$B$2:$B$62,C7,'[1]Brand Family Territories (Enc)'!$C$2:$C$62,B7)>0,1,IF(AND(LEFT(B7,6)="MORRIS",COUNTIFS('[1]Brand Family Territories (Enc)'!$B$2:$B$62,C7,'[1]Brand Family Territories (Enc)'!$C$2:$C$62,"Morri")>0),"Unk",0)) -> 0 | E7: =IFERROR(INDEX('Blackout Brand Fam Areas (Enc)'!$D$6:$D$998,MATCH(UPPER(A7)&"|"&UPPER(B7),'Blackout Brand Fam Areas (Enc)'!$G$6:$G$998,0)),"No Match") -> Inactive | F7: =IF(D7="Unk","Ambiguous (Source Truncated)",IF(E7="Inactive","THEM",IF(D7=1,"US",IF(D7="N/A","No Territory Data","THEM")))) -> THEM | G7: =A7&"|"&B7 -> Angry Orchard|UNION
A8: {=INDEX('[1]Brand Family Territory (Enc)'!$A$2:$A$296,INT((ROW()-2)/10)+1)} -> Angry Orchard | B8: {=INDEX('Whitelist (Blackout Reverse)'!$B$1:$K$1,MOD(ROW()-2,10)+1)} -> SUSSEX | C8: =VLOOKUP(A8,'[1]Brand Family Territory (Enc)'!$A$2:$B$296,2,FALSE) -> Core Market | D8: =IF(COUNTIFS('[1]Brand Family Territories (Enc)'!$B$2:$B$62,C8,'[1]Brand Family Territories (Enc)'!$C$2:$C$62,B8)>0,1,IF(AND(LEFT(B8,6)="MORRIS",COUNTIFS('[1]Brand Family Territories (Enc)'!$B$2:$B$62,C8,'[1]Brand Family Territories (Enc)'!$C$2:$C$62,"Morri")>0),"Unk",0)) -> 1 | E8: =IFERROR(INDEX('Blackout Brand Fam Areas (Enc)'!$D$6:$D$998,MATCH(UPPER(A8)&"|"&UPPER(B8),'Blackout Brand Fam Areas (Enc)'!$G$6:$G$998,0)),"No Match") -> No Match | F8: =IF(D8="Unk","Ambiguous (Source Truncated)",IF(E8="Inactive","THEM",IF(D8=1,"US",IF(D8="N/A","No Territory Data","THEM")))) -> US | G8: =A8&"|"&B8 -> Angry Orchard|SUSSEX
A9: {=INDEX('[1]Brand Family Territory (Enc)'!$A$2:$A$296,INT((ROW()-2)/10)+1)} -> Angry Orchard | B9: {=INDEX('Whitelist (Blackout Reverse)'!$B$1:$K$1,MOD(ROW()-2,10)+1)} -> MORRIS 1 | C9: =VLOOKUP(A9,'[1]Brand Family Territory (Enc)'!$A$2:$B$296,2,FALSE) -> Core Market | D9: =IF(COUNTIFS('[1]Brand Family Territories (Enc)'!$B$2:$B$62,C9,'[1]Brand Family Territories (Enc)'!$C$2:$C$62,B9)>0,1,IF(AND(LEFT(B9,6)="MORRIS",COUNTIFS('[1]Brand Family Territories (Enc)'!$B$2:$B$62,C9,'[1]Brand Family Territories (Enc)'!$C$2:$C$62,"Morri")>0),"Unk",0)) -> 1 | E9: =IFERROR(INDEX('Blackout Brand Fam Areas (Enc)'!$D$6:$D$998,MATCH(UPPER(A9)&"|"&UPPER(B9),'Blackout Brand Fam Areas (Enc)'!$G$6:$G$998,0)),"No Match") -> No Match | F9: =IF(D9="Unk","Ambiguous (Source Truncated)",IF(E9="Inactive","THEM",IF(D9=1,"US",IF(D9="N/A","No Territory Data","THEM")))) -> US | G9: =A9&"|"&B9 -> Angry Orchard|MORRIS 1
A10: {=INDEX('[1]Brand Family Territory (Enc)'!$A$2:$A$296,INT((ROW()-2)/10)+1)} -> Angry Orchard | B10: {=INDEX('Whitelist (Blackout Reverse)'!$B$1:$K$1,MOD(ROW()-2,10)+1)} -> MORRIS 2 | C10: =VLOOKUP(A10,'[1]Brand Family Territory (Enc)'!$A$2:$B$296,2,FALSE) -> Core Market | D10: =IF(COUNTIFS('[1]Brand Family Territories (Enc)'!$B$2:$B$62,C10,'[1]Brand Family Territories (Enc)'!$C$2:$C$62,B10)>0,1,IF(AND(LEFT(B10,6)="MORRIS",COUNTIFS('[1]Brand Family Territories (Enc)'!$B$2:$B$62,C10,'[1]Brand Family Territories (Enc)'!$C$2:$C$62,"Morri")>0),"Unk",0)) -> 0 | E10: =IFERROR(INDEX('Blackout Brand Fam Areas (Enc)'!$D$6:$D$998,MATCH(UPPER(A10)&"|"&UPPER(B10),'Blackout Brand Fam Areas (Enc)'!$G$6:$G$998,0)),"No Match") -> Inactive | F10: =IF(D10="Unk","Ambiguous (Source Truncated)",IF(E10="Inactive","THEM",IF(D10=1,"US",IF(D10="N/A","No Territory Data","THEM")))) -> THEM | G10: =A10&"|"&B10 -> Angry Orchard|MORRIS 2
A11: {=INDEX('[1]Brand Family Territory (Enc)'!$A$2:$A$296,INT((ROW()-2)/10)+1)} -> Angry Orchard | B11: {=INDEX('Whitelist (Blackout Reverse)'!$B$1:$K$1,MOD(ROW()-2,10)+1)} -> MORRIS 3 | C11: =VLOOKUP(A11,'[1]Brand Family Territory (Enc)'!$A$2:$B$296,2,FALSE) -> Core Market | D11: =IF(COUNTIFS('[1]Brand Family Territories (Enc)'!$B$2:$B$62,C11,'[1]Brand Family Territories (Enc)'!$C$2:$C$62,B11)>0,1,IF(AND(LEFT(B11,6)="MORRIS",COUNTIFS('[1]Brand Family Territories (Enc)'!$B$2:$B$62,C11,'[1]Brand Family Territories (Enc)'!$C$2:$C$62,"Morri")>0),"Unk",0)) -> 1 | E11: =IFERROR(INDEX('Blackout Brand Fam Areas (Enc)'!$D$6:$D$998,MATCH(UPPER(A11)&"|"&UPPER(B11),'Blackout Brand Fam Areas (Enc)'!$G$6:$G$998,0)),"No Match") -> No Match | F11: =IF(D11="Unk","Ambiguous (Source Truncated)",IF(E11="Inactive","THEM",IF(D11=1,"US",IF(D11="N/A","No Territory Data","THEM")))) -> US | G11: =A11&"|"&B11 -> Angry Orchard|MORRIS 3
A12: {=INDEX('[1]Brand Family Territory (Enc)'!$A$2:$A$296,INT((ROW()-2)/10)+1)} -> Aguila | B12: {=INDEX('Whitelist (Blackout Reverse)'!$B$1:$K$1,MOD(ROW()-2,10)+1)} -> BERGEN | C12: =VLOOKUP(A12,'[1]Brand Family Territory (Enc)'!$A$2:$B$296,2,FALSE) -> Core Market | D12: =IF(COUNTIFS('[1]Brand Family Territories (Enc)'!$B$2:$B$62,C12,'[1]Brand Family Territories (Enc)'!$C$2:$C$62,B12)>0,1,IF(AND(LEFT(B12,6)="MORRIS",COUNTIFS('[1]Brand Family Territories (Enc)'!$B$2:$B$62,C12,'[1]Brand Family Territories (Enc)'!$C$2:$C$62,"Morri")>0),"Unk",0)) -> 1 | E12: =IFERROR(INDEX('Blackout Brand Fam Areas (Enc)'!$D$6:$D$998,MATCH(UPPER(A12)&"|"&UPPER(B12),'Blackout Brand Fam Areas (Enc)'!$G$6:$G$998,0)),"No Match") -> No Match | F12: =IF(D12="Unk","Ambiguous (Source Truncated)",IF(E12="Inactive","THEM",IF(D12=1,"US",IF(D12="N/A","No Territory Data","THEM")))) -> US | G12: =A12&"|"&B12 -> Aguila|BERGEN
A13: {=INDEX('[1]Brand Family Territory (Enc)'!$A$2:$A$296,INT((ROW()-2)/10)+1)} -> Aguila | B13: {=INDEX('Whitelist (Blackout Reverse)'!$B$1:$K$1,MOD(ROW()-2,10)+1)} -> PASSAIC | C13: =VLOOKUP(A13,'[1]Brand Family Territory (Enc)'!$A$2:$B$296,2,FALSE) -> Core Market | D13: =IF(COUNTIFS('[1]Brand Family Territories (Enc)'!$B$2:$B$62,C13,'[1]Brand Family Territories (Enc)'!$C$2:$C$62,B13)>0,1,IF(AND(LEFT(B13,6)="MORRIS",COUNTIFS('[1]Brand Family Territories (Enc)'!$B$2:$B$62,C13,'[1]Brand Family Territories (Enc)'!$C$2:$C$62,"Morri")>0),"Unk",0)) -> 1 | E13: =IFERROR(INDEX('Blackout Brand Fam Areas (Enc)'!$D$6:$D$998,MATCH(UPPER(A13)&"|"&UPPER(B13),'Blackout Brand Fam Areas (Enc)'!$G$6:$G$998,0)),"No Match") -> No Match | F13: =IF(D13="Unk","Ambiguous (Source Truncated)",IF(E13="Inactive","THEM",IF(D13=1,"US",IF(D13="N/A","No Territory Data","THEM")))) -> US | G13: =A13&"|"&B13 -> Aguila|PASSAIC
... A2951: {=INDEX('[1]Brand Family Territory (Enc)'!$A$2:$A$296,INT((ROW()-2)/10)+1)} -> 2 Canos | B2951: {=INDEX('Whitelist (Blackout Reverse)'!$B$1:$K$1,MOD(ROW()-2,10)+1)} -> MORRIS 3 | C2951: =VLOOKUP(A2951,'[1]Brand Family Territory (Enc)'!$A$2:$B$296,2,FALSE) -> All Counties | D2951: =IF(COUNTIFS('[1]Brand Family Territories (Enc)'!$B$2:$B$62,C2951,'[1]Brand Family Territories (Enc)'!$C$2:$C$62,B2951)>0,1,IF(AND(LEFT(B2951,6)="MORRIS",COUNTIFS('[1]Brand Family Territories (Enc)'!$B$2:$B$62,C2951,'[1]Brand Family Territories (Enc)'!$C$2:$C$62,"Morri")>0),"Unk",0)) -> 1 | E2951: =IFERROR(INDEX('Blackout Brand Fam Areas (Enc)'!$D$6:$D$998,MATCH(UPPER(A2951)&"|"&UPPER(B2951),'Blackout Brand Fam Areas (Enc)'!$G$6:$G$998,0)),"No Match") -> No Match | F2951: =IF(D2951="Unk","Ambiguous (Source Truncated)",IF(E2951="Inactive","THEM",IF(D2951=1,"US",IF(D2951="N/A","No Territory Data","THEM")))) -> US | G2951: =A2951&"|"&B2951 -> 2 Canos|MORRIS 3
A2952: Miller High Life | B2952: {=INDEX('Whitelist (Blackout Reverse)'!$B$1:$K$1,MOD(ROW()-2952,10)+1)} -> BERGEN | C2952: (Blackout list only) | D2952: =IF(INDEX('Whitelist (Blackout Reverse)'!$B$2:$K$300,MATCH($A2952,'Whitelist (Blackout Reverse)'!$A$2:$A$300,0),MATCH($B2952,'Whitelist (Blackout Reverse)'!$B$1:$K$1,0))="CAN SELL",1,0) -> 1 | E2952: =IF(D2952=0,"Inactive","No Match") -> No Match | F2952: =IF(D2952=1,"US","THEM") -> US | G2952: =A2952&"|"&B2952 -> Miller High Life|BERGEN
A2953: Miller High Life | B2953: {=INDEX('Whitelist (Blackout Reverse)'!$B$1:$K$1,MOD(ROW()-2952,10)+1)} -> PASSAIC | C2953: (Blackout list only) | D2953: =IF(INDEX('Whitelist (Blackout Reverse)'!$B$2:$K$300,MATCH($A2953,'Whitelist (Blackout Reverse)'!$A$2:$A$300,0),MATCH($B2953,'Whitelist (Blackout Reverse)'!$B$1:$K$1,0))="CAN SELL",1,0) -> 1 | E2953: =IF(D2953=0,"Inactive","No Match") -> No Match | F2953: =IF(D2953=1,"US","THEM") -> US | G2953: =A2953&"|"&B2953 -> Miller High Life|PASSAIC
A2954: Miller High Life | B2954: {=INDEX('Whitelist (Blackout Reverse)'!$B$1:$K$1,MOD(ROW()-2952,10)+1)} -> PASSAIC-FF | C2954: (Blackout list only) | D2954: =IF(INDEX('Whitelist (Blackout Reverse)'!$B$2:$K$300,MATCH($A2954,'Whitelist (Blackout Reverse)'!$A$2:$A$300,0),MATCH($B2954,'Whitelist (Blackout Reverse)'!$B$1:$K$1,0))="CAN SELL",1,0) -> 1 | E2954: =IF(D2954=0,"Inactive","No Match") -> No Match | F2954: =IF(D2954=1,"US","THEM") -> US | G2954: =A2954&"|"&B2954 -> Miller High Life|PASSAIC-FF
A2955: Miller High Life | B2955: {=INDEX('Whitelist (Blackout Reverse)'!$B$1:$K$1,MOD(ROW()-2952,10)+1)} -> ESSEX | C2955: (Blackout list only) | D2955: =IF(INDEX('Whitelist (Blackout Reverse)'!$B$2:$K$300,MATCH($A2955,'Whitelist (Blackout Reverse)'!$A$2:$A$300,0),MATCH($B2955,'Whitelist (Blackout Reverse)'!$B$1:$K$1,0))="CAN SELL",1,0) -> 0 | E2955: =IF(D2955=0,"Inactive","No Match") -> Inactive | F2955: =IF(D2955=1,"US","THEM") -> THEM | G2955: =A2955&"|"&B2955 -> Miller High Life|ESSEX
A2956: Miller High Life | B2956: {=INDEX('Whitelist (Blackout Reverse)'!$B$1:$K$1,MOD(ROW()-2952,10)+1)} -> HUDSON | C2956: (Blackout list only) | D2956: =IF(INDEX('Whitelist (Blackout Reverse)'!$B$2:$K$300,MATCH($A2956,'Whitelist (Blackout Reverse)'!$A$2:$A$300,0),MATCH($B2956,'Whitelist (Blackout Reverse)'!$B$1:$K$1,0))="CAN SELL",1,0) -> 0 | E2956: =IF(D2956=0,"Inactive","No Match") -> Inactive | F2956: =IF(D2956=1,"US","THEM") -> THEM | G2956: =A2956&"|"&B2956 -> Miller High Life|HUDSON
A2957: Miller High Life | B2957: {=INDEX('Whitelist (Blackout Reverse)'!$B$1:$K$1,MOD(ROW()-2952,10)+1)} -> UNION | C2957: (Blackout list only) | D2957: =IF(INDEX('Whitelist (Blackout Reverse)'!$B$2:$K$300,MATCH($A2957,'Whitelist (Blackout Reverse)'!$A$2:$A$300,0),MATCH($B2957,'Whitelist (Blackout Reverse)'!$B$1:$K$1,0))="CAN SELL",1,0) -> 0 | E2957: =IF(D2957=0,"Inactive","No Match") -> Inactive | F2957: =IF(D2957=1,"US","THEM") -> THEM | G2957: =A2957&"|"&B2957 -> Miller High Life|UNION
A2958: Miller High Life | B2958: {=INDEX('Whitelist (Blackout Reverse)'!$B$1:$K$1,MOD(ROW()-2952,10)+1)} -> SUSSEX | C2958: (Blackout list only) | D2958: =IF(INDEX('Whitelist (Blackout Reverse)'!$B$2:$K$300,MATCH($A2958,'Whitelist (Blackout Reverse)'!$A$2:$A$300,0),MATCH($B2958,'Whitelist (Blackout Reverse)'!$B$1:$K$1,0))="CAN SELL",1,0) -> 1 | E2958: =IF(D2958=0,"Inactive","No Match") -> No Match | F2958: =IF(D2958=1,"US","THEM") -> US | G2958: =A2958&"|"&B2958 -> Miller High Life|SUSSEX
A2959: Miller High Life | B2959: {=INDEX('Whitelist (Blackout Reverse)'!$B$1:$K$1,MOD(ROW()-2952,10)+1)} -> MORRIS 1 | C2959: (Blackout list only) | D2959: =IF(INDEX('Whitelist (Blackout Reverse)'!$B$2:$K$300,MATCH($A2959,'Whitelist (Blackout Reverse)'!$A$2:$A$300,0),MATCH($B2959,'Whitelist (Blackout Reverse)'!$B$1:$K$1,0))="CAN SELL",1,0) -> 1 | E2959: =IF(D2959=0,"Inactive","No Match") -> No Match | F2959: =IF(D2959=1,"US","THEM") -> US | G2959: =A2959&"|"&B2959 -> Miller High Life|MORRIS 1
A2960: Miller High Life | B2960: {=INDEX('Whitelist (Blackout Reverse)'!$B$1:$K$1,MOD(ROW()-2952,10)+1)} -> MORRIS 2 | C2960: (Blackout list only) | D2960: =IF(INDEX('Whitelist (Blackout Reverse)'!$B$2:$K$300,MATCH($A2960,'Whitelist (Blackout Reverse)'!$A$2:$A$300,0),MATCH($B2960,'Whitelist (Blackout Reverse)'!$B$1:$K$1,0))="CAN SELL",1,0) -> 0 | E2960: =IF(D2960=0,"Inactive","No Match") -> Inactive | F2960: =IF(D2960=1,"US","THEM") -> THEM | G2960: =A2960&"|"&B2960 -> Miller High Life|MORRIS 2
A2961: Miller High Life | B2961: {=INDEX('Whitelist (Blackout Reverse)'!$B$1:$K$1,MOD(ROW()-2952,10)+1)} -> MORRIS 3 | C2961: (Blackout list only) | D2961: =IF(INDEX('Whitelist (Blackout Reverse)'!$B$2:$K$300,MATCH($A2961,'Whitelist (Blackout Reverse)'!$A$2:$A$300,0),MATCH($B2961,'Whitelist (Blackout Reverse)'!$B$1:$K$1,0))="CAN SELL",1,0) -> 1 | E2961: =IF(D2961=0,"Inactive","No Match") -> No Match | F2961: =IF(D2961=1,"US","THEM") -> US | G2961: =A2961&"|"&B2961 -> Miller High Life|MORRIS 3
A2962: Sea Dog | B2962: {=INDEX('Whitelist (Blackout Reverse)'!$B$1:$K$1,MOD(ROW()-2952,10)+1)} -> BERGEN | C2962: (Blackout list only) | D2962: =IF(INDEX('Whitelist (Blackout Reverse)'!$B$2:$K$300,MATCH($A2962,'Whitelist (Blackout Reverse)'!$A$2:$A$300,0),MATCH($B2962,'Whitelist (Blackout Reverse)'!$B$1:$K$1,0))="CAN SELL",1,0) -> 1 | E2962: =IF(D2962=0,"Inactive","No Match") -> No Match | F2962: =IF(D2962=1,"US","THEM") -> US | G2962: =A2962&"|"&B2962 -> Sea Dog|BERGEN
A2963: Sea Dog | B2963: {=INDEX('Whitelist (Blackout Reverse)'!$B$1:$K$1,MOD(ROW()-2952,10)+1)} -> PASSAIC | C2963: (Blackout list only) | D2963: =IF(INDEX('Whitelist (Blackout Reverse)'!$B$2:$K$300,MATCH($A2963,'Whitelist (Blackout Reverse)'!$A$2:$A$300,0),MATCH($B2963,'Whitelist (Blackout Reverse)'!$B$1:$K$1,0))="CAN SELL",1,0) -> 1 | E2963: =IF(D2963=0,"Inactive","No Match") -> No Match | F2963: =IF(D2963=1,"US","THEM") -> US | G2963: =A2963&"|"&B2963 -> Sea Dog|PASSAIC
... A2971: Sea Dog | B2971: {=INDEX('Whitelist (Blackout Reverse)'!$B$1:$K$1,MOD(ROW()-2952,10)+1)} -> MORRIS 3 | C2971: (Blackout list only) | D2971: =IF(INDEX('Whitelist (Blackout Reverse)'!$B$2:$K$300,MATCH($A2971,'Whitelist (Blackout Reverse)'!$A$2:$A$300,0),MATCH($B2971,'Whitelist (Blackout Reverse)'!$B$1:$K$1,0))="CAN SELL",1,0) -> 0 | E2971: =IF(D2971=0,"Inactive","No Match") -> Inactive | F2971: =IF(D2971=1,"US","THEM") -> THEM | G2971: =A2971&"|"&B2971 -> Sea Dog|MORRIS 3
A2972: Industrial Arts | B2972: BERGEN | C2972: (User ruling 2026-07-22 - distribute in all counties; no Encompass territory entry) | D2972: =IF(COUNTIFS('Blackout Brand Fam Areas (Enc)'!$B$6:$B$998,A2972,'Blackout Brand Fam Areas (Enc)'!$C$6:$C$998,B2972,'Blackout Brand Fam Areas (Enc)'!$D$6:$D$998,"Inactive")>0,0,1) -> 1 | E2972: =IF(D2972=0,"Inactive","No Match") -> No Match | F2972: =IF(D2972=1,"US","THEM") -> US | G2972: =A2972&"|"&B2972 -> Industrial Arts|BERGEN
A2973: Industrial Arts | B2973: PASSAIC | C2973: (User ruling 2026-07-22 - distribute in all counties; no Encompass territory entry) | D2973: =IF(COUNTIFS('Blackout Brand Fam Areas (Enc)'!$B$6:$B$998,A2973,'Blackout Brand Fam Areas (Enc)'!$C$6:$C$998,B2973,'Blackout Brand Fam Areas (Enc)'!$D$6:$D$998,"Inactive")>0,0,1) -> 1 | E2973: =IF(D2973=0,"Inactive","No Match") -> No Match | F2973: =IF(D2973=1,"US","THEM") -> US | G2973: =A2973&"|"&B2973 -> Industrial Arts|PASSAIC
A2974: Industrial Arts | B2974: PASSAIC-FF | C2974: (User ruling 2026-07-22 - distribute in all counties; no Encompass territory entry) | D2974: =IF(COUNTIFS('Blackout Brand Fam Areas (Enc)'!$B$6:$B$998,A2974,'Blackout Brand Fam Areas (Enc)'!$C$6:$C$998,B2974,'Blackout Brand Fam Areas (Enc)'!$D$6:$D$998,"Inactive")>0,0,1) -> 1 | E2974: =IF(D2974=0,"Inactive","No Match") -> No Match | F2974: =IF(D2974=1,"US","THEM") -> US | G2974: =A2974&"|"&B2974 -> Industrial Arts|PASSAIC-FF
A2975: Industrial Arts | B2975: ESSEX | C2975: (User ruling 2026-07-22 - distribute in all counties; no Encompass territory entry) | D2975: =IF(COUNTIFS('Blackout Brand Fam Areas (Enc)'!$B$6:$B$998,A2975,'Blackout Brand Fam Areas (Enc)'!$C$6:$C$998,B2975,'Blackout Brand Fam Areas (Enc)'!$D$6:$D$998,"Inactive")>0,0,1) -> 1 | E2975: =IF(D2975=0,"Inactive","No Match") -> No Match | F2975: =IF(D2975=1,"US","THEM") -> US | G2975: =A2975&"|"&B2975 -> Industrial Arts|ESSEX
A2976: Industrial Arts | B2976: HUDSON | C2976: (User ruling 2026-07-22 - distribute in all counties; no Encompass territory entry) | D2976: =IF(COUNTIFS('Blackout Brand Fam Areas (Enc)'!$B$6:$B$998,A2976,'Blackout Brand Fam Areas (Enc)'!$C$6:$C$998,B2976,'Blackout Brand Fam Areas (Enc)'!$D$6:$D$998,"Inactive")>0,0,1) -> 1 | E2976: =IF(D2976=0,"Inactive","No Match") -> No Match | F2976: =IF(D2976=1,"US","THEM") -> US | G2976: =A2976&"|"&B2976 -> Industrial Arts|HUDSON
A2977: Industrial Arts | B2977: UNION | C2977: (User ruling 2026-07-22 - distribute in all counties; no Encompass territory entry) | D2977: =IF(COUNTIFS('Blackout Brand Fam Areas (Enc)'!$B$6:$B$998,A2977,'Blackout Brand Fam Areas (Enc)'!$C$6:$C$998,B2977,'Blackout Brand Fam Areas (Enc)'!$D$6:$D$998,"Inactive")>0,0,1) -> 1 | E2977: =IF(D2977=0,"Inactive","No Match") -> No Match | F2977: =IF(D2977=1,"US","THEM") -> US | G2977: =A2977&"|"&B2977 -> Industrial Arts|UNION
A2978: Industrial Arts | B2978: SUSSEX | C2978: (User ruling 2026-07-22 - distribute in all counties; no Encompass territory entry) | D2978: =IF(COUNTIFS('Blackout Brand Fam Areas (Enc)'!$B$6:$B$998,A2978,'Blackout Brand Fam Areas (Enc)'!$C$6:$C$998,B2978,'Blackout Brand Fam Areas (Enc)'!$D$6:$D$998,"Inactive")>0,0,1) -> 1 | E2978: =IF(D2978=0,"Inactive","No Match") -> No Match | F2978: =IF(D2978=1,"US","THEM") -> US | G2978: =A2978&"|"&B2978 -> Industrial Arts|SUSSEX
A2979: Industrial Arts | B2979: MORRIS 1 | C2979: (User ruling 2026-07-22 - distribute in all counties; no Encompass territory entry) | D2979: =IF(COUNTIFS('Blackout Brand Fam Areas (Enc)'!$B$6:$B$998,A2979,'Blackout Brand Fam Areas (Enc)'!$C$6:$C$998,B2979,'Blackout Brand Fam Areas (Enc)'!$D$6:$D$998,"Inactive")>0,0,1) -> 1 | E2979: =IF(D2979=0,"Inactive","No Match") -> No Match | F2979: =IF(D2979=1,"US","THEM") -> US | G2979: =A2979&"|"&B2979 -> Industrial Arts|MORRIS 1
A2980: Industrial Arts | B2980: MORRIS 2 | C2980: (User ruling 2026-07-22 - distribute in all counties; no Encompass territory entry) | D2980: =IF(COUNTIFS('Blackout Brand Fam Areas (Enc)'!$B$6:$B$998,A2980,'Blackout Brand Fam Areas (Enc)'!$C$6:$C$998,B2980,'Blackout Brand Fam Areas (Enc)'!$D$6:$D$998,"Inactive")>0,0,1) -> 1 | E2980: =IF(D2980=0,"Inactive","No Match") -> No Match | F2980: =IF(D2980=1,"US","THEM") -> US | G2980: =A2980&"|"&B2980 -> Industrial Arts|MORRIS 2
A2981: Industrial Arts | B2981: MORRIS 3 | C2981: (User ruling 2026-07-22 - distribute in all counties; no Encompass territory entry) | D2981: =IF(COUNTIFS('Blackout Brand Fam Areas (Enc)'!$B$6:$B$998,A2981,'Blackout Brand Fam Areas (Enc)'!$C$6:$C$998,B2981,'Blackout Brand Fam Areas (Enc)'!$D$6:$D$998,"Inactive")>0,0,1) -> 1 | E2981: =IF(D2981=0,"Inactive","No Match") -> No Match | F2981: =IF(D2981=1,"US","THEM") -> US | G2981: =A2981&"|"&B2981 -> Industrial Arts|MORRIS 3
A2982: Other Half | B2982: BERGEN | C2982: (User ruling 2026-07-22 - distribute in all counties; no Encompass territory entry) | D2982: =IF(COUNTIFS('Blackout Brand Fam Areas (Enc)'!$B$6:$B$998,A2982,'Blackout Brand Fam Areas (Enc)'!$C$6:$C$998,B2982,'Blackout Brand Fam Areas (Enc)'!$D$6:$D$998,"Inactive")>0,0,1) -> 1 | E2982: =IF(D2982=0,"Inactive","No Match") -> No Match | F2982: =IF(D2982=1,"US","THEM") -> US | G2982: =A2982&"|"&B2982 -> Other Half|BERGEN
A2983: Other Half | B2983: PASSAIC | C2983: (User ruling 2026-07-22 - distribute in all counties; no Encompass territory entry) | D2983: =IF(COUNTIFS('Blackout Brand Fam Areas (Enc)'!$B$6:$B$998,A2983,'Blackout Brand Fam Areas (Enc)'!$C$6:$C$998,B2983,'Blackout Brand Fam Areas (Enc)'!$D$6:$D$998,"Inactive")>0,0,1) -> 1 | E2983: =IF(D2983=0,"Inactive","No Match") -> No Match | F2983: =IF(D2983=1,"US","THEM") -> US | G2983: =A2983&"|"&B2983 -> Other Half|PASSAIC
... A2991: Other Half | B2991: MORRIS 3 | C2991: (User ruling 2026-07-22 - distribute in all counties; no Encompass territory entry) | D2991: =IF(COUNTIFS('Blackout Brand Fam Areas (Enc)'!$B$6:$B$998,A2991,'Blackout Brand Fam Areas (Enc)'!$C$6:$C$998,B2991,'Blackout Brand Fam Areas (Enc)'!$D$6:$D$998,"Inactive")>0,0,1) -> 1 | E2991: =IF(D2991=0,"Inactive","No Match") -> No Match | F2991: =IF(D2991=1,"US","THEM") -> US | G2991: =A2991&"|"&B2991 -> Other Half|MORRIS 3

Sheet Master Matrix View
A1: Brand Family | B1: ='Whitelist (Blackout Reverse)'!B1 -> BERGEN | C1: ='Whitelist (Blackout Reverse)'!C1 -> PASSAIC | D1: ='Whitelist (Blackout Reverse)'!D1 -> PASSAIC-FF | E1: ='Whitelist (Blackout Reverse)'!E1 -> ESSEX | F1: ='Whitelist (Blackout Reverse)'!F1 -> HUDSON | G1: ='Whitelist (Blackout Reverse)'!G1 -> UNION | H1: ='Whitelist (Blackout Reverse)'!H1 -> SUSSEX | I1: ='Whitelist (Blackout Reverse)'!I1 -> MORRIS 1 | ... K1: ='Whitelist (Blackout Reverse)'!K1 -> MORRIS 3
A2: ='[1]Brand Family Territory (Enc)'!A2 -> Angry Orchard | B2: =IFERROR(INDEX('Master - US vs THEM'!$F$2:$F$2951,MATCH($A2&"|"&B$1,'Master - US vs THEM'!$G$2:$G$2951,0)),"") -> US | C2: =IFERROR(INDEX('Master - US vs THEM'!$F$2:$F$2951,MATCH($A2&"|"&C$1,'Master - US vs THEM'!$G$2:$G$2951,0)),"") -> US | D2: =IFERROR(INDEX('Master - US vs THEM'!$F$2:$F$2951,MATCH($A2&"|"&D$1,'Master - US vs THEM'!$G$2:$G$2951,0)),"") -> US | E2: =IFERROR(INDEX('Master - US vs THEM'!$F$2:$F$2951,MATCH($A2&"|"&E$1,'Master - US vs THEM'!$G$2:$G$2951,0)),"") -> THEM | F2: =IFERROR(INDEX('Master - US vs THEM'!$F$2:$F$2951,MATCH($A2&"|"&F$1,'Master - US vs THEM'!$G$2:$G$2951,0)),"") -> THEM | G2: =IFERROR(INDEX('Master - US vs THEM'!$F$2:$F$2951,MATCH($A2&"|"&G$1,'Master - US vs THEM'!$G$2:$G$2951,0)),"") -> THEM | H2: =IFERROR(INDEX('Master - US vs THEM'!$F$2:$F$2951,MATCH($A2&"|"&H$1,'Master - US vs THEM'!$G$2:$G$2951,0)),"") -> US | I2: =IFERROR(INDEX('Master - US vs THEM'!$F$2:$F$2951,MATCH($A2&"|"&I$1,'Master - US vs THEM'!$G$2:$G$2951,0)),"") -> US | ... K2: =IFERROR(INDEX('Master - US vs THEM'!$F$2:$F$2951,MATCH($A2&"|"&K$1,'Master - US vs THEM'!$G$2:$G$2951,0)),"") -> US
A3: ='[1]Brand Family Territory (Enc)'!A3 -> Aguila | B3: =IFERROR(INDEX('Master - US vs THEM'!$F$2:$F$2951,MATCH($A3&"|"&B$1,'Master - US vs THEM'!$G$2:$G$2951,0)),"") -> US | C3: =IFERROR(INDEX('Master - US vs THEM'!$F$2:$F$2951,MATCH($A3&"|"&C$1,'Master - US vs THEM'!$G$2:$G$2951,0)),"") -> US | D3: =IFERROR(INDEX('Master - US vs THEM'!$F$2:$F$2951,MATCH($A3&"|"&D$1,'Master - US vs THEM'!$G$2:$G$2951,0)),"") -> US | E3: =IFERROR(INDEX('Master - US vs THEM'!$F$2:$F$2951,MATCH($A3&"|"&E$1,'Master - US vs THEM'!$G$2:$G$2951,0)),"") -> THEM | F3: =IFERROR(INDEX('Master - US vs THEM'!$F$2:$F$2951,MATCH($A3&"|"&F$1,'Master - US vs THEM'!$G$2:$G$2951,0)),"") -> THEM | G3: =IFERROR(INDEX('Master - US vs THEM'!$F$2:$F$2951,MATCH($A3&"|"&G$1,'Master - US vs THEM'!$G$2:$G$2951,0)),"") -> THEM | H3: =IFERROR(INDEX('Master - US vs THEM'!$F$2:$F$2951,MATCH($A3&"|"&H$1,'Master - US vs THEM'!$G$2:$G$2951,0)),"") -> US | I3: =IFERROR(INDEX('Master - US vs THEM'!$F$2:$F$2951,MATCH($A3&"|"&I$1,'Master - US vs THEM'!$G$2:$G$2951,0)),"") -> US | ... K3: =IFERROR(INDEX('Master - US vs THEM'!$F$2:$F$2951,MATCH($A3&"|"&K$1,'Master - US vs THEM'!$G$2:$G$2951,0)),"") -> US
A4: ='[1]Brand Family Territory (Enc)'!A4 -> Arnold Palmer | B4: =IFERROR(INDEX('Master - US vs THEM'!$F$2:$F$2951,MATCH($A4&"|"&B$1,'Master - US vs THEM'!$G$2:$G$2951,0)),"") -> US | C4: =IFERROR(INDEX('Master - US vs THEM'!$F$2:$F$2951,MATCH($A4&"|"&C$1,'Master - US vs THEM'!$G$2:$G$2951,0)),"") -> US | D4: =IFERROR(INDEX('Master - US vs THEM'!$F$2:$F$2951,MATCH($A4&"|"&D$1,'Master - US vs THEM'!$G$2:$G$2951,0)),"") -> US | E4: =IFERROR(INDEX('Master - US vs THEM'!$F$2:$F$2951,MATCH($A4&"|"&E$1,'Master - US vs THEM'!$G$2:$G$2951,0)),"") -> THEM | F4: =IFERROR(INDEX('Master - US vs THEM'!$F$2:$F$2951,MATCH($A4&"|"&F$1,'Master - US vs THEM'!$G$2:$G$2951,0)),"") -> THEM | G4: =IFERROR(INDEX('Master - US vs THEM'!$F$2:$F$2951,MATCH($A4&"|"&G$1,'Master - US vs THEM'!$G$2:$G$2951,0)),"") -> THEM | H4: =IFERROR(INDEX('Master - US vs THEM'!$F$2:$F$2951,MATCH($A4&"|"&H$1,'Master - US vs THEM'!$G$2:$G$2951,0)),"") -> US | I4: =IFERROR(INDEX('Master - US vs THEM'!$F$2:$F$2951,MATCH($A4&"|"&I$1,'Master - US vs THEM'!$G$2:$G$2951,0)),"") -> US | ... K4: =IFERROR(INDEX('Master - US vs THEM'!$F$2:$F$2951,MATCH($A4&"|"&K$1,'Master - US vs THEM'!$G$2:$G$2951,0)),"") -> US
A5: ='[1]Brand Family Territory (Enc)'!A5 -> Athletic | B5: =IFERROR(INDEX('Master - US vs THEM'!$F$2:$F$2951,MATCH($A5&"|"&B$1,'Master - US vs THEM'!$G$2:$G$2951,0)),"") -> US | C5: =IFERROR(INDEX('Master - US vs THEM'!$F$2:$F$2951,MATCH($A5&"|"&C$1,'Master - US vs THEM'!$G$2:$G$2951,0)),"") -> US | D5: =IFERROR(INDEX('Master - US vs THEM'!$F$2:$F$2951,MATCH($A5&"|"&D$1,'Master - US vs THEM'!$G$2:$G$2951,0)),"") -> US | E5: =IFERROR(INDEX('Master - US vs THEM'!$F$2:$F$2951,MATCH($A5&"|"&E$1,'Master - US vs THEM'!$G$2:$G$2951,0)),"") -> THEM | F5: =IFERROR(INDEX('Master - US vs THEM'!$F$2:$F$2951,MATCH($A5&"|"&F$1,'Master - US vs THEM'!$G$2:$G$2951,0)),"") -> THEM | G5: =IFERROR(INDEX('Master - US vs THEM'!$F$2:$F$2951,MATCH($A5&"|"&G$1,'Master - US vs THEM'!$G$2:$G$2951,0)),"") -> THEM | H5: =IFERROR(INDEX('Master - US vs THEM'!$F$2:$F$2951,MATCH($A5&"|"&H$1,'Master - US vs THEM'!$G$2:$G$2951,0)),"") -> US | I5: =IFERROR(INDEX('Master - US vs THEM'!$F$2:$F$2951,MATCH($A5&"|"&I$1,'Master - US vs THEM'!$G$2:$G$2951,0)),"") -> US | ... K5: =IFERROR(INDEX('Master - US vs THEM'!$F$2:$F$2951,MATCH($A5&"|"&K$1,'Master - US vs THEM'!$G$2:$G$2951,0)),"") -> US
A6: ='[1]Brand Family Territory (Enc)'!A6 -> Bardstown Bourbon | B6: =IFERROR(INDEX('Master - US vs THEM'!$F$2:$F$2951,MATCH($A6&"|"&B$1,'Master - US vs THEM'!$G$2:$G$2951,0)),"") -> US | C6: =IFERROR(INDEX('Master - US vs THEM'!$F$2:$F$2951,MATCH($A6&"|"&C$1,'Master - US vs THEM'!$G$2:$G$2951,0)),"") -> US | D6: =IFERROR(INDEX('Master - US vs THEM'!$F$2:$F$2951,MATCH($A6&"|"&D$1,'Master - US vs THEM'!$G$2:$G$2951,0)),"") -> US | E6: =IFERROR(INDEX('Master - US vs THEM'!$F$2:$F$2951,MATCH($A6&"|"&E$1,'Master - US vs THEM'!$G$2:$G$2951,0)),"") -> THEM | F6: =IFERROR(INDEX('Master - US vs THEM'!$F$2:$F$2951,MATCH($A6&"|"&F$1,'Master - US vs THEM'!$G$2:$G$2951,0)),"") -> THEM | G6: =IFERROR(INDEX('Master - US vs THEM'!$F$2:$F$2951,MATCH($A6&"|"&G$1,'Master - US vs THEM'!$G$2:$G$2951,0)),"") -> THEM | H6: =IFERROR(INDEX('Master - US vs THEM'!$F$2:$F$2951,MATCH($A6&"|"&H$1,'Master - US vs THEM'!$G$2:$G$2951,0)),"") -> US | I6: =IFERROR(INDEX('Master - US vs THEM'!$F$2:$F$2951,MATCH($A6&"|"&I$1,'Master - US vs THEM'!$G$2:$G$2951,0)),"") -> US | ... K6: =IFERROR(INDEX('Master - US vs THEM'!$F$2:$F$2951,MATCH($A6&"|"&K$1,'Master - US vs THEM'!$G$2:$G$2951,0)),"") -> US
A7: ='[1]Brand Family Territory (Enc)'!A7 -> Bell's | B7: =IFERROR(INDEX('Master - US vs THEM'!$F$2:$F$2951,MATCH($A7&"|"&B$1,'Master - US vs THEM'!$G$2:$G$2951,0)),"") -> US | C7: =IFERROR(INDEX('Master - US vs THEM'!$F$2:$F$2951,MATCH($A7&"|"&C$1,'Master - US vs THEM'!$G$2:$G$2951,0)),"") -> US | D7: =IFERROR(INDEX('Master - US vs THEM'!$F$2:$F$2951,MATCH($A7&"|"&D$1,'Master - US vs THEM'!$G$2:$G$2951,0)),"") -> US | E7: =IFERROR(INDEX('Master - US vs THEM'!$F$2:$F$2951,MATCH($A7&"|"&E$1,'Master - US vs THEM'!$G$2:$G$2951,0)),"") -> THEM | F7: =IFERROR(INDEX('Master - US vs THEM'!$F$2:$F$2951,MATCH($A7&"|"&F$1,'Master - US vs THEM'!$G$2:$G$2951,0)),"") -> THEM | G7: =IFERROR(INDEX('Master - US vs THEM'!$F$2:$F$2951,MATCH($A7&"|"&G$1,'Master - US vs THEM'!$G$2:$G$2951,0)),"") -> THEM | H7: =IFERROR(INDEX('Master - US vs THEM'!$F$2:$F$2951,MATCH($A7&"|"&H$1,'Master - US vs THEM'!$G$2:$G$2951,0)),"") -> US | I7: =IFERROR(INDEX('Master - US vs THEM'!$F$2:$F$2951,MATCH($A7&"|"&I$1,'Master - US vs THEM'!$G$2:$G$2951,0)),"") -> US | ... K7: =IFERROR(INDEX('Master - US vs THEM'!$F$2:$F$2951,MATCH($A7&"|"&K$1,'Master - US vs THEM'!$G$2:$G$2951,0)),"") -> US
A8: ='[1]Brand Family Territory (Enc)'!A8 -> Bell's Hearted Family | B8: =IFERROR(INDEX('Master - US vs THEM'!$F$2:$F$2951,MATCH($A8&"|"&B$1,'Master - US vs THEM'!$G$2:$G$2951,0)),"") -> US | C8: =IFERROR(INDEX('Master - US vs THEM'!$F$2:$F$2951,MATCH($A8&"|"&C$1,'Master - US vs THEM'!$G$2:$G$2951,0)),"") -> US | D8: =IFERROR(INDEX('Master - US vs THEM'!$F$2:$F$2951,MATCH($A8&"|"&D$1,'Master - US vs THEM'!$G$2:$G$2951,0)),"") -> US | E8: =IFERROR(INDEX('Master - US vs THEM'!$F$2:$F$2951,MATCH($A8&"|"&E$1,'Master - US vs THEM'!$G$2:$G$2951,0)),"") -> THEM | F8: =IFERROR(INDEX('Master - US vs THEM'!$F$2:$F$2951,MATCH($A8&"|"&F$1,'Master - US vs THEM'!$G$2:$G$2951,0)),"") -> THEM | G8: =IFERROR(INDEX('Master - US vs THEM'!$F$2:$F$2951,MATCH($A8&"|"&G$1,'Master - US vs THEM'!$G$2:$G$2951,0)),"") -> THEM | H8: =IFERROR(INDEX('Master - US vs THEM'!$F$2:$F$2951,MATCH($A8&"|"&H$1,'Master - US vs THEM'!$G$2:$G$2951,0)),"") -> US | I8: =IFERROR(INDEX('Master - US vs THEM'!$F$2:$F$2951,MATCH($A8&"|"&I$1,'Master - US vs THEM'!$G$2:$G$2951,0)),"") -> US | ... K8: =IFERROR(INDEX('Master - US vs THEM'!$F$2:$F$2951,MATCH($A8&"|"&K$1,'Master - US vs THEM'!$G$2:$G$2951,0)),"") -> US
A9: ='[1]Brand Family Territory (Enc)'!A9 -> Blue Moon | B9: =IFERROR(INDEX('Master - US vs THEM'!$F$2:$F$2951,MATCH($A9&"|"&B$1,'Master - US vs THEM'!$G$2:$G$2951,0)),"") -> US | C9: =IFERROR(INDEX('Master - US vs THEM'!$F$2:$F$2951,MATCH($A9&"|"&C$1,'Master - US vs THEM'!$G$2:$G$2951,0)),"") -> US | D9: =IFERROR(INDEX('Master - US vs THEM'!$F$2:$F$2951,MATCH($A9&"|"&D$1,'Master - US vs THEM'!$G$2:$G$2951,0)),"") -> US | E9: =IFERROR(INDEX('Master - US vs THEM'!$F$2:$F$2951,MATCH($A9&"|"&E$1,'Master - US vs THEM'!$G$2:$G$2951,0)),"") -> THEM | F9: =IFERROR(INDEX('Master - US vs THEM'!$F$2:$F$2951,MATCH($A9&"|"&F$1,'Master - US vs THEM'!$G$2:$G$2951,0)),"") -> THEM | G9: =IFERROR(INDEX('Master - US vs THEM'!$F$2:$F$2951,MATCH($A9&"|"&G$1,'Master - US vs THEM'!$G$2:$G$2951,0)),"") -> THEM | H9: =IFERROR(INDEX('Master - US vs THEM'!$F$2:$F$2951,MATCH($A9&"|"&H$1,'Master - US vs THEM'!$G$2:$G$2951,0)),"") -> US | I9: =IFERROR(INDEX('Master - US vs THEM'!$F$2:$F$2951,MATCH($A9&"|"&I$1,'Master - US vs THEM'!$G$2:$G$2951,0)),"") -> US | ... K9: =IFERROR(INDEX('Master - US vs THEM'!$F$2:$F$2951,MATCH($A9&"|"&K$1,'Master - US vs THEM'!$G$2:$G$2951,0)),"") -> US
A10: ='[1]Brand Family Territory (Enc)'!A10 -> Cape May | B10: =IFERROR(INDEX('Master - US vs THEM'!$F$2:$F$2951,MATCH($A10&"|"&B$1,'Master - US vs THEM'!$G$2:$G$2951,0)),"") -> US | C10: =IFERROR(INDEX('Master - US vs THEM'!$F$2:$F$2951,MATCH($A10&"|"&C$1,'Master - US vs THEM'!$G$2:$G$2951,0)),"") -> US | D10: =IFERROR(INDEX('Master - US vs THEM'!$F$2:$F$2951,MATCH($A10&"|"&D$1,'Master - US vs THEM'!$G$2:$G$2951,0)),"") -> US | E10: =IFERROR(INDEX('Master - US vs THEM'!$F$2:$F$2951,MATCH($A10&"|"&E$1,'Master - US vs THEM'!$G$2:$G$2951,0)),"") -> THEM | F10: =IFERROR(INDEX('Master - US vs THEM'!$F$2:$F$2951,MATCH($A10&"|"&F$1,'Master - US vs THEM'!$G$2:$G$2951,0)),"") -> THEM | G10: =IFERROR(INDEX('Master - US vs THEM'!$F$2:$F$2951,MATCH($A10&"|"&G$1,'Master - US vs THEM'!$G$2:$G$2951,0)),"") -> THEM | H10: =IFERROR(INDEX('Master - US vs THEM'!$F$2:$F$2951,MATCH($A10&"|"&H$1,'Master - US vs THEM'!$G$2:$G$2951,0)),"") -> US | I10: =IFERROR(INDEX('Master - US vs THEM'!$F$2:$F$2951,MATCH($A10&"|"&I$1,'Master - US vs THEM'!$G$2:$G$2951,0)),"") -> US | ... K10: =IFERROR(INDEX('Master - US vs THEM'!$F$2:$F$2951,MATCH($A10&"|"&K$1,'Master - US vs THEM'!$G$2:$G$2951,0)),"") -> US
A11: ='[1]Brand Family Territory (Enc)'!A11 -> Cayman Jack | B11: =IFERROR(INDEX('Master - US vs THEM'!$F$2:$F$2951,MATCH($A11&"|"&B$1,'Master - US vs THEM'!$G$2:$G$2951,0)),"") -> US | C11: =IFERROR(INDEX('Master - US vs THEM'!$F$2:$F$2951,MATCH($A11&"|"&C$1,'Master - US vs THEM'!$G$2:$G$2951,0)),"") -> US | D11: =IFERROR(INDEX('Master - US vs THEM'!$F$2:$F$2951,MATCH($A11&"|"&D$1,'Master - US vs THEM'!$G$2:$G$2951,0)),"") -> US | E11: =IFERROR(INDEX('Master - US vs THEM'!$F$2:$F$2951,MATCH($A11&"|"&E$1,'Master - US vs THEM'!$G$2:$G$2951,0)),"") -> THEM | F11: =IFERROR(INDEX('Master - US vs THEM'!$F$2:$F$2951,MATCH($A11&"|"&F$1,'Master - US vs THEM'!$G$2:$G$2951,0)),"") -> THEM | G11: =IFERROR(INDEX('Master - US vs THEM'!$F$2:$F$2951,MATCH($A11&"|"&G$1,'Master - US vs THEM'!$G$2:$G$2951,0)),"") -> THEM | H11: =IFERROR(INDEX('Master - US vs THEM'!$F$2:$F$2951,MATCH($A11&"|"&H$1,'Master - US vs THEM'!$G$2:$G$2951,0)),"") -> US | I11: =IFERROR(INDEX('Master - US vs THEM'!$F$2:$F$2951,MATCH($A11&"|"&I$1,'Master - US vs THEM'!$G$2:$G$2951,0)),"") -> US | ... K11: =IFERROR(INDEX('Master - US vs THEM'!$F$2:$F$2951,MATCH($A11&"|"&K$1,'Master - US vs THEM'!$G$2:$G$2951,0)),"") -> US
A12: ='[1]Brand Family Territory (Enc)'!A12 -> Coors | B12: =IFERROR(INDEX('Master - US vs THEM'!$F$2:$F$2951,MATCH($A12&"|"&B$1,'Master - US vs THEM'!$G$2:$G$2951,0)),"") -> US | C12: =IFERROR(INDEX('Master - US vs THEM'!$F$2:$F$2951,MATCH($A12&"|"&C$1,'Master - US vs THEM'!$G$2:$G$2951,0)),"") -> US | D12: =IFERROR(INDEX('Master - US vs THEM'!$F$2:$F$2951,MATCH($A12&"|"&D$1,'Master - US vs THEM'!$G$2:$G$2951,0)),"") -> US | E12: =IFERROR(INDEX('Master - US vs THEM'!$F$2:$F$2951,MATCH($A12&"|"&E$1,'Master - US vs THEM'!$G$2:$G$2951,0)),"") -> THEM | F12: =IFERROR(INDEX('Master - US vs THEM'!$F$2:$F$2951,MATCH($A12&"|"&F$1,'Master - US vs THEM'!$G$2:$G$2951,0)),"") -> THEM | G12: =IFERROR(INDEX('Master - US vs THEM'!$F$2:$F$2951,MATCH($A12&"|"&G$1,'Master - US vs THEM'!$G$2:$G$2951,0)),"") -> THEM | H12: =IFERROR(INDEX('Master - US vs THEM'!$F$2:$F$2951,MATCH($A12&"|"&H$1,'Master - US vs THEM'!$G$2:$G$2951,0)),"") -> US | I12: =IFERROR(INDEX('Master - US vs THEM'!$F$2:$F$2951,MATCH($A12&"|"&I$1,'Master - US vs THEM'!$G$2:$G$2951,0)),"") -> US | ... K12: =IFERROR(INDEX('Master - US vs THEM'!$F$2:$F$2951,MATCH($A12&"|"&K$1,'Master - US vs THEM'!$G$2:$G$2951,0)),"") -> US
A13: ='[1]Brand Family Territory (Enc)'!A13 -> Coors Edge | B13: =IFERROR(INDEX('Master - US vs THEM'!$F$2:$F$2951,MATCH($A13&"|"&B$1,'Master - US vs THEM'!$G$2:$G$2951,0)),"") -> US | C13: =IFERROR(INDEX('Master - US vs THEM'!$F$2:$F$2951,MATCH($A13&"|"&C$1,'Master - US vs THEM'!$G$2:$G$2951,0)),"") -> US | D13: =IFERROR(INDEX('Master - US vs THEM'!$F$2:$F$2951,MATCH($A13&"|"&D$1,'Master - US vs THEM'!$G$2:$G$2951,0)),"") -> US | E13: =IFERROR(INDEX('Master - US vs THEM'!$F$2:$F$2951,MATCH($A13&"|"&E$1,'Master - US vs THEM'!$G$2:$G$2951,0)),"") -> THEM | F13: =IFERROR(INDEX('Master - US vs THEM'!$F$2:$F$2951,MATCH($A13&"|"&F$1,'Master - US vs THEM'!$G$2:$G$2951,0)),"") -> THEM | G13: =IFERROR(INDEX('Master - US vs THEM'!$F$2:$F$2951,MATCH($A13&"|"&G$1,'Master - US vs THEM'!$G$2:$G$2951,0)),"") -> THEM | H13: =IFERROR(INDEX('Master - US vs THEM'!$F$2:$F$2951,MATCH($A13&"|"&H$1,'Master - US vs THEM'!$G$2:$G$2951,0)),"") -> US | I13: =IFERROR(INDEX('Master - US vs THEM'!$F$2:$F$2951,MATCH($A13&"|"&I$1,'Master - US vs THEM'!$G$2:$G$2951,0)),"") -> US | ... K13: =IFERROR(INDEX('Master - US vs THEM'!$F$2:$F$2951,MATCH($A13&"|"&K$1,'Master - US vs THEM'!$G$2:$G$2951,0)),"") -> US
... A296: ='[1]Brand Family Territory (Enc)'!A296 -> 2 Canos | B296: =IFERROR(INDEX('Master - US vs THEM'!$F$2:$F$2951,MATCH($A296&"|"&B$1,'Master - US vs THEM'!$G$2:$G$2951,0)),"") -> US | C296: =IFERROR(INDEX('Master - US vs THEM'!$F$2:$F$2951,MATCH($A296&"|"&C$1,'Master - US vs THEM'!$G$2:$G$2951,0)),"") -> US | D296: =IFERROR(INDEX('Master - US vs THEM'!$F$2:$F$2951,MATCH($A296&"|"&D$1,'Master - US vs THEM'!$G$2:$G$2951,0)),"") -> US | E296: =IFERROR(INDEX('Master - US vs THEM'!$F$2:$F$2951,MATCH($A296&"|"&E$1,'Master - US vs THEM'!$G$2:$G$2951,0)),"") -> US | F296: =IFERROR(INDEX('Master - US vs THEM'!$F$2:$F$2951,MATCH($A296&"|"&F$1,'Master - US vs THEM'!$G$2:$G$2951,0)),"") -> US | G296: =IFERROR(INDEX('Master - US vs THEM'!$F$2:$F$2951,MATCH($A296&"|"&G$1,'Master - US vs THEM'!$G$2:$G$2951,0)),"") -> US | H296: =IFERROR(INDEX('Master - US vs THEM'!$F$2:$F$2951,MATCH($A296&"|"&H$1,'Master - US vs THEM'!$G$2:$G$2951,0)),"") -> US | I296: =IFERROR(INDEX('Master - US vs THEM'!$F$2:$F$2951,MATCH($A296&"|"&I$1,'Master - US vs THEM'!$G$2:$G$2951,0)),"") -> US | ... K296: =IFERROR(INDEX('Master - US vs THEM'!$F$2:$F$2951,MATCH($A296&"|"&K$1,'Master - US vs THEM'!$G$2:$G$2951,0)),"") -> US
A297: Miller High Life | B297: =IFERROR(INDEX('Master - US vs THEM'!$F$2:$F$2961,MATCH($A297&"|"&B$1,'Master - US vs THEM'!$G$2:$G$2961,0)),"") -> US | C297: =IFERROR(INDEX('Master - US vs THEM'!$F$2:$F$2961,MATCH($A297&"|"&C$1,'Master - US vs THEM'!$G$2:$G$2961,0)),"") -> US | D297: =IFERROR(INDEX('Master - US vs THEM'!$F$2:$F$2961,MATCH($A297&"|"&D$1,'Master - US vs THEM'!$G$2:$G$2961,0)),"") -> US | E297: =IFERROR(INDEX('Master - US vs THEM'!$F$2:$F$2961,MATCH($A297&"|"&E$1,'Master - US vs THEM'!$G$2:$G$2961,0)),"") -> THEM | F297: =IFERROR(INDEX('Master - US vs THEM'!$F$2:$F$2961,MATCH($A297&"|"&F$1,'Master - US vs THEM'!$G$2:$G$2961,0)),"") -> THEM | G297: =IFERROR(INDEX('Master - US vs THEM'!$F$2:$F$2961,MATCH($A297&"|"&G$1,'Master - US vs THEM'!$G$2:$G$2961,0)),"") -> THEM | H297: =IFERROR(INDEX('Master - US vs THEM'!$F$2:$F$2961,MATCH($A297&"|"&H$1,'Master - US vs THEM'!$G$2:$G$2961,0)),"") -> US | I297: =IFERROR(INDEX('Master - US vs THEM'!$F$2:$F$2961,MATCH($A297&"|"&I$1,'Master - US vs THEM'!$G$2:$G$2961,0)),"") -> US | ... K297: =IFERROR(INDEX('Master - US vs THEM'!$F$2:$F$2961,MATCH($A297&"|"&K$1,'Master - US vs THEM'!$G$2:$G$2961,0)),"") -> US

Sheet Whitelist (Blackout Reverse)
A1: Brand Family | B1: BERGEN | C1: PASSAIC | D1: PASSAIC-FF | E1: ESSEX | F1: HUDSON | G1: UNION | H1: SUSSEX | I1: MORRIS 1 | J1: MORRIS 2 | K1: MORRIS 3
A2: {=_xlfn._xlws.SORT(_xlfn.UNIQUE(_xlfn._xlws.FILTER('Blackout Brand Fam Areas (Enc)'!B6:B998,'Blackout Brand Fam Areas (Enc)'!B6:B998<>"")))} -> Affligem | B2: =IF($A2="","",IF(COUNTIFS('Blackout Brand Fam Areas (Enc)'!$B$6:$B$998,$A2,'Blackout Brand Fam Areas (Enc)'!$C$6:$C$998,B$1,'Blackout Brand Fam Areas (Enc)'!$D$6:$D$998,"Inactive")>0,"BLOCKED","CAN SELL")) -> CAN SELL | C2: =IF($A2="","",IF(COUNTIFS('Blackout Brand Fam Areas (Enc)'!$B$6:$B$998,$A2,'Blackout Brand Fam Areas (Enc)'!$C$6:$C$998,C$1,'Blackout Brand Fam Areas (Enc)'!$D$6:$D$998,"Inactive")>0,"BLOCKED","CAN SELL")) -> CAN SELL | D2: =IF($A2="","",IF(COUNTIFS('Blackout Brand Fam Areas (Enc)'!$B$6:$B$998,$A2,'Blackout Brand Fam Areas (Enc)'!$C$6:$C$998,D$1,'Blackout Brand Fam Areas (Enc)'!$D$6:$D$998,"Inactive")>0,"BLOCKED","CAN SELL")) -> CAN SELL | E2: =IF($A2="","",IF(COUNTIFS('Blackout Brand Fam Areas (Enc)'!$B$6:$B$998,$A2,'Blackout Brand Fam Areas (Enc)'!$C$6:$C$998,E$1,'Blackout Brand Fam Areas (Enc)'!$D$6:$D$998,"Inactive")>0,"BLOCKED","CAN SELL")) -> BLOCKED | F2: =IF($A2="","",IF(COUNTIFS('Blackout Brand Fam Areas (Enc)'!$B$6:$B$998,$A2,'Blackout Brand Fam Areas (Enc)'!$C$6:$C$998,F$1,'Blackout Brand Fam Areas (Enc)'!$D$6:$D$998,"Inactive")>0,"BLOCKED","CAN SELL")) -> BLOCKED | G2: =IF($A2="","",IF(COUNTIFS('Blackout Brand Fam Areas (Enc)'!$B$6:$B$998,$A2,'Blackout Brand Fam Areas (Enc)'!$C$6:$C$998,G$1,'Blackout Brand Fam Areas (Enc)'!$D$6:$D$998,"Inactive")>0,"BLOCKED","CAN SELL")) -> BLOCKED | H2: =IF($A2="","",IF(COUNTIFS('Blackout Brand Fam Areas (Enc)'!$B$6:$B$998,$A2,'Blackout Brand Fam Areas (Enc)'!$C$6:$C$998,H$1,'Blackout Brand Fam Areas (Enc)'!$D$6:$D$998,"Inactive")>0,"BLOCKED","CAN SELL")) -> BLOCKED | I2: =IF($A2="","",IF(COUNTIFS('Blackout Brand Fam Areas (Enc)'!$B$6:$B$998,$A2,'Blackout Brand Fam Areas (Enc)'!$C$6:$C$998,I$1,'Blackout Brand Fam Areas (Enc)'!$D$6:$D$998,"Inactive")>0,"BLOCKED","CAN SELL")) -> BLOCKED | ... K2: =IF($A2="","",IF(COUNTIFS('Blackout Brand Fam Areas (Enc)'!$B$6:$B$998,$A2,'Blackout Brand Fam Areas (Enc)'!$C$6:$C$998,K$1,'Blackout Brand Fam Areas (Enc)'!$D$6:$D$998,"Inactive")>0,"BLOCKED","CAN SELL")) -> CAN SELL
A3: Aguila | B3: =IF($A3="","",IF(COUNTIFS('Blackout Brand Fam Areas (Enc)'!$B$6:$B$998,$A3,'Blackout Brand Fam Areas (Enc)'!$C$6:$C$998,B$1,'Blackout Brand Fam Areas (Enc)'!$D$6:$D$998,"Inactive")>0,"BLOCKED","CAN SELL")) -> CAN SELL | C3: =IF($A3="","",IF(COUNTIFS('Blackout Brand Fam Areas (Enc)'!$B$6:$B$998,$A3,'Blackout Brand Fam Areas (Enc)'!$C$6:$C$998,C$1,'Blackout Brand Fam Areas (Enc)'!$D$6:$D$998,"Inactive")>0,"BLOCKED","CAN SELL")) -> CAN SELL | D3: =IF($A3="","",IF(COUNTIFS('Blackout Brand Fam Areas (Enc)'!$B$6:$B$998,$A3,'Blackout Brand Fam Areas (Enc)'!$C$6:$C$998,D$1,'Blackout Brand Fam Areas (Enc)'!$D$6:$D$998,"Inactive")>0,"BLOCKED","CAN SELL")) -> CAN SELL | E3: =IF($A3="","",IF(COUNTIFS('Blackout Brand Fam Areas (Enc)'!$B$6:$B$998,$A3,'Blackout Brand Fam Areas (Enc)'!$C$6:$C$998,E$1,'Blackout Brand Fam Areas (Enc)'!$D$6:$D$998,"Inactive")>0,"BLOCKED","CAN SELL")) -> BLOCKED | F3: =IF($A3="","",IF(COUNTIFS('Blackout Brand Fam Areas (Enc)'!$B$6:$B$998,$A3,'Blackout Brand Fam Areas (Enc)'!$C$6:$C$998,F$1,'Blackout Brand Fam Areas (Enc)'!$D$6:$D$998,"Inactive")>0,"BLOCKED","CAN SELL")) -> BLOCKED | G3: =IF($A3="","",IF(COUNTIFS('Blackout Brand Fam Areas (Enc)'!$B$6:$B$998,$A3,'Blackout Brand Fam Areas (Enc)'!$C$6:$C$998,G$1,'Blackout Brand Fam Areas (Enc)'!$D$6:$D$998,"Inactive")>0,"BLOCKED","CAN SELL")) -> BLOCKED | H3: =IF($A3="","",IF(COUNTIFS('Blackout Brand Fam Areas (Enc)'!$B$6:$B$998,$A3,'Blackout Brand Fam Areas (Enc)'!$C$6:$C$998,H$1,'Blackout Brand Fam Areas (Enc)'!$D$6:$D$998,"Inactive")>0,"BLOCKED","CAN SELL")) -> CAN SELL | I3: =IF($A3="","",IF(COUNTIFS('Blackout Brand Fam Areas (Enc)'!$B$6:$B$998,$A3,'Blackout Brand Fam Areas (Enc)'!$C$6:$C$998,I$1,'Blackout Brand Fam Areas (Enc)'!$D$6:$D$998,"Inactive")>0,"BLOCKED","CAN SELL")) -> CAN SELL | ... K3: =IF($A3="","",IF(COUNTIFS('Blackout Brand Fam Areas (Enc)'!$B$6:$B$998,$A3,'Blackout Brand Fam Areas (Enc)'!$C$6:$C$998,K$1,'Blackout Brand Fam Areas (Enc)'!$D$6:$D$998,"Inactive")>0,"BLOCKED","CAN SELL")) -> CAN SELL
A4: Amstel | B4: =IF($A4="","",IF(COUNTIFS('Blackout Brand Fam Areas (Enc)'!$B$6:$B$998,$A4,'Blackout Brand Fam Areas (Enc)'!$C$6:$C$998,B$1,'Blackout Brand Fam Areas (Enc)'!$D$6:$D$998,"Inactive")>0,"BLOCKED","CAN SELL")) -> CAN SELL | C4: =IF($A4="","",IF(COUNTIFS('Blackout Brand Fam Areas (Enc)'!$B$6:$B$998,$A4,'Blackout Brand Fam Areas (Enc)'!$C$6:$C$998,C$1,'Blackout Brand Fam Areas (Enc)'!$D$6:$D$998,"Inactive")>0,"BLOCKED","CAN SELL")) -> CAN SELL | D4: =IF($A4="","",IF(COUNTIFS('Blackout Brand Fam Areas (Enc)'!$B$6:$B$998,$A4,'Blackout Brand Fam Areas (Enc)'!$C$6:$C$998,D$1,'Blackout Brand Fam Areas (Enc)'!$D$6:$D$998,"Inactive")>0,"BLOCKED","CAN SELL")) -> CAN SELL | E4: =IF($A4="","",IF(COUNTIFS('Blackout Brand Fam Areas (Enc)'!$B$6:$B$998,$A4,'Blackout Brand Fam Areas (Enc)'!$C$6:$C$998,E$1,'Blackout Brand Fam Areas (Enc)'!$D$6:$D$998,"Inactive")>0,"BLOCKED","CAN SELL")) -> BLOCKED | F4: =IF($A4="","",IF(COUNTIFS('Blackout Brand Fam Areas (Enc)'!$B$6:$B$998,$A4,'Blackout Brand Fam Areas (Enc)'!$C$6:$C$998,F$1,'Blackout Brand Fam Areas (Enc)'!$D$6:$D$998,"Inactive")>0,"BLOCKED","CAN SELL")) -> BLOCKED | G4: =IF($A4="","",IF(COUNTIFS('Blackout Brand Fam Areas (Enc)'!$B$6:$B$998,$A4,'Blackout Brand Fam Areas (Enc)'!$C$6:$C$998,G$1,'Blackout Brand Fam Areas (Enc)'!$D$6:$D$998,"Inactive")>0,"BLOCKED","CAN SELL")) -> BLOCKED | H4: =IF($A4="","",IF(COUNTIFS('Blackout Brand Fam Areas (Enc)'!$B$6:$B$998,$A4,'Blackout Brand Fam Areas (Enc)'!$C$6:$C$998,H$1,'Blackout Brand Fam Areas (Enc)'!$D$6:$D$998,"Inactive")>0,"BLOCKED","CAN SELL")) -> BLOCKED | I4: =IF($A4="","",IF(COUNTIFS('Blackout Brand Fam Areas (Enc)'!$B$6:$B$998,$A4,'Blackout Brand Fam Areas (Enc)'!$C$6:$C$998,I$1,'Blackout Brand Fam Areas (Enc)'!$D$6:$D$998,"Inactive")>0,"BLOCKED","CAN SELL")) -> BLOCKED | ... K4: =IF($A4="","",IF(COUNTIFS('Blackout Brand Fam Areas (Enc)'!$B$6:$B$998,$A4,'Blackout Brand Fam Areas (Enc)'!$C$6:$C$998,K$1,'Blackout Brand Fam Areas (Enc)'!$D$6:$D$998,"Inactive")>0,"BLOCKED","CAN SELL")) -> CAN SELL
A5: Anchor | B5: =IF($A5="","",IF(COUNTIFS('Blackout Brand Fam Areas (Enc)'!$B$6:$B$998,$A5,'Blackout Brand Fam Areas (Enc)'!$C$6:$C$998,B$1,'Blackout Brand Fam Areas (Enc)'!$D$6:$D$998,"Inactive")>0,"BLOCKED","CAN SELL")) -> CAN SELL | C5: =IF($A5="","",IF(COUNTIFS('Blackout Brand Fam Areas (Enc)'!$B$6:$B$998,$A5,'Blackout Brand Fam Areas (Enc)'!$C$6:$C$998,C$1,'Blackout Brand Fam Areas (Enc)'!$D$6:$D$998,"Inactive")>0,"BLOCKED","CAN SELL")) -> CAN SELL | D5: =IF($A5="","",IF(COUNTIFS('Blackout Brand Fam Areas (Enc)'!$B$6:$B$998,$A5,'Blackout Brand Fam Areas (Enc)'!$C$6:$C$998,D$1,'Blackout Brand Fam Areas (Enc)'!$D$6:$D$998,"Inactive")>0,"BLOCKED","CAN SELL")) -> CAN SELL | E5: =IF($A5="","",IF(COUNTIFS('Blackout Brand Fam Areas (Enc)'!$B$6:$B$998,$A5,'Blackout Brand Fam Areas (Enc)'!$C$6:$C$998,E$1,'Blackout Brand Fam Areas (Enc)'!$D$6:$D$998,"Inactive")>0,"BLOCKED","CAN SELL")) -> BLOCKED | F5: =IF($A5="","",IF(COUNTIFS('Blackout Brand Fam Areas (Enc)'!$B$6:$B$998,$A5,'Blackout Brand Fam Areas (Enc)'!$C$6:$C$998,F$1,'Blackout Brand Fam Areas (Enc)'!$D$6:$D$998,"Inactive")>0,"BLOCKED","CAN SELL")) -> CAN SELL | G5: =IF($A5="","",IF(COUNTIFS('Blackout Brand Fam Areas (Enc)'!$B$6:$B$998,$A5,'Blackout Brand Fam Areas (Enc)'!$C$6:$C$998,G$1,'Blackout Brand Fam Areas (Enc)'!$D$6:$D$998,"Inactive")>0,"BLOCKED","CAN SELL")) -> BLOCKED | H5: =IF($A5="","",IF(COUNTIFS('Blackout Brand Fam Areas (Enc)'!$B$6:$B$998,$A5,'Blackout Brand Fam Areas (Enc)'!$C$6:$C$998,H$1,'Blackout Brand Fam Areas (Enc)'!$D$6:$D$998,"Inactive")>0,"BLOCKED","CAN SELL")) -> BLOCKED | I5: =IF($A5="","",IF(COUNTIFS('Blackout Brand Fam Areas (Enc)'!$B$6:$B$998,$A5,'Blackout Brand Fam Areas (Enc)'!$C$6:$C$998,I$1,'Blackout Brand Fam Areas (Enc)'!$D$6:$D$998,"Inactive")>0,"BLOCKED","CAN SELL")) -> BLOCKED | ... K5: =IF($A5="","",IF(COUNTIFS('Blackout Brand Fam Areas (Enc)'!$B$6:$B$998,$A5,'Blackout Brand Fam Areas (Enc)'!$C$6:$C$998,K$1,'Blackout Brand Fam Areas (Enc)'!$D$6:$D$998,"Inactive")>0,"BLOCKED","CAN SELL")) -> BLOCKED
A6: Angry Orchard | B6: =IF($A6="","",IF(COUNTIFS('Blackout Brand Fam Areas (Enc)'!$B$6:$B$998,$A6,'Blackout Brand Fam Areas (Enc)'!$C$6:$C$998,B$1,'Blackout Brand Fam Areas (Enc)'!$D$6:$D$998,"Inactive")>0,"BLOCKED","CAN SELL")) -> CAN SELL | C6: =IF($A6="","",IF(COUNTIFS('Blackout Brand Fam Areas (Enc)'!$B$6:$B$998,$A6,'Blackout Brand Fam Areas (Enc)'!$C$6:$C$998,C$1,'Blackout Brand Fam Areas (Enc)'!$D$6:$D$998,"Inactive")>0,"BLOCKED","CAN SELL")) -> CAN SELL | D6: =IF($A6="","",IF(COUNTIFS('Blackout Brand Fam Areas (Enc)'!$B$6:$B$998,$A6,'Blackout Brand Fam Areas (Enc)'!$C$6:$C$998,D$1,'Blackout Brand Fam Areas (Enc)'!$D$6:$D$998,"Inactive")>0,"BLOCKED","CAN SELL")) -> CAN SELL | E6: =IF($A6="","",IF(COUNTIFS('Blackout Brand Fam Areas (Enc)'!$B$6:$B$998,$A6,'Blackout Brand Fam Areas (Enc)'!$C$6:$C$998,E$1,'Blackout Brand Fam Areas (Enc)'!$D$6:$D$998,"Inactive")>0,"BLOCKED","CAN SELL")) -> BLOCKED | F6: =IF($A6="","",IF(COUNTIFS('Blackout Brand Fam Areas (Enc)'!$B$6:$B$998,$A6,'Blackout Brand Fam Areas (Enc)'!$C$6:$C$998,F$1,'Blackout Brand Fam Areas (Enc)'!$D$6:$D$998,"Inactive")>0,"BLOCKED","CAN SELL")) -> BLOCKED | G6: =IF($A6="","",IF(COUNTIFS('Blackout Brand Fam Areas (Enc)'!$B$6:$B$998,$A6,'Blackout Brand Fam Areas (Enc)'!$C$6:$C$998,G$1,'Blackout Brand Fam Areas (Enc)'!$D$6:$D$998,"Inactive")>0,"BLOCKED","CAN SELL")) -> BLOCKED | H6: =IF($A6="","",IF(COUNTIFS('Blackout Brand Fam Areas (Enc)'!$B$6:$B$998,$A6,'Blackout Brand Fam Areas (Enc)'!$C$6:$C$998,H$1,'Blackout Brand Fam Areas (Enc)'!$D$6:$D$998,"Inactive")>0,"BLOCKED","CAN SELL")) -> CAN SELL | I6: =IF($A6="","",IF(COUNTIFS('Blackout Brand Fam Areas (Enc)'!$B$6:$B$998,$A6,'Blackout Brand Fam Areas (Enc)'!$C$6:$C$998,I$1,'Blackout Brand Fam Areas (Enc)'!$D$6:$D$998,"Inactive")>0,"BLOCKED","CAN SELL")) -> CAN SELL | ... K6: =IF($A6="","",IF(COUNTIFS('Blackout Brand Fam Areas (Enc)'!$B$6:$B$998,$A6,'Blackout Brand Fam Areas (Enc)'!$C$6:$C$998,K$1,'Blackout Brand Fam Areas (Enc)'!$D$6:$D$998,"Inactive")>0,"BLOCKED","CAN SELL")) -> CAN SELL
A7: Arnold Palmer | B7: =IF($A7="","",IF(COUNTIFS('Blackout Brand Fam Areas (Enc)'!$B$6:$B$998,$A7,'Blackout Brand Fam Areas (Enc)'!$C$6:$C$998,B$1,'Blackout Brand Fam Areas (Enc)'!$D$6:$D$998,"Inactive")>0,"BLOCKED","CAN SELL")) -> CAN SELL | C7: =IF($A7="","",IF(COUNTIFS('Blackout Brand Fam Areas (Enc)'!$B$6:$B$998,$A7,'Blackout Brand Fam Areas (Enc)'!$C$6:$C$998,C$1,'Blackout Brand Fam Areas (Enc)'!$D$6:$D$998,"Inactive")>0,"BLOCKED","CAN SELL")) -> CAN SELL | D7: =IF($A7="","",IF(COUNTIFS('Blackout Brand Fam Areas (Enc)'!$B$6:$B$998,$A7,'Blackout Brand Fam Areas (Enc)'!$C$6:$C$998,D$1,'Blackout Brand Fam Areas (Enc)'!$D$6:$D$998,"Inactive")>0,"BLOCKED","CAN SELL")) -> CAN SELL | E7: =IF($A7="","",IF(COUNTIFS('Blackout Brand Fam Areas (Enc)'!$B$6:$B$998,$A7,'Blackout Brand Fam Areas (Enc)'!$C$6:$C$998,E$1,'Blackout Brand Fam Areas (Enc)'!$D$6:$D$998,"Inactive")>0,"BLOCKED","CAN SELL")) -> BLOCKED | F7: =IF($A7="","",IF(COUNTIFS('Blackout Brand Fam Areas (Enc)'!$B$6:$B$998,$A7,'Blackout Brand Fam Areas (Enc)'!$C$6:$C$998,F$1,'Blackout Brand Fam Areas (Enc)'!$D$6:$D$998,"Inactive")>0,"BLOCKED","CAN SELL")) -> BLOCKED | G7: =IF($A7="","",IF(COUNTIFS('Blackout Brand Fam Areas (Enc)'!$B$6:$B$998,$A7,'Blackout Brand Fam Areas (Enc)'!$C$6:$C$998,G$1,'Blackout Brand Fam Areas (Enc)'!$D$6:$D$998,"Inactive")>0,"BLOCKED","CAN SELL")) -> BLOCKED | H7: =IF($A7="","",IF(COUNTIFS('Blackout Brand Fam Areas (Enc)'!$B$6:$B$998,$A7,'Blackout Brand Fam Areas (Enc)'!$C$6:$C$998,H$1,'Blackout Brand Fam Areas (Enc)'!$D$6:$D$998,"Inactive")>0,"BLOCKED","CAN SELL")) -> CAN SELL | I7: =IF($A7="","",IF(COUNTIFS('Blackout Brand Fam Areas (Enc)'!$B$6:$B$998,$A7,'Blackout Brand Fam Areas (Enc)'!$C$6:$C$998,I$1,'Blackout Brand Fam Areas (Enc)'!$D$6:$D$998,"Inactive")>0,"BLOCKED","CAN SELL")) -> CAN SELL | ... K7: =IF($A7="","",IF(COUNTIFS('Blackout Brand Fam Areas (Enc)'!$B$6:$B$998,$A7,'Blackout Brand Fam Areas (Enc)'!$C$6:$C$998,K$1,'Blackout Brand Fam Areas (Enc)'!$D$6:$D$998,"Inactive")>0,"BLOCKED","CAN SELL")) -> CAN SELL
A8: Athletic | B8: =IF($A8="","",IF(COUNTIFS('Blackout Brand Fam Areas (Enc)'!$B$6:$B$998,$A8,'Blackout Brand Fam Areas (Enc)'!$C$6:$C$998,B$1,'Blackout Brand Fam Areas (Enc)'!$D$6:$D$998,"Inactive")>0,"BLOCKED","CAN SELL")) -> CAN SELL | C8: =IF($A8="","",IF(COUNTIFS('Blackout Brand Fam Areas (Enc)'!$B$6:$B$998,$A8,'Blackout Brand Fam Areas (Enc)'!$C$6:$C$998,C$1,'Blackout Brand Fam Areas (Enc)'!$D$6:$D$998,"Inactive")>0,"BLOCKED","CAN SELL")) -> CAN SELL | D8: =IF($A8="","",IF(COUNTIFS('Blackout Brand Fam Areas (Enc)'!$B$6:$B$998,$A8,'Blackout Brand Fam Areas (Enc)'!$C$6:$C$998,D$1,'Blackout Brand Fam Areas (Enc)'!$D$6:$D$998,"Inactive")>0,"BLOCKED","CAN SELL")) -> CAN SELL | E8: =IF($A8="","",IF(COUNTIFS('Blackout Brand Fam Areas (Enc)'!$B$6:$B$998,$A8,'Blackout Brand Fam Areas (Enc)'!$C$6:$C$998,E$1,'Blackout Brand Fam Areas (Enc)'!$D$6:$D$998,"Inactive")>0,"BLOCKED","CAN SELL")) -> BLOCKED | F8: =IF($A8="","",IF(COUNTIFS('Blackout Brand Fam Areas (Enc)'!$B$6:$B$998,$A8,'Blackout Brand Fam Areas (Enc)'!$C$6:$C$998,F$1,'Blackout Brand Fam Areas (Enc)'!$D$6:$D$998,"Inactive")>0,"BLOCKED","CAN SELL")) -> BLOCKED | G8: =IF($A8="","",IF(COUNTIFS('Blackout Brand Fam Areas (Enc)'!$B$6:$B$998,$A8,'Blackout Brand Fam Areas (Enc)'!$C$6:$C$998,G$1,'Blackout Brand Fam Areas (Enc)'!$D$6:$D$998,"Inactive")>0,"BLOCKED","CAN SELL")) -> BLOCKED | H8: =IF($A8="","",IF(COUNTIFS('Blackout Brand Fam Areas (Enc)'!$B$6:$B$998,$A8,'Blackout Brand Fam Areas (Enc)'!$C$6:$C$998,H$1,'Blackout Brand Fam Areas (Enc)'!$D$6:$D$998,"Inactive")>0,"BLOCKED","CAN SELL")) -> CAN SELL | I8: =IF($A8="","",IF(COUNTIFS('Blackout Brand Fam Areas (Enc)'!$B$6:$B$998,$A8,'Blackout Brand Fam Areas (Enc)'!$C$6:$C$998,I$1,'Blackout Brand Fam Areas (Enc)'!$D$6:$D$998,"Inactive")>0,"BLOCKED","CAN SELL")) -> CAN SELL | ... K8: =IF($A8="","",IF(COUNTIFS('Blackout Brand Fam Areas (Enc)'!$B$6:$B$998,$A8,'Blackout Brand Fam Areas (Enc)'!$C$6:$C$998,K$1,'Blackout Brand Fam Areas (Enc)'!$D$6:$D$998,"Inactive")>0,"BLOCKED","CAN SELL")) -> CAN SELL
A9: Ballast Point | B9: =IF($A9="","",IF(COUNTIFS('Blackout Brand Fam Areas (Enc)'!$B$6:$B$998,$A9,'Blackout Brand Fam Areas (Enc)'!$C$6:$C$998,B$1,'Blackout Brand Fam Areas (Enc)'!$D$6:$D$998,"Inactive")>0,"BLOCKED","CAN SELL")) -> CAN SELL | C9: =IF($A9="","",IF(COUNTIFS('Blackout Brand Fam Areas (Enc)'!$B$6:$B$998,$A9,'Blackout Brand Fam Areas (Enc)'!$C$6:$C$998,C$1,'Blackout Brand Fam Areas (Enc)'!$D$6:$D$998,"Inactive")>0,"BLOCKED","CAN SELL")) -> CAN SELL | D9: =IF($A9="","",IF(COUNTIFS('Blackout Brand Fam Areas (Enc)'!$B$6:$B$998,$A9,'Blackout Brand Fam Areas (Enc)'!$C$6:$C$998,D$1,'Blackout Brand Fam Areas (Enc)'!$D$6:$D$998,"Inactive")>0,"BLOCKED","CAN SELL")) -> CAN SELL | E9: =IF($A9="","",IF(COUNTIFS('Blackout Brand Fam Areas (Enc)'!$B$6:$B$998,$A9,'Blackout Brand Fam Areas (Enc)'!$C$6:$C$998,E$1,'Blackout Brand Fam Areas (Enc)'!$D$6:$D$998,"Inactive")>0,"BLOCKED","CAN SELL")) -> BLOCKED | F9: =IF($A9="","",IF(COUNTIFS('Blackout Brand Fam Areas (Enc)'!$B$6:$B$998,$A9,'Blackout Brand Fam Areas (Enc)'!$C$6:$C$998,F$1,'Blackout Brand Fam Areas (Enc)'!$D$6:$D$998,"Inactive")>0,"BLOCKED","CAN SELL")) -> BLOCKED | G9: =IF($A9="","",IF(COUNTIFS('Blackout Brand Fam Areas (Enc)'!$B$6:$B$998,$A9,'Blackout Brand Fam Areas (Enc)'!$C$6:$C$998,G$1,'Blackout Brand Fam Areas (Enc)'!$D$6:$D$998,"Inactive")>0,"BLOCKED","CAN SELL")) -> BLOCKED | H9: =IF($A9="","",IF(COUNTIFS('Blackout Brand Fam Areas (Enc)'!$B$6:$B$998,$A9,'Blackout Brand Fam Areas (Enc)'!$C$6:$C$998,H$1,'Blackout Brand Fam Areas (Enc)'!$D$6:$D$998,"Inactive")>0,"BLOCKED","CAN SELL")) -> CAN SELL | I9: =IF($A9="","",IF(COUNTIFS('Blackout Brand Fam Areas (Enc)'!$B$6:$B$998,$A9,'Blackout Brand Fam Areas (Enc)'!$C$6:$C$998,I$1,'Blackout Brand Fam Areas (Enc)'!$D$6:$D$998,"Inactive")>0,"BLOCKED","CAN SELL")) -> CAN SELL | ... K9: =IF($A9="","",IF(COUNTIFS('Blackout Brand Fam Areas (Enc)'!$B$6:$B$998,$A9,'Blackout Brand Fam Areas (Enc)'!$C$6:$C$998,K$1,'Blackout Brand Fam Areas (Enc)'!$D$6:$D$998,"Inactive")>0,"BLOCKED","CAN SELL")) -> CAN SELL
A10: Banks | B10: =IF($A10="","",IF(COUNTIFS('Blackout Brand Fam Areas (Enc)'!$B$6:$B$998,$A10,'Blackout Brand Fam Areas (Enc)'!$C$6:$C$998,B$1,'Blackout Brand Fam Areas (Enc)'!$D$6:$D$998,"Inactive")>0,"BLOCKED","CAN SELL")) -> CAN SELL | C10: =IF($A10="","",IF(COUNTIFS('Blackout Brand Fam Areas (Enc)'!$B$6:$B$998,$A10,'Blackout Brand Fam Areas (Enc)'!$C$6:$C$998,C$1,'Blackout Brand Fam Areas (Enc)'!$D$6:$D$998,"Inactive")>0,"BLOCKED","CAN SELL")) -> CAN SELL | D10: =IF($A10="","",IF(COUNTIFS('Blackout Brand Fam Areas (Enc)'!$B$6:$B$998,$A10,'Blackout Brand Fam Areas (Enc)'!$C$6:$C$998,D$1,'Blackout Brand Fam Areas (Enc)'!$D$6:$D$998,"Inactive")>0,"BLOCKED","CAN SELL")) -> CAN SELL | E10: =IF($A10="","",IF(COUNTIFS('Blackout Brand Fam Areas (Enc)'!$B$6:$B$998,$A10,'Blackout Brand Fam Areas (Enc)'!$C$6:$C$998,E$1,'Blackout Brand Fam Areas (Enc)'!$D$6:$D$998,"Inactive")>0,"BLOCKED","CAN SELL")) -> CAN SELL | F10: =IF($A10="","",IF(COUNTIFS('Blackout Brand Fam Areas (Enc)'!$B$6:$B$998,$A10,'Blackout Brand Fam Areas (Enc)'!$C$6:$C$998,F$1,'Blackout Brand Fam Areas (Enc)'!$D$6:$D$998,"Inactive")>0,"BLOCKED","CAN SELL")) -> CAN SELL | G10: =IF($A10="","",IF(COUNTIFS('Blackout Brand Fam Areas (Enc)'!$B$6:$B$998,$A10,'Blackout Brand Fam Areas (Enc)'!$C$6:$C$998,G$1,'Blackout Brand Fam Areas (Enc)'!$D$6:$D$998,"Inactive")>0,"BLOCKED","CAN SELL")) -> BLOCKED | H10: =IF($A10="","",IF(COUNTIFS('Blackout Brand Fam Areas (Enc)'!$B$6:$B$998,$A10,'Blackout Brand Fam Areas (Enc)'!$C$6:$C$998,H$1,'Blackout Brand Fam Areas (Enc)'!$D$6:$D$998,"Inactive")>0,"BLOCKED","CAN SELL")) -> BLOCKED | I10: =IF($A10="","",IF(COUNTIFS('Blackout Brand Fam Areas (Enc)'!$B$6:$B$998,$A10,'Blackout Brand Fam Areas (Enc)'!$C$6:$C$998,I$1,'Blackout Brand Fam Areas (Enc)'!$D$6:$D$998,"Inactive")>0,"BLOCKED","CAN SELL")) -> BLOCKED | ... K10: =IF($A10="","",IF(COUNTIFS('Blackout Brand Fam Areas (Enc)'!$B$6:$B$998,$A10,'Blackout Brand Fam Areas (Enc)'!$C$6:$C$998,K$1,'Blackout Brand Fam Areas (Enc)'!$D$6:$D$998,"Inactive")>0,"BLOCKED","CAN SELL")) -> BLOCKED
A11: Bardstown Bourbon | B11: =IF($A11="","",IF(COUNTIFS('Blackout Brand Fam Areas (Enc)'!$B$6:$B$998,$A11,'Blackout Brand Fam Areas (Enc)'!$C$6:$C$998,B$1,'Blackout Brand Fam Areas (Enc)'!$D$6:$D$998,"Inactive")>0,"BLOCKED","CAN SELL")) -> CAN SELL | C11: =IF($A11="","",IF(COUNTIFS('Blackout Brand Fam Areas (Enc)'!$B$6:$B$998,$A11,'Blackout Brand Fam Areas (Enc)'!$C$6:$C$998,C$1,'Blackout Brand Fam Areas (Enc)'!$D$6:$D$998,"Inactive")>0,"BLOCKED","CAN SELL")) -> CAN SELL | D11: =IF($A11="","",IF(COUNTIFS('Blackout Brand Fam Areas (Enc)'!$B$6:$B$998,$A11,'Blackout Brand Fam Areas (Enc)'!$C$6:$C$998,D$1,'Blackout Brand Fam Areas (Enc)'!$D$6:$D$998,"Inactive")>0,"BLOCKED","CAN SELL")) -> CAN SELL | E11: =IF($A11="","",IF(COUNTIFS('Blackout Brand Fam Areas (Enc)'!$B$6:$B$998,$A11,'Blackout Brand Fam Areas (Enc)'!$C$6:$C$998,E$1,'Blackout Brand Fam Areas (Enc)'!$D$6:$D$998,"Inactive")>0,"BLOCKED","CAN SELL")) -> BLOCKED | F11: =IF($A11="","",IF(COUNTIFS('Blackout Brand Fam Areas (Enc)'!$B$6:$B$998,$A11,'Blackout Brand Fam Areas (Enc)'!$C$6:$C$998,F$1,'Blackout Brand Fam Areas (Enc)'!$D$6:$D$998,"Inactive")>0,"BLOCKED","CAN SELL")) -> BLOCKED | G11: =IF($A11="","",IF(COUNTIFS('Blackout Brand Fam Areas (Enc)'!$B$6:$B$998,$A11,'Blackout Brand Fam Areas (Enc)'!$C$6:$C$998,G$1,'Blackout Brand Fam Areas (Enc)'!$D$6:$D$998,"Inactive")>0,"BLOCKED","CAN SELL")) -> BLOCKED | H11: =IF($A11="","",IF(COUNTIFS('Blackout Brand Fam Areas (Enc)'!$B$6:$B$998,$A11,'Blackout Brand Fam Areas (Enc)'!$C$6:$C$998,H$1,'Blackout Brand Fam Areas (Enc)'!$D$6:$D$998,"Inactive")>0,"BLOCKED","CAN SELL")) -> CAN SELL | I11: =IF($A11="","",IF(COUNTIFS('Blackout Brand Fam Areas (Enc)'!$B$6:$B$998,$A11,'Blackout Brand Fam Areas (Enc)'!$C$6:$C$998,I$1,'Blackout Brand Fam Areas (Enc)'!$D$6:$D$998,"Inactive")>0,"BLOCKED","CAN SELL")) -> CAN SELL | ... K11: =IF($A11="","",IF(COUNTIFS('Blackout Brand Fam Areas (Enc)'!$B$6:$B$998,$A11,'Blackout Brand Fam Areas (Enc)'!$C$6:$C$998,K$1,'Blackout Brand Fam Areas (Enc)'!$D$6:$D$998,"Inactive")>0,"BLOCKED","CAN SELL")) -> CAN SELL
A12: Bardstown Green River | B12: =IF($A12="","",IF(COUNTIFS('Blackout Brand Fam Areas (Enc)'!$B$6:$B$998,$A12,'Blackout Brand Fam Areas (Enc)'!$C$6:$C$998,B$1,'Blackout Brand Fam Areas (Enc)'!$D$6:$D$998,"Inactive")>0,"BLOCKED","CAN SELL")) -> CAN SELL | C12: =IF($A12="","",IF(COUNTIFS('Blackout Brand Fam Areas (Enc)'!$B$6:$B$998,$A12,'Blackout Brand Fam Areas (Enc)'!$C$6:$C$998,C$1,'Blackout Brand Fam Areas (Enc)'!$D$6:$D$998,"Inactive")>0,"BLOCKED","CAN SELL")) -> CAN SELL | D12: =IF($A12="","",IF(COUNTIFS('Blackout Brand Fam Areas (Enc)'!$B$6:$B$998,$A12,'Blackout Brand Fam Areas (Enc)'!$C$6:$C$998,D$1,'Blackout Brand Fam Areas (Enc)'!$D$6:$D$998,"Inactive")>0,"BLOCKED","CAN SELL")) -> CAN SELL | E12: =IF($A12="","",IF(COUNTIFS('Blackout Brand Fam Areas (Enc)'!$B$6:$B$998,$A12,'Blackout Brand Fam Areas (Enc)'!$C$6:$C$998,E$1,'Blackout Brand Fam Areas (Enc)'!$D$6:$D$998,"Inactive")>0,"BLOCKED","CAN SELL")) -> BLOCKED | F12: =IF($A12="","",IF(COUNTIFS('Blackout Brand Fam Areas (Enc)'!$B$6:$B$998,$A12,'Blackout Brand Fam Areas (Enc)'!$C$6:$C$998,F$1,'Blackout Brand Fam Areas (Enc)'!$D$6:$D$998,"Inactive")>0,"BLOCKED","CAN SELL")) -> BLOCKED | G12: =IF($A12="","",IF(COUNTIFS('Blackout Brand Fam Areas (Enc)'!$B$6:$B$998,$A12,'Blackout Brand Fam Areas (Enc)'!$C$6:$C$998,G$1,'Blackout Brand Fam Areas (Enc)'!$D$6:$D$998,"Inactive")>0,"BLOCKED","CAN SELL")) -> BLOCKED | H12: =IF($A12="","",IF(COUNTIFS('Blackout Brand Fam Areas (Enc)'!$B$6:$B$998,$A12,'Blackout Brand Fam Areas (Enc)'!$C$6:$C$998,H$1,'Blackout Brand Fam Areas (Enc)'!$D$6:$D$998,"Inactive")>0,"BLOCKED","CAN SELL")) -> CAN SELL | I12: =IF($A12="","",IF(COUNTIFS('Blackout Brand Fam Areas (Enc)'!$B$6:$B$998,$A12,'Blackout Brand Fam Areas (Enc)'!$C$6:$C$998,I$1,'Blackout Brand Fam Areas (Enc)'!$D$6:$D$998,"Inactive")>0,"BLOCKED","CAN SELL")) -> CAN SELL | ... K12: =IF($A12="","",IF(COUNTIFS('Blackout Brand Fam Areas (Enc)'!$B$6:$B$998,$A12,'Blackout Brand Fam Areas (Enc)'!$C$6:$C$998,K$1,'Blackout Brand Fam Areas (Enc)'!$D$6:$D$998,"Inactive")>0,"BLOCKED","CAN SELL")) -> CAN SELL
A13: Bartender Series | B13: =IF($A13="","",IF(COUNTIFS('Blackout Brand Fam Areas (Enc)'!$B$6:$B$998,$A13,'Blackout Brand Fam Areas (Enc)'!$C$6:$C$998,B$1,'Blackout Brand Fam Areas (Enc)'!$D$6:$D$998,"Inactive")>0,"BLOCKED","CAN SELL")) -> CAN SELL | C13: =IF($A13="","",IF(COUNTIFS('Blackout Brand Fam Areas (Enc)'!$B$6:$B$998,$A13,'Blackout Brand Fam Areas (Enc)'!$C$6:$C$998,C$1,'Blackout Brand Fam Areas (Enc)'!$D$6:$D$998,"Inactive")>0,"BLOCKED","CAN SELL")) -> CAN SELL | D13: =IF($A13="","",IF(COUNTIFS('Blackout Brand Fam Areas (Enc)'!$B$6:$B$998,$A13,'Blackout Brand Fam Areas (Enc)'!$C$6:$C$998,D$1,'Blackout Brand Fam Areas (Enc)'!$D$6:$D$998,"Inactive")>0,"BLOCKED","CAN SELL")) -> CAN SELL | E13: =IF($A13="","",IF(COUNTIFS('Blackout Brand Fam Areas (Enc)'!$B$6:$B$998,$A13,'Blackout Brand Fam Areas (Enc)'!$C$6:$C$998,E$1,'Blackout Brand Fam Areas (Enc)'!$D$6:$D$998,"Inactive")>0,"BLOCKED","CAN SELL")) -> BLOCKED | F13: =IF($A13="","",IF(COUNTIFS('Blackout Brand Fam Areas (Enc)'!$B$6:$B$998,$A13,'Blackout Brand Fam Areas (Enc)'!$C$6:$C$998,F$1,'Blackout Brand Fam Areas (Enc)'!$D$6:$D$998,"Inactive")>0,"BLOCKED","CAN SELL")) -> CAN SELL | G13: =IF($A13="","",IF(COUNTIFS('Blackout Brand Fam Areas (Enc)'!$B$6:$B$998,$A13,'Blackout Brand Fam Areas (Enc)'!$C$6:$C$998,G$1,'Blackout Brand Fam Areas (Enc)'!$D$6:$D$998,"Inactive")>0,"BLOCKED","CAN SELL")) -> BLOCKED | H13: =IF($A13="","",IF(COUNTIFS('Blackout Brand Fam Areas (Enc)'!$B$6:$B$998,$A13,'Blackout Brand Fam Areas (Enc)'!$C$6:$C$998,H$1,'Blackout Brand Fam Areas (Enc)'!$D$6:$D$998,"Inactive")>0,"BLOCKED","CAN SELL")) -> CAN SELL | I13: =IF($A13="","",IF(COUNTIFS('Blackout Brand Fam Areas (Enc)'!$B$6:$B$998,$A13,'Blackout Brand Fam Areas (Enc)'!$C$6:$C$998,I$1,'Blackout Brand Fam Areas (Enc)'!$D$6:$D$998,"Inactive")>0,"BLOCKED","CAN SELL")) -> CAN SELL | ... K13: =IF($A13="","",IF(COUNTIFS('Blackout Brand Fam Areas (Enc)'!$B$6:$B$998,$A13,'Blackout Brand Fam Areas (Enc)'!$C$6:$C$998,K$1,'Blackout Brand Fam Areas (Enc)'!$D$6:$D$998,"Inactive")>0,"BLOCKED","CAN SELL")) -> CAN SELL
A14: Basic | B14: =IF($A14="","",IF(COUNTIFS('Blackout Brand Fam Areas (Enc)'!$B$6:$B$998,$A14,'Blackout Brand Fam Areas (Enc)'!$C$6:$C$998,B$1,'Blackout Brand Fam Areas (Enc)'!$D$6:$D$998,"Inactive")>0,"BLOCKED","CAN SELL")) -> CAN SELL | C14: =IF($A14="","",IF(COUNTIFS('Blackout Brand Fam Areas (Enc)'!$B$6:$B$998,$A14,'Blackout Brand Fam Areas (Enc)'!$C$6:$C$998,C$1,'Blackout Brand Fam Areas (Enc)'!$D$6:$D$998,"Inactive")>0,"BLOCKED","CAN SELL")) -> CAN SELL | D14: =IF($A14="","",IF(COUNTIFS('Blackout Brand Fam Areas (Enc)'!$B$6:$B$998,$A14,'Blackout Brand Fam Areas (Enc)'!$C$6:$C$998,D$1,'Blackout Brand Fam Areas (Enc)'!$D$6:$D$998,"Inactive")>0,"BLOCKED","CAN SELL")) -> CAN SELL | E14: =IF($A14="","",IF(COUNTIFS('Blackout Brand Fam Areas (Enc)'!$B$6:$B$998,$A14,'Blackout Brand Fam Areas (Enc)'!$C$6:$C$998,E$1,'Blackout Brand Fam Areas (Enc)'!$D$6:$D$998,"Inactive")>0,"BLOCKED","CAN SELL")) -> BLOCKED | F14: =IF($A14="","",IF(COUNTIFS('Blackout Brand Fam Areas (Enc)'!$B$6:$B$998,$A14,'Blackout Brand Fam Areas (Enc)'!$C$6:$C$998,F$1,'Blackout Brand Fam Areas (Enc)'!$D$6:$D$998,"Inactive")>0,"BLOCKED","CAN SELL")) -> CAN SELL | G14: =IF($A14="","",IF(COUNTIFS('Blackout Brand Fam Areas (Enc)'!$B$6:$B$998,$A14,'Blackout Brand Fam Areas (Enc)'!$C$6:$C$998,G$1,'Blackout Brand Fam Areas (Enc)'!$D$6:$D$998,"Inactive")>0,"BLOCKED","CAN SELL")) -> BLOCKED | H14: =IF($A14="","",IF(COUNTIFS('Blackout Brand Fam Areas (Enc)'!$B$6:$B$998,$A14,'Blackout Brand Fam Areas (Enc)'!$C$6:$C$998,H$1,'Blackout Brand Fam Areas (Enc)'!$D$6:$D$998,"Inactive")>0,"BLOCKED","CAN SELL")) -> CAN SELL | I14: =IF($A14="","",IF(COUNTIFS('Blackout Brand Fam Areas (Enc)'!$B$6:$B$998,$A14,'Blackout Brand Fam Areas (Enc)'!$C$6:$C$998,I$1,'Blackout Brand Fam Areas (Enc)'!$D$6:$D$998,"Inactive")>0,"BLOCKED","CAN SELL")) -> CAN SELL | ... K14: =IF($A14="","",IF(COUNTIFS('Blackout Brand Fam Areas (Enc)'!$B$6:$B$998,$A14,'Blackout Brand Fam Areas (Enc)'!$C$6:$C$998,K$1,'Blackout Brand Fam Areas (Enc)'!$D$6:$D$998,"Inactive")>0,"BLOCKED","CAN SELL")) -> CAN SELL
... A238: Zima | B238: =IF($A238="","",IF(COUNTIFS('Blackout Brand Fam Areas (Enc)'!$B$6:$B$998,$A238,'Blackout Brand Fam Areas (Enc)'!$C$6:$C$998,B$1,'Blackout Brand Fam Areas (Enc)'!$D$6:$D$998,"Inactive")>0,"BLOCKED","CAN SELL")) -> CAN SELL | C238: =IF($A238="","",IF(COUNTIFS('Blackout Brand Fam Areas (Enc)'!$B$6:$B$998,$A238,'Blackout Brand Fam Areas (Enc)'!$C$6:$C$998,C$1,'Blackout Brand Fam Areas (Enc)'!$D$6:$D$998,"Inactive")>0,"BLOCKED","CAN SELL")) -> CAN SELL | D238: =IF($A238="","",IF(COUNTIFS('Blackout Brand Fam Areas (Enc)'!$B$6:$B$998,$A238,'Blackout Brand Fam Areas (Enc)'!$C$6:$C$998,D$1,'Blackout Brand Fam Areas (Enc)'!$D$6:$D$998,"Inactive")>0,"BLOCKED","CAN SELL")) -> CAN SELL | E238: =IF($A238="","",IF(COUNTIFS('Blackout Brand Fam Areas (Enc)'!$B$6:$B$998,$A238,'Blackout Brand Fam Areas (Enc)'!$C$6:$C$998,E$1,'Blackout Brand Fam Areas (Enc)'!$D$6:$D$998,"Inactive")>0,"BLOCKED","CAN SELL")) -> BLOCKED | F238: =IF($A238="","",IF(COUNTIFS('Blackout Brand Fam Areas (Enc)'!$B$6:$B$998,$A238,'Blackout Brand Fam Areas (Enc)'!$C$6:$C$998,F$1,'Blackout Brand Fam Areas (Enc)'!$D$6:$D$998,"Inactive")>0,"BLOCKED","CAN SELL")) -> BLOCKED | G238: =IF($A238="","",IF(COUNTIFS('Blackout Brand Fam Areas (Enc)'!$B$6:$B$998,$A238,'Blackout Brand Fam Areas (Enc)'!$C$6:$C$998,G$1,'Blackout Brand Fam Areas (Enc)'!$D$6:$D$998,"Inactive")>0,"BLOCKED","CAN SELL")) -> BLOCKED | H238: =IF($A238="","",IF(COUNTIFS('Blackout Brand Fam Areas (Enc)'!$B$6:$B$998,$A238,'Blackout Brand Fam Areas (Enc)'!$C$6:$C$998,H$1,'Blackout Brand Fam Areas (Enc)'!$D$6:$D$998,"Inactive")>0,"BLOCKED","CAN SELL")) -> CAN SELL | I238: =IF($A238="","",IF(COUNTIFS('Blackout Brand Fam Areas (Enc)'!$B$6:$B$998,$A238,'Blackout Brand Fam Areas (Enc)'!$C$6:$C$998,I$1,'Blackout Brand Fam Areas (Enc)'!$D$6:$D$998,"Inactive")>0,"BLOCKED","CAN SELL")) -> CAN SELL | ... K238: =IF($A238="","",IF(COUNTIFS('Blackout Brand Fam Areas (Enc)'!$B$6:$B$998,$A238,'Blackout Brand Fam Areas (Enc)'!$C$6:$C$998,K$1,'Blackout Brand Fam Areas (Enc)'!$D$6:$D$998,"Inactive")>0,"BLOCKED","CAN SELL")) -> CAN SELL
B239: =IF($A239="","",IF(COUNTIFS('Blackout Brand Fam Areas (Enc)'!$B$6:$B$998,$A239,'Blackout Brand Fam Areas (Enc)'!$C$6:$C$998,B$1,'Blackout Brand Fam Areas (Enc)'!$D$6:$D$998,"Inactive")>0,"BLOCKED","CAN SELL")) | C239: =IF($A239="","",IF(COUNTIFS('Blackout Brand Fam Areas (Enc)'!$B$6:$B$998,$A239,'Blackout Brand Fam Areas (Enc)'!$C$6:$C$998,C$1,'Blackout Brand Fam Areas (Enc)'!$D$6:$D$998,"Inactive")>0,"BLOCKED","CAN SELL")) | D239: =IF($A239="","",IF(COUNTIFS('Blackout Brand Fam Areas (Enc)'!$B$6:$B$998,$A239,'Blackout Brand Fam Areas (Enc)'!$C$6:$C$998,D$1,'Blackout Brand Fam Areas (Enc)'!$D$6:$D$998,"Inactive")>0,"BLOCKED","CAN SELL")) | E239: =IF($A239="","",IF(COUNTIFS('Blackout Brand Fam Areas (Enc)'!$B$6:$B$998,$A239,'Blackout Brand Fam Areas (Enc)'!$C$6:$C$998,E$1,'Blackout Brand Fam Areas (Enc)'!$D$6:$D$998,"Inactive")>0,"BLOCKED","CAN SELL")) | F239: =IF($A239="","",IF(COUNTIFS('Blackout Brand Fam Areas (Enc)'!$B$6:$B$998,$A239,'Blackout Brand Fam Areas (Enc)'!$C$6:$C$998,F$1,'Blackout Brand Fam Areas (Enc)'!$D$6:$D$998,"Inactive")>0,"BLOCKED","CAN SELL")) | G239: =IF($A239="","",IF(COUNTIFS('Blackout Brand Fam Areas (Enc)'!$B$6:$B$998,$A239,'Blackout Brand Fam Areas (Enc)'!$C$6:$C$998,G$1,'Blackout Brand Fam Areas (Enc)'!$D$6:$D$998,"Inactive")>0,"BLOCKED","CAN SELL")) | H239: =IF($A239="","",IF(COUNTIFS('Blackout Brand Fam Areas (Enc)'!$B$6:$B$998,$A239,'Blackout Brand Fam Areas (Enc)'!$C$6:$C$998,H$1,'Blackout Brand Fam Areas (Enc)'!$D$6:$D$998,"Inactive")>0,"BLOCKED","CAN SELL")) | I239: =IF($A239="","",IF(COUNTIFS('Blackout Brand Fam Areas (Enc)'!$B$6:$B$998,$A239,'Blackout Brand Fam Areas (Enc)'!$C$6:$C$998,I$1,'Blackout Brand Fam Areas (Enc)'!$D$6:$D$998,"Inactive")>0,"BLOCKED","CAN SELL")) | ... K239: =IF($A239="","",IF(COUNTIFS('Blackout Brand Fam Areas (Enc)'!$B$6:$B$998,$A239,'Blackout Brand Fam Areas (Enc)'!$C$6:$C$998,K$1,'Blackout Brand Fam Areas (Enc)'!$D$6:$D$998,"Inactive")>0,"BLOCKED","CAN SELL"))
B240: =IF($A240="","",IF(COUNTIFS('Blackout Brand Fam Areas (Enc)'!$B$6:$B$998,$A240,'Blackout Brand Fam Areas (Enc)'!$C$6:$C$998,B$1,'Blackout Brand Fam Areas (Enc)'!$D$6:$D$998,"Inactive")>0,"BLOCKED","CAN SELL")) | C240: =IF($A240="","",IF(COUNTIFS('Blackout Brand Fam Areas (Enc)'!$B$6:$B$998,$A240,'Blackout Brand Fam Areas (Enc)'!$C$6:$C$998,C$1,'Blackout Brand Fam Areas (Enc)'!$D$6:$D$998,"Inactive")>0,"BLOCKED","CAN SELL")) | D240: =IF($A240="","",IF(COUNTIFS('Blackout Brand Fam Areas (Enc)'!$B$6:$B$998,$A240,'Blackout Brand Fam Areas (Enc)'!$C$6:$C$998,D$1,'Blackout Brand Fam Areas (Enc)'!$D$6:$D$998,"Inactive")>0,"BLOCKED","CAN SELL")) | E240: =IF($A240="","",IF(COUNTIFS('Blackout Brand Fam Areas (Enc)'!$B$6:$B$998,$A240,'Blackout Brand Fam Areas (Enc)'!$C$6:$C$998,E$1,'Blackout Brand Fam Areas (Enc)'!$D$6:$D$998,"Inactive")>0,"BLOCKED","CAN SELL")) | F240: =IF($A240="","",IF(COUNTIFS('Blackout Brand Fam Areas (Enc)'!$B$6:$B$998,$A240,'Blackout Brand Fam Areas (Enc)'!$C$6:$C$998,F$1,'Blackout Brand Fam Areas (Enc)'!$D$6:$D$998,"Inactive")>0,"BLOCKED","CAN SELL")) | G240: =IF($A240="","",IF(COUNTIFS('Blackout Brand Fam Areas (Enc)'!$B$6:$B$998,$A240,'Blackout Brand Fam Areas (Enc)'!$C$6:$C$998,G$1,'Blackout Brand Fam Areas (Enc)'!$D$6:$D$998,"Inactive")>0,"BLOCKED","CAN SELL")) | H240: =IF($A240="","",IF(COUNTIFS('Blackout Brand Fam Areas (Enc)'!$B$6:$B$998,$A240,'Blackout Brand Fam Areas (Enc)'!$C$6:$C$998,H$1,'Blackout Brand Fam Areas (Enc)'!$D$6:$D$998,"Inactive")>0,"BLOCKED","CAN SELL")) | I240: =IF($A240="","",IF(COUNTIFS('Blackout Brand Fam Areas (Enc)'!$B$6:$B$998,$A240,'Blackout Brand Fam Areas (Enc)'!$C$6:$C$998,I$1,'Blackout Brand Fam Areas (Enc)'!$D$6:$D$998,"Inactive")>0,"BLOCKED","CAN SELL")) | ... K240: =IF($A240="","",IF(COUNTIFS('Blackout Brand Fam Areas (Enc)'!$B$6:$B$998,$A240,'Blackout Brand Fam Areas (Enc)'!$C$6:$C$998,K$1,'Blackout Brand Fam Areas (Enc)'!$D$6:$D$998,"Inactive")>0,"BLOCKED","CAN SELL"))
B241: =IF($A241="","",IF(COUNTIFS('Blackout Brand Fam Areas (Enc)'!$B$6:$B$998,$A241,'Blackout Brand Fam Areas (Enc)'!$C$6:$C$998,B$1,'Blackout Brand Fam Areas (Enc)'!$D$6:$D$998,"Inactive")>0,"BLOCKED","CAN SELL")) | C241: =IF($A241="","",IF(COUNTIFS('Blackout Brand Fam Areas (Enc)'!$B$6:$B$998,$A241,'Blackout Brand Fam Areas (Enc)'!$C$6:$C$998,C$1,'Blackout Brand Fam Areas (Enc)'!$D$6:$D$998,"Inactive")>0,"BLOCKED","CAN SELL")) | D241: =IF($A241="","",IF(COUNTIFS('Blackout Brand Fam Areas (Enc)'!$B$6:$B$998,$A241,'Blackout Brand Fam Areas (Enc)'!$C$6:$C$998,D$1,'Blackout Brand Fam Areas (Enc)'!$D$6:$D$998,"Inactive")>0,"BLOCKED","CAN SELL")) | E241: =IF($A241="","",IF(COUNTIFS('Blackout Brand Fam Areas (Enc)'!$B$6:$B$998,$A241,'Blackout Brand Fam Areas (Enc)'!$C$6:$C$998,E$1,'Blackout Brand Fam Areas (Enc)'!$D$6:$D$998,"Inactive")>0,"BLOCKED","CAN SELL")) | F241: =IF($A241="","",IF(COUNTIFS('Blackout Brand Fam Areas (Enc)'!$B$6:$B$998,$A241,'Blackout Brand Fam Areas (Enc)'!$C$6:$C$998,F$1,'Blackout Brand Fam Areas (Enc)'!$D$6:$D$998,"Inactive")>0,"BLOCKED","CAN SELL")) | G241: =IF($A241="","",IF(COUNTIFS('Blackout Brand Fam Areas (Enc)'!$B$6:$B$998,$A241,'Blackout Brand Fam Areas (Enc)'!$C$6:$C$998,G$1,'Blackout Brand Fam Areas (Enc)'!$D$6:$D$998,"Inactive")>0,"BLOCKED","CAN SELL")) | H241: =IF($A241="","",IF(COUNTIFS('Blackout Brand Fam Areas (Enc)'!$B$6:$B$998,$A241,'Blackout Brand Fam Areas (Enc)'!$C$6:$C$998,H$1,'Blackout Brand Fam Areas (Enc)'!$D$6:$D$998,"Inactive")>0,"BLOCKED","CAN SELL")) | I241: =IF($A241="","",IF(COUNTIFS('Blackout Brand Fam Areas (Enc)'!$B$6:$B$998,$A241,'Blackout Brand Fam Areas (Enc)'!$C$6:$C$998,I$1,'Blackout Brand Fam Areas (Enc)'!$D$6:$D$998,"Inactive")>0,"BLOCKED","CAN SELL")) | ... K241: =IF($A241="","",IF(COUNTIFS('Blackout Brand Fam Areas (Enc)'!$B$6:$B$998,$A241,'Blackout Brand Fam Areas (Enc)'!$C$6:$C$998,K$1,'Blackout Brand Fam Areas (Enc)'!$D$6:$D$998,"Inactive")>0,"BLOCKED","CAN SELL"))
B242: =IF($A242="","",IF(COUNTIFS('Blackout Brand Fam Areas (Enc)'!$B$6:$B$998,$A242,'Blackout Brand Fam Areas (Enc)'!$C$6:$C$998,B$1,'Blackout Brand Fam Areas (Enc)'!$D$6:$D$998,"Inactive")>0,"BLOCKED","CAN SELL")) | C242: =IF($A242="","",IF(COUNTIFS('Blackout Brand Fam Areas (Enc)'!$B$6:$B$998,$A242,'Blackout Brand Fam Areas (Enc)'!$C$6:$C$998,C$1,'Blackout Brand Fam Areas (Enc)'!$D$6:$D$998,"Inactive")>0,"BLOCKED","CAN SELL")) | D242: =IF($A242="","",IF(COUNTIFS('Blackout Brand Fam Areas (Enc)'!$B$6:$B$998,$A242,'Blackout Brand Fam Areas (Enc)'!$C$6:$C$998,D$1,'Blackout Brand Fam Areas (Enc)'!$D$6:$D$998,"Inactive")>0,"BLOCKED","CAN SELL")) | E242: =IF($A242="","",IF(COUNTIFS('Blackout Brand Fam Areas (Enc)'!$B$6:$B$998,$A242,'Blackout Brand Fam Areas (Enc)'!$C$6:$C$998,E$1,'Blackout Brand Fam Areas (Enc)'!$D$6:$D$998,"Inactive")>0,"BLOCKED","CAN SELL")) | F242: =IF($A242="","",IF(COUNTIFS('Blackout Brand Fam Areas (Enc)'!$B$6:$B$998,$A242,'Blackout Brand Fam Areas (Enc)'!$C$6:$C$998,F$1,'Blackout Brand Fam Areas (Enc)'!$D$6:$D$998,"Inactive")>0,"BLOCKED","CAN SELL")) | G242: =IF($A242="","",IF(COUNTIFS('Blackout Brand Fam Areas (Enc)'!$B$6:$B$998,$A242,'Blackout Brand Fam Areas (Enc)'!$C$6:$C$998,G$1,'Blackout Brand Fam Areas (Enc)'!$D$6:$D$998,"Inactive")>0,"BLOCKED","CAN SELL")) | H242: =IF($A242="","",IF(COUNTIFS('Blackout Brand Fam Areas (Enc)'!$B$6:$B$998,$A242,'Blackout Brand Fam Areas (Enc)'!$C$6:$C$998,H$1,'Blackout Brand Fam Areas (Enc)'!$D$6:$D$998,"Inactive")>0,"BLOCKED","CAN SELL")) | I242: =IF($A242="","",IF(COUNTIFS('Blackout Brand Fam Areas (Enc)'!$B$6:$B$998,$A242,'Blackout Brand Fam Areas (Enc)'!$C$6:$C$998,I$1,'Blackout Brand Fam Areas (Enc)'!$D$6:$D$998,"Inactive")>0,"BLOCKED","CAN SELL")) | ... K242: =IF($A242="","",IF(COUNTIFS('Blackout Brand Fam Areas (Enc)'!$B$6:$B$998,$A242,'Blackout Brand Fam Areas (Enc)'!$C$6:$C$998,K$1,'Blackout Brand Fam Areas (Enc)'!$D$6:$D$998,"Inactive")>0,"BLOCKED","CAN SELL"))
B243: =IF($A243="","",IF(COUNTIFS('Blackout Brand Fam Areas (Enc)'!$B$6:$B$998,$A243,'Blackout Brand Fam Areas (Enc)'!$C$6:$C$998,B$1,'Blackout Brand Fam Areas (Enc)'!$D$6:$D$998,"Inactive")>0,"BLOCKED","CAN SELL")) | C243: =IF($A243="","",IF(COUNTIFS('Blackout Brand Fam Areas (Enc)'!$B$6:$B$998,$A243,'Blackout Brand Fam Areas (Enc)'!$C$6:$C$998,C$1,'Blackout Brand Fam Areas (Enc)'!$D$6:$D$998,"Inactive")>0,"BLOCKED","CAN SELL")) | D243: =IF($A243="","",IF(COUNTIFS('Blackout Brand Fam Areas (Enc)'!$B$6:$B$998,$A243,'Blackout Brand Fam Areas (Enc)'!$C$6:$C$998,D$1,'Blackout Brand Fam Areas (Enc)'!$D$6:$D$998,"Inactive")>0,"BLOCKED","CAN SELL")) | E243: =IF($A243="","",IF(COUNTIFS('Blackout Brand Fam Areas (Enc)'!$B$6:$B$998,$A243,'Blackout Brand Fam Areas (Enc)'!$C$6:$C$998,E$1,'Blackout Brand Fam Areas (Enc)'!$D$6:$D$998,"Inactive")>0,"BLOCKED","CAN SELL")) | F243: =IF($A243="","",IF(COUNTIFS('Blackout Brand Fam Areas (Enc)'!$B$6:$B$998,$A243,'Blackout Brand Fam Areas (Enc)'!$C$6:$C$998,F$1,'Blackout Brand Fam Areas (Enc)'!$D$6:$D$998,"Inactive")>0,"BLOCKED","CAN SELL")) | G243: =IF($A243="","",IF(COUNTIFS('Blackout Brand Fam Areas (Enc)'!$B$6:$B$998,$A243,'Blackout Brand Fam Areas (Enc)'!$C$6:$C$998,G$1,'Blackout Brand Fam Areas (Enc)'!$D$6:$D$998,"Inactive")>0,"BLOCKED","CAN SELL")) | H243: =IF($A243="","",IF(COUNTIFS('Blackout Brand Fam Areas (Enc)'!$B$6:$B$998,$A243,'Blackout Brand Fam Areas (Enc)'!$C$6:$C$998,H$1,'Blackout Brand Fam Areas (Enc)'!$D$6:$D$998,"Inactive")>0,"BLOCKED","CAN SELL")) | I243: =IF($A243="","",IF(COUNTIFS('Blackout Brand Fam Areas (Enc)'!$B$6:$B$998,$A243,'Blackout Brand Fam Areas (Enc)'!$C$6:$C$998,I$1,'Blackout Brand Fam Areas (Enc)'!$D$6:$D$998,"Inactive")>0,"BLOCKED","CAN SELL")) | ... K243: =IF($A243="","",IF(COUNTIFS('Blackout Brand Fam Areas (Enc)'!$B$6:$B$998,$A243,'Blackout Brand Fam Areas (Enc)'!$C$6:$C$998,K$1,'Blackout Brand Fam Areas (Enc)'!$D$6:$D$998,"Inactive")>0,"BLOCKED","CAN SELL"))
B244: =IF($A244="","",IF(COUNTIFS('Blackout Brand Fam Areas (Enc)'!$B$6:$B$998,$A244,'Blackout Brand Fam Areas (Enc)'!$C$6:$C$998,B$1,'Blackout Brand Fam Areas (Enc)'!$D$6:$D$998,"Inactive")>0,"BLOCKED","CAN SELL")) | C244: =IF($A244="","",IF(COUNTIFS('Blackout Brand Fam Areas (Enc)'!$B$6:$B$998,$A244,'Blackout Brand Fam Areas (Enc)'!$C$6:$C$998,C$1,'Blackout Brand Fam Areas (Enc)'!$D$6:$D$998,"Inactive")>0,"BLOCKED","CAN SELL")) | D244: =IF($A244="","",IF(COUNTIFS('Blackout Brand Fam Areas (Enc)'!$B$6:$B$998,$A244,'Blackout Brand Fam Areas (Enc)'!$C$6:$C$998,D$1,'Blackout Brand Fam Areas (Enc)'!$D$6:$D$998,"Inactive")>0,"BLOCKED","CAN SELL")) | E244: =IF($A244="","",IF(COUNTIFS('Blackout Brand Fam Areas (Enc)'!$B$6:$B$998,$A244,'Blackout Brand Fam Areas (Enc)'!$C$6:$C$998,E$1,'Blackout Brand Fam Areas (Enc)'!$D$6:$D$998,"Inactive")>0,"BLOCKED","CAN SELL")) | F244: =IF($A244="","",IF(COUNTIFS('Blackout Brand Fam Areas (Enc)'!$B$6:$B$998,$A244,'Blackout Brand Fam Areas (Enc)'!$C$6:$C$998,F$1,'Blackout Brand Fam Areas (Enc)'!$D$6:$D$998,"Inactive")>0,"BLOCKED","CAN SELL")) | G244: =IF($A244="","",IF(COUNTIFS('Blackout Brand Fam Areas (Enc)'!$B$6:$B$998,$A244,'Blackout Brand Fam Areas (Enc)'!$C$6:$C$998,G$1,'Blackout Brand Fam Areas (Enc)'!$D$6:$D$998,"Inactive")>0,"BLOCKED","CAN SELL")) | H244: =IF($A244="","",IF(COUNTIFS('Blackout Brand Fam Areas (Enc)'!$B$6:$B$998,$A244,'Blackout Brand Fam Areas (Enc)'!$C$6:$C$998,H$1,'Blackout Brand Fam Areas (Enc)'!$D$6:$D$998,"Inactive")>0,"BLOCKED","CAN SELL")) | I244: =IF($A244="","",IF(COUNTIFS('Blackout Brand Fam Areas (Enc)'!$B$6:$B$998,$A244,'Blackout Brand Fam Areas (Enc)'!$C$6:$C$998,I$1,'Blackout Brand Fam Areas (Enc)'!$D$6:$D$998,"Inactive")>0,"BLOCKED","CAN SELL")) | ... K244: =IF($A244="","",IF(COUNTIFS('Blackout Brand Fam Areas (Enc)'!$B$6:$B$998,$A244,'Blackout Brand Fam Areas (Enc)'!$C$6:$C$998,K$1,'Blackout Brand Fam Areas (Enc)'!$D$6:$D$998,"Inactive")>0,"BLOCKED","CAN SELL"))
B245: =IF($A245="","",IF(COUNTIFS('Blackout Brand Fam Areas (Enc)'!$B$6:$B$998,$A245,'Blackout Brand Fam Areas (Enc)'!$C$6:$C$998,B$1,'Blackout Brand Fam Areas (Enc)'!$D$6:$D$998,"Inactive")>0,"BLOCKED","CAN SELL")) | C245: =IF($A245="","",IF(COUNTIFS('Blackout Brand Fam Areas (Enc)'!$B$6:$B$998,$A245,'Blackout Brand Fam Areas (Enc)'!$C$6:$C$998,C$1,'Blackout Brand Fam Areas (Enc)'!$D$6:$D$998,"Inactive")>0,"BLOCKED","CAN SELL")) | D245: =IF($A245="","",IF(COUNTIFS('Blackout Brand Fam Areas (Enc)'!$B$6:$B$998,$A245,'Blackout Brand Fam Areas (Enc)'!$C$6:$C$998,D$1,'Blackout Brand Fam Areas (Enc)'!$D$6:$D$998,"Inactive")>0,"BLOCKED","CAN SELL")) | E245: =IF($A245="","",IF(COUNTIFS('Blackout Brand Fam Areas (Enc)'!$B$6:$B$998,$A245,'Blackout Brand Fam Areas (Enc)'!$C$6:$C$998,E$1,'Blackout Brand Fam Areas (Enc)'!$D$6:$D$998,"Inactive")>0,"BLOCKED","CAN SELL")) | F245: =IF($A245="","",IF(COUNTIFS('Blackout Brand Fam Areas (Enc)'!$B$6:$B$998,$A245,'Blackout Brand Fam Areas (Enc)'!$C$6:$C$998,F$1,'Blackout Brand Fam Areas (Enc)'!$D$6:$D$998,"Inactive")>0,"BLOCKED","CAN SELL")) | G245: =IF($A245="","",IF(COUNTIFS('Blackout Brand Fam Areas (Enc)'!$B$6:$B$998,$A245,'Blackout Brand Fam Areas (Enc)'!$C$6:$C$998,G$1,'Blackout Brand Fam Areas (Enc)'!$D$6:$D$998,"Inactive")>0,"BLOCKED","CAN SELL")) | H245: =IF($A245="","",IF(COUNTIFS('Blackout Brand Fam Areas (Enc)'!$B$6:$B$998,$A245,'Blackout Brand Fam Areas (Enc)'!$C$6:$C$998,H$1,'Blackout Brand Fam Areas (Enc)'!$D$6:$D$998,"Inactive")>0,"BLOCKED","CAN SELL")) | I245: =IF($A245="","",IF(COUNTIFS('Blackout Brand Fam Areas (Enc)'!$B$6:$B$998,$A245,'Blackout Brand Fam Areas (Enc)'!$C$6:$C$998,I$1,'Blackout Brand Fam Areas (Enc)'!$D$6:$D$998,"Inactive")>0,"BLOCKED","CAN SELL")) | ... K245: =IF($A245="","",IF(COUNTIFS('Blackout Brand Fam Areas (Enc)'!$B$6:$B$998,$A245,'Blackout Brand Fam Areas (Enc)'!$C$6:$C$998,K$1,'Blackout Brand Fam Areas (Enc)'!$D$6:$D$998,"Inactive")>0,"BLOCKED","CAN SELL"))
B246: =IF($A246="","",IF(COUNTIFS('Blackout Brand Fam Areas (Enc)'!$B$6:$B$998,$A246,'Blackout Brand Fam Areas (Enc)'!$C$6:$C$998,B$1,'Blackout Brand Fam Areas (Enc)'!$D$6:$D$998,"Inactive")>0,"BLOCKED","CAN SELL")) | C246: =IF($A246="","",IF(COUNTIFS('Blackout Brand Fam Areas (Enc)'!$B$6:$B$998,$A246,'Blackout Brand Fam Areas (Enc)'!$C$6:$C$998,C$1,'Blackout Brand Fam Areas (Enc)'!$D$6:$D$998,"Inactive")>0,"BLOCKED","CAN SELL")) | D246: =IF($A246="","",IF(COUNTIFS('Blackout Brand Fam Areas (Enc)'!$B$6:$B$998,$A246,'Blackout Brand Fam Areas (Enc)'!$C$6:$C$998,D$1,'Blackout Brand Fam Areas (Enc)'!$D$6:$D$998,"Inactive")>0,"BLOCKED","CAN SELL")) | E246: =IF($A246="","",IF(COUNTIFS('Blackout Brand Fam Areas (Enc)'!$B$6:$B$998,$A246,'Blackout Brand Fam Areas (Enc)'!$C$6:$C$998,E$1,'Blackout Brand Fam Areas (Enc)'!$D$6:$D$998,"Inactive")>0,"BLOCKED","CAN SELL")) | F246: =IF($A246="","",IF(COUNTIFS('Blackout Brand Fam Areas (Enc)'!$B$6:$B$998,$A246,'Blackout Brand Fam Areas (Enc)'!$C$6:$C$998,F$1,'Blackout Brand Fam Areas (Enc)'!$D$6:$D$998,"Inactive")>0,"BLOCKED","CAN SELL")) | G246: =IF($A246="","",IF(COUNTIFS('Blackout Brand Fam Areas (Enc)'!$B$6:$B$998,$A246,'Blackout Brand Fam Areas (Enc)'!$C$6:$C$998,G$1,'Blackout Brand Fam Areas (Enc)'!$D$6:$D$998,"Inactive")>0,"BLOCKED","CAN SELL")) | H246: =IF($A246="","",IF(COUNTIFS('Blackout Brand Fam Areas (Enc)'!$B$6:$B$998,$A246,'Blackout Brand Fam Areas (Enc)'!$C$6:$C$998,H$1,'Blackout Brand Fam Areas (Enc)'!$D$6:$D$998,"Inactive")>0,"BLOCKED","CAN SELL")) | I246: =IF($A246="","",IF(COUNTIFS('Blackout Brand Fam Areas (Enc)'!$B$6:$B$998,$A246,'Blackout Brand Fam Areas (Enc)'!$C$6:$C$998,I$1,'Blackout Brand Fam Areas (Enc)'!$D$6:$D$998,"Inactive")>0,"BLOCKED","CAN SELL")) | ... K246: =IF($A246="","",IF(COUNTIFS('Blackout Brand Fam Areas (Enc)'!$B$6:$B$998,$A246,'Blackout Brand Fam Areas (Enc)'!$C$6:$C$998,K$1,'Blackout Brand Fam Areas (Enc)'!$D$6:$D$998,"Inactive")>0,"BLOCKED","CAN SELL"))
B247: =IF($A247="","",IF(COUNTIFS('Blackout Brand Fam Areas (Enc)'!$B$6:$B$998,$A247,'Blackout Brand Fam Areas (Enc)'!$C$6:$C$998,B$1,'Blackout Brand Fam Areas (Enc)'!$D$6:$D$998,"Inactive")>0,"BLOCKED","CAN SELL")) | C247: =IF($A247="","",IF(COUNTIFS('Blackout Brand Fam Areas (Enc)'!$B$6:$B$998,$A247,'Blackout Brand Fam Areas (Enc)'!$C$6:$C$998,C$1,'Blackout Brand Fam Areas (Enc)'!$D$6:$D$998,"Inactive")>0,"BLOCKED","CAN SELL")) | D247: =IF($A247="","",IF(COUNTIFS('Blackout Brand Fam Areas (Enc)'!$B$6:$B$998,$A247,'Blackout Brand Fam Areas (Enc)'!$C$6:$C$998,D$1,'Blackout Brand Fam Areas (Enc)'!$D$6:$D$998,"Inactive")>0,"BLOCKED","CAN SELL")) | E247: =IF($A247="","",IF(COUNTIFS('Blackout Brand Fam Areas (Enc)'!$B$6:$B$998,$A247,'Blackout Brand Fam Areas (Enc)'!$C$6:$C$998,E$1,'Blackout Brand Fam Areas (Enc)'!$D$6:$D$998,"Inactive")>0,"BLOCKED","CAN SELL")) | F247: =IF($A247="","",IF(COUNTIFS('Blackout Brand Fam Areas (Enc)'!$B$6:$B$998,$A247,'Blackout Brand Fam Areas (Enc)'!$C$6:$C$998,F$1,'Blackout Brand Fam Areas (Enc)'!$D$6:$D$998,"Inactive")>0,"BLOCKED","CAN SELL")) | G247: =IF($A247="","",IF(COUNTIFS('Blackout Brand Fam Areas (Enc)'!$B$6:$B$998,$A247,'Blackout Brand Fam Areas (Enc)'!$C$6:$C$998,G$1,'Blackout Brand Fam Areas (Enc)'!$D$6:$D$998,"Inactive")>0,"BLOCKED","CAN SELL")) | H247: =IF($A247="","",IF(COUNTIFS('Blackout Brand Fam Areas (Enc)'!$B$6:$B$998,$A247,'Blackout Brand Fam Areas (Enc)'!$C$6:$C$998,H$1,'Blackout Brand Fam Areas (Enc)'!$D$6:$D$998,"Inactive")>0,"BLOCKED","CAN SELL")) | I247: =IF($A247="","",IF(COUNTIFS('Blackout Brand Fam Areas (Enc)'!$B$6:$B$998,$A247,'Blackout Brand Fam Areas (Enc)'!$C$6:$C$998,I$1,'Blackout Brand Fam Areas (Enc)'!$D$6:$D$998,"Inactive")>0,"BLOCKED","CAN SELL")) | ... K247: =IF($A247="","",IF(COUNTIFS('Blackout Brand Fam Areas (Enc)'!$B$6:$B$998,$A247,'Blackout Brand Fam Areas (Enc)'!$C$6:$C$998,K$1,'Blackout Brand Fam Areas (Enc)'!$D$6:$D$998,"Inactive")>0,"BLOCKED","CAN SELL"))
B248: =IF($A248="","",IF(COUNTIFS('Blackout Brand Fam Areas (Enc)'!$B$6:$B$998,$A248,'Blackout Brand Fam Areas (Enc)'!$C$6:$C$998,B$1,'Blackout Brand Fam Areas (Enc)'!$D$6:$D$998,"Inactive")>0,"BLOCKED","CAN SELL")) | C248: =IF($A248="","",IF(COUNTIFS('Blackout Brand Fam Areas (Enc)'!$B$6:$B$998,$A248,'Blackout Brand Fam Areas (Enc)'!$C$6:$C$998,C$1,'Blackout Brand Fam Areas (Enc)'!$D$6:$D$998,"Inactive")>0,"BLOCKED","CAN SELL")) | D248: =IF($A248="","",IF(COUNTIFS('Blackout Brand Fam Areas (Enc)'!$B$6:$B$998,$A248,'Blackout Brand Fam Areas (Enc)'!$C$6:$C$998,D$1,'Blackout Brand Fam Areas (Enc)'!$D$6:$D$998,"Inactive")>0,"BLOCKED","CAN SELL")) | E248: =IF($A248="","",IF(COUNTIFS('Blackout Brand Fam Areas (Enc)'!$B$6:$B$998,$A248,'Blackout Brand Fam Areas (Enc)'!$C$6:$C$998,E$1,'Blackout Brand Fam Areas (Enc)'!$D$6:$D$998,"Inactive")>0,"BLOCKED","CAN SELL")) | F248: =IF($A248="","",IF(COUNTIFS('Blackout Brand Fam Areas (Enc)'!$B$6:$B$998,$A248,'Blackout Brand Fam Areas (Enc)'!$C$6:$C$998,F$1,'Blackout Brand Fam Areas (Enc)'!$D$6:$D$998,"Inactive")>0,"BLOCKED","CAN SELL")) | G248: =IF($A248="","",IF(COUNTIFS('Blackout Brand Fam Areas (Enc)'!$B$6:$B$998,$A248,'Blackout Brand Fam Areas (Enc)'!$C$6:$C$998,G$1,'Blackout Brand Fam Areas (Enc)'!$D$6:$D$998,"Inactive")>0,"BLOCKED","CAN SELL")) | H248: =IF($A248="","",IF(COUNTIFS('Blackout Brand Fam Areas (Enc)'!$B$6:$B$998,$A248,'Blackout Brand Fam Areas (Enc)'!$C$6:$C$998,H$1,'Blackout Brand Fam Areas (Enc)'!$D$6:$D$998,"Inactive")>0,"BLOCKED","CAN SELL")) | I248: =IF($A248="","",IF(COUNTIFS('Blackout Brand Fam Areas (Enc)'!$B$6:$B$998,$A248,'Blackout Brand Fam Areas (Enc)'!$C$6:$C$998,I$1,'Blackout Brand Fam Areas (Enc)'!$D$6:$D$998,"Inactive")>0,"BLOCKED","CAN SELL")) | ... K248: =IF($A248="","",IF(COUNTIFS('Blackout Brand Fam Areas (Enc)'!$B$6:$B$998,$A248,'Blackout Brand Fam Areas (Enc)'!$C$6:$C$998,K$1,'Blackout Brand Fam Areas (Enc)'!$D$6:$D$998,"Inactive")>0,"BLOCKED","CAN SELL"))
B249: =IF($A249="","",IF(COUNTIFS('Blackout Brand Fam Areas (Enc)'!$B$6:$B$998,$A249,'Blackout Brand Fam Areas (Enc)'!$C$6:$C$998,B$1,'Blackout Brand Fam Areas (Enc)'!$D$6:$D$998,"Inactive")>0,"BLOCKED","CAN SELL")) | C249: =IF($A249="","",IF(COUNTIFS('Blackout Brand Fam Areas (Enc)'!$B$6:$B$998,$A249,'Blackout Brand Fam Areas (Enc)'!$C$6:$C$998,C$1,'Blackout Brand Fam Areas (Enc)'!$D$6:$D$998,"Inactive")>0,"BLOCKED","CAN SELL")) | D249: =IF($A249="","",IF(COUNTIFS('Blackout Brand Fam Areas (Enc)'!$B$6:$B$998,$A249,'Blackout Brand Fam Areas (Enc)'!$C$6:$C$998,D$1,'Blackout Brand Fam Areas (Enc)'!$D$6:$D$998,"Inactive")>0,"BLOCKED","CAN SELL")) | E249: =IF($A249="","",IF(COUNTIFS('Blackout Brand Fam Areas (Enc)'!$B$6:$B$998,$A249,'Blackout Brand Fam Areas (Enc)'!$C$6:$C$998,E$1,'Blackout Brand Fam Areas (Enc)'!$D$6:$D$998,"Inactive")>0,"BLOCKED","CAN SELL")) | F249: =IF($A249="","",IF(COUNTIFS('Blackout Brand Fam Areas (Enc)'!$B$6:$B$998,$A249,'Blackout Brand Fam Areas (Enc)'!$C$6:$C$998,F$1,'Blackout Brand Fam Areas (Enc)'!$D$6:$D$998,"Inactive")>0,"BLOCKED","CAN SELL")) | G249: =IF($A249="","",IF(COUNTIFS('Blackout Brand Fam Areas (Enc)'!$B$6:$B$998,$A249,'Blackout Brand Fam Areas (Enc)'!$C$6:$C$998,G$1,'Blackout Brand Fam Areas (Enc)'!$D$6:$D$998,"Inactive")>0,"BLOCKED","CAN SELL")) | H249: =IF($A249="","",IF(COUNTIFS('Blackout Brand Fam Areas (Enc)'!$B$6:$B$998,$A249,'Blackout Brand Fam Areas (Enc)'!$C$6:$C$998,H$1,'Blackout Brand Fam Areas (Enc)'!$D$6:$D$998,"Inactive")>0,"BLOCKED","CAN SELL")) | I249: =IF($A249="","",IF(COUNTIFS('Blackout Brand Fam Areas (Enc)'!$B$6:$B$998,$A249,'Blackout Brand Fam Areas (Enc)'!$C$6:$C$998,I$1,'Blackout Brand Fam Areas (Enc)'!$D$6:$D$998,"Inactive")>0,"BLOCKED","CAN SELL")) | ... K249: =IF($A249="","",IF(COUNTIFS('Blackout Brand Fam Areas (Enc)'!$B$6:$B$998,$A249,'Blackout Brand Fam Areas (Enc)'!$C$6:$C$998,K$1,'Blackout Brand Fam Areas (Enc)'!$D$6:$D$998,"Inactive")>0,"BLOCKED","CAN SELL"))
B250: =IF($A250="","",IF(COUNTIFS('Blackout Brand Fam Areas (Enc)'!$B$6:$B$998,$A250,'Blackout Brand Fam Areas (Enc)'!$C$6:$C$998,B$1,'Blackout Brand Fam Areas (Enc)'!$D$6:$D$998,"Inactive")>0,"BLOCKED","CAN SELL")) | C250: =IF($A250="","",IF(COUNTIFS('Blackout Brand Fam Areas (Enc)'!$B$6:$B$998,$A250,'Blackout Brand Fam Areas (Enc)'!$C$6:$C$998,C$1,'Blackout Brand Fam Areas (Enc)'!$D$6:$D$998,"Inactive")>0,"BLOCKED","CAN SELL")) | D250: =IF($A250="","",IF(COUNTIFS('Blackout Brand Fam Areas (Enc)'!$B$6:$B$998,$A250,'Blackout Brand Fam Areas (Enc)'!$C$6:$C$998,D$1,'Blackout Brand Fam Areas (Enc)'!$D$6:$D$998,"Inactive")>0,"BLOCKED","CAN SELL")) | E250: =IF($A250="","",IF(COUNTIFS('Blackout Brand Fam Areas (Enc)'!$B$6:$B$998,$A250,'Blackout Brand Fam Areas (Enc)'!$C$6:$C$998,E$1,'Blackout Brand Fam Areas (Enc)'!$D$6:$D$998,"Inactive")>0,"BLOCKED","CAN SELL")) | F250: =IF($A250="","",IF(COUNTIFS('Blackout Brand Fam Areas (Enc)'!$B$6:$B$998,$A250,'Blackout Brand Fam Areas (Enc)'!$C$6:$C$998,F$1,'Blackout Brand Fam Areas (Enc)'!$D$6:$D$998,"Inactive")>0,"BLOCKED","CAN SELL")) | G250: =IF($A250="","",IF(COUNTIFS('Blackout Brand Fam Areas (Enc)'!$B$6:$B$998,$A250,'Blackout Brand Fam Areas (Enc)'!$C$6:$C$998,G$1,'Blackout Brand Fam Areas (Enc)'!$D$6:$D$998,"Inactive")>0,"BLOCKED","CAN SELL")) | H250: =IF($A250="","",IF(COUNTIFS('Blackout Brand Fam Areas (Enc)'!$B$6:$B$998,$A250,'Blackout Brand Fam Areas (Enc)'!$C$6:$C$998,H$1,'Blackout Brand Fam Areas (Enc)'!$D$6:$D$998,"Inactive")>0,"BLOCKED","CAN SELL")) | I250: =IF($A250="","",IF(COUNTIFS('Blackout Brand Fam Areas (Enc)'!$B$6:$B$998,$A250,'Blackout Brand Fam Areas (Enc)'!$C$6:$C$998,I$1,'Blackout Brand Fam Areas (Enc)'!$D$6:$D$998,"Inactive")>0,"BLOCKED","CAN SELL")) | ... K250: =IF($A250="","",IF(COUNTIFS('Blackout Brand Fam Areas (Enc)'!$B$6:$B$998,$A250,'Blackout Brand Fam Areas (Enc)'!$C$6:$C$998,K$1,'Blackout Brand Fam Areas (Enc)'!$D$6:$D$998,"Inactive")>0,"BLOCKED","CAN SELL"))
... B300: =IF($A300="","",IF(COUNTIFS('Blackout Brand Fam Areas (Enc)'!$B$6:$B$998,$A300,'Blackout Brand Fam Areas (Enc)'!$C$6:$C$998,B$1,'Blackout Brand Fam Areas (Enc)'!$D$6:$D$998,"Inactive")>0,"BLOCKED","CAN SELL")) | C300: =IF($A300="","",IF(COUNTIFS('Blackout Brand Fam Areas (Enc)'!$B$6:$B$998,$A300,'Blackout Brand Fam Areas (Enc)'!$C$6:$C$998,C$1,'Blackout Brand Fam Areas (Enc)'!$D$6:$D$998,"Inactive")>0,"BLOCKED","CAN SELL")) | D300: =IF($A300="","",IF(COUNTIFS('Blackout Brand Fam Areas (Enc)'!$B$6:$B$998,$A300,'Blackout Brand Fam Areas (Enc)'!$C$6:$C$998,D$1,'Blackout Brand Fam Areas (Enc)'!$D$6:$D$998,"Inactive")>0,"BLOCKED","CAN SELL")) | E300: =IF($A300="","",IF(COUNTIFS('Blackout Brand Fam Areas (Enc)'!$B$6:$B$998,$A300,'Blackout Brand Fam Areas (Enc)'!$C$6:$C$998,E$1,'Blackout Brand Fam Areas (Enc)'!$D$6:$D$998,"Inactive")>0,"BLOCKED","CAN SELL")) | F300: =IF($A300="","",IF(COUNTIFS('Blackout Brand Fam Areas (Enc)'!$B$6:$B$998,$A300,'Blackout Brand Fam Areas (Enc)'!$C$6:$C$998,F$1,'Blackout Brand Fam Areas (Enc)'!$D$6:$D$998,"Inactive")>0,"BLOCKED","CAN SELL")) | G300: =IF($A300="","",IF(COUNTIFS('Blackout Brand Fam Areas (Enc)'!$B$6:$B$998,$A300,'Blackout Brand Fam Areas (Enc)'!$C$6:$C$998,G$1,'Blackout Brand Fam Areas (Enc)'!$D$6:$D$998,"Inactive")>0,"BLOCKED","CAN SELL")) | H300: =IF($A300="","",IF(COUNTIFS('Blackout Brand Fam Areas (Enc)'!$B$6:$B$998,$A300,'Blackout Brand Fam Areas (Enc)'!$C$6:$C$998,H$1,'Blackout Brand Fam Areas (Enc)'!$D$6:$D$998,"Inactive")>0,"BLOCKED","CAN SELL")) | I300: =IF($A300="","",IF(COUNTIFS('Blackout Brand Fam Areas (Enc)'!$B$6:$B$998,$A300,'Blackout Brand Fam Areas (Enc)'!$C$6:$C$998,I$1,'Blackout Brand Fam Areas (Enc)'!$D$6:$D$998,"Inactive")>0,"BLOCKED","CAN SELL")) | ... K300: =IF($A300="","",IF(COUNTIFS('Blackout Brand Fam Areas (Enc)'!$B$6:$B$998,$A300,'Blackout Brand Fam Areas (Enc)'!$C$6:$C$998,K$1,'Blackout Brand Fam Areas (Enc)'!$D$6:$D$998,"Inactive")>0,"BLOCKED","CAN SELL"))

Sheet Blackout Brand Fam Areas (Enc)
A1: This serves as a BLACK LIST or WHERE WE CAN NOT SELL A BRAND.
A2: COLUMN D = INACTIVE means WE CAN NOT SELL THE BRAND IN THAT COUNTY
A5: ID | B5: Brand Family | C5: Distribution Area | D5: Active | E5: Distributor | G5: Match Key
A6: 8804 | B6: Anchor | C6: Morris 3 | D6: Inactive | E6: Not Set Yet | G6: =UPPER(B6)&"|"&UPPER(C6) -> ANCHOR|MORRIS 3
A7: 8805 | B7: Famosa | C7: Morris 3 | D7: Inactive | E7: Not Set Yet | G7: =UPPER(B7)&"|"&UPPER(C7) -> FAMOSA|MORRIS 3
A8: 8806 | B8: Genesee | C8: Morris 3 | D8: Inactive | E8: Not Set Yet | G8: =UPPER(B8)&"|"&UPPER(C8) -> GENESEE|MORRIS 3
A9: 8807 | B9: Honey Brown | C9: Morris 3 | D9: Inactive | E9: Not Set Yet | G9: =UPPER(B9)&"|"&UPPER(C9) -> HONEY BROWN|MORRIS 3
A10: 8808 | B10: Imperial | C10: Morris 3 | D10: Inactive | E10: Not Set Yet | G10: =UPPER(B10)&"|"&UPPER(C10) -> IMPERIAL|MORRIS 3
A11: 8809 | B11: Misissippi | C11: Morris 3 | D11: Inactive | E11: Not Set Yet | G11: =UPPER(B11)&"|"&UPPER(C11) -> MISISSIPPI|MORRIS 3
A12: 8810 | B12: Czechvar | C12: Morris 3 | D12: Inactive | E12: Not Set Yet | G12: =UPPER(B12)&"|"&UPPER(C12) -> CZECHVAR|MORRIS 3
A13: 8811 | B13: Daura | C13: Morris 3 | D13: Inactive | E13: Not Set Yet | G13: =UPPER(B13)&"|"&UPPER(C13) -> DAURA|MORRIS 3
A14: 8812 | B14: Estrella | C14: Morris 3 | D14: Inactive | E14: Not Set Yet | G14: =UPPER(B14)&"|"&UPPER(C14) -> ESTRELLA|MORRIS 3
A15: 8813 | B15: Inedit | C15: Morris 3 | D15: Inactive | E15: Not Set Yet | G15: =UPPER(B15)&"|"&UPPER(C15) -> INEDIT|MORRIS 3
A16: 8815 | B16: Flying Fish | C16: Morris 3 | D16: Inactive | E16: Not Set Yet | G16: =UPPER(B16)&"|"&UPPER(C16) -> FLYING FISH|MORRIS 3
A17: 8816 | B17: Bold Rock | C17: Morris 3 | D17: Inactive | E17: Not Set Yet | G17: =UPPER(B17)&"|"&UPPER(C17) -> BOLD ROCK|MORRIS 3
... A998: 9897 | B998: Beviamo | C998: Morris 2 | D998: Inactive | E998: Not Set Yet | G998: =UPPER(B998)&"|"&UPPER(C998) -> BEVIAMO|MORRIS 2

Sheet Brand Family Territory (Enc)
A1: Brand Family | B1: Brand Family Territory ID
A2: Angry Orchard | B2: Core Market
A3: Aguila | B3: Core Market
A4: Arnold Palmer | B4: Core Market
A5: Athletic | B5: Core Market
A6: Bardstown Bourbon | B6: Core Market
A7: Bell's | B7: Core Market
A8: Bell's Hearted Family | B8: Core Market
A9: Blue Moon | B9: Core Market
A10: Cape May | B10: Core Market
A11: Cayman Jack | B11: Core Market
A12: Coors | B12: Core Market
... A296: 2 Canos | B296: All Counties

Sheet Sales Reps Customer Base
A1: Sales Rep Assigned | B1: Customer Num | C1: Customer Name | D1: Shipping Address | E1: Distribution Area | F1: County | G1: City | H1: Area | I1: Premise | J1: Buyer Count 2026 | K1: Cases 2026
A2: Alex Rodriguez | B2: 250316 | C2: Rancho Mateo Asadero Colombian | D2: 27 Westfield Ave | E2: Union | F2: Union | G2: Elizabeth | H2: Union | I2: On Premise | J2: 1 | K2: 41
A3: Alex Rodriguez | B3: 250068 | C3: Jakob Liquors | D3: 1114-1126 Elizabeth Ave | E3: Union | F3: Union | G3: Elizabeth | H3: Union | I3: Off Premise | J3: 1 | K3: 261
A4: Alex Rodriguez | B4: 250303 | C4: Olga's Place | D4: 212 Lt.Glenn Zamolski Dr | E4: Union | F4: Union | G4: Elizabeth | H4: Union | I4: On Premise | J4: 1 | K4: 39
A5: Alex Rodriguez | B5: 250128 | C5: Liquor Depot | D5: 435 Rahway Ave | E5: Union | F5: Union | G5: Elizabeth | H5: Union | I5: Off Premise | J5: 1 | K5: 889.92
A6: Alex Rodriguez | B6: 250080 | C6: Crown Liquors | D6: 711 E. 1st Ave | E6: Union | F6: Union | G6: Roselle | H6: Union | I6: Off Premise | J6: 1 | K6: 97
A7: Alex Rodriguez | B7: 250093 | C7: San Homa Liquors | D7: 1003 E. 2nd St. | E7: Union | F7: Union | G7: Plainfield | H7: Union | I7: Off Premise | J7: 1 | K7: 332
A8: Alex Rodriguez | B8: 250137 | C8: Elmora Liquors | D8: 615 Westfield Ave | E8: Union | F8: Union | G8: Elizabeth | H8: Union | I8: Off Premise | J8: 1 | K8: 51
A9: Alex Rodriguez | B9: 150118 | C9: Wine Legend | D9: 277 Eisenhower Pkwy | E9: Essex | F9: Essex | G9: Livingston | H9: Essex | I9: Off Premise | J9: 1 | K9: 249
A10: Alex Rodriguez | B10: 250191 | C10: Roselle Park Liquors | D10: 117 W. Colfax Ave | E10: Union | F10: Union | G10: Roselle Park | H10: Union | I10: Off Premise | J10: 1 | K10: 96
A11: Alex Rodriguez | B11: 250059 | C11: Payless Liquor | D11: 1041 Elizabeth Ave | E11: Union | F11: Union | G11: Elizabeth | H11: Union | I11: Off Premise | J11: 1 | K11: 119
A12: Alex Rodriguez | B12: 250132 | C12: Butlers Liquor Store | D12: 182 Elmora Ave | E12: Union | F12: Union | G12: Elizabeth | H12: Union | I12: Off Premise | J12: 1 | K12: 45
A13: Alex Rodriguez | B13: 250135 | C13: Garcias Liquor Depot | D13: 309 Westfield Ave | E13: Union | F13: Union | G13: Elizabeth | H13: Union | I13: Off Premise | J13: 1 | K13: 243
... A2371: Shane Barreca | B2371: 67008 | C2371: Woori Mart | D2371: 206 Pegasus Ave. | E2371: Sales | F2371: Bergen | G2371: Northvale | H2371: Sales | I2371: Off Premise | J2371: 1 | K2371: 941
